Workbook

Sheet Смета СН-2012 по гл. 1-5
A1: =CONCATENATE(Source!B1, " СН-2012 (© ОАО МЦЦС 'Мосстройцены', ", "2026", ")") -> Smeta.RU (495) 974-1589 СН-2012 (© ОАО МЦЦС 'Мосстройцены', 2026)
J2: Форма № 1а (глава 1-5)
B3: "СОГЛАСОВАНО" | G3: "УТВЕРЖДАЮ"
B6: =CONCATENATE("______________________ ", IF(Source!AL12<>"", Source!AL12, "")) -> ______________________ | G6: =CONCATENATE("______________________ ", IF(Source!AH12<>"", Source!AH12, "")) -> ______________________
B7: "_____"________________ 2026 г. | G7: "_____"________________ 2026 г.
A10: =CONCATENATE( "ЛОКАЛЬНАЯ СМЕТА № ",IF(Source!F12<>"Новый объект", Source!F12, "")) -> ЛОКАЛЬНАЯ СМЕТА №
A11: (локальный сметный расчет)
A15: =IF(Source!G12<>"Новый объект", Source!G12, "") -> Электрика новая
A16: (наименование работ и затрат, наименование объекта)
A18: =CONCATENATE( "Основание: чертежи № ", Source!J12) -> Основание: чертежи №
F20: Сметная стоимость | I20: =I21+I22+I23+I24 -> 10358.32 | K20: тыс.руб
F21: Строительные работы | I21: =ROUND((Source!F3937)/1000, 2) -> 2489.84 | K21: тыс.руб
F22: Монтажные работы | I22: =ROUND((Source!F3938)/1000, 2) -> 0 | K22: тыс.руб
F23: Оборудование | I23: =ROUND((Source!F3929)/1000, 2) -> 0 | K23: тыс.руб
F24: Прочие работы | I24: =ROUND((Source!F3939+Source!F3940)/1000, 2) -> 7868.48 | K24: тыс.руб
F25: Средства на оплату труда | I25: =(Source!F3935+ Source!F3934)/1000 -> 3759.6864 | K25: тыс.руб
A26: Составлен(а) в уровне текущих (прогнозных) цен на январь 2026 года
A27: №№ п/п | B27: Шифр расценки и коды ресурсов | C27: Наименование работ и затрат | D27: Единица измерения | E27: Кол-во единиц | F27: Цена на ед. изм. руб. | G27: Попра-вочные коэфф. | H27: Коэфф. зимних удоро-жаний | I27: Коэфф. пересчета | J27: ВСЕГО затрат, руб. | K27: Справочно
K28: ЗТР, всего чел.-час
K29: Ст-ть ед. с начислен.
A30: 1 | B30: 2 | C30: 3 | D30: 4 | E30: 5 | F30: 6 | G30: 7 | H30: 8 | I30: 9 | J30: 10 | K30: 11
A32: =CONCATENATE("Локальная смета: ",IF(Source!G20<>"Новая локальная смета", Source!G20, "")) -> Локальная смета:
A34: =CONCATENATE("Раздел: ",IF(Source!G24<>"Новый раздел", Source!G24, "")) -> Раздел: Помещение 312 Актовый зал
A35: 1 | B35: =Source!F28 -> 1.21-3305-1-1/1 | C35: =Source!G28 -> Демонтаж выключателей, розеток | D35: =Source!H28 -> 100 шт. | E35: =Source!I28 -> 0.1 | Q35: =ROUND((Source!BZ28/100)*ROUND((Source!AF28*Source!AV28)*Source!I28, 2), 2) -> 189.74 | R35: =Source!X28 -> 189.74 | S35: =ROUND((Source!CA28/100)*ROUND((Source!AF28*Source!AV28)*Source!I28, 2), 2) -> 27.11 | T35: =Source!Y28 -> 27.11 | U35: =ROUND((175/100)*ROUND((Source!AE28*Source!AV28)*Source!I28, 2), 2) -> 0 | V35: =ROUND((108/100)*ROUND(Source!CS28*Source!I28, 2), 2) -> 0
C36: ="Объем: "&Source!I28&"=10/"&"100" -> Объем: 0,1=10/100
C37: ЗП | F37: =Source!AO28 -> 2710.46 | G37: =Source!DG28 | H37: =Source!AV28 -> 1 | I37: =IF(Source!BA28<> 0, Source!BA28, 1) -> 1 | J37: =Source!S28 -> 271.05
C38: НР от ЗП | D38: % | E38: =Source!AT28 -> 70 | J38: =SUM(R35:R37) -> 189.74
C39: СП от ЗП | D39: % | E39: =Source!AU28 -> 10 | J39: =SUM(T35:T38) -> 27.11
C40: ЗТР | D40: чел-ч | E40: =Source!AQ28 -> 5.84 | G40: =Source!DI28 | H40: =Source!AV28 -> 1 | K40: =Source!U28 -> 0.584
I41: =J37+J38+J39 -> 487.9 | K41: =IF(Source!I28<>0, ROUND(I41/Source!I28, 2), 0) -> 4879 | P41: =I41 -> 487.9
A42: 2 | B42: =Source!F29 -> 1.21-3103-31-2/3 | C42: =Source!G29 -> Прокладка пластикового кабель-канала - по бетонному основанию / сечение 60х40 мм | D42: =Source!H29 -> 100 м | E42: =Source!I29 -> 3.15 | Q42: =ROUND((Source!BZ29/100)*ROUND((Source!AF29*Source!AV29)*Source!I29, 2), 2) -> 58621.89 | R42: =Source!X29 -> 58621.89 | S42: =ROUND((Source!CA29/100)*ROUND((Source!AF29*Source!AV29)*Source!I29, 2), 2) -> 8374.56 | T42: =Source!Y29 -> 8374.56 | U42: =ROUND((175/100)*ROUND((Source!AE29*Source!AV29)*Source!I29, 2), 2) -> 5.13 | V42: =ROUND((108/100)*ROUND(Source!CS29*Source!I29, 2), 2) -> 3.16
C43: ="Объем: "&Source!I29&"=315/"&"100" -> Объем: 3,15=315/100
C44: ЗП | F44: =Source!AO29 -> 26585.89 | G44: =Source!DG29 | H44: =Source!AV29 -> 1 | I44: =IF(Source!BA29<> 0, Source!BA29, 1) -> 1 | J44: =Source!S29 -> 83745.55
C45: ЭМ | F45: =Source!AM29 -> 67.4 | G45: =Source!DE29 | H45: =Source!AV29 -> 1 | I45: =IF(Source!BB29<> 0, Source!BB29, 1) -> 1 | J45: =Source!Q29 -> 212.31
C46: в т.ч. ЗПМ | F46: =Source!AN29 -> 0.93 | G46: =Source!DF29 | H46: =Source!AV29 -> 1 | I46: =IF(Source!BS29<> 0, Source!BS29, 1) -> 1 | J46: =Source!R29 -> 2.93
C47: МР | F47: =Source!AL29 -> 31223.74 | G47: =Source!DD29 | H47: =Source!AW29 -> 1 | I47: =IF(Source!BC29<> 0, Source!BC29, 1) -> 1 | J47: =Source!P29 -> 98354.78
C48: НР от ЗП | D48: % | E48: =Source!AT29 -> 70 | J48: =SUM(R42:R47) -> 58621.89
C49: СП от ЗП | D49: % | E49: =Source!AU29 -> 10 | J49: =SUM(T42:T48) -> 8374.56
C50: НР и СП от ЗПМ | D50: % | E50: =108 -> 108 | J50: =SUM(V42:V49) -> 3.16
C51: ЗТР | D51: чел-ч | E51: =Source!AQ29 -> 46.78 | G51: =Source!DI29 | H51: =Source!AV29 -> 1 | K51: =Source!U29 -> 147.357
I52: =J44+J45+J47+J48+J49+J50 -> 249312.25 | K52: =IF(Source!I29<>0, ROUND(I52/Source!I29, 2), 0) -> 79146.75 | P52: =I52 -> 249312.25
A53: 3 | B53: =Source!F30 -> 1.21-3103-7-1/1 | C53: =Source!G30 -> Прокладка проводов и кабелей в лотках, провод сечением до 6 мм2 | D53: =Source!H30 -> 100 м | E53: =Source!I30 -> 3.15 | Q53: =ROUND((Source!BZ30/100)*ROUND((Source!AF30*Source!AV30)*Source!I30, 2), 2) -> 1586.59 | R53: =Source!X30 -> 1586.59 | S53: =ROUND((Source!CA30/100)*ROUND((Source!AF30*Source!AV30)*Source!I30, 2), 2) -> 226.66 | T53: =Source!Y30 -> 226.66 | U53: =ROUND((175/100)*ROUND((Source!AE30*Source!AV30)*Source!I30, 2), 2) -> 2504.6 | V53: =ROUND((108/100)*ROUND(Source!CS30*Source!I30, 2), 2) -> 1545.7
C54: ="Объем: "&Source!I30&"=315/"&"100" -> Объем: 3,15=315/100
C55: ЗП | F55: =Source!AO30 -> 719.54 | G55: =Source!DG30 | H55: =Source!AV30 -> 1 | I55: =IF(Source!BA30<> 0, Source!BA30, 1) -> 1 | J55: =Source!S30 -> 2266.55
C56: ЭМ | F56: =Source!AM30 -> 891.59 | G56: =Source!DE30 | H56: =Source!AV30 -> 1 | I56: =IF(Source!BB30<> 0, Source!BB30, 1) -> 1 | J56: =Source!Q30 -> 2808.51
C57: в т.ч. ЗПМ | F57: =Source!AN30 -> 454.35 | G57: =Source!DF30 | H57: =Source!AV30 -> 1 | I57: =IF(Source!BS30<> 0, Source!BS30, 1) -> 1 | J57: =Source!R30 -> 1431.2
C58: МР | F58: =Source!AL30 -> 10685.41 | G58: =Source!DD30 | H58: =Source!AW30 -> 1 | I58: =IF(Source!BC30<> 0, Source!BC30, 1) -> 1 | J58: =Source!P30 -> 33659.04
C59: НР от ЗП | D59: % | E59: =Source!AT30 -> 70 | J59: =SUM(R53:R58) -> 1586.59
C60: СП от ЗП | D60: % | E60: =Source!AU30 -> 10 | J60: =SUM(T53:T59) -> 226.66
C61: НР и СП от ЗПМ | D61: % | E61: =108 -> 108 | J61: =SUM(V53:V60) -> 1545.7
C62: ЗТР | D62: чел-ч | E62: =Source!AQ30 -> 1.18 | G62: =Source!DI30 | H62: =Source!AV30 -> 1 | K62: =Source!U30 -> 3.717
I63: =J55+J56+J58+J59+J60+J61 -> 42093.05 | K63: =IF(Source!I30<>0, ROUND(I63/Source!I30, 2), 0) -> 13362.87 | P63: =I63 -> 42093.05
A64: 4 | B64: =Source!F31 -> 21.23-8-270 | C64: =Source!G31 -> Кабели силовые, с медными жилами, с изоляц. и оболоч.из ПВХ пластиката пониж.пожар.опасности, не распростр.горение, с пониж.дымо- и газовыделением и с низк.токсич-тью продуктов горения, напряж.1000 В, марка ВВГнг(А)-LSLTx, число жил и сечение, мм2: 3х2,5 | D64: =Source!H31 -> км | E64: =Source!I31 -> 0.27 | F64: =Source!AL31 -> 129532.62 | G64: =Source!DD31 | H64: =Source!AW31 -> 1 | I64: =IF(Source!BC31<> 0, Source!BC31, 1) -> 1 | J64: =Source!P31 -> 34973.81 | Q64: =ROUND((Source!BZ31/100)*ROUND((Source!AF31*Source!AV31)*Source!I31, 2), 2) -> 0 | R64: =Source!X31 -> 0 | S64: =ROUND((Source!CA31/100)*ROUND((Source!AF31*Source!AV31)*Source!I31, 2), 2) -> 0 | T64: =Source!Y31 -> 0 | U64: =ROUND((175/100)*ROUND((Source!AE31*Source!AV31)*Source!I31, 2), 2) -> 0 | V64: =ROUND((108/100)*ROUND(Source!CS31*Source!I31, 2), 2) -> 0
I65: =J64 -> 34973.81 | K65: =IF(Source!I31<>0, ROUND(I65/Source!I31, 2), 0) -> 129532.63 | P65: =I65 -> 34973.81
A66: 5 | B66: =Source!F32 -> 1.20-3103-1-8/1 | C66: =Source!G32 -> Установка розетки штепсельной неутопленного типа при открытой проводке | D66: =Source!H32 -> 100 шт. | E66: =Source!I32 -> 0.12 | Q66: =ROUND((Source!BZ32/100)*ROUND((Source!AF32*Source!AV32)*Source!I32, 2), 2) -> 2342.21 | R66: =Source!X32 -> 2342.21 | S66: =ROUND((Source!CA32/100)*ROUND((Source!AF32*Source!AV32)*Source!I32, 2), 2) -> 334.6 | T66: =Source!Y32 -> 334.6 | U66: =ROUND((175/100)*ROUND((Source!AE32*Source!AV32)*Source!I32, 2), 2) -> 0.14 | V66: =ROUND((108/100)*ROUND(Source!CS32*Source!I32, 2), 2) -> 0.09
C67: ="Объем: "&Source!I32&"=12/"&"100" -> Объем: 0,12=12/100
C68: ЗП | F68: =Source!AO32 -> 27883.44 | G68: =Source!DG32 | H68: =Source!AV32 -> 1 | I68: =IF(Source!BA32<> 0, Source!BA32, 1) -> 1 | J68: =Source!S32 -> 3346.01
C69: ЭМ | F69: =Source!AM32 -> 32.57 | G69: =Source!DE32 | H69: =Source!AV32 -> 1 | I69: =IF(Source!BB32<> 0, Source!BB32, 1) -> 1 | J69: =Source!Q32 -> 3.91
C70: в т.ч. ЗПМ | F70: =Source!AN32 -> 0.69 | G70: =Source!DF32 | H70: =Source!AV32 -> 1 | I70: =IF(Source!BS32<> 0, Source!BS32, 1) -> 1 | J70: =Source!R32 -> 0.08
C71: НР от ЗП | D71: % | E71: =Source!AT32 -> 70 | J71: =SUM(R66:R70) -> 2342.21
C72: СП от ЗП | D72: % | E72: =Source!AU32 -> 10 | J72: =SUM(T66:T71) -> 334.6
C73: НР и СП от ЗПМ | D73: % | E73: =108 -> 108 | J73: =SUM(V66:V72) -> 0.09
C74: ЗТР | D74: чел-ч | E74: =Source!AQ32 -> 42.81 | G74: =Source!DI32 | H74: =Source!AV32 -> 1 | K74: =Source!U32 -> 5.1372
I75: =J68+J69+J71+J72+J73 -> 6026.82 | K75: =IF(Source!I32<>0, ROUND(I75/Source!I32, 2), 0) -> 50223.5 | P75: =I75 -> 6026.82
A76: 6 | B76: =Source!F33 -> 1.20-3103-1-1/1 | C76: =Source!G33 -> Установка выключателя одноклавишного неутопленного типа при открытой проводке | D76: =Source!H33 -> 100 шт. | E76: =Source!I33 -> 0.02 | Q76: =ROUND((Source!BZ33/100)*ROUND((Source!AF33*Source!AV33)*Source!I33, 2), 2) -> 357.63 | R76: =Source!X33 -> 357.63 | S76: =ROUND((Source!CA33/100)*ROUND((Source!AF33*Source!AV33)*Source!I33, 2), 2) -> 51.09 | T76: =Source!Y33 -> 51.09 | U76: =ROUND((175/100)*ROUND((Source!AE33*Source!AV33)*Source!I33, 2), 2) -> 0.02 | V76: =ROUND((108/100)*ROUND(Source!CS33*Source!I33, 2), 2) -> 0.01
C77: ="Объем: "&Source!I33&"=2/"&"100" -> Объем: 0,02=2/100
C78: ЗП | F78: =Source!AO33 -> 25545.16 | G78: =Source!DG33 | H78: =Source!AV33 -> 1 | I78: =IF(Source!BA33<> 0, Source!BA33, 1) -> 1 | J78: =Source!S33 -> 510.9
C79: ЭМ | F79: =Source!AM33 -> 32.57 | G79: =Source!DE33 | H79: =Source!AV33 -> 1 | I79: =IF(Source!BB33<> 0, Source!BB33, 1) -> 1 | J79: =Source!Q33 -> 0.65
C80: в т.ч. ЗПМ | F80: =Source!AN33 -> 0.69 | G80: =Source!DF33 | H80: =Source!AV33 -> 1 | I80: =IF(Source!BS33<> 0, Source!BS33, 1) -> 1 | J80: =Source!R33 -> 0.01
C81: НР от ЗП | D81: % | E81: =Source!AT33 -> 70 | J81: =SUM(R76:R80) -> 357.63
C82: СП от ЗП | D82: % | E82: =Source!AU33 -> 10 | J82: =SUM(T76:T81) -> 51.09
C83: НР и СП от ЗПМ | D83: % | E83: =108 -> 108 | J83: =SUM(V76:V82) -> 0.01
C84: ЗТР | D84: чел-ч | E84: =Source!AQ33 -> 39.22 | G84: =Source!DI33 | H84: =Source!AV33 -> 1 | K84: =Source!U33 -> 0.7844
I85: =J78+J79+J81+J82+J83 -> 920.28 | K85: =IF(Source!I33<>0, ROUND(I85/Source!I33, 2), 0) -> 46014 | P85: =I85 -> 920.28
A86: 7 | B86: =Source!F34 -> 1.20-3103-1-4/1 | C86: =Source!G34 -> Установка выключателя двухклавишного неутопленного типа при открытой проводке | D86: =Source!H34 -> 100 шт. | E86: =Source!I34 -> 0.02 | Q86: =ROUND((Source!BZ34/100)*ROUND((Source!AF34*Source!AV34)*Source!I34, 2), 2) -> 399.58 | R86: =Source!X34 -> 399.58 | S86: =ROUND((Source!CA34/100)*ROUND((Source!AF34*Source!AV34)*Source!I34, 2), 2) -> 57.08 | T86: =Source!Y34 -> 57.08 | U86: =ROUND((175/100)*ROUND((Source!AE34*Source!AV34)*Source!I34, 2), 2) -> 0.02 | V86: =ROUND((108/100)*ROUND(Source!CS34*Source!I34, 2), 2) -> 0.01
C87: ="Объем: "&Source!I34&"=2/"&"100" -> Объем: 0,02=2/100
C88: ЗП | F88: =Source!AO34 -> 28541.28 | G88: =Source!DG34 | H88: =Source!AV34 -> 1 | I88: =IF(Source!BA34<> 0, Source!BA34, 1) -> 1 | J88: =Source!S34 -> 570.83
C89: ЭМ | F89: =Source!AM34 -> 32.57 | G89: =Source!DE34 | H89: =Source!AV34 -> 1 | I89: =IF(Source!BB34<> 0, Source!BB34, 1) -> 1 | J89: =Source!Q34 -> 0.65
C90: в т.ч. ЗПМ | F90: =Source!AN34 -> 0.69 | G90: =Source!DF34 | H90: =Source!AV34 -> 1 | I90: =IF(Source!BS34<> 0, Source!BS34, 1) -> 1 | J90: =Source!R34 -> 0.01
C91: НР от ЗП | D91: % | E91: =Source!AT34 -> 70 | J91: =SUM(R86:R90) -> 399.58
C92: СП от ЗП | D92: % | E92: =Source!AU34 -> 10 | J92: =SUM(T86:T91) -> 57.08
C93: НР и СП от ЗПМ | D93: % | E93: =108 -> 108 | J93: =SUM(V86:V92) -> 0.01
C94: ЗТР | D94: чел-ч | E94: =Source!AQ34 -> 43.82 | G94: =Source!DI34 | H94: =Source!AV34 -> 1 | K94: =Source!U34 -> 0.8764
I95: =J88+J89+J91+J92+J93 -> 1028.15 | K95: =IF(Source!I34<>0, ROUND(I95/Source!I34, 2), 0) -> 51407.5 | P95: =I95 -> 1028.15
A96: 8 | B96: =Source!F35 -> 1.20-3103-23-1/1 | C96: =Source!G35 -> Установка светильника светодиодного (панели) 595х595 мм в подвесном потолке, устанавливаемого на профиле, со встроенным драйвером / светильник (панель) 595х595х19 мм, 27 Вт, 3000 Лм, 4000 К, IP40 / (демонтаж) | D96: =Source!H35 -> шт. | E96: =Source!I35 -> 22 | Q96: =ROUND((Source!BZ35/100)*ROUND((Source!AF35*Source!AV35)*Source!I35, 2), 2) -> 993.12 | R96: =Source!X35 -> 993.12 | S96: =ROUND((Source!CA35/100)*ROUND((Source!AF35*Source!AV35)*Source!I35, 2), 2) -> 141.87 | T96: =Source!Y35 -> 141.87 | U96: =ROUND((175/100)*ROUND((Source!AE35*Source!AV35)*Source!I35, 2), 2) -> 0 | V96: =ROUND((108/100)*ROUND(Source!CS35*Source!I35, 2), 2) -> 0
C97: ЗП | F97: =Source!AO35 -> 322.44 | G97: =Source!DG35 -> *0,2 | H97: =Source!AV35 -> 1 | I97: =IF(Source!BA35<> 0, Source!BA35, 1) -> 1 | J97: =Source!S35 -> 1418.74
C98: НР от ЗП | D98: % | E98: =Source!AT35 -> 70 | J98: =SUM(R96:R97) -> 993.12
C99: СП от ЗП | D99: % | E99: =Source!AU35 -> 10 | J99: =SUM(T96:T98) -> 141.87
C100: ЗТР | D100: чел-ч | E100: =Source!AQ35 -> 0.56 | G100: =Source!DI35 -> *0,2 | H100: =Source!AV35 -> 1 | K100: =Source!U35 -> 2.464
I101: =J97+J98+J99 -> 2553.73 | K101: =IF(Source!I35<>0, ROUND(I101/Source!I35, 2), 0) -> 116.08 | P101: =I101 -> 2553.73
A102: 9 | B102: =Source!F36 -> 1.20-3103-4-10/1 | C102: =Source!G36 -> Установка светильников с люминесцентными лампами в подвесных потолках, устанавливаемых на подвесках, с количеством ламп в светильнике до 2 | D102: =Source!H36 -> 100 шт. | E102: =Source!I36 -> 0.3 | Q102: =ROUND((Source!BZ36/100)*ROUND((Source!AF36*Source!AV36)*Source!I36, 2), 2) -> 37067.19 | R102: =Source!X36 -> 37067.19 | S102: =ROUND((Source!CA36/100)*ROUND((Source!AF36*Source!AV36)*Source!I36, 2), 2) -> 5295.31 | T102: =Source!Y36 -> 5295.31 | U102: =ROUND((175/100)*ROUND((Source!AE36*Source!AV36)*Source!I36, 2), 2) -> 0.3 | V102: =ROUND((108/100)*ROUND(Source!CS36*Source!I36, 2), 2) -> 0.18
C103: ="Объем: "&Source!I36&"=30/"&"100" -> Объем: 0,3=30/100
C104: ЗП | F104: =Source!AO36 -> 176510.43 | G104: =Source!DG36 | H104: =Source!AV36 -> 1 | I104: =IF(Source!BA36<> 0, Source!BA36, 1) -> 1 | J104: =Source!S36 -> 52953.13
C105: ЭМ | F105: =Source!AM36 -> 79.92 | G105: =Source!DE36 | H105: =Source!AV36 -> 1 | I105: =IF(Source!BB36<> 0, Source!BB36, 1) -> 1 | J105: =Source!Q36 -> 23.98
C106: в т.ч. ЗПМ | F106: =Source!AN36 -> 0.55 | G106: =Source!DF36 | H106: =Source!AV36 -> 1 | I106: =IF(Source!BS36<> 0, Source!BS36, 1) -> 1 | J106: =Source!R36 -> 0.17
C107: МР | F107: =Source!AL36 -> 36190.04 | G107: =Source!DD36 | H107: =Source!AW36 -> 1 | I107: =IF(Source!BC36<> 0, Source!BC36, 1) -> 1 | J107: =Source!P36 -> 10857.01
C108: НР от ЗП | D108: % | E108: =Source!AT36 -> 70 | J108: =SUM(R102:R107) -> 37067.19
C109: СП от ЗП | D109: % | E109: =Source!AU36 -> 10 | J109: =SUM(T102:T108) -> 5295.31
C110: НР и СП от ЗПМ | D110: % | E110: =108 -> 108 | J110: =SUM(V102:V109) -> 0.18
C111: ЗТР | D111: чел-ч | E111: =Source!AQ36 -> 271 | G111: =Source!DI36 | H111: =Source!AV36 -> 1 | K111: =Source!U36 -> 81.3
...

Sheet Дефектная ведомость
A1: =Source!B1 -> Smeta.RU (495) 974-1589
B3: "СОГЛАСОВАНО" | D3: "УТВЕРЖДАЮ"
B5: ___________________________ | C5: ___________________________
B7: ___________________________ | C7: ___________________________
C9: " ___ " ___________ 20 ___ г.
A11: =CONCATENATE("Дефектный акт ", IF(Source!AN15<>"", Source!AN15," ")) -> Дефектный акт
A12: =CONCATENATE("На капитальный ремонт ", Source!G12) -> На капитальный ремонт Электрика новая
B14: Мы, нижеподписавшиеся, произвели осмотр объекта
B15: и постановили произвести ремонт объекта в
B16: следующем объеме:
A17: № п/п | B17: Наименование работ и затрат | C17: Единица измерения | D17: Количество | E17: Примечание
A18: 1 | B18: 2 | C18: 3 | D18: 4 | E18: 5
A19: =CONCATENATE("Локальная смета: ", Source!G20) -> Локальная смета: Новая локальная смета
A20: =CONCATENATE("Раздел: ", Source!G24) -> Раздел: Помещение 312 Актовый зал
A21: 1 | B21: =Source!G28 -> Демонтаж выключателей, розеток | C21: =Source!H28 -> 100 шт. | D21: =Source!I28 -> 0.1
A22: 2 | B22: =Source!G29 -> Прокладка пластикового кабель-канала - по бетонному основанию / сечение 60х40 мм | C22: =Source!H29 -> 100 м | D22: =Source!I29 -> 3.15
A23: 3 | B23: =Source!G30 -> Прокладка проводов и кабелей в лотках, провод сечением до 6 мм2 | C23: =Source!H30 -> 100 м | D23: =Source!I30 -> 3.15
A24: 4 | B24: =Source!G31 -> Кабели силовые, с медными жилами, с изоляц. и оболоч.из ПВХ пластиката пониж.пожар.опасности, не распростр.горение, с пониж.дымо- и газовыделением и с низк.токсич-тью продуктов горения, напряж.1000 В, марка ВВГнг(А)-LSLTx, число жил и сечение, мм2: 3х2,5 | C24: =Source!H31 -> км | D24: =Source!I31 -> 0.27
A25: 5 | B25: =Source!G32 -> Установка розетки штепсельной неутопленного типа при открытой проводке | C25: =Source!H32 -> 100 шт. | D25: =Source!I32 -> 0.12
A26: 6 | B26: =Source!G33 -> Установка выключателя одноклавишного неутопленного типа при открытой проводке | C26: =Source!H33 -> 100 шт. | D26: =Source!I33 -> 0.02
A27: 7 | B27: =Source!G34 -> Установка выключателя двухклавишного неутопленного типа при открытой проводке | C27: =Source!H34 -> 100 шт. | D27: =Source!I34 -> 0.02
A28: 8 | B28: =Source!G35 -> Установка светильника светодиодного (панели) 595х595 мм в подвесном потолке, устанавливаемого на профиле, со встроенным драйвером / светильник (панель) 595х595х19 мм, 27 Вт, 3000 Лм, 4000 К, IP40 / (демонтаж) | C28: =Source!H35 -> шт. | D28: =Source!I35 -> 22
A29: 9 | B29: =Source!G36 -> Установка светильников с люминесцентными лампами в подвесных потолках, устанавливаемых на подвесках, с количеством ламп в светильнике до 2 | C29: =Source!H36 -> 100 шт. | D29: =Source!I36 -> 0.3
A30: 10 | B30: =Source!G37 -> Разводка по устройствам и подключение жил кабелей или проводов внешней сети к блокам зажимов и к зажимам аппаратов и приборов, установленных на устройствах, кабели и провода сечение до 10 мм2 (без стоимости материалов) | C30: =Source!H37 -> 100 жил | D30: =Source!I37 -> 0.9
A31: =CONCATENATE("Раздел: ", Source!G69) -> Раздел: Электрощит ЩАО (актовый зал)
A32: 11 | B32: =Source!G73 -> Установка выключателя установочного автоматического (автомата) или неавтоматического одно-, двух-, трехполюсного на конструкции на стене или колонне на ток до 100 А (демонтаж) | C32: =Source!H73 -> шт. | D32: =Source!I73 -> 13
A33: 12 | B33: =Source!G74 -> Установка выключателя установочного автоматического (автомата) или неавтоматического одно-, двух-, трехполюсного на конструкции на стене или колонне на ток до 100 А | C33: =Source!H74 -> шт. | D33: =Source!I74 -> 13
A34: 12.1 | B34: =Source!G75 -> Выключатели автоматические, серия "Домовой", трехполюсные, тип ВА 63(С), на ток: 50 А, 63 А | C34: =Source!H75 -> шт. | D34: =Source!I75 -> -13
A35: =CONCATENATE("Раздел: ", Source!G107) -> Раздел: Электрощит ЩО (актовый зал)
A36: 13 | B36: =Source!G111 -> Установка выключателя установочного автоматического (автомата) или неавтоматического одно-, двух-, трехполюсного на конструкции на стене или колонне на ток до 100 А (демонтаж) | C36: =Source!H111 -> шт. | D36: =Source!I111 -> 11
A37: 14 | B37: =Source!G112 -> Установка выключателя установочного автоматического (автомата) или неавтоматического одно-, двух-, трехполюсного на конструкции на стене или колонне на ток до 100 А | C37: =Source!H112 -> шт. | D37: =Source!I112 -> 11
A38: 14.1 | B38: =Source!G113 -> Выключатели автоматические, серия "Домовой", трехполюсные, тип ВА 63(С), на ток: 50 А, 63 А | C38: =Source!H113 -> шт. | D38: =Source!I113 -> -11
A39: =CONCATENATE("Раздел: ", Source!G145) -> Раздел: Электрощит РЩ (актовый зал)
A40: 15 | B40: =Source!G149 -> Установка выключателя установочного автоматического (автомата) или неавтоматического одно-, двух-, трехполюсного на конструкции на стене или колонне на ток до 100 А (демонтаж) | C40: =Source!H149 -> шт. | D40: =Source!I149 -> 11
A41: 16 | B41: =Source!G150 -> Установка выключателя установочного автоматического (автомата) или неавтоматического одно-, двух-, трехполюсного на конструкции на стене или колонне на ток до 100 А | C41: =Source!H150 -> шт. | D41: =Source!I150 -> 11
A42: 16.1 | B42: =Source!G151 -> Выключатели автоматические, серия "Домовой", трехполюсные, тип ВА 63(С), на ток: 50 А, 63 А | C42: =Source!H151 -> шт. | D42: =Source!I151 -> -11
A43: =CONCATENATE("Раздел: ", Source!G183) -> Раздел: Помещение 108 Обеденный зал с умывальником
A44: 17 | B44: =Source!G187 -> Демонтаж выключателей, розеток | C44: =Source!H187 -> 100 шт. | D44: =Source!I187 -> 0.12
A45: 18 | B45: =Source!G188 -> Установка розетки штепсельной неутопленного типа при открытой проводке | C45: =Source!H188 -> 100 шт. | D45: =Source!I188 -> 0.1
A46: 19 | B46: =Source!G189 -> Установка выключателя одноклавишного неутопленного типа при открытой проводке | C46: =Source!H189 -> 100 шт. | D46: =Source!I189 -> 0.01
A47: 20 | B47: =Source!G190 -> Установка выключателя двухклавишного неутопленного типа при открытой проводке | C47: =Source!H190 -> 100 шт. | D47: =Source!I190 -> 0.01
A48: 21 | B48: =Source!G191 -> Замена электрополотенца (сушителя для рук) (без стоимости) (монтаж) | C48: =Source!H191 -> шт. | D48: =Source!I191 -> 2
A49: 22 | B49: =Source!G192 -> Разводка по устройствам и подключение жил кабелей или проводов внешней сети к блокам зажимов и к зажимам аппаратов и приборов, установленных на устройствах, кабели и провода сечение до 10 мм2 (без стоимости материалов) | C49: =Source!H192 -> 100 жил | D49: =Source!I192 -> 0.12
A50: =CONCATENATE("Раздел: ", Source!G224) -> Раздел: Помещение 110 Кухня
A51: 23 | B51: =Source!G228 -> Демонтаж выключателей, розеток | C51: =Source!H228 -> 100 шт. | D51: =Source!I228 -> 0.06
A52: 24 | B52: =Source!G229 -> Установка розетки штепсельной неутопленного типа при открытой проводке | C52: =Source!H229 -> 100 шт. | D52: =Source!I229 -> 0.02
A53: 25 | B53: =Source!G230 -> Установка выключателя одноклавишного неутопленного типа при открытой проводке | C53: =Source!H230 -> 100 шт. | D53: =Source!I230 -> 0.04
A54: 26 | B54: =Source!G231 -> Разводка по устройствам и подключение жил кабелей или проводов внешней сети к блокам зажимов и к зажимам аппаратов и приборов, установленных на устройствах, кабели и провода сечение до 10 мм2 (без стоимости материалов) | C54: =Source!H231 -> 100 жил | D54: =Source!I231 -> 1.31
A55: =CONCATENATE("Раздел: ", Source!G263) -> Раздел: Помещение 111 Моечная
A56: 27 | B56: =Source!G267 -> Разводка по устройствам и подключение жил кабелей или проводов внешней сети к блокам зажимов и к зажимам аппаратов и приборов, установленных на устройствах, кабели и провода сечение до 10 мм2 (без стоимости материалов) | C56: =Source!H267 -> 100 жил | D56: =Source!I267 -> 0.08
A57: =CONCATENATE("Раздел: ", Source!G299) -> Раздел: Помещение 116 Душ
A58: 28 | B58: =Source!G303 -> Разводка по устройствам и подключение жил кабелей или проводов внешней сети к блокам зажимов и к зажимам аппаратов и приборов, установленных на устройствах, кабели и провода сечение до 10 мм2 (без стоимости материалов) | C58: =Source!H303 -> 100 жил | D58: =Source!I303 -> 0.03
A59: =CONCATENATE("Раздел: ", Source!G335) -> Раздел: Помещение 117 Коридор
A60: 29 | B60: =Source!G339 -> Демонтаж выключателей, розеток | C60: =Source!H339 -> 100 шт. | D60: =Source!I339 -> 0.03
A61: 30 | B61: =Source!G340 -> Установка выключателя одноклавишного неутопленного типа при открытой проводке | C61: =Source!H340 -> 100 шт. | D61: =Source!I340 -> 0.03
A62: =CONCATENATE("Раздел: ", Source!G372) -> Раздел: Помещение 118 Венткамера
A63: 31 | B63: =Source!G376 -> Демонтаж выключателей, розеток | C63: =Source!H376 -> 100 шт. | D63: =Source!I376 -> 0.01
A64: 32 | B64: =Source!G377 -> Установка выключателя двухклавишного неутопленного типа при открытой проводке | C64: =Source!H377 -> 100 шт. | D64: =Source!I377 -> 0.01
A65: =CONCATENATE("Раздел: ", Source!G409) -> Раздел: Помещение 119 помещение уборочного инвентаря
A66: 33 | B66: =Source!G413 -> Разводка по устройствам и подключение жил кабелей или проводов внешней сети к блокам зажимов и к зажимам аппаратов и приборов, установленных на устройствах, кабели и провода сечение до 10 мм2 (без стоимости материалов) | C66: =Source!H413 -> 100 жил | D66: =Source!I413 -> 0.03
A67: =CONCATENATE("Раздел: ", Source!G445) -> Раздел: Электрощит ТХ1
A68: 34 | B68: =Source!G449 -> Установка выключателя установочного автоматического (автомата) или неавтоматического одно-, двух-, трехполюсного на конструкции на стене или колонне на ток до 25 А (демонтаж) | C68: =Source!H449 -> шт. | D68: =Source!I449 -> 18
A69: 35 | B69: =Source!G450 -> Установка выключателя установочного автоматического (автомата) или неавтоматического одно-, двух-, трехполюсного на конструкции на стене или колонне на ток до 100 А (демонтаж) | C69: =Source!H450 -> шт. | D69: =Source!I450 -> 6
A70: 36 | B70: =Source!G451 -> Установка выключателя установочного автоматического (автомата) или неавтоматического одно-, двух-, трехполюсного на конструкции на стене или колонне на ток до 25 А | C70: =Source!H451 -> шт. | D70: =Source!I451 -> 18
A71: 36.1 | B71: =Source!G452 -> Выключатели автоматические, серия "Домовой", однополюсные с нейтралью, тип ВА 63(С), на ток: 10 А - 40 А | C71: =Source!H452 -> шт. | D71: =Source!I452 -> -18
A72: 37 | B72: =Source!G453 -> Установка выключателя установочного автоматического (автомата) или неавтоматического одно-, двух-, трехполюсного на конструкции на стене или колонне на ток до 100 А (демонтаж) | C72: =Source!H453 -> шт. | D72: =Source!I453 -> 6
A73: 37.1 | B73: =Source!G454 -> Выключатели автоматические, серия "Домовой", трехполюсные, тип ВА 63(С), на ток: 50 А, 63 А | C73: =Source!H454 -> шт. | D73: =Source!I454 -> -6
A74: =CONCATENATE("Раздел: ", Source!G486) -> Раздел: Электрощит ТХ2
A75: 38 | B75: =Source!G490 -> Установка выключателя установочного автоматического (автомата) или неавтоматического одно-, двух-, трехполюсного на конструкции на стене или колонне на ток до 25 А (демонтаж) | C75: =Source!H490 -> шт. | D75: =Source!I490 -> 14
A76: 39 | B76: =Source!G491 -> Установка выключателя установочного автоматического (автомата) или неавтоматического одно-, двух-, трехполюсного на конструкции на стене или колонне на ток до 100 А (демонтаж) | C76: =Source!H491 -> шт. | D76: =Source!I491 -> 1
A77: 40 | B77: =Source!G492 -> Установка выключателя установочного автоматического (автомата) или неавтоматического одно-, двух-, трехполюсного на конструкции на стене или колонне на ток до 25 А | C77: =Source!H492 -> шт. | D77: =Source!I492 -> 14
A78: 40.1 | B78: =Source!G493 -> Выключатели автоматические, серия "Домовой", однополюсные с нейтралью, тип ВА 63(С), на ток: 10 А - 40 А | C78: =Source!H493 -> шт. | D78: =Source!I493 -> -14
A79: 41 | B79: =Source!G494 -> Установка выключателя установочного автоматического (автомата) или неавтоматического одно-, двух-, трехполюсного на конструкции на стене или колонне на ток до 100 А (демонтаж) | C79: =Source!H494 -> шт. | D79: =Source!I494 -> 1
A80: 41.1 | B80: =Source!G495 -> Выключатели автоматические, серия "Домовой", трехполюсные, тип ВА 63(С), на ток: 50 А, 63 А | C80: =Source!H495 -> шт. | D80: =Source!I495 -> -1
A81: =CONCATENATE("Раздел: ", Source!G527) -> Раздел: Электрощит ТХ3
A82: 42 | B82: =Source!G531 -> Установка выключателя установочного автоматического (автомата) или неавтоматического одно-, двух-, трехполюсного на конструкции на стене или колонне на ток до 25 А (демонтаж) | C82: =Source!H531 -> шт. | D82: =Source!I531 -> 6
A83: 43 | B83: =Source!G532 -> Установка выключателя установочного автоматического (автомата) или неавтоматического одно-, двух-, трехполюсного на конструкции на стене или колонне на ток до 100 А (демонтаж) | C83: =Source!H532 -> шт. | D83: =Source!I532 -> 1
A84: 44 | B84: =Source!G533 -> Установка выключателя установочного автоматического (автомата) или неавтоматического одно-, двух-, трехполюсного на конструкции на стене или колонне на ток до 25 А | C84: =Source!H533 -> шт. | D84: =Source!I533 -> 8
A85: 44.1 | B85: =Source!G534 -> Выключатели автоматические, серия "Домовой", однополюсные с нейтралью, тип ВА 63(С), на ток: 10 А - 40 А | C85: =Source!H534 -> шт. | D85: =Source!I534 -> -8
A86: 45 | B86: =Source!G535 -> Установка выключателя установочного автоматического (автомата) или неавтоматического одно-, двух-, трехполюсного на конструкции на стене или колонне на ток до 100 А (демонтаж) | C86: =Source!H535 -> шт. | D86: =Source!I535 -> 1
A87: 45.1 | B87: =Source!G536 -> Выключатели автоматические, серия "Домовой", трехполюсные, тип ВА 63(С), на ток: 50 А, 63 А | C87: =Source!H536 -> шт. | D87: =Source!I536 -> -1
A88: =CONCATENATE("Раздел: ", Source!G568) -> Раздел: Помещение 104 Вестибюль
A89: 46 | B89: =Source!G572 -> Демонтаж выключателей, розеток | C89: =Source!H572 -> 100 шт. | D89: =Source!I572 -> 0.05
A90: 47 | B90: =Source!G573 -> Прокладка пластикового кабель-канала - по кирпичному основанию / сечение 105х50 мм (демонтаж) | C90: =Source!H573 -> 100 м | D90: =Source!I573 -> 0.01
A91: 48 | B91: =Source!G574 -> Прокладка пластикового кабель-канала - по кирпичному основанию / сечение 105х50 мм | C91: =Source!H574 -> 100 м | D91: =Source!I574 -> 0.01
A92: 49 | B92: =Source!G575 -> Розетки (механизмы) штепсельные, серия "Мозаик", тип 2К+3, с винтовыми зажимами, с защитными шторками и заземляющим контактом | C92: =Source!H575 -> шт. | D92: =Source!I575 -> 3
A93: 50 | B93: =Source!G576 -> Установка нового рабочего места в составе ЛВС, установка розетки | C93: =Source!H576 -> шт. | D93: =Source!I576 -> 2
A94: =CONCATENATE("Раздел: ", Source!G608) -> Раздел: Помещение 123 Электрощитовая
A95: 51 | B95: =Source!G612 -> прозвон* | C95: =Source!H612 | D95: =Source!I612 -> 0
A96: 52 | B96: =Source!G613 | C96: =Source!H613 | D96: =Source!I613 -> 0
A97: =CONCATENATE("Раздел: ", Source!G645) -> Раздел: Помещение 125 Водомерный узел
A98: 53 | B98: =Source!G649 -> Демонтаж выключателей, розеток | C98: =Source!H649 -> 100 шт. | D98: =Source!I649 -> 0.03
A99: 54 | B99: =Source!G650 -> Установка розетки штепсельной неутопленного типа при открытой проводке | C99: =Source!H650 -> 100 шт. | D99: =Source!I650 -> 0.02
A100: 55 | B100: =Source!G651 -> Установка выключателя одноклавишного неутопленного типа при открытой проводке | C100: =Source!H651 -> 100 шт. | D100: =Source!I651 -> 0.01
A101: =CONCATENATE("Раздел: ", Source!G683) -> Раздел: Помещение 126 Комната охраны
A102: 56 | B102: =Source!G687 -> Демонтаж выключателей, розеток | C102: =Source!H687 -> 100 шт. | D102: =Source!I687 -> 0.14
A103: 57 | B103: =Source!G688 -> Установка розетки штепсельной неутопленного типа при открытой проводке | C103: =Source!H688 -> 100 шт. | D103: =Source!I688 -> 0.05
A104: 58 | B104: =Source!G689 -> Установка выключателя одноклавишного неутопленного типа при открытой проводке | C104: =Source!H689 -> 100 шт. | D104: =Source!I689 -> 0.01
A105: 59 | B105: =Source!G690 -> Установка выключателя двухклавишного неутопленного типа при открытой проводке | C105: =Source!H690 -> 100 шт. | D105: =Source!I690 -> 0.08
A106: =CONCATENATE("Раздел: ", Source!G722) -> Раздел: Помещение 127 Подсобное помещение
...

Sheet RV_DATA
A1: BuildingFinished | B1: Trud | C1: Mash | D1: Mat | E1: MatZak | F1: Oborud | G1: OborudZak | H1: ZeroStoim | I1: NegativeKoll | J1: ReUnionKollResurcy | K1: UnionOneUchRes | L1: IdLevel | M1: ViewCodes | N1: UnionCodes | O1: PEREVOZKA
A2: 1 | B2: 0 | C2: 0 | D2: 1 | E2: 1 | F2: 1 | G2: 1 | H2: 0 | I2: 1 | J2: 0 | K2: 1 | L2: 35364244 | M2: 0 | N2: 0 | O2: 0
A4: TYPE | B4: SOURCE_LINK | C4: RABMAT_EX | D4: TIP_RAB | E4: TYPE_TRUD | F4: TAB | G4: NAME | H4: EDIZM | I4: KOLL | J4: UCH | K4: PRICE_B | L4: PRICE_ED | M4: STOIM_B | N4: PRICE_C | O4: STOIM_C | P4: ZPM_B | Q4: ZPM_ED | R4: STOIM_ZPM_B | S4: ZPM_C | T4: STOIM_ZPM_C | U4: RABMAT | V4: WBS | W4: CBSI | X4: CBSII | Y4: TechSpecCVORPP | Z4: CRC_GR_RES | AA4: CRC_B | AB4: CRC_C
A6: =Source!A20 -> 3 | B6: 20 | G6: =Source!G20 -> Новая локальная смета
A7: =Source!A24 -> 4 | B7: 24 | G7: =Source!G24 -> Помещение 312 Актовый зал
A8: 20 | B8: 14 | C8: 3 | D8: 0 | E8: =SmtRes!AV14 -> 0 | F8: =SmtRes!I14 -> 21.7-3-54 | G8: =SmtRes!K14 -> Сверло с алмазным покрытием, диаметр 6 мм | H8: =SmtRes!O14 -> шт. | I8: =SmtRes!Y14*Source!I29 -> 12.6 | J8: =SmtRes!AO14 -> 1 | K8: =SmtRes!AE14 -> 1555.5 | L8: =SmtRes!DB14 -> 6222 | M8: =ROUND(ROUND(L8*Source!I29, 6)*1, 2) -> 19599.3 | N8: =SmtRes!AA14 -> 1555.5 | O8: =ROUND(ROUND(L8*Source!I29, 6)*SmtRes!DA14, 2) -> 19599.3 | P8: =SmtRes!AG14 -> 0 | Q8: =SmtRes!DC14 -> 0 | R8: =ROUND(ROUND(Q8*Source!I29, 6)*1, 2) -> 0 | S8: =SmtRes!AC14 -> 0 | T8: =ROUND(ROUND(Q8*Source!I29, 6)*SmtRes!AK14, 2) -> 0 | U8: 3 | Z8: =SmtRes!X14 -> 1662095060 | AA8: -618828638 | AB8: -618828638
A9: 20 | B9: 13 | C9: 3 | D9: 0 | E9: =SmtRes!AV13 -> 0 | F9: =SmtRes!I13 -> 21.1-25-1034 | G9: =SmtRes!K13 -> Кабель-каналы, размер 60х40 мм: углы плоские | H9: =SmtRes!O13 -> шт. | I9: =SmtRes!Y13*Source!I29 -> 6.3 | J9: =SmtRes!AO13 -> 1 | K9: =SmtRes!AE13 -> 214.92 | L9: =SmtRes!DB13 -> 429.84 | M9: =ROUND(ROUND(L9*Source!I29, 6)*1, 2) -> 1354 | N9: =SmtRes!AA13 -> 214.92 | O9: =ROUND(ROUND(L9*Source!I29, 6)*SmtRes!DA13, 2) -> 1354 | P9: =SmtRes!AG13 -> 0 | Q9: =SmtRes!DC13 -> 0 | R9: =ROUND(ROUND(Q9*Source!I29, 6)*1, 2) -> 0 | S9: =SmtRes!AC13 -> 0 | T9: =ROUND(ROUND(Q9*Source!I29, 6)*SmtRes!AK13, 2) -> 0 | U9: 3 | Z9: =SmtRes!X13 -> -1452375277 | AA9: 1614893387 | AB9: 1614893387
A10: 20 | B10: 12 | C10: 3 | D10: 0 | E10: =SmtRes!AV12 -> 0 | F10: =SmtRes!I12 -> 21.1-25-1033 | G10: =SmtRes!K12 -> Кабель-каналы, размер 60х40 мм: углы наружные | H10: =SmtRes!O12 -> шт. | I10: =SmtRes!Y12*Source!I29 -> 47.25 | J10: =SmtRes!AO12 -> 1 | K10: =SmtRes!AE12 -> 203.06 | L10: =SmtRes!DB12 -> 3045.9 | M10: =ROUND(ROUND(L10*Source!I29, 6)*1, 2) -> 9594.59 | N10: =SmtRes!AA12 -> 203.06 | O10: =ROUND(ROUND(L10*Source!I29, 6)*SmtRes!DA12, 2) -> 9594.59 | P10: =SmtRes!AG12 -> 0 | Q10: =SmtRes!DC12 -> 0 | R10: =ROUND(ROUND(Q10*Source!I29, 6)*1, 2) -> 0 | S10: =SmtRes!AC12 -> 0 | T10: =ROUND(ROUND(Q10*Source!I29, 6)*SmtRes!AK12, 2) -> 0 | U10: 3 | Z10: =SmtRes!X12 -> 1479709201 | AA10: -124735961 | AB10: -124735961
A11: 20 | B11: 11 | C11: 3 | D11: 0 | E11: =SmtRes!AV11 -> 0 | F11: =SmtRes!I11 -> 21.1-25-1032 | G11: =SmtRes!K11 -> Кабель-каналы, размер 60х40 мм: углы внутренние | H11: =SmtRes!O11 -> шт. | I11: =SmtRes!Y11*Source!I29 -> 6.3 | J11: =SmtRes!AO11 -> 1 | K11: =SmtRes!AE11 -> 186.55 | L11: =SmtRes!DB11 -> 373.1 | M11: =ROUND(ROUND(L11*Source!I29, 6)*1, 2) -> 1175.27 | N11: =SmtRes!AA11 -> 186.55 | O11: =ROUND(ROUND(L11*Source!I29, 6)*SmtRes!DA11, 2) -> 1175.27 | P11: =SmtRes!AG11 -> 0 | Q11: =SmtRes!DC11 -> 0 | R11: =ROUND(ROUND(Q11*Source!I29, 6)*1, 2) -> 0 | S11: =SmtRes!AC11 -> 0 | T11: =ROUND(ROUND(Q11*Source!I29, 6)*SmtRes!AK11, 2) -> 0 | U11: 3 | Z11: =SmtRes!X11 -> -32305080 | AA11: -1064398607 | AB11: -1064398607
A12: 20 | B12: 10 | C12: 3 | D12: 0 | E12: =SmtRes!AV10 -> 0 | F12: =SmtRes!I10 -> 21.1-25-1031 | G12: =SmtRes!K10 -> Кабель-каналы, размер 60х40 мм: тройники | H12: =SmtRes!O10 -> шт. | I12: =SmtRes!Y10*Source!I29 -> 6.3 | J12: =SmtRes!AO10 -> 1 | K12: =SmtRes!AE10 -> 219.52 | L12: =SmtRes!DB10 -> 439.04 | M12: =ROUND(ROUND(L12*Source!I29, 6)*1, 2) -> 1382.98 | N12: =SmtRes!AA10 -> 219.52 | O12: =ROUND(ROUND(L12*Source!I29, 6)*SmtRes!DA10, 2) -> 1382.98 | P12: =SmtRes!AG10 -> 0 | Q12: =SmtRes!DC10 -> 0 | R12: =ROUND(ROUND(Q12*Source!I29, 6)*1, 2) -> 0 | S12: =SmtRes!AC10 -> 0 | T12: =ROUND(ROUND(Q12*Source!I29, 6)*SmtRes!AK10, 2) -> 0 | U12: 3 | Z12: =SmtRes!X10 -> 1816340030 | AA12: -1841828503 | AB12: -1841828503
A13: 20 | B13: 9 | C13: 3 | D13: 0 | E13: =SmtRes!AV9 -> 0 | F13: =SmtRes!I9 -> 21.1-25-1029 | G13: =SmtRes!K9 -> Кабель-каналы, размер 60х40 мм: накладки стыковые | H13: =SmtRes!O9 -> шт. | I13: =SmtRes!Y9*Source!I29 -> 12.6 | J13: =SmtRes!AO9 -> 1 | K13: =SmtRes!AE9 -> 126.89 | L13: =SmtRes!DB9 -> 507.56 | M13: =ROUND(ROUND(L13*Source!I29, 6)*1, 2) -> 1598.81 | N13: =SmtRes!AA9 -> 126.89 | O13: =ROUND(ROUND(L13*Source!I29, 6)*SmtRes!DA9, 2) -> 1598.81 | P13: =SmtRes!AG9 -> 0 | Q13: =SmtRes!DC9 -> 0 | R13: =ROUND(ROUND(Q13*Source!I29, 6)*1, 2) -> 0 | S13: =SmtRes!AC9 -> 0 | T13: =ROUND(ROUND(Q13*Source!I29, 6)*SmtRes!AK9, 2) -> 0 | U13: 3 | Z13: =SmtRes!X9 -> -1376764488 | AA13: 1140495319 | AB13: 1140495319
A14: 20 | B14: 8 | C14: 3 | D14: 0 | E14: =SmtRes!AV8 -> 0 | F14: =SmtRes!I8 -> 21.1-25-1028 | G14: =SmtRes!K8 -> Кабель-каналы, размер 60х40 мм: заглушки | H14: =SmtRes!O8 -> шт. | I14: =SmtRes!Y8*Source!I29 -> 47.25 | J14: =SmtRes!AO8 -> 1 | K14: =SmtRes!AE8 -> 145.46 | L14: =SmtRes!DB8 -> 2181.9 | M14: =ROUND(ROUND(L14*Source!I29, 6)*1, 2) -> 6872.99 | N14: =SmtRes!AA8 -> 145.46 | O14: =ROUND(ROUND(L14*Source!I29, 6)*SmtRes!DA8, 2) -> 6872.99 | P14: =SmtRes!AG8 -> 0 | Q14: =SmtRes!DC8 -> 0 | R14: =ROUND(ROUND(Q14*Source!I29, 6)*1, 2) -> 0 | S14: =SmtRes!AC8 -> 0 | T14: =ROUND(ROUND(Q14*Source!I29, 6)*SmtRes!AK8, 2) -> 0 | U14: 3 | Z14: =SmtRes!X8 -> -1986506557 | AA14: 368106192 | AB14: 368106192
A15: 20 | B15: 7 | C15: 3 | D15: 0 | E15: =SmtRes!AV7 -> 0 | F15: =SmtRes!I7 -> 21.1-25-1027 | G15: =SmtRes!K7 -> Кабель-каналы, размер 60х40 мм: кабель-каналы | H15: =SmtRes!O7 -> м | I15: =SmtRes!Y7*Source!I29 -> 315 | J15: =SmtRes!AO7 -> 1 | K15: =SmtRes!AE7 -> 138.94 | L15: =SmtRes!DB7 -> 13894 | M15: =ROUND(ROUND(L15*Source!I29, 6)*1, 2) -> 43766.1 | N15: =SmtRes!AA7 -> 138.94 | O15: =ROUND(ROUND(L15*Source!I29, 6)*SmtRes!DA7, 2) -> 43766.1 | P15: =SmtRes!AG7 -> 0 | Q15: =SmtRes!DC7 -> 0 | R15: =ROUND(ROUND(Q15*Source!I29, 6)*1, 2) -> 0 | S15: =SmtRes!AC7 -> 0 | T15: =ROUND(ROUND(Q15*Source!I29, 6)*SmtRes!AK7, 2) -> 0 | U15: 3 | Z15: =SmtRes!X7 -> 1471616812 | AA15: -402984879 | AB15: -402984879
A16: 20 | B16: 6 | C16: 3 | D16: 0 | E16: =SmtRes!AV6 -> 0 | F16: =SmtRes!I6 -> 21.1-11-81 | G16: =SmtRes!K6 -> Патроны, калибр 6,8/11 М для дюбеля | H16: =SmtRes!O6 -> 100 шт. | I16: =SmtRes!Y6*Source!I29 -> 12.6 | J16: =SmtRes!AO6 -> 1 | K16: =SmtRes!AE6 -> 997.35 | L16: =SmtRes!DB6 -> 3989.4 | M16: =ROUND(ROUND(L16*Source!I29, 6)*1, 2) -> 12566.61 | N16: =SmtRes!AA6 -> 997.35 | O16: =ROUND(ROUND(L16*Source!I29, 6)*SmtRes!DA6, 2) -> 12566.61 | P16: =SmtRes!AG6 -> 0 | Q16: =SmtRes!DC6 -> 0 | R16: =ROUND(ROUND(Q16*Source!I29, 6)*1, 2) -> 0 | S16: =SmtRes!AC6 -> 0 | T16: =ROUND(ROUND(Q16*Source!I29, 6)*SmtRes!AK6, 2) -> 0 | U16: 3 | Z16: =SmtRes!X6 -> 1583670906 | AA16: -274985448 | AB16: -274985448
A17: 20 | B17: 5 | C17: 3 | D17: 0 | E17: =SmtRes!AV5 -> 0 | F17: =SmtRes!I5 -> 21.1-11-108 | G17: =SmtRes!K5 -> Шурупы-саморезы, размер 3,5х45 мм | H17: =SmtRes!O5 -> т | I17: =SmtRes!Y5*Source!I29 -> 0.002331 | J17: =SmtRes!AO5 -> 1 | K17: =SmtRes!AE5 -> 190540.34 | L17: =SmtRes!DB5 -> 141 | M17: =ROUND(ROUND(L17*Source!I29, 6)*1, 2) -> 444.15 | N17: =SmtRes!AA5 -> 190540.34 | O17: =ROUND(ROUND(L17*Source!I29, 6)*SmtRes!DA5, 2) -> 444.15 | P17: =SmtRes!AG5 -> 0 | Q17: =SmtRes!DC5 -> 0 | R17: =ROUND(ROUND(Q17*Source!I29, 6)*1, 2) -> 0 | S17: =SmtRes!AC5 -> 0 | T17: =ROUND(ROUND(Q17*Source!I29, 6)*SmtRes!AK5, 2) -> 0 | U17: 3 | Z17: =SmtRes!X5 -> -181271767 | AA17: -2066596354 | AB17: -2066596354
A18: 20 | B18: 23 | C18: 3 | D18: 0 | E18: =SmtRes!AV23 -> 0 | F18: =SmtRes!I23 -> 21.23-13-14 | G18: =SmtRes!K23 -> Провода силовые с медными жилами в поливинилхлоридной изоляции, марка ПуГВ, номинальное напряжение до 450 В, число жил и сечение 1х6 мм2 | H18: =SmtRes!O23 -> км | I18: =SmtRes!Y23*Source!I30 -> 0.32445 | J18: =SmtRes!AO23 -> 1 | K18: =SmtRes!AE23 -> 99643.05 | L18: =SmtRes!DB23 -> 10263.23 | M18: =ROUND(ROUND(L18*Source!I30, 6)*1, 2) -> 32329.17 | N18: =SmtRes!AA23 -> 99643.05 | O18: =ROUND(ROUND(L18*Source!I30, 6)*SmtRes!DA23, 2) -> 32329.17 | P18: =SmtRes!AG23 -> 0 | Q18: =SmtRes!DC23 -> 0 | R18: =ROUND(ROUND(Q18*Source!I30, 6)*1, 2) -> 0 | S18: =SmtRes!AC23 -> 0 | T18: =ROUND(ROUND(Q18*Source!I30, 6)*SmtRes!AK23, 2) -> 0 | U18: 3 | Z18: =SmtRes!X23 -> 1173250179 | AA18: -458052105 | AB18: -458052105
A19: 20 | B19: 22 | C19: 3 | D19: 0 | E19: =SmtRes!AV22 -> 0 | F19: =SmtRes!I22 -> 21.21-5-44 | G19: =SmtRes!K22 -> Кнопки для ленты ЛМ, тип 3,5 | H19: =SmtRes!O22 -> 1000 шт. | I19: =SmtRes!Y22*Source!I30 -> 0.063 | J19: =SmtRes!AO22 -> 1 | K19: =SmtRes!AE22 -> 258.44 | L19: =SmtRes!DB22 -> 5.17 | M19: =ROUND(ROUND(L19*Source!I30, 6)*1, 2) -> 16.29 | N19: =SmtRes!AA22 -> 258.44 | O19: =ROUND(ROUND(L19*Source!I30, 6)*SmtRes!DA22, 2) -> 16.29 | P19: =SmtRes!AG22 -> 0 | Q19: =SmtRes!DC22 -> 0 | R19: =ROUND(ROUND(Q19*Source!I30, 6)*1, 2) -> 0 | S19: =SmtRes!AC22 -> 0 | T19: =ROUND(ROUND(Q19*Source!I30, 6)*SmtRes!AK22, 2) -> 0 | U19: 3 | Z19: =SmtRes!X22 -> -1680055193 | AA19: -2054620093 | AB19: -2054620093
A20: 20 | B20: 21 | C20: 3 | D20: 0 | E20: =SmtRes!AV21 -> 0 | F20: =SmtRes!I21 -> 21.21-5-342 | G20: =SmtRes!K21 -> Хомуты (стяжки) кабельные из полиамида, размеры 3,6х200 мм | H20: =SmtRes!O21 -> 100 шт. | I20: =SmtRes!Y21*Source!I30 -> 0.819 | J20: =SmtRes!AO21 -> 1 | K20: =SmtRes!AE21 -> 127.48 | L20: =SmtRes!DB21 -> 33.14 | M20: =ROUND(ROUND(L20*Source!I30, 6)*1, 2) -> 104.39 | N20: =SmtRes!AA21 -> 127.48 | O20: =ROUND(ROUND(L20*Source!I30, 6)*SmtRes!DA21, 2) -> 104.39 | P20: =SmtRes!AG21 -> 0 | Q20: =SmtRes!DC21 -> 0 | R20: =ROUND(ROUND(Q20*Source!I30, 6)*1, 2) -> 0 | S20: =SmtRes!AC21 -> 0 | T20: =ROUND(ROUND(Q20*Source!I30, 6)*SmtRes!AK21, 2) -> 0 | U20: 3 | Z20: =SmtRes!X21 -> 527662241 | AA20: -1533345047 | AB20: -1533345047
A21: 20 | B21: 20 | C21: 3 | D21: 0 | E21: =SmtRes!AV20 -> 0 | F21: =SmtRes!I20 -> 21.21-5-305 | G21: =SmtRes!K20 -> Сжимы, тип У731М для проводников магистральных сечением от 4 до 10 мм2 и ответвительных от 1,5 до 10 мм2 | H21: =SmtRes!O20 -> шт. | I21: =SmtRes!Y20*Source!I30 -> 31.5 | J21: =SmtRes!AO20 -> 1 | K21: =SmtRes!AE20 -> 29.36 | L21: =SmtRes!DB20 -> 293.6 | M21: =ROUND(ROUND(L21*Source!I30, 6)*1, 2) -> 924.84 | N21: =SmtRes!AA20 -> 29.36 | O21: =ROUND(ROUND(L21*Source!I30, 6)*SmtRes!DA20, 2) -> 924.84 | P21: =SmtRes!AG20 -> 0 | Q21: =SmtRes!DC20 -> 0 | R21: =ROUND(ROUND(Q21*Source!I30, 6)*1, 2) -> 0 | S21: =SmtRes!AC20 -> 0 | T21: =ROUND(ROUND(Q21*Source!I30, 6)*SmtRes!AK20, 2) -> 0 | U21: 3 | Z21: =SmtRes!X20 -> 1884843886 | AA21: 1143219249 | AB21: 1143219249
A22: 20 | B22: 19 | C22: 3 | D22: 0 | E22: =SmtRes!AV19 -> 0 | F22: =SmtRes!I19 -> 21.21-5-2 | G22: =SmtRes!K19 -> Бирки маркировочные для кабелей и проводов, тип У153 У3,5 | H22: =SmtRes!O19 -> 1000 шт. | I22: =SmtRes!Y19*Source!I30 -> 0.01575 | J22: =SmtRes!AO19 -> 1 | K22: =SmtRes!AE19 -> 718.56 | L22: =SmtRes!DB19 -> 3.59 | M22: =ROUND(ROUND(L22*Source!I30, 6)*1, 2) -> 11.31 | N22: =SmtRes!AA19 -> 718.56 | O22: =ROUND(ROUND(L22*Source!I30, 6)*SmtRes!DA19, 2) -> 11.31 | P22: =SmtRes!AG19 -> 0 | Q22: =SmtRes!DC19 -> 0 | R22: =ROUND(ROUND(Q22*Source!I30, 6)*1, 2) -> 0 | S22: =SmtRes!AC19 -> 0 | T22: =ROUND(ROUND(Q22*Source!I30, 6)*SmtRes!AK19, 2) -> 0 | U22: 3 | Z22: =SmtRes!X19 -> -1948375318 | AA22: 299589489 | AB22: 299589489
A23: 20 | B23: 18 | C23: 3 | D23: 0 | E23: =SmtRes!AV18 -> 0 | F23: =SmtRes!I18 -> 21.21-5-114 | G23: =SmtRes!K18 -> Лента монтажная, тип ЛМ-5 | H23: =SmtRes!O18 -> м | I23: =SmtRes!Y18*Source!I30 -> 15.75 | J23: =SmtRes!AO18 -> 1 | K23: =SmtRes!AE18 -> 5.71 | L23: =SmtRes!DB18 -> 28.55 | M23: =ROUND(ROUND(L23*Source!I30, 6)*1, 2) -> 89.93 | N23: =SmtRes!AA18 -> 5.71 | O23: =ROUND(ROUND(L23*Source!I30, 6)*SmtRes!DA18, 2) -> 89.93 | P23: =SmtRes!AG18 -> 0 | Q23: =SmtRes!DC18 -> 0 | R23: =ROUND(ROUND(Q23*Source!I30, 6)*1, 2) -> 0 | S23: =SmtRes!AC18 -> 0 | T23: =ROUND(ROUND(Q23*Source!I30, 6)*SmtRes!AK18, 2) -> 0 | U23: 3 | Z23: =SmtRes!X18 -> -1189895200 | AA23: 193152040 | AB23: 193152040
A24: 20 | B24: 17 | C24: 3 | D24: 0 | E24: =SmtRes!AV17 -> 0 | F24: =SmtRes!I17 -> 21.1-20-10 | G24: =SmtRes!K17 -> Лента изоляционная хлопчатобумажная | H24: =SmtRes!O17 -> кг | I24: =SmtRes!Y17*Source!I30 -> 0.504 | J24: =SmtRes!AO17 -> 1 | K24: =SmtRes!AE17 -> 363.22 | L24: =SmtRes!DB17 -> 58.12 | M24: =ROUND(ROUND(L24*Source!I30, 6)*1, 2) -> 183.08 | N24: =SmtRes!AA17 -> 363.22 | O24: =ROUND(ROUND(L24*Source!I30, 6)*SmtRes!DA17, 2) -> 183.08 | P24: =SmtRes!AG17 -> 0 | Q24: =SmtRes!DC17 -> 0 | R24: =ROUND(ROUND(Q24*Source!I30, 6)*1, 2) -> 0 | S24: =SmtRes!AC17 -> 0 | T24: =ROUND(ROUND(Q24*Source!I30, 6)*SmtRes!AK17, 2) -> 0 | U24: 3 | Z24: =SmtRes!X17 -> 1719425291 | AA24: -1596111638 | AB24: -1596111638
A25: =Source!A31 -> 17 | B25: 31 | C25: 3 | D25: =Source!BI31 -> 4 | E25: =Source!FS31 -> 0 | F25: =Source!F31 -> 21.23-8-270 | G25: =Source!G31 -> Кабели силовые, с медными жилами, с изоляц. и оболоч.из ПВХ пластиката пониж.пожар.опасности, не распростр.горение, с пониж.дымо- и газовыделением и с низк.токсич-тью продуктов горения, напряж.1000 В, марка ВВГнг(А)-LSLTx, число жил и сечение, мм2: 3х2,5 | H25: =Source!H31 -> км | I25: =Source!I31 -> 0.27 | J25: 1 | K25: =Source!AC31 -> 129532.62 | M25: =ROUND(K25*I25, 2) -> 34973.81 | N25: =Source!AC31*IF(Source!BC31<> 0, Source!BC31, 1) -> 129532.62 | O25: =ROUND(N25*I25, 2) -> 34973.81 | P25: =Source!AE31 -> 0 | R25: =ROUND(P25*I25, 2) -> 0 | S25: =Source!AE31*IF(Source!BS31<> 0, Source!BS31, 1) -> 0 | T25: =ROUND(S25*I25, 2) -> 0 | U25: 3 | Z25: =Source!GF31 -> 7717958 | AA25: 2094450950 | AB25: 2094450950
A26: 20 | B26: 44 | C26: 3 | D26: 0 | E26: =SmtRes!AV44 -> 0 | F26: =SmtRes!I44 -> 21.7-4-15 | G26: =SmtRes!K44 -> Профили стоек металлические для монтажа гипсовых перегородок и подвесных потолков стальные, оцинкованные, марка ПСЭ-2, сечение 50х35х0,55 мм | H26: =SmtRes!O44 -> т | I26: =SmtRes!Y44*Source!I36 -> 0.0108 | J26: =SmtRes!AO44 -> 1 | K26: =SmtRes!AE44 -> 40246.74 | L26: =SmtRes!DB44 -> 1448.88 | M26: =ROUND(ROUND(L26*Source!I36, 6)*1, 2) -> 434.66 | N26: =SmtRes!AA44 -> 40246.74 | O26: =ROUND(ROUND(L26*Source!I36, 6)*SmtRes!DA44, 2) -> 434.66 | P26: =SmtRes!AG44 -> 0 | Q26: =SmtRes!DC44 -> 0 | R26: =ROUND(ROUND(Q26*Source!I36, 6)*1, 2) -> 0 | S26: =SmtRes!AC44 -> 0 | T26: =ROUND(ROUND(Q26*Source!I36, 6)*SmtRes!AK44, 2) -> 0 | U26: 3 | Z26: =SmtRes!X44 -> -493677975 | AA26: 162372630 | AB26: 162372630
A27: 20 | B27: 43 | C27: 3 | D27: 0 | E27: =SmtRes!AV43 -> 0 | F27: =SmtRes!I43 -> 21.23-8-258 | G27: =SmtRes!K43 -> Кабели силовые с медными жилами с поливинилхлоридной изоляцией в оболочке из поливинилхлоридного пластиката пониженной горючести, напряжение 660 В, марка ВВГнг(А), число жил и сечение, мм2: 1х 4 | H27: =SmtRes!O43 -> км | I27: =SmtRes!Y43*Source!I36 -> 0.0108 | J27: =SmtRes!AO43 -> 1 | K27: =SmtRes!AE43 -> 47900.07 | L27: =SmtRes!DB43 -> 1724.4 | M27: =ROUND(ROUND(L27*Source!I36, 6)*1, 2) -> 517.32 | N27: =SmtRes!AA43 -> 47900.07 | O27: =ROUND(ROUND(L27*Source!I36, 6)*SmtRes!DA43, 2) -> 517.32 | P27: =SmtRes!AG43 -> 0 | Q27: =SmtRes!DC43 -> 0 | R27: =ROUND(ROUND(Q27*Source!I36, 6)*1, 2) -> 0 | S27: =SmtRes!AC43 -> 0 | T27: =ROUND(ROUND(Q27*Source!I36, 6)*SmtRes!AK43, 2) -> 0 | U27: 3 | Z27: =SmtRes!X43 -> 286422571 | AA27: 249487062 | AB27: 249487062
A28: 20 | B28: 42 | C28: 3 | D28: 0 | E28: =SmtRes!AV42 -> 0 | F28: =SmtRes!I42 -> 21.1-6-37 | G28: =SmtRes!K42 -> Краски водно-дисперсионные поливинилацетатные, белые, марка ВД-ВА-17 | H28: =SmtRes!O42 -> т | I28: =SmtRes!Y42*Source!I36 -> 0.0009 | J28: =SmtRes!AO42 -> 1 | K28: =SmtRes!AE42 -> 75121.86 | L28: =SmtRes!DB42 -> 225.37 | M28: =ROUND(ROUND(L28*Source!I36, 6)*1, 2) -> 67.61 | N28: =SmtRes!AA42 -> 75121.86 | O28: =ROUND(ROUND(L28*Source!I36, 6)*SmtRes!DA42, 2) -> 67.61 | P28: =SmtRes!AG42 -> 0 | Q28: =SmtRes!DC42 -> 0 | R28: =ROUND(ROUND(Q28*Source!I36, 6)*1, 2) -> 0 | S28: =SmtRes!AC42 -> 0 | T28: =ROUND(ROUND(Q28*Source!I36, 6)*SmtRes!AK42, 2) -> 0 | U28: 3 | Z28: =SmtRes!X42 -> -794464499 | AA28: 266707854 | AB28: 266707854
A29: 20 | B29: 41 | C29: 3 | D29: 0 | E29: =SmtRes!AV41 -> 0 | F29: =SmtRes!I41 -> 21.1-23-9 | G29: =SmtRes!K41 -> Электроды, тип Э-42, 46, 50, диаметр 4 - 6 мм | H29: =SmtRes!O41 -> т | I29: =SmtRes!Y41*Source!I36 -> 0.00063 | J29: =SmtRes!AO41 -> 1 | K29: =SmtRes!AE41 -> 109992.36 | L29: =SmtRes!DB41 -> 230.98 | M29: =ROUND(ROUND(L29*Source!I36, 6)*1, 2) -> 69.29 | N29: =SmtRes!AA41 -> 109992.36 | O29: =ROUND(ROUND(L29*Source!I36, 6)*SmtRes!DA41, 2) -> 69.29 | P29: =SmtRes!AG41 -> 0 | Q29: =SmtRes!DC41 -> 0 | R29: =ROUND(ROUND(Q29*Source!I36, 6)*1, 2) -> 0 | S29: =SmtRes!AC41 -> 0 | T29: =ROUND(ROUND(Q29*Source!I36, 6)*SmtRes!AK41, 2) -> 0 | U29: 3 | Z29: =SmtRes!X41 -> 277207382 | AA29: 1948239711 | AB29: 1948239711
A30: 20 | B30: 40 | C30: 3 | D30: 0 | E30: =SmtRes!AV40 -> 0 | F30: =SmtRes!I40 -> 21.1-20-10 | G30: =SmtRes!K40 -> Лента изоляционная хлопчатобумажная | H30: =SmtRes!O40 -> кг | I30: =SmtRes!Y40*Source!I36 -> 0.126 | J30: =SmtRes!AO40 -> 1 | K30: =SmtRes!AE40 -> 363.22 | L30: =SmtRes!DB40 -> 152.55 | M30: =ROUND(ROUND(L30*Source!I36, 6)*1, 2) -> 45.77 | N30: =SmtRes!AA40 -> 363.22 | O30: =ROUND(ROUND(L30*Source!I36, 6)*SmtRes!DA40, 2) -> 45.77 | P30: =SmtRes!AG40 -> 0 | Q30: =SmtRes!DC40 -> 0 | R30: =ROUND(ROUND(Q30*Source!I36, 6)*1, 2) -> 0 | S30: =SmtRes!AC40 -> 0 | T30: =ROUND(ROUND(Q30*Source!I36, 6)*SmtRes!AK40, 2) -> 0 | U30: 3 | Z30: =SmtRes!X40 -> 1719425291 | AA30: -1596111638 | AB30: -1596111638
A31: 20 | B31: 39 | C31: 3 | D31: 0 | E31: =SmtRes!AV39 -> 0 | F31: =SmtRes!I39 -> 21.1-11-21 | G31: =SmtRes!K39 -> Болты строительные черные с гайками и шайбами (10х100мм) | H31: =SmtRes!O39 -> т | I31: =SmtRes!Y39*Source!I36 -> 0.00312 | J31: =SmtRes!AO39 -> 1 | K31: =SmtRes!AE39 -> 161977.32 | L31: =SmtRes!DB39 -> 1684.56 | M31: =ROUND(ROUND(L31*Source!I36, 6)*1, 2) -> 505.37 | N31: =SmtRes!AA39 -> 161977.32 | O31: =ROUND(ROUND(L31*Source!I36, 6)*SmtRes!DA39, 2) -> 505.37 | P31: =SmtRes!AG39 -> 0 | Q31: =SmtRes!DC39 -> 0 | R31: =ROUND(ROUND(Q31*Source!I36, 6)*1, 2) -> 0 | S31: =SmtRes!AC39 -> 0 | T31: =ROUND(ROUND(Q31*Source!I36, 6)*SmtRes!AK39, 2) -> 0 | U31: 3 | Z31: =SmtRes!X39 -> 1955262950 | AA31: -1191326009 | AB31: -1191326009
A32: 20 | B32: 38 | C32: 3 | D32: 0 | E32: =SmtRes!AV38 -> 0 | F32: =SmtRes!I38 -> 21.1-11-198 | G32: =SmtRes!K38 -> Дюбели пластмассовые | H32: =SmtRes!O38 -> шт. | I32: =SmtRes!Y38*Source!I36 -> 45.9 | J32: =SmtRes!AO38 -> 1 | K32: =SmtRes!AE38 -> 1.23 | L32: =SmtRes!DB38 -> 188.19 | M32: =ROUND(ROUND(L32*Source!I36, 6)*1, 2) -> 56.46 | N32: =SmtRes!AA38 -> 1.23 | O32: =ROUND(ROUND(L32*Source!I36, 6)*SmtRes!DA38, 2) -> 56.46 | P32: =SmtRes!AG38 -> 0 | Q32: =SmtRes!DC38 -> 0 | R32: =ROUND(ROUND(Q32*Source!I36, 6)*1, 2) -> 0 | S32: =SmtRes!AC38 -> 0 | T32: =ROUND(ROUND(Q32*Source!I36, 6)*SmtRes!AK38, 2) -> 0 | U32: 3 | Z32: =SmtRes!X38 -> 136717287 | AA32: 798392207 | AB32: 798392207
A33: 20 | B33: 37 | C33: 3 | D33: 0 | E33: =SmtRes!AV37 -> 0 | F33: =SmtRes!I37 -> 21.1-11-133 | G33: =SmtRes!K37 -> Дюбель-гвоздь с патроном | H33: =SmtRes!O37 -> шт. | I33: =SmtRes!Y37*Source!I36 -> 45.9 | J33: =SmtRes!AO37 -> 1 | K33: =SmtRes!AE37 -> 10.83 | L33: =SmtRes!DB37 -> 1656.99 | M33: =ROUND(ROUND(L33*Source!I36, 6)*1, 2) -> 497.1 | N33: =SmtRes!AA37 -> 10.83 | O33: =ROUND(ROUND(L33*Source!I36, 6)*SmtRes!DA37, 2) -> 497.1 | P33: =SmtRes!AG37 -> 0 | Q33: =SmtRes!DC37 -> 0 | R33: =ROUND(ROUND(Q33*Source!I36, 6)*1, 2) -> 0 | S33: =SmtRes!AC37 -> 0 | T33: =ROUND(ROUND(Q33*Source!I36, 6)*SmtRes!AK37, 2) -> 0 | U33: 3 | Z33: =SmtRes!X37 -> -795121688 | AA33: -503754449 | AB33: -503754449
A34: 20 | B34: 36 | C34: 3 | D34: 0 | E34: =SmtRes!AV36 -> 0 | F34: =SmtRes!I36 -> 21.1-10-159 | G34: =SmtRes!K36 -> Сталь круглая и квадратная общего назначения углеродистая кипящая, марка Ст0, размер 5-12 мм | H34: =SmtRes!O36 -> т | I34: =SmtRes!Y36*Source!I36 -> 0.168 | J34: =SmtRes!AO36 -> 1 | K34: =SmtRes!AE36 -> 51568.06 | L34: =SmtRes!DB36 -> 28878.11 | M34: =ROUND(ROUND(L34*Source!I36, 6)*1, 2) -> 8663.43 | N34: =SmtRes!AA36 -> 51568.06 | O34: =ROUND(ROUND(L34*Source!I36, 6)*SmtRes!DA36, 2) -> 8663.43 | P34: =SmtRes!AG36 -> 0 | Q34: =SmtRes!DC36 -> 0 | R34: =ROUND(ROUND(Q34*Source!I36, 6)*1, 2) -> 0 | S34: =SmtRes!AC36 -> 0 | T34: =ROUND(ROUND(Q34*Source!I36, 6)*SmtRes!AK36, 2) -> 0 | U34: 3 | Z34: =SmtRes!X36 -> -480916634 | AA34: 1531175116 | AB34: 1531175116
A35: =Source!A69 -> 4 | B35: 69 | G35: =Source!G69 -> Электрощит ЩАО (актовый зал)
A36: =Source!A107 -> 4 | B36: 107 | G36: =Source!G107 -> Электрощит ЩО (актовый зал)
A37: =Source!A145 -> 4 | B37: 145 | G37: =Source!G145 -> Электрощит РЩ (актовый зал)
A38: =Source!A183 -> 4 | B38: 183 | G38: =Source!G183 -> Помещение 108 Обеденный зал с умывальником
A39: =Source!A224 -> 4 | B39: 224 | G39: =Source!G224 -> Помещение 110 Кухня
A40: =Source!A263 -> 4 | B40: 263 | G40: =Source!G263 -> Помещение 111 Моечная
A41: =Source!A299 -> 4 | B41: 299 | G41: =Source!G299 -> Помещение 116 Душ
A42: =Source!A335 -> 4 | B42: 335 | G42: =Source!G335 -> Помещение 117 Коридор
A43: =Source!A372 -> 4 | B43: 372 | G43: =Source!G372 -> Помещение 118 Венткамера
A44: =Source!A409 -> 4 | B44: 409 | G44: =Source!G409 -> Помещение 119 помещение уборочного инвентаря
A45: =Source!A445 -> 4 | B45: 445 | G45: =Source!G445 -> Электрощит ТХ1
A46: =Source!A486 -> 4 | B46: 486 | G46: =Source!G486 -> Электрощит ТХ2
A47: =Source!A527 -> 4 | B47: 527 | G47: =Source!G527 -> Электрощит ТХ3
A48: =Source!A568 -> 4 | B48: 568 | G48: =Source!G568 -> Помещение 104 Вестибюль
A49: 20 | B49: 180 | C49: 3 | D49: 0 | E49: =SmtRes!AV180 -> 0 | F49: =SmtRes!I180 -> 21.1-25-1042 | G49: =SmtRes!K180 -> Кабель-каналы, размер 105х50 мм: углы плоские | H49: =SmtRes!O180 -> шт. | I49: =SmtRes!Y180*Source!I574 -> 0.02 | J49: =SmtRes!AO180 -> 1 | K49: =SmtRes!AE180 -> 947.75 | L49: =SmtRes!DB180 -> 1895.5 | M49: =ROUND(ROUND(L49*Source!I574, 6)*1, 2) -> 18.96 | N49: =SmtRes!AA180 -> 947.75 | O49: =ROUND(ROUND(L49*Source!I574, 6)*SmtRes!DA180, 2) -> 18.96 | P49: =SmtRes!AG180 -> 0 | Q49: =SmtRes!DC180 -> 0 | R49: =ROUND(ROUND(Q49*Source!I574, 6)*1, 2) -> 0 | S49: =SmtRes!AC180 -> 0 | T49: =ROUND(ROUND(Q49*Source!I574, 6)*SmtRes!AK180, 2) -> 0 | U49: 3 | Z49: =SmtRes!X180 -> 1625024360 | AA49: 1537823898 | AB49: 1537823898
A50: 20 | B50: 179 | C50: 3 | D50: 0 | E50: =SmtRes!AV179 -> 0 | F50: =SmtRes!I179 -> 21.1-25-1041 | G50: =SmtRes!K179 -> Кабель-каналы, размер 105х50 мм: углы наружные | H50: =SmtRes!O179 -> шт. | I50: =SmtRes!Y179*Source!I574 -> 0.15 | J50: =SmtRes!AO179 -> 1 | K50: =SmtRes!AE179 -> 776.23 | L50: =SmtRes!DB179 -> 11643.45 | M50: =ROUND(ROUND(L50*Source!I574, 6)*1, 2) -> 116.43 | N50: =SmtRes!AA179 -> 776.23 | O50: =ROUND(ROUND(L50*Source!I574, 6)*SmtRes!DA179, 2) -> 116.43 | P50: =SmtRes!AG179 -> 0 | Q50: =SmtRes!DC179 -> 0 | R50: =ROUND(ROUND(Q50*Source!I574, 6)*1, 2) -> 0 | S50: =SmtRes!AC179 -> 0 | T50: =ROUND(ROUND(Q50*Source!I574, 6)*SmtRes!AK179, 2) -> 0 | U50: 3 | Z50: =SmtRes!X179 -> -1994768362 | AA50: -619013872 | AB50: -619013872
A51: 20 | B51: 178 | C51: 3 | D51: 0 | E51: =SmtRes!AV178 -> 0 | F51: =SmtRes!I178 -> 21.1-25-1040 | G51: =SmtRes!K178 -> Кабель-каналы, размер 105х50 мм: углы внутренние | H51: =SmtRes!O178 -> шт. | I51: =SmtRes!Y178*Source!I574 -> 0.02 | J51: =SmtRes!AO178 -> 1 | K51: =SmtRes!AE178 -> 666.11 | L51: =SmtRes!DB178 -> 1332.22 | M51: =ROUND(ROUND(L51*Source!I574, 6)*1, 2) -> 13.32 | N51: =SmtRes!AA178 -> 666.11 | O51: =ROUND(ROUND(L51*Source!I574, 6)*SmtRes!DA178, 2) -> 13.32 | P51: =SmtRes!AG178 -> 0 | Q51: =SmtRes!DC178 -> 0 | R51: =ROUND(ROUND(Q51*Source!I574, 6)*1, 2) -> 0 | S51: =SmtRes!AC178 -> 0 | T51: =ROUND(ROUND(Q51*Source!I574, 6)*SmtRes!AK178, 2) -> 0 | U51: 3 | Z51: =SmtRes!X178 -> 1509415827 | AA51: 746688475 | AB51: 746688475
A52: 20 | B52: 177 | C52: 3 | D52: 0 | E52: =SmtRes!AV177 -> 0 | F52: =SmtRes!I177 -> 21.1-25-1038 | G52: =SmtRes!K177 -> Кабель-каналы, размер 105х50 мм: накладки на стык профилей | H52: =SmtRes!O177 -> шт. | I52: =SmtRes!Y177*Source!I574 -> 0.04 | J52: =SmtRes!AO177 -> 1 | K52: =SmtRes!AE177 -> 54.24 | L52: =SmtRes!DB177 -> 216.96 | M52: =ROUND(ROUND(L52*Source!I574, 6)*1, 2) -> 2.17 | N52: =SmtRes!AA177 -> 54.24 | O52: =ROUND(ROUND(L52*Source!I574, 6)*SmtRes!DA177, 2) -> 2.17 | P52: =SmtRes!AG177 -> 0 | Q52: =SmtRes!DC177 -> 0 | R52: =ROUND(ROUND(Q52*Source!I574, 6)*1, 2) -> 0 | S52: =SmtRes!AC177 -> 0 | T52: =ROUND(ROUND(Q52*Source!I574, 6)*SmtRes!AK177, 2) -> 0 | U52: 3 | Z52: =SmtRes!X177 -> -2070555848 | AA52: -158674467 | AB52: -158674467
A53: 20 | B53: 176 | C53: 3 | D53: 0 | E53: =SmtRes!AV176 -> 0 | F53: =SmtRes!I176 -> 21.1-25-1037 | G53: =SmtRes!K176 -> Кабель-каналы, размер 105х50 мм: накладки на стык крышки | H53: =SmtRes!O176 -> шт. | I53: =SmtRes!Y176*Source!I574 -> 0.04 | J53: =SmtRes!AO176 -> 1 | K53: =SmtRes!AE176 -> 172.42 | L53: =SmtRes!DB176 -> 689.68 | M53: =ROUND(ROUND(L53*Source!I574, 6)*1, 2) -> 6.9 | N53: =SmtRes!AA176 -> 172.42 | O53: =ROUND(ROUND(L53*Source!I574, 6)*SmtRes!DA176, 2) -> 6.9 | P53: =SmtRes!AG176 -> 0 | Q53: =SmtRes!DC176 -> 0 | R53: =ROUND(ROUND(Q53*Source!I574, 6)*1, 2) -> 0 | S53: =SmtRes!AC176 -> 0 | T53: =ROUND(ROUND(Q53*Source!I574, 6)*SmtRes!AK176, 2) -> 0 | U53: 3 | Z53: =SmtRes!X176 -> 1474194811 | AA53: 528708715 | AB53: 528708715
A54: 20 | B54: 175 | C54: 3 | D54: 0 | E54: =SmtRes!AV175 -> 0 | F54: =SmtRes!I175 -> 21.1-25-1036 | G54: =SmtRes!K175 -> Кабель-каналы, размер 105х50 мм: заглушки | H54: =SmtRes!O175 -> шт. | I54: =SmtRes!Y175*Source!I574 -> 0.15 | J54: =SmtRes!AO175 -> 1 | K54: =SmtRes!AE175 -> 153.13 | L54: =SmtRes!DB175 -> 2296.95 | M54: =ROUND(ROUND(L54*Source!I574, 6)*1, 2) -> 22.97 | N54: =SmtRes!AA175 -> 153.13 | O54: =ROUND(ROUND(L54*Source!I574, 6)*SmtRes!DA175, 2) -> 22.97 | P54: =SmtRes!AG175 -> 0 | Q54: =SmtRes!DC175 -> 0 | R54: =ROUND(ROUND(Q54*Source!I574, 6)*1, 2) -> 0 | S54: =SmtRes!AC175 -> 0 | T54: =ROUND(ROUND(Q54*Source!I574, 6)*SmtRes!AK175, 2) -> 0 | U54: 3 | Z54: =SmtRes!X175 -> 1594614613 | AA54: -1719495285 | AB54: -1719495285
A55: 20 | B55: 174 | C55: 3 | D55: 0 | E55: =SmtRes!AV174 -> 0 | F55: =SmtRes!I174 -> 21.1-25-1035 | G55: =SmtRes!K174 -> Кабель-каналы, размер 105х50 мм: короба c направляющими | H55: =SmtRes!O174 -> м | I55: =SmtRes!Y174*Source!I574 -> 1 | J55: =SmtRes!AO174 -> 1 | K55: =SmtRes!AE174 -> 658.59 | L55: =SmtRes!DB174 -> 65859 | M55: =ROUND(ROUND(L55*Source!I574, 6)*1, 2) -> 658.59 | N55: =SmtRes!AA174 -> 658.59 | O55: =ROUND(ROUND(L55*Source!I574, 6)*SmtRes!DA174, 2) -> 658.59 | P55: =SmtRes!AG174 -> 0 | Q55: =SmtRes!DC174 -> 0 | R55: =ROUND(ROUND(Q55*Source!I574, 6)*1, 2) -> 0 | S55: =SmtRes!AC174 -> 0 | T55: =ROUND(ROUND(Q55*Source!I574, 6)*SmtRes!AK174, 2) -> 0 | U55: 3 | Z55: =SmtRes!X174 -> 1505022798 | AA55: 892245811 | AB55: 892245811
A56: 20 | B56: 173 | C56: 3 | D56: 0 | E56: =SmtRes!AV173 -> 0 | F56: =SmtRes!I173 -> 21.1-11-81 | G56: =SmtRes!K173 -> Патроны, калибр 6,8/11 М для дюбеля | H56: =SmtRes!O173 -> 100 шт. | I56: =SmtRes!Y173*Source!I574 -> 0.04 | J56: =SmtRes!AO173 -> 1 | K56: =SmtRes!AE173 -> 997.35 | L56: =SmtRes!DB173 -> 3989.4 | M56: =ROUND(ROUND(L56*Source!I574, 6)*1, 2) -> 39.89 | N56: =SmtRes!AA173 -> 997.35 | O56: =ROUND(ROUND(L56*Source!I574, 6)*SmtRes!DA173, 2) -> 39.89 | P56: =SmtRes!AG173 -> 0 | Q56: =SmtRes!DC173 -> 0 | R56: =ROUND(ROUND(Q56*Source!I574, 6)*1, 2) -> 0 | S56: =SmtRes!AC173 -> 0 | T56: =ROUND(ROUND(Q56*Source!I574, 6)*SmtRes!AK173, 2) -> 0 | U56: 3 | Z56: =SmtRes!X173 -> 1583670906 | AA56: -274985448 | AB56: -274985448
A57: 20 | B57: 172 | C57: 3 | D57: 0 | E57: =SmtRes!AV172 -> 0 | F57: =SmtRes!I172 -> 21.1-11-108 | G57: =SmtRes!K172 -> Шурупы-саморезы, размер 3,5х45 мм | H57: =SmtRes!O172 -> т | I57: =SmtRes!Y172*Source!I574 -> 7.4e-06 | J57: =SmtRes!AO172 -> 1 | K57: =SmtRes!AE172 -> 190540.34 | L57: =SmtRes!DB172 -> 141 | M57: =ROUND(ROUND(L57*Source!I574, 6)*1, 2) -> 1.41 | N57: =SmtRes!AA172 -> 190540.34 | O57: =ROUND(ROUND(L57*Source!I574, 6)*SmtRes!DA172, 2) -> 1.41 | P57: =SmtRes!AG172 -> 0 | Q57: =SmtRes!DC172 -> 0 | R57: =ROUND(ROUND(Q57*Source!I574, 6)*1, 2) -> 0 | S57: =SmtRes!AC172 -> 0 | T57: =ROUND(ROUND(Q57*Source!I574, 6)*SmtRes!AK172, 2) -> 0 | U57: 3 | Z57: =SmtRes!X172 -> -181271767 | AA57: -2066596354 | AB57: -2066596354
A58: 20 | B58: 171 | C58: 3 | D58: 0 | E58: =SmtRes!AV171 -> 0 | F58: =SmtRes!I171 -> 21.1-1-1065 | G58: =SmtRes!K171 -> Кабель-каналы, размер 105х50 мм: ответвления Т-образные | H58: =SmtRes!O171 -> шт. | I58: =SmtRes!Y171*Source!I574 -> 0.02 | J58: =SmtRes!AO171 -> 1 | K58: =SmtRes!AE171 -> 1415.18 | L58: =SmtRes!DB171 -> 2830.36 | M58: =ROUND(ROUND(L58*Source!I574, 6)*1, 2) -> 28.3 | N58: =SmtRes!AA171 -> 1415.18 | O58: =ROUND(ROUND(L58*Source!I574, 6)*SmtRes!DA171, 2) -> 28.3 | P58: =SmtRes!AG171 -> 0 | Q58: =SmtRes!DC171 -> 0 | R58: =ROUND(ROUND(Q58*Source!I574, 6)*1, 2) -> 0 | S58: =SmtRes!AC171 -> 0 | T58: =ROUND(ROUND(Q58*Source!I574, 6)*SmtRes!AK171, 2) -> 0 | U58: 3 | Z58: =SmtRes!X171 -> -1464590454 | AA58: -1296774037 | AB58: -1296774037
A59: =Source!A575 -> 17 | B59: 575 | C59: 3 | D59: =Source!BI575 -> 4 | E59: =Source!FS575 -> 0 | F59: =Source!F575 -> 21.21-5-397 | G59: =Source!G575 -> Розетки (механизмы) штепсельные, серия "Мозаик", тип 2К+3, с винтовыми зажимами, с защитными шторками и заземляющим контактом | H59: =Source!H575 -> шт. | I59: =Source!I575 -> 3 | J59: 1 | K59: =Source!AC575 -> 432.44 | M59: =ROUND(K59*I59, 2) -> 1297.32 | N59: =Source!AC575*IF(Source!BC575<> 0, Source!BC575, 1) -> 432.44 | O59: =ROUND(N59*I59, 2) -> 1297.32 | P59: =Source!AE575 -> 0 | R59: =ROUND(P59*I59, 2) -> 0 | S59: =Source!AE575*IF(Source!BS575<> 0, Source!BS575, 1) -> 0 | T59: =ROUND(S59*I59, 2) -> 0 | U59: 3 | Z59: =Source!GF575 -> -1520967538 | AA59: -303846849 | AB59: -303846849
A60: =Source!A608 -> 4 | B60: 608 | G60: =Source!G608 -> Помещение 123 Электрощитовая
A61: =Source!A645 -> 4 | B61: 645 | G61: =Source!G645 -> Помещение 125 Водомерный узел
A62: =Source!A683 -> 4 | B62: 683 | G62: =Source!G683 -> Помещение 126 Комната охраны
A63: =Source!A722 -> 4 | B63: 722 | G63: =Source!G722 -> Помещение 127 Подсобное помещение
A64: 20 | B64: 198 | C64: 3 | D64: 0 | E64: =SmtRes!AV198 -> 0 | F64: =SmtRes!I198 -> 21.7-3-29 | G64: =SmtRes!K198 -> Сверло алмазное кольцевое, высокоэффективное, для всех типов бетона, длина 430 мм, диаметр 72 мм | H64: =SmtRes!O198 -> шт. | I64: =SmtRes!Y198*Source!I727 -> 0.00067 | J64: =SmtRes!AO198 -> 1 | K64: =SmtRes!AE198 -> 16620.27 | L64: =SmtRes!DB198 -> 111.36 | M64: =ROUND(ROUND(L64*Source!I727, 6)*1, 2) -> 11.14 | N64: =SmtRes!AA198 -> 16620.27 | O64: =ROUND(ROUND(L64*Source!I727, 6)*SmtRes!DA198, 2) -> 11.14 | P64: =SmtRes!AG198 -> 0 | Q64: =SmtRes!DC198 -> 0 | R64: =ROUND(ROUND(Q64*Source!I727, 6)*1, 2) -> 0 | S64: =SmtRes!AC198 -> 0 | T64: =ROUND(ROUND(Q64*Source!I727, 6)*SmtRes!AK198, 2) -> 0 | U64: 3 | Z64: =SmtRes!X198 -> 656259231 | AA64: -55341773 | AB64: -55341773
A65: 20 | B65: 197 | C65: 3 | D65: 0 | E65: =SmtRes!AV197 -> 0 | F65: =SmtRes!I197 -> 21.1-25-13 | G65: =SmtRes!K197 -> Вода | H65: =SmtRes!O197 -> м3 | I65: =SmtRes!Y197*Source!I727 -> 0.00176 | J65: =SmtRes!AO197 -> 1 | K65: =SmtRes!AE197 -> 54.81 | L65: =SmtRes!DB197 -> 0.96 | M65: =ROUND(ROUND(L65*Source!I727, 6)*1, 2) -> 0.1 | N65: =SmtRes!AA197 -> 54.81 | O65: =ROUND(ROUND(L65*Source!I727, 6)*SmtRes!DA197, 2) -> 0.1 | P65: =SmtRes!AG197 -> 0 | Q65: =SmtRes!DC197 -> 0 | R65: =ROUND(ROUND(Q65*Source!I727, 6)*1, 2) -> 0 | S65: =SmtRes!AC197 -> 0 | T65: =ROUND(ROUND(Q65*Source!I727, 6)*SmtRes!AK197, 2) -> 0 | U65: 3 | Z65: =SmtRes!X197 -> -35091971 | AA65: 1203958368 | AB65: 1203958368
A66: =Source!A729 -> 17 | B66: 729 | C66: 3 | D66: =Source!BI729 -> 4 | E66: =Source!FS729 -> 0 | F66: =Source!F729 -> 21.23-8-140 | G66: =Source!G729 -> Кабели силовые с медными жилами, с изоляцией и оболочкой из поливинилхлоридных композиций пониженной пожароопасности, с низким дымо - и газовыделением, марка ВВГнг(А)-LS, напряжение 660 В, число жил и сечение, мм2: 3х2,5 | H66: =Source!H729 -> км | I66: =Source!I729 -> 0.001 | J66: 1 | K66: =Source!AC729 -> 99860.32 | M66: =ROUND(K66*I66, 2) -> 99.86 | N66: =Source!AC729*IF(Source!BC729<> 0, Source!BC729, 1) -> 99860.32 | O66: =ROUND(N66*I66, 2) -> 99.86 | P66: =Source!AE729 -> 0 | R66: =ROUND(P66*I66, 2) -> 0 | S66: =Source!AE729*IF(Source!BS729<> 0, Source!BS729, 1) -> 0 | T66: =ROUND(S66*I66, 2) -> 0 | U66: 3 | Z66: =Source!GF729 -> 2077141205 | AA66: 472379674 | AB66: 472379674
A67: =Source!A730 -> 17 | B67: 730 | C67: 3 | D67: =Source!BI730 -> 4 | E67: =Source!FS730 -> 0 | F67: =Source!F730 -> 21.21-5-84 | G67: =Source!G730 -> Коробки для установки выключателей, переключателей и штепсельных розеток при скрытой электропроводке, тип КУВ-1М УХЛЗ | H67: =Source!H730 -> 1000 шт. | I67: =Source!I730 -> 0.002 | J67: 1 | K67: =Source!AC730 -> 72169.9 | M67: =ROUND(K67*I67, 2) -> 144.34 | N67: =Source!AC730*IF(Source!BC730<> 0, Source!BC730, 1) -> 72169.9 | O67: =ROUND(N67*I67, 2) -> 144.34 | P67: =Source!AE730 -> 0 | R67: =ROUND(P67*I67, 2) -> 0 | S67: =Source!AE730*IF(Source!BS730<> 0, Source!BS730, 1) -> 0 | T67: =ROUND(S67*I67, 2) -> 0 | U67: 3 | Z67: =Source!GF730 -> 653953554 | AA67: -1378273173 | AB67: -1378273173
A68: =Source!A764 -> 4 | B68: 764 | G68: =Source!G764 -> Помещение 128 Кабинет завхоза
A69: 20 | B69: 210 | C69: 3 | D69: 0 | E69: =SmtRes!AV210 -> 0 | F69: =SmtRes!I210 -> 21.7-3-29 | G69: =SmtRes!K210 -> Сверло алмазное кольцевое, высокоэффективное, для всех типов бетона, длина 430 мм, диаметр 72 мм | H69: =SmtRes!O210 -> шт. | I69: =SmtRes!Y210*Source!I769 -> 0.00067 | J69: =SmtRes!AO210 -> 1 | K69: =SmtRes!AE210 -> 16620.27 | L69: =SmtRes!DB210 -> 111.36 | M69: =ROUND(ROUND(L69*Source!I769, 6)*1, 2) -> 11.14 | N69: =SmtRes!AA210 -> 16620.27 | O69: =ROUND(ROUND(L69*Source!I769, 6)*SmtRes!DA210, 2) -> 11.14 | P69: =SmtRes!AG210 -> 0 | Q69: =SmtRes!DC210 -> 0 | R69: =ROUND(ROUND(Q69*Source!I769, 6)*1, 2) -> 0 | S69: =SmtRes!AC210 -> 0 | T69: =ROUND(ROUND(Q69*Source!I769, 6)*SmtRes!AK210, 2) -> 0 | U69: 3 | Z69: =SmtRes!X210 -> 656259231 | AA69: -55341773 | AB69: -55341773
A70: 20 | B70: 209 | C70: 3 | D70: 0 | E70: =SmtRes!AV209 -> 0 | F70: =SmtRes!I209 -> 21.1-25-13 | G70: =SmtRes!K209 -> Вода | H70: =SmtRes!O209 -> м3 | I70: =SmtRes!Y209*Source!I769 -> 0.00176 | J70: =SmtRes!AO209 -> 1 | K70: =SmtRes!AE209 -> 54.81 | L70: =SmtRes!DB209 -> 0.96 | M70: =ROUND(ROUND(L70*Source!I769, 6)*1, 2) -> 0.1 | N70: =SmtRes!AA209 -> 54.81 | O70: =ROUND(ROUND(L70*Source!I769, 6)*SmtRes!DA209, 2) -> 0.1 | P70: =SmtRes!AG209 -> 0 | Q70: =SmtRes!DC209 -> 0 | R70: =ROUND(ROUND(Q70*Source!I769, 6)*1, 2) -> 0 | S70: =SmtRes!AC209 -> 0 | T70: =ROUND(ROUND(Q70*Source!I769, 6)*SmtRes!AK209, 2) -> 0 | U70: 3 | Z70: =SmtRes!X209 -> -35091971 | AA70: 1203958368 | AB70: 1203958368
A71: =Source!A771 -> 17 | B71: 771 | C71: 3 | D71: =Source!BI771 -> 4 | E71: =Source!FS771 -> 0 | F71: =Source!F771 -> 21.23-8-140 | G71: =Source!G771 -> Кабели силовые с медными жилами, с изоляцией и оболочкой из поливинилхлоридных композиций пониженной пожароопасности, с низким дымо - и газовыделением, марка ВВГнг(А)-LS, напряжение 660 В, число жил и сечение, мм2: 3х2,5 | H71: =Source!H771 -> км | I71: =Source!I771 -> 0.001 | J71: 1 | K71: =Source!AC771 -> 99860.32 | M71: =ROUND(K71*I71, 2) -> 99.86 | N71: =Source!AC771*IF(Source!BC771<> 0, Source!BC771, 1) -> 99860.32 | O71: =ROUND(N71*I71, 2) -> 99.86 | P71: =Source!AE771 -> 0 | R71: =ROUND(P71*I71, 2) -> 0 | S71: =Source!AE771*IF(Source!BS771<> 0, Source!BS771, 1) -> 0 | T71: =ROUND(S71*I71, 2) -> 0 | U71: 3 | Z71: =Source!GF771 -> 2077141205 | AA71: 472379674 | AB71: 472379674
A72: =Source!A772 -> 17 | B72: 772 | C72: 3 | D72: =Source!BI772 -> 4 | E72: =Source!FS772 -> 0 | F72: =Source!F772 -> 21.21-5-84 | G72: =Source!G772 -> Коробки для установки выключателей, переключателей и штепсельных розеток при скрытой электропроводке, тип КУВ-1М УХЛЗ | H72: =Source!H772 -> 1000 шт. | I72: =Source!I772 -> 0.002 | J72: 1 | K72: =Source!AC772 -> 72169.9 | M72: =ROUND(K72*I72, 2) -> 144.34 | N72: =Source!AC772*IF(Source!BC772<> 0, Source!BC772, 1) -> 72169.9 | O72: =ROUND(N72*I72, 2) -> 144.34 | P72: =Source!AE772 -> 0 | R72: =ROUND(P72*I72, 2) -> 0 | S72: =Source!AE772*IF(Source!BS772<> 0, Source!BS772, 1) -> 0 | T72: =ROUND(S72*I72, 2) -> 0 | U72: 3 | Z72: =Source!GF772 -> 653953554 | AA72: -1378273173 | AB72: -1378273173
A73: =Source!A807 -> 4 | B73: 807 | G73: =Source!G807 -> Помещение 129 Интерактивная библиотека
A74: 20 | B74: 223 | C74: 3 | D74: 0 | E74: =SmtRes!AV223 -> 0 | F74: =SmtRes!I223 -> 21.7-3-29 | G74: =SmtRes!K223 -> Сверло алмазное кольцевое, высокоэффективное, для всех типов бетона, длина 430 мм, диаметр 72 мм | H74: =SmtRes!O223 -> шт. | I74: =SmtRes!Y223*Source!I812 -> 0.0134 | J74: =SmtRes!AO223 -> 1 | K74: =SmtRes!AE223 -> 16620.27 | L74: =SmtRes!DB223 -> 111.36 | M74: =ROUND(ROUND(L74*Source!I812, 6)*1, 2) -> 222.72 | N74: =SmtRes!AA223 -> 16620.27 | O74: =ROUND(ROUND(L74*Source!I812, 6)*SmtRes!DA223, 2) -> 222.72 | P74: =SmtRes!AG223 -> 0 | Q74: =SmtRes!DC223 -> 0 | R74: =ROUND(ROUND(Q74*Source!I812, 6)*1, 2) -> 0 | S74: =SmtRes!AC223 -> 0 | T74: =ROUND(ROUND(Q74*Source!I812, 6)*SmtRes!AK223, 2) -> 0 | U74: 3 | Z74: =SmtRes!X223 -> 656259231 | AA74: -55341773 | AB74: -55341773
A75: 20 | B75: 222 | C75: 3 | D75: 0 | E75: =SmtRes!AV222 -> 0 | F75: =SmtRes!I222 -> 21.1-25-13 | G75: =SmtRes!K222 -> Вода | H75: =SmtRes!O222 -> м3 | I75: =SmtRes!Y222*Source!I812 -> 0.0352 | J75: =SmtRes!AO222 -> 1 | K75: =SmtRes!AE222 -> 54.81 | L75: =SmtRes!DB222 -> 0.96 | M75: =ROUND(ROUND(L75*Source!I812, 6)*1, 2) -> 1.92 | N75: =SmtRes!AA222 -> 54.81 | O75: =ROUND(ROUND(L75*Source!I812, 6)*SmtRes!DA222, 2) -> 1.92 | P75: =SmtRes!AG222 -> 0 | Q75: =SmtRes!DC222 -> 0 | R75: =ROUND(ROUND(Q75*Source!I812, 6)*1, 2) -> 0 | S75: =SmtRes!AC222 -> 0 | T75: =ROUND(ROUND(Q75*Source!I812, 6)*SmtRes!AK222, 2) -> 0 | U75: 3 | Z75: =SmtRes!X222 -> -35091971 | AA75: 1203958368 | AB75: 1203958368
A76: =Source!A814 -> 17 | B76: 814 | C76: 3 | D76: =Source!BI814 -> 4 | E76: =Source!FS814 -> 0 | F76: =Source!F814 -> 21.23-8-140 | G76: =Source!G814 -> Кабели силовые с медными жилами, с изоляцией и оболочкой из поливинилхлоридных композиций пониженной пожароопасности, с низким дымо - и газовыделением, марка ВВГнг(А)-LS, напряжение 660 В, число жил и сечение, мм2: 3х2,5 | H76: =Source!H814 -> км | I76: =Source!I814 -> 0.001 | J76: 1 | K76: =Source!AC814 -> 99860.32 | M76: =ROUND(K76*I76, 2) -> 99.86 | N76: =Source!AC814*IF(Source!BC814<> 0, Source!BC814, 1) -> 99860.32 | O76: =ROUND(N76*I76, 2) -> 99.86 | P76: =Source!AE814 -> 0 | R76: =ROUND(P76*I76, 2) -> 0 | S76: =Source!AE814*IF(Source!BS814<> 0, Source!BS814, 1) -> 0 | T76: =ROUND(S76*I76, 2) -> 0 | U76: 3 | Z76: =Source!GF814 -> 2077141205 | AA76: 472379674 | AB76: 472379674
A77: =Source!A815 -> 17 | B77: 815 | C77: 3 | D77: =Source!BI815 -> 4 | E77: =Source!FS815 -> 0 | F77: =Source!F815 -> 21.21-5-84 | G77: =Source!G815 -> Коробки для установки выключателей, переключателей и штепсельных розеток при скрытой электропроводке, тип КУВ-1М УХЛЗ | H77: =Source!H815 -> 1000 шт. | I77: =Source!I815 -> 0.004 | J77: 1 | K77: =Source!AC815 -> 72169.9 | M77: =ROUND(K77*I77, 2) -> 288.68 | N77: =Source!AC815*IF(Source!BC815<> 0, Source!BC815, 1) -> 72169.9 | O77: =ROUND(N77*I77, 2) -> 288.68 | P77: =Source!AE815 -> 0 | R77: =ROUND(P77*I77, 2) -> 0 | S77: =Source!AE815*IF(Source!BS815<> 0, Source!BS815, 1) -> 0 | T77: =ROUND(S77*I77, 2) -> 0 | U77: 3 | Z77: =Source!GF815 -> 653953554 | AA77: -1378273173 | AB77: -1378273173
A78: 20 | B78: 244 | C78: 3 | D78: 0 | E78: =SmtRes!AV244 -> 0 | F78: =SmtRes!I244 -> 21.7-3-54 | G78: =SmtRes!K244 -> Сверло с алмазным покрытием, диаметр 6 мм | H78: =SmtRes!O244 -> шт. | I78: =SmtRes!Y244*Source!I819 -> 2 | J78: =SmtRes!AO244 -> 1 | K78: =SmtRes!AE244 -> 1555.5 | L78: =SmtRes!DB244 -> 6222 | M78: =ROUND(ROUND(L78*Source!I819, 6)*1, 2) -> 3111 | N78: =SmtRes!AA244 -> 1555.5 | O78: =ROUND(ROUND(L78*Source!I819, 6)*SmtRes!DA244, 2) -> 3111 | P78: =SmtRes!AG244 -> 0 | Q78: =SmtRes!DC244 -> 0 | R78: =ROUND(ROUND(Q78*Source!I819, 6)*1, 2) -> 0 | S78: =SmtRes!AC244 -> 0 | T78: =ROUND(ROUND(Q78*Source!I819, 6)*SmtRes!AK244, 2) -> 0 | U78: 3 | Z78: =SmtRes!X244 -> 1662095060 | AA78: -618828638 | AB78: -618828638
A79: 20 | B79: 243 | C79: 3 | D79: 0 | E79: =SmtRes!AV243 -> 0 | F79: =SmtRes!I243 -> 21.1-25-1034 | G79: =SmtRes!K243 -> Кабель-каналы, размер 60х40 мм: углы плоские | H79: =SmtRes!O243 -> шт. | I79: =SmtRes!Y243*Source!I819 -> 1 | J79: =SmtRes!AO243 -> 1 | K79: =SmtRes!AE243 -> 214.92 | L79: =SmtRes!DB243 -> 429.84 | M79: =ROUND(ROUND(L79*Source!I819, 6)*1, 2) -> 214.92 | N79: =SmtRes!AA243 -> 214.92 | O79: =ROUND(ROUND(L79*Source!I819, 6)*SmtRes!DA243, 2) -> 214.92 | P79: =SmtRes!AG243 -> 0 | Q79: =SmtRes!DC243 -> 0 | R79: =ROUND(ROUND(Q79*Source!I819, 6)*1, 2) -> 0 | S79: =SmtRes!AC243 -> 0 | T79: =ROUND(ROUND(Q79*Source!I819, 6)*SmtRes!AK243, 2) -> 0 | U79: 3 | Z79: =SmtRes!X243 -> -1452375277 | AA79: 1614893387 | AB79: 1614893387
A80: 20 | B80: 242 | C80: 3 | D80: 0 | E80: =SmtRes!AV242 -> 0 | F80: =SmtRes!I242 -> 21.1-25-1033 | G80: =SmtRes!K242 -> Кабель-каналы, размер 60х40 мм: углы наружные | H80: =SmtRes!O242 -> шт. | I80: =SmtRes!Y242*Source!I819 -> 7.5 | J80: =SmtRes!AO242 -> 1 | K80: =SmtRes!AE242 -> 203.06 | L80: =SmtRes!DB242 -> 3045.9 | M80: =ROUND(ROUND(L80*Source!I819, 6)*1, 2) -> 1522.95 | N80: =SmtRes!AA242 -> 203.06 | O80: =ROUND(ROUND(L80*Source!I819, 6)*SmtRes!DA242, 2) -> 1522.95 | P80: =SmtRes!AG242 -> 0 | Q80: =SmtRes!DC242 -> 0 | R80: =ROUND(ROUND(Q80*Source!I819, 6)*1, 2) -> 0 | S80: =SmtRes!AC242 -> 0 | T80: =ROUND(ROUND(Q80*Source!I819, 6)*SmtRes!AK242, 2) -> 0 | U80: 3 | Z80: =SmtRes!X242 -> 1479709201 | AA80: -124735961 | AB80: -124735961
A81: 20 | B81: 241 | C81: 3 | D81: 0 | E81: =SmtRes!AV241 -> 0 | F81: =SmtRes!I241 -> 21.1-25-1032 | G81: =SmtRes!K241 -> Кабель-каналы, размер 60х40 мм: углы внутренние | H81: =SmtRes!O241 -> шт. | I81: =SmtRes!Y241*Source!I819 -> 1 | J81: =SmtRes!AO241 -> 1 | K81: =SmtRes!AE241 -> 186.55 | L81: =SmtRes!DB241 -> 373.1 | M81: =ROUND(ROUND(L81*Source!I819, 6)*1, 2) -> 186.55 | N81: =SmtRes!AA241 -> 186.55 | O81: =ROUND(ROUND(L81*Source!I819, 6)*SmtRes!DA241, 2) -> 186.55 | P81: =SmtRes!AG241 -> 0 | Q81: =SmtRes!DC241 -> 0 | R81: =ROUND(ROUND(Q81*Source!I819, 6)*1, 2) -> 0 | S81: =SmtRes!AC241 -> 0 | T81: =ROUND(ROUND(Q81*Source!I819, 6)*SmtRes!AK241, 2) -> 0 | U81: 3 | Z81: =SmtRes!X241 -> -32305080 | AA81: -1064398607 | AB81: -1064398607
A82: 20 | B82: 240 | C82: 3 | D82: 0 | E82: =SmtRes!AV240 -> 0 | F82: =SmtRes!I240 -> 21.1-25-1031 | G82: =SmtRes!K240 -> Кабель-каналы, размер 60х40 мм: тройники | H82: =SmtRes!O240 -> шт. | I82: =SmtRes!Y240*Source!I819 -> 1 | J82: =SmtRes!AO240 -> 1 | K82: =SmtRes!AE240 -> 219.52 | L82: =SmtRes!DB240 -> 439.04 | M82: =ROUND(ROUND(L82*Source!I819, 6)*1, 2) -> 219.52 | N82: =SmtRes!AA240 -> 219.52 | O82: =ROUND(ROUND(L82*Source!I819, 6)*SmtRes!DA240, 2) -> 219.52 | P82: =SmtRes!AG240 -> 0 | Q82: =SmtRes!DC240 -> 0 | R82: =ROUND(ROUND(Q82*Source!I819, 6)*1, 2) -> 0 | S82: =SmtRes!AC240 -> 0 | T82: =ROUND(ROUND(Q82*Source!I819, 6)*SmtRes!AK240, 2) -> 0 | U82: 3 | Z82: =SmtRes!X240 -> 1816340030 | AA82: -1841828503 | AB82: -1841828503
A83: 20 | B83: 239 | C83: 3 | D83: 0 | E83: =SmtRes!AV239 -> 0 | F83: =SmtRes!I239 -> 21.1-25-1029 | G83: =SmtRes!K239 -> Кабель-каналы, размер 60х40 мм: накладки стыковые | H83: =SmtRes!O239 -> шт. | I83: =SmtRes!Y239*Source!I819 -> 2 | J83: =SmtRes!AO239 -> 1 | K83: =SmtRes!AE239 -> 126.89 | L83: =SmtRes!DB239 -> 507.56 | M83: =ROUND(ROUND(L83*Source!I819, 6)*1, 2) -> 253.78 | N83: =SmtRes!AA239 -> 126.89 | O83: =ROUND(ROUND(L83*Source!I819, 6)*SmtRes!DA239, 2) -> 253.78 | P83: =SmtRes!AG239 -> 0 | Q83: =SmtRes!DC239 -> 0 | R83: =ROUND(ROUND(Q83*Source!I819, 6)*1, 2) -> 0 | S83: =SmtRes!AC239 -> 0 | T83: =ROUND(ROUND(Q83*Source!I819, 6)*SmtRes!AK239, 2) -> 0 | U83: 3 | Z83: =SmtRes!X239 -> -1376764488 | AA83: 1140495319 | AB83: 1140495319
A84: 20 | B84: 238 | C84: 3 | D84: 0 | E84: =SmtRes!AV238 -> 0 | F84: =SmtRes!I238 -> 21.1-25-1028 | G84: =SmtRes!K238 -> Кабель-каналы, размер 60х40 мм: заглушки | H84: =SmtRes!O238 -> шт. | I84: =SmtRes!Y238*Source!I819 -> 7.5 | J84: =SmtRes!AO238 -> 1 | K84: =SmtRes!AE238 -> 145.46 | L84: =SmtRes!DB238 -> 2181.9 | M84: =ROUND(ROUND(L84*Source!I819, 6)*1, 2) -> 1090.95 | N84: =SmtRes!AA238 -> 145.46 | O84: =ROUND(ROUND(L84*Source!I819, 6)*SmtRes!DA238, 2) -> 1090.95 | P84: =SmtRes!AG238 -> 0 | Q84: =SmtRes!DC238 -> 0 | R84: =ROUND(ROUND(Q84*Source!I819, 6)*1, 2) -> 0 | S84: =SmtRes!AC238 -> 0 | T84: =ROUND(ROUND(Q84*Source!I819, 6)*SmtRes!AK238, 2) -> 0 | U84: 3 | Z84: =SmtRes!X238 -> -1986506557 | AA84: 368106192 | AB84: 368106192
A85: 20 | B85: 237 | C85: 3 | D85: 0 | E85: =SmtRes!AV237 -> 0 | F85: =SmtRes!I237 -> 21.1-25-1027 | G85: =SmtRes!K237 -> Кабель-каналы, размер 60х40 мм: кабель-каналы | H85: =SmtRes!O237 -> м | I85: =SmtRes!Y237*Source!I819 -> 50 | J85: =SmtRes!AO237 -> 1 | K85: =SmtRes!AE237 -> 138.94 | L85: =SmtRes!DB237 -> 13894 | M85: =ROUND(ROUND(L85*Source!I819, 6)*1, 2) -> 6947 | N85: =SmtRes!AA237 -> 138.94 | O85: =ROUND(ROUND(L85*Source!I819, 6)*SmtRes!DA237, 2) -> 6947 | P85: =SmtRes!AG237 -> 0 | Q85: =SmtRes!DC237 -> 0 | R85: =ROUND(ROUND(Q85*Source!I819, 6)*1, 2) -> 0 | S85: =SmtRes!AC237 -> 0 | T85: =ROUND(ROUND(Q85*Source!I819, 6)*SmtRes!AK237, 2) -> 0 | U85: 3 | Z85: =SmtRes!X237 -> 1471616812 | AA85: -402984879 | AB85: -402984879
A86: 20 | B86: 236 | C86: 3 | D86: 0 | E86: =SmtRes!AV236 -> 0 | F86: =SmtRes!I236 -> 21.1-11-81 | G86: =SmtRes!K236 -> Патроны, калибр 6,8/11 М для дюбеля | H86: =SmtRes!O236 -> 100 шт. | I86: =SmtRes!Y236*Source!I819 -> 2 | J86: =SmtRes!AO236 -> 1 | K86: =SmtRes!AE236 -> 997.35 | L86: =SmtRes!DB236 -> 3989.4 | M86: =ROUND(ROUND(L86*Source!I819, 6)*1, 2) -> 1994.7 | N86: =SmtRes!AA236 -> 997.35 | O86: =ROUND(ROUND(L86*Source!I819, 6)*SmtRes!DA236, 2) -> 1994.7 | P86: =SmtRes!AG236 -> 0 | Q86: =SmtRes!DC236 -> 0 | R86: =ROUND(ROUND(Q86*Source!I819, 6)*1, 2) -> 0 | S86: =SmtRes!AC236 -> 0 | T86: =ROUND(ROUND(Q86*Source!I819, 6)*SmtRes!AK236, 2) -> 0 | U86: 3 | Z86: =SmtRes!X236 -> 1583670906 | AA86: -274985448 | AB86: -274985448
A87: 20 | B87: 235 | C87: 3 | D87: 0 | E87: =SmtRes!AV235 -> 0 | F87: =SmtRes!I235 -> 21.1-11-108 | G87: =SmtRes!K235 -> Шурупы-саморезы, размер 3,5х45 мм | H87: =SmtRes!O235 -> т | I87: =SmtRes!Y235*Source!I819 -> 0.00037 | J87: =SmtRes!AO235 -> 1 | K87: =SmtRes!AE235 -> 190540.34 | L87: =SmtRes!DB235 -> 141 | M87: =ROUND(ROUND(L87*Source!I819, 6)*1, 2) -> 70.5 | N87: =SmtRes!AA235 -> 190540.34 | O87: =ROUND(ROUND(L87*Source!I819, 6)*SmtRes!DA235, 2) -> 70.5 | P87: =SmtRes!AG235 -> 0 | Q87: =SmtRes!DC235 -> 0 | R87: =ROUND(ROUND(Q87*Source!I819, 6)*1, 2) -> 0 | S87: =SmtRes!AC235 -> 0 | T87: =ROUND(ROUND(Q87*Source!I819, 6)*SmtRes!AK235, 2) -> 0 | U87: 3 | Z87: =SmtRes!X235 -> -181271767 | AA87: -2066596354 | AB87: -2066596354
A88: 20 | B88: 253 | C88: 3 | D88: 0 | E88: =SmtRes!AV253 -> 0 | F88: =SmtRes!I253 -> 21.23-13-14 | G88: =SmtRes!K253 -> Провода силовые с медными жилами в поливинилхлоридной изоляции, марка ПуГВ, номинальное напряжение до 450 В, число жил и сечение 1х6 мм2 | H88: =SmtRes!O253 -> км | I88: =SmtRes!Y253*Source!I820 -> 0.0515 | J88: =SmtRes!AO253 -> 1 | K88: =SmtRes!AE253 -> 99643.05 | L88: =SmtRes!DB253 -> 10263.23 | M88: =ROUND(ROUND(L88*Source!I820, 6)*1, 2) -> 5131.62 | N88: =SmtRes!AA253 -> 99643.05 | O88: =ROUND(ROUND(L88*Source!I820, 6)*SmtRes!DA253, 2) -> 5131.62 | P88: =SmtRes!AG253 -> 0 | Q88: =SmtRes!DC253 -> 0 | R88: =ROUND(ROUND(Q88*Source!I820, 6)*1, 2) -> 0 | S88: =SmtRes!AC253 -> 0 | T88: =ROUND(ROUND(Q88*Source!I820, 6)*SmtRes!AK253, 2) -> 0 | U88: 3 | Z88: =SmtRes!X253 -> 1173250179 | AA88: -458052105 | AB88: -458052105
A89: 20 | B89: 252 | C89: 3 | D89: 0 | E89: =SmtRes!AV252 -> 0 | F89: =SmtRes!I252 -> 21.21-5-44 | G89: =SmtRes!K252 -> Кнопки для ленты ЛМ, тип 3,5 | H89: =SmtRes!O252 -> 1000 шт. | I89: =SmtRes!Y252*Source!I820 -> 0.01 | J89: =SmtRes!AO252 -> 1 | K89: =SmtRes!AE252 -> 258.44 | L89: =SmtRes!DB252 -> 5.17 | M89: =ROUND(ROUND(L89*Source!I820, 6)*1, 2) -> 2.59 | N89: =SmtRes!AA252 -> 258.44 | O89: =ROUND(ROUND(L89*Source!I820, 6)*SmtRes!DA252, 2) -> 2.59 | P89: =SmtRes!AG252 -> 0 | Q89: =SmtRes!DC252 -> 0 | R89: =ROUND(ROUND(Q89*Source!I820, 6)*1, 2) -> 0 | S89: =SmtRes!AC252 -> 0 | T89: =ROUND(ROUND(Q89*Source!I820, 6)*SmtRes!AK252, 2) -> 0 | U89: 3 | Z89: =SmtRes!X252 -> -1680055193 | AA89: -2054620093 | AB89: -2054620093
A90: 20 | B90: 251 | C90: 3 | D90: 0 | E90: =SmtRes!AV251 -> 0 | F90: =SmtRes!I251 -> 21.21-5-342 | G90: =SmtRes!K251 -> Хомуты (стяжки) кабельные из полиамида, размеры 3,6х200 мм | H90: =SmtRes!O251 -> 100 шт. | I90: =SmtRes!Y251*Source!I820 -> 0.13 | J90: =SmtRes!AO251 -> 1 | K90: =SmtRes!AE251 -> 127.48 | L90: =SmtRes!DB251 -> 33.14 | M90: =ROUND(ROUND(L90*Source!I820, 6)*1, 2) -> 16.57 | N90: =SmtRes!AA251 -> 127.48 | O90: =ROUND(ROUND(L90*Source!I820, 6)*SmtRes!DA251, 2) -> 16.57 | P90: =SmtRes!AG251 -> 0 | Q90: =SmtRes!DC251 -> 0 | R90: =ROUND(ROUND(Q90*Source!I820, 6)*1, 2) -> 0 | S90: =SmtRes!AC251 -> 0 | T90: =ROUND(ROUND(Q90*Source!I820, 6)*SmtRes!AK251, 2) -> 0 | U90: 3 | Z90: =SmtRes!X251 -> 527662241 | AA90: -1533345047 | AB90: -1533345047
A91: 20 | B91: 250 | C91: 3 | D91: 0 | E91: =SmtRes!AV250 -> 0 | F91: =SmtRes!I250 -> 21.21-5-305 | G91: =SmtRes!K250 -> Сжимы, тип У731М для проводников магистральных сечением от 4 до 10 мм2 и ответвительных от 1,5 до 10 мм2 | H91: =SmtRes!O250 -> шт. | I91: =SmtRes!Y250*Source!I820 -> 5 | J91: =SmtRes!AO250 -> 1 | K91: =SmtRes!AE250 -> 29.36 | L91: =SmtRes!DB250 -> 293.6 | M91: =ROUND(ROUND(L91*Source!I820, 6)*1, 2) -> 146.8 | N91: =SmtRes!AA250 -> 29.36 | O91: =ROUND(ROUND(L91*Source!I820, 6)*SmtRes!DA250, 2) -> 146.8 | P91: =SmtRes!AG250 -> 0 | Q91: =SmtRes!DC250 -> 0 | R91: =ROUND(ROUND(Q91*Source!I820, 6)*1, 2) -> 0 | S91: =SmtRes!AC250 -> 0 | T91: =ROUND(ROUND(Q91*Source!I820, 6)*SmtRes!AK250, 2) -> 0 | U91: 3 | Z91: =SmtRes!X250 -> 1884843886 | AA91: 1143219249 | AB91: 1143219249
A92: 20 | B92: 249 | C92: 3 | D92: 0 | E92: =SmtRes!AV249 -> 0 | F92: =SmtRes!I249 -> 21.21-5-2 | G92: =SmtRes!K249 -> Бирки маркировочные для кабелей и проводов, тип У153 У3,5 | H92: =SmtRes!O249 -> 1000 шт. | I92: =SmtRes!Y249*Source!I820 -> 0.0025 | J92: =SmtRes!AO249 -> 1 | K92: =SmtRes!AE249 -> 718.56 | L92: =SmtRes!DB249 -> 3.59 | M92: =ROUND(ROUND(L92*Source!I820, 6)*1, 2) -> 1.8 | N92: =SmtRes!AA249 -> 718.56 | O92: =ROUND(ROUND(L92*Source!I820, 6)*SmtRes!DA249, 2) -> 1.8 | P92: =SmtRes!AG249 -> 0 | Q92: =SmtRes!DC249 -> 0 | R92: =ROUND(ROUND(Q92*Source!I820, 6)*1, 2) -> 0 | S92: =SmtRes!AC249 -> 0 | T92: =ROUND(ROUND(Q92*Source!I820, 6)*SmtRes!AK249, 2) -> 0 | U92: 3 | Z92: =SmtRes!X249 -> -1948375318 | AA92: 299589489 | AB92: 299589489
A93: 20 | B93: 248 | C93: 3 | D93: 0 | E93: =SmtRes!AV248 -> 0 | F93: =SmtRes!I248 -> 21.21-5-114 | G93: =SmtRes!K248 -> Лента монтажная, тип ЛМ-5 | H93: =SmtRes!O248 -> м | I93: =SmtRes!Y248*Source!I820 -> 2.5 | J93: =SmtRes!AO248 -> 1 | K93: =SmtRes!AE248 -> 5.71 | L93: =SmtRes!DB248 -> 28.55 | M93: =ROUND(ROUND(L93*Source!I820, 6)*1, 2) -> 14.28 | N93: =SmtRes!AA248 -> 5.71 | O93: =ROUND(ROUND(L93*Source!I820, 6)*SmtRes!DA248, 2) -> 14.28 | P93: =SmtRes!AG248 -> 0 | Q93: =SmtRes!DC248 -> 0 | R93: =ROUND(ROUND(Q93*Source!I820, 6)*1, 2) -> 0 | S93: =SmtRes!AC248 -> 0 | T93: =ROUND(ROUND(Q93*Source!I820, 6)*SmtRes!AK248, 2) -> 0 | U93: 3 | Z93: =SmtRes!X248 -> -1189895200 | AA93: 193152040 | AB93: 193152040
A94: 20 | B94: 247 | C94: 3 | D94: 0 | E94: =SmtRes!AV247 -> 0 | F94: =SmtRes!I247 -> 21.1-20-10 | G94: =SmtRes!K247 -> Лента изоляционная хлопчатобумажная | H94: =SmtRes!O247 -> кг | I94: =SmtRes!Y247*Source!I820 -> 0.08 | J94: =SmtRes!AO247 -> 1 | K94: =SmtRes!AE247 -> 363.22 | L94: =SmtRes!DB247 -> 58.12 | M94: =ROUND(ROUND(L94*Source!I820, 6)*1, 2) -> 29.06 | N94: =SmtRes!AA247 -> 363.22 | O94: =ROUND(ROUND(L94*Source!I820, 6)*SmtRes!DA247, 2) -> 29.06 | P94: =SmtRes!AG247 -> 0 | Q94: =SmtRes!DC247 -> 0 | R94: =ROUND(ROUND(Q94*Source!I820, 6)*1, 2) -> 0 | S94: =SmtRes!AC247 -> 0 | T94: =ROUND(ROUND(Q94*Source!I820, 6)*SmtRes!AK247, 2) -> 0 | U94: 3 | Z94: =SmtRes!X247 -> 1719425291 | AA94: -1596111638 | AB94: -1596111638
A95: =Source!A821 -> 17 | B95: 821 | C95: 3 | D95: =Source!BI821 -> 4 | E95: =Source!FS821 -> 0 | F95: =Source!F821 -> 21.23-8-270 | G95: =Source!G821 -> Кабели силовые, с медными жилами, с изоляц. и оболоч.из ПВХ пластиката пониж.пожар.опасности, не распростр.горение, с пониж.дымо- и газовыделением и с низк.токсич-тью продуктов горения, напряж.1000 В, марка ВВГнг(А)-LSLTx, число жил и сечение, мм2: 3х2,5 | H95: =Source!H821 -> км | I95: =Source!I821 -> 0.05 | J95: 1 | K95: =Source!AC821 -> 129532.62 | M95: =ROUND(K95*I95, 2) -> 6476.63 | N95: =Source!AC821*IF(Source!BC821<> 0, Source!BC821, 1) -> 129532.62 | O95: =ROUND(N95*I95, 2) -> 6476.63 | P95: =Source!AE821 -> 0 | R95: =ROUND(P95*I95, 2) -> 0 | S95: =Source!AE821*IF(Source!BS821<> 0, Source!BS821, 1) -> 0 | T95: =ROUND(S95*I95, 2) -> 0 | U95: 3 | Z95: =Source!GF821 -> 7717958 | AA95: 2094450950 | AB95: 2094450950
A96: =Source!A854 -> 4 | B96: 854 | G96: =Source!G854 -> Помещение 130 Вспомогательное помещение интерактивной библиотеки
A97: 20 | B97: 259 | C97: 3 | D97: 0 | E97: =SmtRes!AV259 -> 0 | F97: =SmtRes!I259 -> 21.7-3-29 | G97: =SmtRes!K259 -> Сверло алмазное кольцевое, высокоэффективное, для всех типов бетона, длина 430 мм, диаметр 72 мм | H97: =SmtRes!O259 -> шт. | I97: =SmtRes!Y259*Source!I859 -> 0.00134 | J97: =SmtRes!AO259 -> 1 | K97: =SmtRes!AE259 -> 16620.27 | L97: =SmtRes!DB259 -> 111.36 | M97: =ROUND(ROUND(L97*Source!I859, 6)*1, 2) -> 22.27 | N97: =SmtRes!AA259 -> 16620.27 | O97: =ROUND(ROUND(L97*Source!I859, 6)*SmtRes!DA259, 2) -> 22.27 | P97: =SmtRes!AG259 -> 0 | Q97: =SmtRes!DC259 -> 0 | R97: =ROUND(ROUND(Q97*Source!I859, 6)*1, 2) -> 0 | S97: =SmtRes!AC259 -> 0 | T97: =ROUND(ROUND(Q97*Source!I859, 6)*SmtRes!AK259, 2) -> 0 | U97: 3 | Z97: =SmtRes!X259 -> 656259231 | AA97: -55341773 | AB97: -55341773
A98: 20 | B98: 258 | C98: 3 | D98: 0 | E98: =SmtRes!AV258 -> 0 | F98: =SmtRes!I258 -> 21.1-25-13 | G98: =SmtRes!K258 -> Вода | H98: =SmtRes!O258 -> м3 | I98: =SmtRes!Y258*Source!I859 -> 0.00352 | J98: =SmtRes!AO258 -> 1 | K98: =SmtRes!AE258 -> 54.81 | L98: =SmtRes!DB258 -> 0.96 | M98: =ROUND(ROUND(L98*Source!I859, 6)*1, 2) -> 0.19 | N98: =SmtRes!AA258 -> 54.81 | O98: =ROUND(ROUND(L98*Source!I859, 6)*SmtRes!DA258, 2) -> 0.19 | P98: =SmtRes!AG258 -> 0 | Q98: =SmtRes!DC258 -> 0 | R98: =ROUND(ROUND(Q98*Source!I859, 6)*1, 2) -> 0 | S98: =SmtRes!AC258 -> 0 | T98: =ROUND(ROUND(Q98*Source!I859, 6)*SmtRes!AK258, 2) -> 0 | U98: 3 | Z98: =SmtRes!X258 -> -35091971 | AA98: 1203958368 | AB98: 1203958368
A99: =Source!A861 -> 17 | B99: 861 | C99: 3 | D99: =Source!BI861 -> 4 | E99: =Source!FS861 -> 0 | F99: =Source!F861 -> 21.23-8-140 | G99: =Source!G861 -> Кабели силовые с медными жилами, с изоляцией и оболочкой из поливинилхлоридных композиций пониженной пожароопасности, с низким дымо - и газовыделением, марка ВВГнг(А)-LS, напряжение 660 В, число жил и сечение, мм2: 3х2,5 | H99: =Source!H861 -> км | I99: =Source!I861 -> 0.001 | J99: 1 | K99: =Source!AC861 -> 99860.32 | M99: =ROUND(K99*I99, 2) -> 99.86 | N99: =Source!AC861*IF(Source!BC861<> 0, Source!BC861, 1) -> 99860.32 | O99: =ROUND(N99*I99, 2) -> 99.86 | P99: =Source!AE861 -> 0 | R99: =ROUND(P99*I99, 2) -> 0 | S99: =Source!AE861*IF(Source!BS861<> 0, Source!BS861, 1) -> 0 | T99: =ROUND(S99*I99, 2) -> 0 | U99: 3 | Z99: =Source!GF861 -> 2077141205 | AA99: 472379674 | AB99: 472379674
A100: =Source!A862 -> 17 | B100: 862 | C100: 3 | D100: =Source!BI862 -> 4 | E100: =Source!FS862 -> 0 | F100: =Source!F862 -> 21.21-5-84 | G100: =Source!G862 -> Коробки для установки выключателей, переключателей и штепсельных розеток при скрытой электропроводке, тип КУВ-1М УХЛЗ | H100: =Source!H862 -> 1000 шт. | I100: =Source!I862 -> 0.004 | J100: 1 | K100: =Source!AC862 -> 72169.9 | M100: =ROUND(K100*I100, 2) -> 288.68 | N100: =Source!AC862*IF(Source!BC862<> 0, Source!BC862, 1) -> 72169.9 | O100: =ROUND(N100*I100, 2) -> 288.68 | P100: =Source!AE862 -> 0 | R100: =ROUND(P100*I100, 2) -> 0 | S100: =Source!AE862*IF(Source!BS862<> 0, Source!BS862, 1) -> 0 | T100: =ROUND(S100*I100, 2) -> 0 | U100: 3 | Z100: =Source!GF862 -> 653953554 | AA100: -1378273173 | AB100: -1378273173
A101: =Source!A897 -> 4 | B101: 897 | G101: =Source!G897 -> Помещение 131 Подсобное помещение
A102: 20 | B102: 272 | C102: 3 | D102: 0 | E102: =SmtRes!AV272 -> 0 | F102: =SmtRes!I272 -> 21.7-3-29 | G102: =SmtRes!K272 -> Сверло алмазное кольцевое, высокоэффективное, для всех типов бетона, длина 430 мм, диаметр 72 мм | H102: =SmtRes!O272 -> шт. | I102: =SmtRes!Y272*Source!I902 -> 0.00134 | J102: =SmtRes!AO272 -> 1 | K102: =SmtRes!AE272 -> 16620.27 | L102: =SmtRes!DB272 -> 111.36 | M102: =ROUND(ROUND(L102*Source!I902, 6)*1, 2) -> 22.27 | N102: =SmtRes!AA272 -> 16620.27 | O102: =ROUND(ROUND(L102*Source!I902, 6)*SmtRes!DA272, 2) -> 22.27 | P102: =SmtRes!AG272 -> 0 | Q102: =SmtRes!DC272 -> 0 | R102: =ROUND(ROUND(Q102*Source!I902, 6)*1, 2) -> 0 | S102: =SmtRes!AC272 -> 0 | T102: =ROUND(ROUND(Q102*Source!I902, 6)*SmtRes!AK272, 2) -> 0 | U102: 3 | Z102: =SmtRes!X272 -> 656259231 | AA102: -55341773 | AB102: -55341773
...

Sheet Расчет стоимости ресурсов
A2: Ресурсная ведомость на
A3: =CONCATENATE("Объект: ",IF(Source!G3920<>"Новый объект", Source!G3920, "")) -> Объект: Электрика новая
A4: Обоснование | B4: Наименование | C4: Единица измерения | D4: Объем | E4: Базовая
E6: цена | F6: стоимость
A7: 1 | B7: 2 | C7: 3 | D7: 4 | E7: 5 | F7: 6
A8: =CONCATENATE("Локальная смета: ",IF(Source!G22<>"Новая локальная смета", Source!G22, "")) -> Локальная смета:
A9: =CONCATENATE("Раздел: ",IF(Source!G26<>"Новый раздел", Source!G26, "")) -> Раздел: Помещение 312 Актовый зал
A10: Материальные ресурсы
A11: 21.1-10-159 | B11: Сталь круглая и квадратная общего назначения углеродистая кипящая, марка Ст0, размер 5-12 мм | C11: т | D11: =ROUND(SUMIF(RV_DATA!AA8:AA34, 1531175116, RV_DATA!I8:I34), 6) -> 0.168 | E11: =ROUND(RV_DATA!K34, 6) -> 51568.06 | F11: =ROUND(SUMIF(RV_DATA!AA8:AA34, 1531175116, RV_DATA!M8:M34), 6) -> 8663.43 | Q11: 3
A12: 21.1-11-108 | B12: Шурупы-саморезы, размер 3,5х45 мм | C12: т | D12: =ROUND(SUMIF(RV_DATA!AA8:AA34, -2066596354, RV_DATA!I8:I34), 6) -> 0.002331 | E12: =ROUND(RV_DATA!K17, 6) -> 190540.34 | F12: =ROUND(SUMIF(RV_DATA!AA8:AA34, -2066596354, RV_DATA!M8:M34), 6) -> 444.15 | Q12: 3
A13: 21.1-11-133 | B13: Дюбель-гвоздь с патроном | C13: шт. | D13: =ROUND(SUMIF(RV_DATA!AA8:AA34, -503754449, RV_DATA!I8:I34), 6) -> 45.9 | E13: =ROUND(RV_DATA!K33, 6) -> 10.83 | F13: =ROUND(SUMIF(RV_DATA!AA8:AA34, -503754449, RV_DATA!M8:M34), 6) -> 497.1 | Q13: 3
A14: 21.1-11-198 | B14: Дюбели пластмассовые | C14: шт. | D14: =ROUND(SUMIF(RV_DATA!AA8:AA34, 798392207, RV_DATA!I8:I34), 6) -> 45.9 | E14: =ROUND(RV_DATA!K32, 6) -> 1.23 | F14: =ROUND(SUMIF(RV_DATA!AA8:AA34, 798392207, RV_DATA!M8:M34), 6) -> 56.46 | Q14: 3
A15: 21.1-11-21 | B15: Болты строительные черные с гайками и шайбами (10х100мм) | C15: т | D15: =ROUND(SUMIF(RV_DATA!AA8:AA34, -1191326009, RV_DATA!I8:I34), 6) -> 0.00312 | E15: =ROUND(RV_DATA!K31, 6) -> 161977.32 | F15: =ROUND(SUMIF(RV_DATA!AA8:AA34, -1191326009, RV_DATA!M8:M34), 6) -> 505.37 | Q15: 3
A16: 21.1-11-81 | B16: Патроны, калибр 6,8/11 М для дюбеля | C16: 100 шт. | D16: =ROUND(SUMIF(RV_DATA!AA8:AA34, -274985448, RV_DATA!I8:I34), 6) -> 12.6 | E16: =ROUND(RV_DATA!K16, 6) -> 997.35 | F16: =ROUND(SUMIF(RV_DATA!AA8:AA34, -274985448, RV_DATA!M8:M34), 6) -> 12566.61 | Q16: 3
A17: 21.1-20-10 | B17: Лента изоляционная хлопчатобумажная | C17: кг | D17: =ROUND(SUMIF(RV_DATA!AA8:AA34, -1596111638, RV_DATA!I8:I34), 6) -> 0.63 | E17: =ROUND(RV_DATA!K24, 6) -> 363.22 | F17: =ROUND(SUMIF(RV_DATA!AA8:AA34, -1596111638, RV_DATA!M8:M34), 6) -> 228.85 | Q17: 3
A18: 21.1-23-9 | B18: Электроды, тип Э-42, 46, 50, диаметр 4 - 6 мм | C18: т | D18: =ROUND(SUMIF(RV_DATA!AA8:AA34, 1948239711, RV_DATA!I8:I34), 6) -> 0.00063 | E18: =ROUND(RV_DATA!K29, 6) -> 109992.36 | F18: =ROUND(SUMIF(RV_DATA!AA8:AA34, 1948239711, RV_DATA!M8:M34), 6) -> 69.29 | Q18: 3
A19: 21.1-25-1027 | B19: Кабель-каналы, размер 60х40 мм: кабель-каналы | C19: м | D19: =ROUND(SUMIF(RV_DATA!AA8:AA34, -402984879, RV_DATA!I8:I34), 6) -> 315 | E19: =ROUND(RV_DATA!K15, 6) -> 138.94 | F19: =ROUND(SUMIF(RV_DATA!AA8:AA34, -402984879, RV_DATA!M8:M34), 6) -> 43766.1 | Q19: 3
A20: 21.1-25-1028 | B20: Кабель-каналы, размер 60х40 мм: заглушки | C20: шт. | D20: =ROUND(SUMIF(RV_DATA!AA8:AA34, 368106192, RV_DATA!I8:I34), 6) -> 47.25 | E20: =ROUND(RV_DATA!K14, 6) -> 145.46 | F20: =ROUND(SUMIF(RV_DATA!AA8:AA34, 368106192, RV_DATA!M8:M34), 6) -> 6872.99 | Q20: 3
A21: 21.1-25-1029 | B21: Кабель-каналы, размер 60х40 мм: накладки стыковые | C21: шт. | D21: =ROUND(SUMIF(RV_DATA!AA8:AA34, 1140495319, RV_DATA!I8:I34), 6) -> 12.6 | E21: =ROUND(RV_DATA!K13, 6) -> 126.89 | F21: =ROUND(SUMIF(RV_DATA!AA8:AA34, 1140495319, RV_DATA!M8:M34), 6) -> 1598.81 | Q21: 3
A22: 21.1-25-1031 | B22: Кабель-каналы, размер 60х40 мм: тройники | C22: шт. | D22: =ROUND(SUMIF(RV_DATA!AA8:AA34, -1841828503, RV_DATA!I8:I34), 6) -> 6.3 | E22: =ROUND(RV_DATA!K12, 6) -> 219.52 | F22: =ROUND(SUMIF(RV_DATA!AA8:AA34, -1841828503, RV_DATA!M8:M34), 6) -> 1382.98 | Q22: 3
A23: 21.1-25-1032 | B23: Кабель-каналы, размер 60х40 мм: углы внутренние | C23: шт. | D23: =ROUND(SUMIF(RV_DATA!AA8:AA34, -1064398607, RV_DATA!I8:I34), 6) -> 6.3 | E23: =ROUND(RV_DATA!K11, 6) -> 186.55 | F23: =ROUND(SUMIF(RV_DATA!AA8:AA34, -1064398607, RV_DATA!M8:M34), 6) -> 1175.27 | Q23: 3
A24: 21.1-25-1033 | B24: Кабель-каналы, размер 60х40 мм: углы наружные | C24: шт. | D24: =ROUND(SUMIF(RV_DATA!AA8:AA34, -124735961, RV_DATA!I8:I34), 6) -> 47.25 | E24: =ROUND(RV_DATA!K10, 6) -> 203.06 | F24: =ROUND(SUMIF(RV_DATA!AA8:AA34, -124735961, RV_DATA!M8:M34), 6) -> 9594.59 | Q24: 3
A25: 21.1-25-1034 | B25: Кабель-каналы, размер 60х40 мм: углы плоские | C25: шт. | D25: =ROUND(SUMIF(RV_DATA!AA8:AA34, 1614893387, RV_DATA!I8:I34), 6) -> 6.3 | E25: =ROUND(RV_DATA!K9, 6) -> 214.92 | F25: =ROUND(SUMIF(RV_DATA!AA8:AA34, 1614893387, RV_DATA!M8:M34), 6) -> 1354 | Q25: 3
A26: 21.1-6-37 | B26: Краски водно-дисперсионные поливинилацетатные, белые, марка ВД-ВА-17 | C26: т | D26: =ROUND(SUMIF(RV_DATA!AA8:AA34, 266707854, RV_DATA!I8:I34), 6) -> 0.0009 | E26: =ROUND(RV_DATA!K28, 6) -> 75121.86 | F26: =ROUND(SUMIF(RV_DATA!AA8:AA34, 266707854, RV_DATA!M8:M34), 6) -> 67.61 | Q26: 3
A27: 21.21-5-114 | B27: Лента монтажная, тип ЛМ-5 | C27: м | D27: =ROUND(SUMIF(RV_DATA!AA8:AA34, 193152040, RV_DATA!I8:I34), 6) -> 15.75 | E27: =ROUND(RV_DATA!K23, 6) -> 5.71 | F27: =ROUND(SUMIF(RV_DATA!AA8:AA34, 193152040, RV_DATA!M8:M34), 6) -> 89.93 | Q27: 3
A28: 21.21-5-2 | B28: Бирки маркировочные для кабелей и проводов, тип У153 У3,5 | C28: 1000 шт. | D28: =ROUND(SUMIF(RV_DATA!AA8:AA34, 299589489, RV_DATA!I8:I34), 6) -> 0.01575 | E28: =ROUND(RV_DATA!K22, 6) -> 718.56 | F28: =ROUND(SUMIF(RV_DATA!AA8:AA34, 299589489, RV_DATA!M8:M34), 6) -> 11.31 | Q28: 3
A29: 21.21-5-305 | B29: Сжимы, тип У731М для проводников магистральных сечением от 4 до 10 мм2 и ответвительных от 1,5 до 10 мм2 | C29: шт. | D29: =ROUND(SUMIF(RV_DATA!AA8:AA34, 1143219249, RV_DATA!I8:I34), 6) -> 31.5 | E29: =ROUND(RV_DATA!K21, 6) -> 29.36 | F29: =ROUND(SUMIF(RV_DATA!AA8:AA34, 1143219249, RV_DATA!M8:M34), 6) -> 924.84 | Q29: 3
A30: 21.21-5-342 | B30: Хомуты (стяжки) кабельные из полиамида, размеры 3,6х200 мм | C30: 100 шт. | D30: =ROUND(SUMIF(RV_DATA!AA8:AA34, -1533345047, RV_DATA!I8:I34), 6) -> 0.819 | E30: =ROUND(RV_DATA!K20, 6) -> 127.48 | F30: =ROUND(SUMIF(RV_DATA!AA8:AA34, -1533345047, RV_DATA!M8:M34), 6) -> 104.39 | Q30: 3
A31: 21.21-5-44 | B31: Кнопки для ленты ЛМ, тип 3,5 | C31: 1000 шт. | D31: =ROUND(SUMIF(RV_DATA!AA8:AA34, -2054620093, RV_DATA!I8:I34), 6) -> 0.063 | E31: =ROUND(RV_DATA!K19, 6) -> 258.44 | F31: =ROUND(SUMIF(RV_DATA!AA8:AA34, -2054620093, RV_DATA!M8:M34), 6) -> 16.29 | Q31: 3
A32: 21.23-13-14 | B32: Провода силовые с медными жилами в поливинилхлоридной изоляции, марка ПуГВ, номинальное напряжение до 450 В, число жил и сечение 1х6 мм2 | C32: км | D32: =ROUND(SUMIF(RV_DATA!AA8:AA34, -458052105, RV_DATA!I8:I34), 6) -> 0.32445 | E32: =ROUND(RV_DATA!K18, 6) -> 99643.05 | F32: =ROUND(SUMIF(RV_DATA!AA8:AA34, -458052105, RV_DATA!M8:M34), 6) -> 32329.17 | Q32: 3
A33: 21.23-8-258 | B33: Кабели силовые с медными жилами с поливинилхлоридной изоляцией в оболочке из поливинилхлоридного пластиката пониженной горючести, напряжение 660 В, марка ВВГнг(А), число жил и сечение, мм2: 1х 4 | C33: км | D33: =ROUND(SUMIF(RV_DATA!AA8:AA34, 249487062, RV_DATA!I8:I34), 6) -> 0.0108 | E33: =ROUND(RV_DATA!K27, 6) -> 47900.07 | F33: =ROUND(SUMIF(RV_DATA!AA8:AA34, 249487062, RV_DATA!M8:M34), 6) -> 517.32 | Q33: 3
A34: 21.23-8-270 | B34: Кабели силовые, с медными жилами, с изоляц. и оболоч.из ПВХ пластиката пониж.пожар.опасности, не распростр.горение, с пониж.дымо- и газовыделением и с низк.токсич-тью продуктов горения, напряж.1000 В, марка ВВГнг(А)-LSLTx, число жил и сечение, мм2: 3х2,5 | C34: км | D34: =ROUND(SUMIF(RV_DATA!AA8:AA34, 2094450950, RV_DATA!I8:I34), 6) -> 0.27 | E34: =ROUND(RV_DATA!K25, 6) -> 129532.62 | F34: =ROUND(SUMIF(RV_DATA!AA8:AA34, 2094450950, RV_DATA!M8:M34), 6) -> 34973.81 | Q34: 3
A35: 21.7-3-54 | B35: Сверло с алмазным покрытием, диаметр 6 мм | C35: шт. | D35: =ROUND(SUMIF(RV_DATA!AA8:AA34, -618828638, RV_DATA!I8:I34), 6) -> 12.6 | E35: =ROUND(RV_DATA!K8, 6) -> 1555.5 | F35: =ROUND(SUMIF(RV_DATA!AA8:AA34, -618828638, RV_DATA!M8:M34), 6) -> 19599.3 | Q35: 3
A36: 21.7-4-15 | B36: Профили стоек металлические для монтажа гипсовых перегородок и подвесных потолков стальные, оцинкованные, марка ПСЭ-2, сечение 50х35х0,55 мм | C36: т | D36: =ROUND(SUMIF(RV_DATA!AA8:AA34, 162372630, RV_DATA!I8:I34), 6) -> 0.0108 | E36: =ROUND(RV_DATA!K26, 6) -> 40246.74 | F36: =ROUND(SUMIF(RV_DATA!AA8:AA34, 162372630, RV_DATA!M8:M34), 6) -> 434.66 | Q36: 3
A37: Итого материальные ресурсы | E37: =SUMIF(Q11:Q36, 3, F11:F36) -> 177844.63
A38: =CONCATENATE("Раздел: ",IF(Source!G71<>"Новый раздел", Source!G71, "")) -> Раздел: Электрощит ЩАО (актовый зал)
A39: =CONCATENATE("Раздел: ",IF(Source!G109<>"Новый раздел", Source!G109, "")) -> Раздел: Электрощит ЩО (актовый зал)
A40: =CONCATENATE("Раздел: ",IF(Source!G147<>"Новый раздел", Source!G147, "")) -> Раздел: Электрощит РЩ (актовый зал)
A41: =CONCATENATE("Раздел: ",IF(Source!G185<>"Новый раздел", Source!G185, "")) -> Раздел: Помещение 108 Обеденный зал с умывальником
A42: =CONCATENATE("Раздел: ",IF(Source!G226<>"Новый раздел", Source!G226, "")) -> Раздел: Помещение 110 Кухня
A43: =CONCATENATE("Раздел: ",IF(Source!G265<>"Новый раздел", Source!G265, "")) -> Раздел: Помещение 111 Моечная
A44: =CONCATENATE("Раздел: ",IF(Source!G301<>"Новый раздел", Source!G301, "")) -> Раздел: Помещение 116 Душ
A45: =CONCATENATE("Раздел: ",IF(Source!G337<>"Новый раздел", Source!G337, "")) -> Раздел: Помещение 117 Коридор
A46: =CONCATENATE("Раздел: ",IF(Source!G374<>"Новый раздел", Source!G374, "")) -> Раздел: Помещение 118 Венткамера
A47: =CONCATENATE("Раздел: ",IF(Source!G411<>"Новый раздел", Source!G411, "")) -> Раздел: Помещение 119 помещение уборочного инвентаря
A48: =CONCATENATE("Раздел: ",IF(Source!G447<>"Новый раздел", Source!G447, "")) -> Раздел: Электрощит ТХ1
A49: =CONCATENATE("Раздел: ",IF(Source!G488<>"Новый раздел", Source!G488, "")) -> Раздел: Электрощит ТХ2
A50: =CONCATENATE("Раздел: ",IF(Source!G529<>"Новый раздел", Source!G529, "")) -> Раздел: Электрощит ТХ3
A51: =CONCATENATE("Раздел: ",IF(Source!G570<>"Новый раздел", Source!G570, "")) -> Раздел: Помещение 104 Вестибюль
A52: Материальные ресурсы
A53: 21.1-1-1065 | B53: Кабель-каналы, размер 105х50 мм: ответвления Т-образные | C53: шт. | D53: =ROUND(SUMIF(RV_DATA!AA49:AA59, -1296774037, RV_DATA!I49:I59), 6) -> 0.02 | E53: =ROUND(RV_DATA!K58, 6) -> 1415.18 | F53: =ROUND(SUMIF(RV_DATA!AA49:AA59, -1296774037, RV_DATA!M49:M59), 6) -> 28.3 | Q53: 3
A54: 21.1-11-108 | B54: Шурупы-саморезы, размер 3,5х45 мм | C54: т | D54: =ROUND(SUMIF(RV_DATA!AA49:AA59, -2066596354, RV_DATA!I49:I59), 6) -> 7e-06 | E54: =ROUND(RV_DATA!K57, 6) -> 190540.34 | F54: =ROUND(SUMIF(RV_DATA!AA49:AA59, -2066596354, RV_DATA!M49:M59), 6) -> 1.41 | Q54: 3
A55: 21.1-11-81 | B55: Патроны, калибр 6,8/11 М для дюбеля | C55: 100 шт. | D55: =ROUND(SUMIF(RV_DATA!AA49:AA59, -274985448, RV_DATA!I49:I59), 6) -> 0.04 | E55: =ROUND(RV_DATA!K56, 6) -> 997.35 | F55: =ROUND(SUMIF(RV_DATA!AA49:AA59, -274985448, RV_DATA!M49:M59), 6) -> 39.89 | Q55: 3
A56: 21.1-25-1035 | B56: Кабель-каналы, размер 105х50 мм: короба c направляющими | C56: м | D56: =ROUND(SUMIF(RV_DATA!AA49:AA59, 892245811, RV_DATA!I49:I59), 6) -> 1 | E56: =ROUND(RV_DATA!K55, 6) -> 658.59 | F56: =ROUND(SUMIF(RV_DATA!AA49:AA59, 892245811, RV_DATA!M49:M59), 6) -> 658.59 | Q56: 3
A57: 21.1-25-1036 | B57: Кабель-каналы, размер 105х50 мм: заглушки | C57: шт. | D57: =ROUND(SUMIF(RV_DATA!AA49:AA59, -1719495285, RV_DATA!I49:I59), 6) -> 0.15 | E57: =ROUND(RV_DATA!K54, 6) -> 153.13 | F57: =ROUND(SUMIF(RV_DATA!AA49:AA59, -1719495285, RV_DATA!M49:M59), 6) -> 22.97 | Q57: 3
A58: 21.1-25-1037 | B58: Кабель-каналы, размер 105х50 мм: накладки на стык крышки | C58: шт. | D58: =ROUND(SUMIF(RV_DATA!AA49:AA59, 528708715, RV_DATA!I49:I59), 6) -> 0.04 | E58: =ROUND(RV_DATA!K53, 6) -> 172.42 | F58: =ROUND(SUMIF(RV_DATA!AA49:AA59, 528708715, RV_DATA!M49:M59), 6) -> 6.9 | Q58: 3
A59: 21.1-25-1038 | B59: Кабель-каналы, размер 105х50 мм: накладки на стык профилей | C59: шт. | D59: =ROUND(SUMIF(RV_DATA!AA49:AA59, -158674467, RV_DATA!I49:I59), 6) -> 0.04 | E59: =ROUND(RV_DATA!K52, 6) -> 54.24 | F59: =ROUND(SUMIF(RV_DATA!AA49:AA59, -158674467, RV_DATA!M49:M59), 6) -> 2.17 | Q59: 3
A60: 21.1-25-1040 | B60: Кабель-каналы, размер 105х50 мм: углы внутренние | C60: шт. | D60: =ROUND(SUMIF(RV_DATA!AA49:AA59, 746688475, RV_DATA!I49:I59), 6) -> 0.02 | E60: =ROUND(RV_DATA!K51, 6) -> 666.11 | F60: =ROUND(SUMIF(RV_DATA!AA49:AA59, 746688475, RV_DATA!M49:M59), 6) -> 13.32 | Q60: 3
A61: 21.1-25-1041 | B61: Кабель-каналы, размер 105х50 мм: углы наружные | C61: шт. | D61: =ROUND(SUMIF(RV_DATA!AA49:AA59, -619013872, RV_DATA!I49:I59), 6) -> 0.15 | E61: =ROUND(RV_DATA!K50, 6) -> 776.23 | F61: =ROUND(SUMIF(RV_DATA!AA49:AA59, -619013872, RV_DATA!M49:M59), 6) -> 116.43 | Q61: 3
A62: 21.1-25-1042 | B62: Кабель-каналы, размер 105х50 мм: углы плоские | C62: шт. | D62: =ROUND(SUMIF(RV_DATA!AA49:AA59, 1537823898, RV_DATA!I49:I59), 6) -> 0.02 | E62: =ROUND(RV_DATA!K49, 6) -> 947.75 | F62: =ROUND(SUMIF(RV_DATA!AA49:AA59, 1537823898, RV_DATA!M49:M59), 6) -> 18.96 | Q62: 3
A63: 21.21-5-397 | B63: Розетки (механизмы) штепсельные, серия "Мозаик", тип 2К+3, с винтовыми зажимами, с защитными шторками и заземляющим контактом | C63: шт. | D63: =ROUND(SUMIF(RV_DATA!AA49:AA59, -303846849, RV_DATA!I49:I59), 6) -> 3 | E63: =ROUND(RV_DATA!K59, 6) -> 432.44 | F63: =ROUND(SUMIF(RV_DATA!AA49:AA59, -303846849, RV_DATA!M49:M59), 6) -> 1297.32 | Q63: 3
A64: Итого материальные ресурсы | E64: =SUMIF(Q53:Q63, 3, F53:F63) -> 2206.26
A65: =CONCATENATE("Раздел: ",IF(Source!G610<>"Новый раздел", Source!G610, "")) -> Раздел: Помещение 123 Электрощитовая
A66: =CONCATENATE("Раздел: ",IF(Source!G647<>"Новый раздел", Source!G647, "")) -> Раздел: Помещение 125 Водомерный узел
A67: =CONCATENATE("Раздел: ",IF(Source!G685<>"Новый раздел", Source!G685, "")) -> Раздел: Помещение 126 Комната охраны
A68: =CONCATENATE("Раздел: ",IF(Source!G724<>"Новый раздел", Source!G724, "")) -> Раздел: Помещение 127 Подсобное помещение
A69: Материальные ресурсы
A70: 21.1-25-13 | B70: Вода | C70: м3 | D70: =ROUND(SUMIF(RV_DATA!AA64:AA67, 1203958368, RV_DATA!I64:I67), 6) -> 0.00176 | E70: =ROUND(RV_DATA!K65, 6) -> 54.81 | F70: =ROUND(SUMIF(RV_DATA!AA64:AA67, 1203958368, RV_DATA!M64:M67), 6) -> 0.1 | Q70: 3
A71: 21.21-5-84 | B71: Коробки для установки выключателей, переключателей и штепсельных розеток при скрытой электропроводке, тип КУВ-1М УХЛЗ | C71: 1000 шт. | D71: =ROUND(SUMIF(RV_DATA!AA64:AA67, -1378273173, RV_DATA!I64:I67), 6) -> 0.002 | E71: =ROUND(RV_DATA!K67, 6) -> 72169.9 | F71: =ROUND(SUMIF(RV_DATA!AA64:AA67, -1378273173, RV_DATA!M64:M67), 6) -> 144.34 | Q71: 3
A72: 21.23-8-140 | B72: Кабели силовые с медными жилами, с изоляцией и оболочкой из поливинилхлоридных композиций пониженной пожароопасности, с низким дымо - и газовыделением, марка ВВГнг(А)-LS, напряжение 660 В, число жил и сечение, мм2: 3х2,5 | C72: км | D72: =ROUND(SUMIF(RV_DATA!AA64:AA67, 472379674, RV_DATA!I64:I67), 6) -> 0.001 | E72: =ROUND(RV_DATA!K66, 6) -> 99860.32 | F72: =ROUND(SUMIF(RV_DATA!AA64:AA67, 472379674, RV_DATA!M64:M67), 6) -> 99.86 | Q72: 3
A73: 21.7-3-29 | B73: Сверло алмазное кольцевое, высокоэффективное, для всех типов бетона, длина 430 мм, диаметр 72 мм | C73: шт. | D73: =ROUND(SUMIF(RV_DATA!AA64:AA67, -55341773, RV_DATA!I64:I67), 6) -> 0.00067 | E73: =ROUND(RV_DATA!K64, 6) -> 16620.27 | F73: =ROUND(SUMIF(RV_DATA!AA64:AA67, -55341773, RV_DATA!M64:M67), 6) -> 11.14 | Q73: 3
A74: Итого материальные ресурсы | E74: =SUMIF(Q70:Q73, 3, F70:F73) -> 255.44
A75: =CONCATENATE("Раздел: ",IF(Source!G766<>"Новый раздел", Source!G766, "")) -> Раздел: Помещение 128 Кабинет завхоза
A76: Материальные ресурсы
A77: 21.1-25-13 | B77: Вода | C77: м3 | D77: =ROUND(SUMIF(RV_DATA!AA69:AA72, 1203958368, RV_DATA!I69:I72), 6) -> 0.00176 | E77: =ROUND(RV_DATA!K70, 6) -> 54.81 | F77: =ROUND(SUMIF(RV_DATA!AA69:AA72, 1203958368, RV_DATA!M69:M72), 6) -> 0.1 | Q77: 3
A78: 21.21-5-84 | B78: Коробки для установки выключателей, переключателей и штепсельных розеток при скрытой электропроводке, тип КУВ-1М УХЛЗ | C78: 1000 шт. | D78: =ROUND(SUMIF(RV_DATA!AA69:AA72, -1378273173, RV_DATA!I69:I72), 6) -> 0.002 | E78: =ROUND(RV_DATA!K72, 6) -> 72169.9 | F78: =ROUND(SUMIF(RV_DATA!AA69:AA72, -1378273173, RV_DATA!M69:M72), 6) -> 144.34 | Q78: 3
A79: 21.23-8-140 | B79: Кабели силовые с медными жилами, с изоляцией и оболочкой из поливинилхлоридных композиций пониженной пожароопасности, с низким дымо - и газовыделением, марка ВВГнг(А)-LS, напряжение 660 В, число жил и сечение, мм2: 3х2,5 | C79: км | D79: =ROUND(SUMIF(RV_DATA!AA69:AA72, 472379674, RV_DATA!I69:I72), 6) -> 0.001 | E79: =ROUND(RV_DATA!K71, 6) -> 99860.32 | F79: =ROUND(SUMIF(RV_DATA!AA69:AA72, 472379674, RV_DATA!M69:M72), 6) -> 99.86 | Q79: 3
A80: 21.7-3-29 | B80: Сверло алмазное кольцевое, высокоэффективное, для всех типов бетона, длина 430 мм, диаметр 72 мм | C80: шт. | D80: =ROUND(SUMIF(RV_DATA!AA69:AA72, -55341773, RV_DATA!I69:I72), 6) -> 0.00067 | E80: =ROUND(RV_DATA!K69, 6) -> 16620.27 | F80: =ROUND(SUMIF(RV_DATA!AA69:AA72, -55341773, RV_DATA!M69:M72), 6) -> 11.14 | Q80: 3
A81: Итого материальные ресурсы | E81: =SUMIF(Q77:Q80, 3, F77:F80) -> 255.44
A82: =CONCATENATE("Раздел: ",IF(Source!G809<>"Новый раздел", Source!G809, "")) -> Раздел: Помещение 129 Интерактивная библиотека
A83: Материальные ресурсы
A84: 21.1-11-108 | B84: Шурупы-саморезы, размер 3,5х45 мм | C84: т | D84: =ROUND(SUMIF(RV_DATA!AA74:AA95, -2066596354, RV_DATA!I74:I95), 6) -> 0.00037 | E84: =ROUND(RV_DATA!K87, 6) -> 190540.34 | F84: =ROUND(SUMIF(RV_DATA!AA74:AA95, -2066596354, RV_DATA!M74:M95), 6) -> 70.5 | Q84: 3
A85: 21.1-11-81 | B85: Патроны, калибр 6,8/11 М для дюбеля | C85: 100 шт. | D85: =ROUND(SUMIF(RV_DATA!AA74:AA95, -274985448, RV_DATA!I74:I95), 6) -> 2 | E85: =ROUND(RV_DATA!K86, 6) -> 997.35 | F85: =ROUND(SUMIF(RV_DATA!AA74:AA95, -274985448, RV_DATA!M74:M95), 6) -> 1994.7 | Q85: 3
A86: 21.1-20-10 | B86: Лента изоляционная хлопчатобумажная | C86: кг | D86: =ROUND(SUMIF(RV_DATA!AA74:AA95, -1596111638, RV_DATA!I74:I95), 6) -> 0.08 | E86: =ROUND(RV_DATA!K94, 6) -> 363.22 | F86: =ROUND(SUMIF(RV_DATA!AA74:AA95, -1596111638, RV_DATA!M74:M95), 6) -> 29.06 | Q86: 3
A87: 21.1-25-1027 | B87: Кабель-каналы, размер 60х40 мм: кабель-каналы | C87: м | D87: =ROUND(SUMIF(RV_DATA!AA74:AA95, -402984879, RV_DATA!I74:I95), 6) -> 50 | E87: =ROUND(RV_DATA!K85, 6) -> 138.94 | F87: =ROUND(SUMIF(RV_DATA!AA74:AA95, -402984879, RV_DATA!M74:M95), 6) -> 6947 | Q87: 3
A88: 21.1-25-1028 | B88: Кабель-каналы, размер 60х40 мм: заглушки | C88: шт. | D88: =ROUND(SUMIF(RV_DATA!AA74:AA95, 368106192, RV_DATA!I74:I95), 6) -> 7.5 | E88: =ROUND(RV_DATA!K84, 6) -> 145.46 | F88: =ROUND(SUMIF(RV_DATA!AA74:AA95, 368106192, RV_DATA!M74:M95), 6) -> 1090.95 | Q88: 3
A89: 21.1-25-1029 | B89: Кабель-каналы, размер 60х40 мм: накладки стыковые | C89: шт. | D89: =ROUND(SUMIF(RV_DATA!AA74:AA95, 1140495319, RV_DATA!I74:I95), 6) -> 2 | E89: =ROUND(RV_DATA!K83, 6) -> 126.89 | F89: =ROUND(SUMIF(RV_DATA!AA74:AA95, 1140495319, RV_DATA!M74:M95), 6) -> 253.78 | Q89: 3
A90: 21.1-25-1031 | B90: Кабель-каналы, размер 60х40 мм: тройники | C90: шт. | D90: =ROUND(SUMIF(RV_DATA!AA74:AA95, -1841828503, RV_DATA!I74:I95), 6) -> 1 | E90: =ROUND(RV_DATA!K82, 6) -> 219.52 | F90: =ROUND(SUMIF(RV_DATA!AA74:AA95, -1841828503, RV_DATA!M74:M95), 6) -> 219.52 | Q90: 3
A91: 21.1-25-1032 | B91: Кабель-каналы, размер 60х40 мм: углы внутренние | C91: шт. | D91: =ROUND(SUMIF(RV_DATA!AA74:AA95, -1064398607, RV_DATA!I74:I95), 6) -> 1 | E91: =ROUND(RV_DATA!K81, 6) -> 186.55 | F91: =ROUND(SUMIF(RV_DATA!AA74:AA95, -1064398607, RV_DATA!M74:M95), 6) -> 186.55 | Q91: 3
A92: 21.1-25-1033 | B92: Кабель-каналы, размер 60х40 мм: углы наружные | C92: шт. | D92: =ROUND(SUMIF(RV_DATA!AA74:AA95, -124735961, RV_DATA!I74:I95), 6) -> 7.5 | E92: =ROUND(RV_DATA!K80, 6) -> 203.06 | F92: =ROUND(SUMIF(RV_DATA!AA74:AA95, -124735961, RV_DATA!M74:M95), 6) -> 1522.95 | Q92: 3
A93: 21.1-25-1034 | B93: Кабель-каналы, размер 60х40 мм: углы плоские | C93: шт. | D93: =ROUND(SUMIF(RV_DATA!AA74:AA95, 1614893387, RV_DATA!I74:I95), 6) -> 1 | E93: =ROUND(RV_DATA!K79, 6) -> 214.92 | F93: =ROUND(SUMIF(RV_DATA!AA74:AA95, 1614893387, RV_DATA!M74:M95), 6) -> 214.92 | Q93: 3
A94: 21.1-25-13 | B94: Вода | C94: м3 | D94: =ROUND(SUMIF(RV_DATA!AA74:AA95, 1203958368, RV_DATA!I74:I95), 6) -> 0.0352 | E94: =ROUND(RV_DATA!K75, 6) -> 54.81 | F94: =ROUND(SUMIF(RV_DATA!AA74:AA95, 1203958368, RV_DATA!M74:M95), 6) -> 1.92 | Q94: 3
A95: 21.21-5-114 | B95: Лента монтажная, тип ЛМ-5 | C95: м | D95: =ROUND(SUMIF(RV_DATA!AA74:AA95, 193152040, RV_DATA!I74:I95), 6) -> 2.5 | E95: =ROUND(RV_DATA!K93, 6) -> 5.71 | F95: =ROUND(SUMIF(RV_DATA!AA74:AA95, 193152040, RV_DATA!M74:M95), 6) -> 14.28 | Q95: 3
A96: 21.21-5-2 | B96: Бирки маркировочные для кабелей и проводов, тип У153 У3,5 | C96: 1000 шт. | D96: =ROUND(SUMIF(RV_DATA!AA74:AA95, 299589489, RV_DATA!I74:I95), 6) -> 0.0025 | E96: =ROUND(RV_DATA!K92, 6) -> 718.56 | F96: =ROUND(SUMIF(RV_DATA!AA74:AA95, 299589489, RV_DATA!M74:M95), 6) -> 1.8 | Q96: 3
A97: 21.21-5-305 | B97: Сжимы, тип У731М для проводников магистральных сечением от 4 до 10 мм2 и ответвительных от 1,5 до 10 мм2 | C97: шт. | D97: =ROUND(SUMIF(RV_DATA!AA74:AA95, 1143219249, RV_DATA!I74:I95), 6) -> 5 | E97: =ROUND(RV_DATA!K91, 6) -> 29.36 | F97: =ROUND(SUMIF(RV_DATA!AA74:AA95, 1143219249, RV_DATA!M74:M95), 6) -> 146.8 | Q97: 3
A98: 21.21-5-342 | B98: Хомуты (стяжки) кабельные из полиамида, размеры 3,6х200 мм | C98: 100 шт. | D98: =ROUND(SUMIF(RV_DATA!AA74:AA95, -1533345047, RV_DATA!I74:I95), 6) -> 0.13 | E98: =ROUND(RV_DATA!K90, 6) -> 127.48 | F98: =ROUND(SUMIF(RV_DATA!AA74:AA95, -1533345047, RV_DATA!M74:M95), 6) -> 16.57 | Q98: 3
A99: 21.21-5-44 | B99: Кнопки для ленты ЛМ, тип 3,5 | C99: 1000 шт. | D99: =ROUND(SUMIF(RV_DATA!AA74:AA95, -2054620093, RV_DATA!I74:I95), 6) -> 0.01 | E99: =ROUND(RV_DATA!K89, 6) -> 258.44 | F99: =ROUND(SUMIF(RV_DATA!AA74:AA95, -2054620093, RV_DATA!M74:M95), 6) -> 2.59 | Q99: 3
A100: 21.21-5-84 | B100: Коробки для установки выключателей, переключателей и штепсельных розеток при скрытой электропроводке, тип КУВ-1М УХЛЗ | C100: 1000 шт. | D100: =ROUND(SUMIF(RV_DATA!AA74:AA95, -1378273173, RV_DATA!I74:I95), 6) -> 0.004 | E100: =ROUND(RV_DATA!K77, 6) -> 72169.9 | F100: =ROUND(SUMIF(RV_DATA!AA74:AA95, -1378273173, RV_DATA!M74:M95), 6) -> 288.68 | Q100: 3
A101: 21.23-13-14 | B101: Провода силовые с медными жилами в поливинилхлоридной изоляции, марка ПуГВ, номинальное напряжение до 450 В, число жил и сечение 1х6 мм2 | C101: км | D101: =ROUND(SUMIF(RV_DATA!AA74:AA95, -458052105, RV_DATA!I74:I95), 6) -> 0.0515 | E101: =ROUND(RV_DATA!K88, 6) -> 99643.05 | F101: =ROUND(SUMIF(RV_DATA!AA74:AA95, -458052105, RV_DATA!M74:M95), 6) -> 5131.62 | Q101: 3
A102: 21.23-8-140 | B102: Кабели силовые с медными жилами, с изоляцией и оболочкой из поливинилхлоридных композиций пониженной пожароопасности, с низким дымо - и газовыделением, марка ВВГнг(А)-LS, напряжение 660 В, число жил и сечение, мм2: 3х2,5 | C102: км | D102: =ROUND(SUMIF(RV_DATA!AA74:AA95, 472379674, RV_DATA!I74:I95), 6) -> 0.001 | E102: =ROUND(RV_DATA!K76, 6) -> 99860.32 | F102: =ROUND(SUMIF(RV_DATA!AA74:AA95, 472379674, RV_DATA!M74:M95), 6) -> 99.86 | Q102: 3
...

Sheet Source
A1: 0 | B1: Smeta.RU (495) 974-1589 | D1: _PS_ | F1: 0 | G1: 0 | H1: 0 | I1: Smeta.RU | K1: 1 | L1: 54800 | M1: 10 | N1: 11 | O1: 15 | P1: 0 | Q1: 2
A12: 1 | B12: 3956 | C12: 0 | D12: =ROW(A3920) -> 3920 | E12: 0 | F12: Новый объект | G12: Электрика новая | I12: 0 | K12: 0 | L12: 0 | M12: 2 | O12: 0 | P12: 0 | Q12: 0 | R12: 108 | T12: 1 | V12: 0 | BB12: 0 | BH12: Сметные нормы списания | BI12: Коды ОКП для СН-2012 Выпуск № 6 (в ценах на 01.01.2026 г) | BJ12: 1 | BK12: 1 | BL12: 0 | BM12: 0 | BN12: 1 | BO12: 0 | BP12: 6 | BQ12: 2 | BR12: 1 | BS12: 1 | BT12: 0 | BU12: 0 | BV12: 1 | BW12: 0 | BX12: 0 | BY12: СН-2012 Выпуск № 6. (в ценах на 01.01.2026) глава_1-5, 7 | BZ12: Типовой расчет для СН-2012 Выпуск №6 (в ценах на 01.01.2026 г) | CA12: СН-2012 Выпуск № 6. База данных "Сборник стоимостных нормативов" в текущих ценах по состоянию на 01.01.2026 года | CB12: СН-2012 Выпуск № 6. База данных "Сборник стоимостных нормативов" в текущих ценах по состоянию на 01.01.2026 года | CC12: СН-2012 Выпуск № 6. База данных "Сборник стоимостных нормативов" в текущих ценах по состоянию на 01.01.2026 года | CD12: СН-2012 Выпуск № 6. База данных "Сборник стоимостных нормативов" в текущих ценах по состоянию на 01.01.2026 года | CE12: Поправки для СН-2012 Выпуск № 6 в ценах на 01.01.2026 г от 12.01.2026 | CF12: 0 | CG12: 0 | CH12: 2097160 | CK12: 0 | CY12: 0 | EC12: 0
A15: 15 | B15: 1
A18: 52 | B18: =B3920 -> 3956 | C18: =C3920 -> 1 | D18: =D3920 -> 12 | E18: =E3920 -> 0 | F18: =F3920 -> Новый объект | G18: =G3920 -> Электрика новая | O18: =O3920 -> 7348913 | P18: =P3920 -> 3554749.7 | Q18: =Q3920 -> 40402.55 | R18: =R3920 -> 5925.72 | S18: =S3920 -> 3753760.7 | T18: =T3920 -> 0 | U18: =U3920 -> 5228.5613 | V18: =V3920 -> 0 | ... GX18: =GX3920 -> 0
A20: 3 | B20: 1 | D20: =ROW(A3887) -> 3887 | F20: Новая локальная смета | G20: Новая локальная смета | I20: 0 | K20: 0 | L20: Новая локальная смета | S20: 0 | V20: 0 | BX20: 0 | CF20: 0 | CG20: 0
A22: 52 | B22: =B3887 -> 1 | C22: =C3887 -> 3 | D22: =D3887 -> 20 | E22: =E3887 -> 0 | F22: =F3887 -> Новая локальная смета | G22: =G3887 -> Новая локальная смета | O22: =O3887 -> 7348913 | P22: =P3887 -> 3554749.7 | Q22: =Q3887 -> 40402.55 | R22: =R3887 -> 5925.72 | S22: =S3887 -> 3753760.7 | T22: =T3887 -> 0 | U22: =U3887 -> 5228.5613 | V22: =V3887 -> 0 | ... GX22: =GX3887 -> 0
A24: 4 | B24: 1 | D24: =ROW(A39) -> 39 | F24: Новый раздел | G24: Помещение 312 Актовый зал | I24: 0 | K24: 0 | S24: 0 | V24: 0 | BX24: 0 | CJ24: 0
A26: 52 | B26: =B39 -> 1 | C26: =C39 -> 4 | D26: =D39 -> 24 | E26: =E39 -> 0 | F26: =F39 -> Новый раздел | G26: =G39 -> Помещение 312 Актовый зал | O26: =O39 -> 336394.13 | P26: =P39 -> 177844.64 | Q26: =Q39 -> 3050.01 | R26: =R39 -> 1434.4 | S26: =S39 -> 155499.48 | T26: =T39 -> 0 | U26: =U39 -> 258.213 | V26: =V39 -> 0 | ... GX26: =GX39 -> 0
A28: 17 | B28: 1 | C28: =ROW(SmtRes!A1) -> 1 | D28: =ROW(EtalonRes!A1) -> 1 | E28: 1 | F28: 1.21-3305-1-1/1 | G28: Демонтаж выключателей, розеток | H28: 100 шт. | I28: =ROUND(10/100,9) -> 0.1 | J28: 0 | K28: =ROUND(10/100,9) -> 0.1 | O28: =ROUND(CP28,2) -> 271.05 | P28: =ROUND(CQ28*I28,2) -> 0 | Q28: =ROUND(CR28*I28,2) -> 0 | R28: =ROUND(CS28*I28,2) -> 0 | S28: =ROUND(CT28*I28,2) -> 271.05 | T28: =ROUND(CU28*I28,2) -> 0 | U28: =CV28*I28 -> 0.584 | V28: =CW28*I28 -> 0 | W28: =ROUND(CX28*I28,2) -> 0 | X28: =ROUND(CY28,2) -> 189.74 | Y28: =ROUND(CZ28,2) -> 27.11 | AA28: 35364244 | AB28: =ROUND((AC28+AD28+AF28),6) -> 2710.46 | AC28: =ROUND((ES28),6) -> 0 | AD28: =ROUND((((ET28)-(EU28))+AE28),6) -> 0 | AE28: =ROUND((EU28),6) -> 0 | AF28: =ROUND((EV28),6) -> 2710.46 | AG28: =ROUND((AP28),6) -> 0 | AH28: =(EW28) -> 5.84 | AI28: =(EX28) -> 0 | AJ28: =(AS28) -> 0 | AK28: 2710.46 | AL28: 0 | AM28: 0 | AN28: 0 | AO28: 2710.46 | AP28: 0 | AQ28: 5.84 | AR28: 0 | AS28: 0 | AT28: 70 | AU28: 10 | AV28: 1 | AW28: 1 | AZ28: 1 | BA28: 1 | BB28: 1 | BC28: 1 | BH28: 0 | BI28: 4 | BJ28: СН-2012.1 Выпуск № 6 (в текущих ценах по состоянию на 01.01.2026 г.). 1.21-3305-1-1/1 | BM28: 0 | BN28: 0 | BP28: 0 | BQ28: 1 | BR28: 0 | BS28: 1 | BT28: 1 | BU28: 1 | BV28: 1 | BW28: 1 | BX28: 1 | BZ28: 70 | CA28: 10 | CE28: 0 | CF28: 0 | CG28: 0 | CM28: 0 | CO28: 0 | CP28: =(P28+Q28+S28) -> 271.05 | CQ28: =(AC28*BC28*AW28) -> 0 | CR28: =((((ET28)*BB28-(EU28)*BS28)+AE28*BS28)*AV28) -> 0 | CS28: =(AE28*BS28*AV28) -> 0 | CT28: =(AF28*BA28*AV28) -> 2710.46 | CU28: =AG28 -> 0 | CV28: =(AH28*AV28) -> 5.84 | CW28: =AI28 -> 0 | CX28: =AJ28 -> 0 | CY28: =((S28*BZ28)/100) -> 189.735 | CZ28: =((S28*CA28)/100) -> 27.105 | DN28: 0 | DO28: 0 | DP28: 1 | DQ28: 1 | DU28: 1010 | DV28: 100 шт. | DW28: 100 шт. | DX28: 100 | EE28: 35096056 | EF28: 1 | EG28: СН-2012 | EH28: 0 | EJ28: 4 | EK28: 0 | EL28: Подрядные работы, гл. 1-5,7 | EM28: работа | EQ28: 0 | ER28: 2710.46 | ES28: 0 | ET28: 0 | EU28: 0 | EV28: 2710.46 | EW28: 5.84 | EX28: 0 | EY28: 0 | FQ28: 0 | FR28: 0 | FS28: 0 | FX28: 70 | FY28: 10 | GD28: 0 | GF28: -931379651 | GG28: 2 | GH28: 1 | GI28: -2 | GJ28: 0 | GK28: =ROUND(R28*(R12)/100,2) -> 0 | GL28: =ROUND(IF(AND(BH28=3,BI28=3,FS28<>0),P28,0),2) -> 0 | GM28: =ROUND(O28+X28+Y28+GK28,2)+GX28 -> 487.9 | GN28: =IF(OR(BI28=0,BI28=1),GM28-GX28,0) -> 0 | GO28: =IF(BI28=2,GM28-GX28,0) -> 0 | GP28: =IF(BI28=4,GM28-GX28,0) -> 487.9 | GR28: 0 | GS28: 3 | GT28: 0 | GV28: =ROUND((GT28),6) -> 0 | GW28: 1 | GX28: =ROUND(HC28*I28,2) -> 0 | HA28: 0 | HB28: 0 | HC28: =GV28*GW28 -> 0 | HS28: 0 | IK28: 0
A29: 17 | B29: 1 | C29: =ROW(SmtRes!A14) -> 14 | D29: =ROW(EtalonRes!A14) -> 14 | E29: 2 | F29: 1.21-3103-31-2/3 | G29: Прокладка пластикового кабель-канала - по бетонному основанию / сечение 60х40 мм | H29: 100 м | I29: =ROUND(315/100,9) -> 3.15 | J29: 0 | K29: =ROUND(315/100,9) -> 3.15 | O29: =ROUND(CP29,2) -> 182312.64 | P29: =ROUND(CQ29*I29,2) -> 98354.78 | Q29: =ROUND(CR29*I29,2) -> 212.31 | R29: =ROUND(CS29*I29,2) -> 2.93 | S29: =ROUND(CT29*I29,2) -> 83745.55 | T29: =ROUND(CU29*I29,2) -> 0 | U29: =CV29*I29 -> 147.357 | V29: =CW29*I29 -> 0 | W29: =ROUND(CX29*I29,2) -> 0 | X29: =ROUND(CY29,2) -> 58621.89 | Y29: =ROUND(CZ29,2) -> 8374.56 | AA29: 35364244 | AB29: =ROUND((AC29+AD29+AF29),6) -> 57877.03 | AC29: =ROUND((ES29),6) -> 31223.74 | AD29: =ROUND((((ET29)-(EU29))+AE29),6) -> 67.4 | AE29: =ROUND((EU29),6) -> 0.93 | AF29: =ROUND((EV29),6) -> 26585.89 | AG29: =ROUND((AP29),6) -> 0 | AH29: =(EW29) -> 46.78 | AI29: =(EX29) -> 0 | AJ29: =(AS29) -> 0 | AK29: 57877.03 | AL29: 31223.74 | AM29: 67.4 | AN29: 0.93 | AO29: 26585.89 | AP29: 0 | AQ29: 46.78 | AR29: 0 | AS29: 0 | AT29: 70 | AU29: 10 | AV29: 1 | AW29: 1 | AZ29: 1 | BA29: 1 | BB29: 1 | BC29: 1 | BH29: 0 | BI29: 4 | BJ29: СН-2012.1 Выпуск № 6 (в текущих ценах по состоянию на 01.01.2026 г.). 1.21-3103-31-2/3 | BM29: 0 | BN29: 0 | BP29: 0 | BQ29: 1 | BR29: 0 | BS29: 1 | BT29: 1 | BU29: 1 | BV29: 1 | BW29: 1 | BX29: 1 | BZ29: 70 | CA29: 10 | CE29: 0 | CF29: 0 | CG29: 0 | CM29: 0 | CO29: 0 | CP29: =(P29+Q29+S29) -> 182312.64 | CQ29: =(AC29*BC29*AW29) -> 31223.74 | CR29: =((((ET29)*BB29-(EU29)*BS29)+AE29*BS29)*AV29) -> 67.4 | CS29: =(AE29*BS29*AV29) -> 0.93 | CT29: =(AF29*BA29*AV29) -> 26585.89 | CU29: =AG29 -> 0 | CV29: =(AH29*AV29) -> 46.78 | CW29: =AI29 -> 0 | CX29: =AJ29 -> 0 | CY29: =((S29*BZ29)/100) -> 58621.885 | CZ29: =((S29*CA29)/100) -> 8374.555 | DN29: 0 | DO29: 0 | DP29: 1 | DQ29: 1 | DU29: 1003 | DV29: 100 м | DW29: 100 м | DX29: 100 | EE29: 35096056 | EF29: 1 | EG29: СН-2012 | EH29: 0 | EJ29: 4 | EK29: 0 | EL29: Подрядные работы, гл. 1-5,7 | EM29: работа | EQ29: 0 | ER29: 57877.03 | ES29: 31223.74 | ET29: 67.4 | EU29: 0.93 | EV29: 26585.89 | EW29: 46.78 | EX29: 0 | EY29: 0 | FQ29: 0 | FR29: 0 | FS29: 0 | FX29: 70 | FY29: 10 | GD29: 0 | GF29: -236507790 | GG29: 2 | GH29: 1 | GI29: -2 | GJ29: 0 | GK29: =ROUND(R29*(R12)/100,2) -> 3.16 | GL29: =ROUND(IF(AND(BH29=3,BI29=3,FS29<>0),P29,0),2) -> 0 | GM29: =ROUND(O29+X29+Y29+GK29,2)+GX29 -> 249312.25 | GN29: =IF(OR(BI29=0,BI29=1),GM29-GX29,0) -> 0 | GO29: =IF(BI29=2,GM29-GX29,0) -> 0 | GP29: =IF(BI29=4,GM29-GX29,0) -> 249312.25 | GR29: 0 | GS29: 3 | GT29: 0 | GV29: =ROUND((GT29),6) -> 0 | GW29: 1 | GX29: =ROUND(HC29*I29,2) -> 0 | HA29: 0 | HB29: 0 | HC29: =GV29*GW29 -> 0 | HS29: 0 | IK29: 0
A30: 17 | B30: 1 | C30: =ROW(SmtRes!A23) -> 23 | D30: =ROW(EtalonRes!A23) -> 23 | E30: 3 | F30: 1.21-3103-7-1/1 | G30: Прокладка проводов и кабелей в лотках, провод сечением до 6 мм2 | H30: 100 м | I30: =ROUND(315/100,9) -> 3.15 | J30: 0 | K30: =ROUND(315/100,9) -> 3.15 | O30: =ROUND(CP30,2) -> 38734.1 | P30: =ROUND(CQ30*I30,2) -> 33659.04 | Q30: =ROUND(CR30*I30,2) -> 2808.51 | R30: =ROUND(CS30*I30,2) -> 1431.2 | S30: =ROUND(CT30*I30,2) -> 2266.55 | T30: =ROUND(CU30*I30,2) -> 0 | U30: =CV30*I30 -> 3.717 | V30: =CW30*I30 -> 0 | W30: =ROUND(CX30*I30,2) -> 0 | X30: =ROUND(CY30,2) -> 1586.59 | Y30: =ROUND(CZ30,2) -> 226.66 | AA30: 35364244 | AB30: =ROUND((AC30+AD30+AF30),6) -> 12296.54 | AC30: =ROUND((ES30),6) -> 10685.41 | AD30: =ROUND((((ET30)-(EU30))+AE30),6) -> 891.59 | AE30: =ROUND((EU30),6) -> 454.35 | AF30: =ROUND((EV30),6) -> 719.54 | AG30: =ROUND((AP30),6) -> 0 | AH30: =(EW30) -> 1.18 | AI30: =(EX30) -> 0 | AJ30: =(AS30) -> 0 | AK30: 12296.54 | AL30: 10685.41 | AM30: 891.59 | AN30: 454.35 | AO30: 719.54 | AP30: 0 | AQ30: 1.18 | AR30: 0 | AS30: 0 | AT30: 70 | AU30: 10 | AV30: 1 | AW30: 1 | AZ30: 1 | BA30: 1 | BB30: 1 | BC30: 1 | BH30: 0 | BI30: 4 | BJ30: СН-2012.1 Выпуск № 6 (в текущих ценах по состоянию на 01.01.2026 г.). 1.21-3103-7-1/1 | BM30: 0 | BN30: 0 | BP30: 0 | BQ30: 1 | BR30: 0 | BS30: 1 | BT30: 1 | BU30: 1 | BV30: 1 | BW30: 1 | BX30: 1 | BZ30: 70 | CA30: 10 | CE30: 0 | CF30: 0 | CG30: 0 | CM30: 0 | CO30: 0 | CP30: =(P30+Q30+S30) -> 38734.1 | CQ30: =(AC30*BC30*AW30) -> 10685.41 | CR30: =((((ET30)*BB30-(EU30)*BS30)+AE30*BS30)*AV30) -> 891.59 | CS30: =(AE30*BS30*AV30) -> 454.35 | CT30: =(AF30*BA30*AV30) -> 719.54 | CU30: =AG30 -> 0 | CV30: =(AH30*AV30) -> 1.18 | CW30: =AI30 -> 0 | CX30: =AJ30 -> 0 | CY30: =((S30*BZ30)/100) -> 1586.585 | CZ30: =((S30*CA30)/100) -> 226.655 | DN30: 0 | DO30: 0 | DP30: 1 | DQ30: 1 | DU30: 1003 | DV30: 100 м | DW30: 100 м | DX30: 100 | EE30: 35096056 | EF30: 1 | EG30: СН-2012 | EH30: 0 | EJ30: 4 | EK30: 0 | EL30: Подрядные работы, гл. 1-5,7 | EM30: работа | EQ30: 0 | ER30: 12296.54 | ES30: 10685.41 | ET30: 891.59 | EU30: 454.35 | EV30: 719.54 | EW30: 1.18 | EX30: 0 | EY30: 0 | FQ30: 0 | FR30: 0 | FS30: 0 | FX30: 70 | FY30: 10 | GD30: 0 | GF30: 1756020469 | GG30: 2 | GH30: 1 | GI30: -2 | GJ30: 0 | GK30: =ROUND(R30*(R12)/100,2) -> 1545.7 | GL30: =ROUND(IF(AND(BH30=3,BI30=3,FS30<>0),P30,0),2) -> 0 | GM30: =ROUND(O30+X30+Y30+GK30,2)+GX30 -> 42093.05 | GN30: =IF(OR(BI30=0,BI30=1),GM30-GX30,0) -> 0 | GO30: =IF(BI30=2,GM30-GX30,0) -> 0 | GP30: =IF(BI30=4,GM30-GX30,0) -> 42093.05 | GR30: 0 | GS30: 3 | GT30: 0 | GV30: =ROUND((GT30),6) -> 0 | GW30: 1 | GX30: =ROUND(HC30*I30,2) -> 0 | HA30: 0 | HB30: 0 | HC30: =GV30*GW30 -> 0 | HS30: 0 | IK30: 0
A31: 17 | B31: 1 | E31: 4 | F31: 21.23-8-270 | G31: Кабели силовые, с медными жилами, с изоляц. и оболоч.из ПВХ пластиката пониж.пожар.опасности, не распростр.горение, с пониж.дымо- и газовыделением и с низк.токсич-тью продуктов горения, напряж.1000 В, марка ВВГнг(А)-LSLTx, число жил и сечение, мм2: 3х2,5 | H31: км | I31: 0.27 | J31: 0 | K31: 0.27 | O31: =ROUND(CP31,2) -> 34973.81 | P31: =ROUND(CQ31*I31,2) -> 34973.81 | Q31: =ROUND(CR31*I31,2) -> 0 | R31: =ROUND(CS31*I31,2) -> 0 | S31: =ROUND(CT31*I31,2) -> 0 | T31: =ROUND(CU31*I31,2) -> 0 | U31: =CV31*I31 -> 0 | V31: =CW31*I31 -> 0 | W31: =ROUND(CX31*I31,2) -> 0 | X31: =ROUND(CY31,2) -> 0 | Y31: =ROUND(CZ31,2) -> 0 | AA31: 35364244 | AB31: =ROUND((AC31+AD31+AF31),6) -> 129532.62 | AC31: =ROUND((ES31),6) -> 129532.62 | AD31: =ROUND((((ET31)-(EU31))+AE31),6) -> 0 | AE31: =ROUND((EU31),6) -> 0 | AF31: =ROUND((EV31),6) -> 0 | AG31: =ROUND((AP31),6) -> 0 | AH31: =(EW31) -> 0 | AI31: =(EX31) -> 0 | AJ31: =(AS31) -> 0 | AK31: 129532.62 | AL31: 129532.62 | AM31: 0 | AN31: 0 | AO31: 0 | AP31: 0 | AQ31: 0 | AR31: 0 | AS31: 0 | AT31: 70 | AU31: 10 | AV31: 1 | AW31: 1 | AZ31: 1 | BA31: 1 | BB31: 1 | BC31: 1 | BH31: 3 | BI31: 4 | BJ31: СН-2012.21 Выпуск № 6 (в текущих ценах по состоянию на 01.01.2026 г.). 21.23-8-270 | BM31: 0 | BN31: 0 | BP31: 0 | BQ31: 1 | BR31: 0 | BS31: 1 | BT31: 1 | BU31: 1 | BV31: 1 | BW31: 1 | BX31: 1 | BZ31: 70 | CA31: 10 | CE31: 0 | CF31: 0 | CG31: 0 | CM31: 0 | CO31: 0 | CP31: =(P31+Q31+S31) -> 34973.81 | CQ31: =(AC31*BC31*AW31) -> 129532.62 | CR31: =((((ET31)*BB31-(EU31)*BS31)+AE31*BS31)*AV31) -> 0 | CS31: =(AE31*BS31*AV31) -> 0 | CT31: =(AF31*BA31*AV31) -> 0 | CU31: =AG31 -> 0 | CV31: =(AH31*AV31) -> 0 | CW31: =AI31 -> 0 | CX31: =AJ31 -> 0 | CY31: =((S31*BZ31)/100) -> 0 | CZ31: =((S31*CA31)/100) -> 0 | DN31: 0 | DO31: 0 | DP31: 1 | DQ31: 1 | DU31: 1003 | DV31: км | DW31: км | DX31: 1000 | EE31: 35096056 | EF31: 1 | EG31: СН-2012 | EH31: 0 | EJ31: 4 | EK31: 0 | EL31: Подрядные работы, гл. 1-5,7 | EM31: работа | EQ31: 0 | ER31: 129532.62 | ES31: 129532.62 | ET31: 0 | EU31: 0 | EV31: 0 | EW31: 0 | EX31: 0 | EY31: 0 | FQ31: 0 | FR31: 0 | FS31: 0 | FX31: 70 | FY31: 10 | GD31: 0 | GF31: 7717958 | GG31: 2 | GH31: 1 | GI31: -2 | GJ31: 0 | GK31: =ROUND(R31*(R12)/100,2) -> 0 | GL31: =ROUND(IF(AND(BH31=3,BI31=3,FS31<>0),P31,0),2) -> 0 | GM31: =ROUND(O31+X31+Y31+GK31,2)+GX31 -> 34973.81 | GN31: =IF(OR(BI31=0,BI31=1),GM31-GX31,0) -> 0 | GO31: =IF(BI31=2,GM31-GX31,0) -> 0 | GP31: =IF(BI31=4,GM31-GX31,0) -> 34973.81 | GR31: 0 | GS31: 3 | GT31: 0 | GV31: =ROUND((GT31),6) -> 0 | GW31: 1 | GX31: =ROUND(HC31*I31,2) -> 0 | HA31: 0 | HB31: 0 | HC31: =GV31*GW31 -> 0 | HS31: 0 | IK31: 0
A32: 17 | B32: 1 | C32: =ROW(SmtRes!A25) -> 25 | D32: =ROW(EtalonRes!A25) -> 25 | E32: 5 | F32: 1.20-3103-1-8/1 | G32: Установка розетки штепсельной неутопленного типа при открытой проводке | H32: 100 шт. | I32: =ROUND(12/100,9) -> 0.12 | J32: 0 | K32: =ROUND(12/100,9) -> 0.12 | O32: =ROUND(CP32,2) -> 3349.92 | P32: =ROUND(CQ32*I32,2) -> 0 | Q32: =ROUND(CR32*I32,2) -> 3.91 | R32: =ROUND(CS32*I32,2) -> 0.08 | S32: =ROUND(CT32*I32,2) -> 3346.01 | T32: =ROUND(CU32*I32,2) -> 0 | U32: =CV32*I32 -> 5.1372 | V32: =CW32*I32 -> 0 | W32: =ROUND(CX32*I32,2) -> 0 | X32: =ROUND(CY32,2) -> 2342.21 | Y32: =ROUND(CZ32,2) -> 334.6 | AA32: 35364244 | AB32: =ROUND((AC32+AD32+AF32),6) -> 27916.01 | AC32: =ROUND((ES32),6) -> 0 | AD32: =ROUND((((ET32)-(EU32))+AE32),6) -> 32.57 | AE32: =ROUND((EU32),6) -> 0.69 | AF32: =ROUND((EV32),6) -> 27883.44 | AG32: =ROUND((AP32),6) -> 0 | AH32: =(EW32) -> 42.81 | AI32: =(EX32) -> 0 | AJ32: =(AS32) -> 0 | AK32: 27916.01 | AL32: 0 | AM32: 32.57 | AN32: 0.69 | AO32: 27883.44 | AP32: 0 | AQ32: 42.81 | AR32: 0 | AS32: 0 | AT32: 70 | AU32: 10 | AV32: 1 | AW32: 1 | AZ32: 1 | BA32: 1 | BB32: 1 | BC32: 1 | BH32: 0 | BI32: 4 | BJ32: СН-2012.1 Выпуск № 6 (в текущих ценах по состоянию на 01.01.2026 г.). 1.20-3103-1-8/1 | BM32: 0 | BN32: 0 | BP32: 0 | BQ32: 1 | BR32: 0 | BS32: 1 | BT32: 1 | BU32: 1 | BV32: 1 | BW32: 1 | BX32: 1 | BZ32: 70 | CA32: 10 | CE32: 0 | CF32: 0 | CG32: 0 | CM32: 0 | CO32: 0 | CP32: =(P32+Q32+S32) -> 3349.92 | CQ32: =(AC32*BC32*AW32) -> 0 | CR32: =((((ET32)*BB32-(EU32)*BS32)+AE32*BS32)*AV32) -> 32.57 | CS32: =(AE32*BS32*AV32) -> 0.69 | CT32: =(AF32*BA32*AV32) -> 27883.44 | CU32: =AG32 -> 0 | CV32: =(AH32*AV32) -> 42.81 | CW32: =AI32 -> 0 | CX32: =AJ32 -> 0 | CY32: =((S32*BZ32)/100) -> 2342.207 | CZ32: =((S32*CA32)/100) -> 334.601 | DN32: 0 | DO32: 0 | DP32: 1 | DQ32: 1 | DU32: 1010 | DV32: 100 шт. | DW32: 100 шт. | DX32: 100 | EE32: 35096056 | EF32: 1 | EG32: СН-2012 | EH32: 0 | EJ32: 4 | EK32: 0 | EL32: Подрядные работы, гл. 1-5,7 | EM32: работа | EQ32: 262144 | ER32: 27916.01 | ES32: 0 | ET32: 32.57 | EU32: 0.69 | EV32: 27883.44 | EW32: 42.81 | EX32: 0 | EY32: 0 | FQ32: 0 | FR32: 0 | FS32: 0 | FX32: 70 | FY32: 10 | GD32: 0 | GF32: 1394402761 | GG32: 2 | GH32: 1 | GI32: -2 | GJ32: 0 | GK32: =ROUND(R32*(R12)/100,2) -> 0.09 | GL32: =ROUND(IF(AND(BH32=3,BI32=3,FS32<>0),P32,0),2) -> 0 | GM32: =ROUND(O32+X32+Y32+GK32,2)+GX32 -> 6026.82 | GN32: =IF(OR(BI32=0,BI32=1),GM32-GX32,0) -> 0 | GO32: =IF(BI32=2,GM32-GX32,0) -> 0 | GP32: =IF(BI32=4,GM32-GX32,0) -> 6026.82 | GR32: 0 | GS32: 3 | GT32: 0 | GV32: =ROUND((GT32),6) -> 0 | GW32: 1 | GX32: =ROUND(HC32*I32,2) -> 0 | HA32: 0 | HB32: 0 | HC32: =GV32*GW32 -> 0 | HS32: 0 | IK32: 0
A33: 17 | B33: 1 | C33: =ROW(SmtRes!A27) -> 27 | D33: =ROW(EtalonRes!A27) -> 27 | E33: 6 | F33: 1.20-3103-1-1/1 | G33: Установка выключателя одноклавишного неутопленного типа при открытой проводке | H33: 100 шт. | I33: =ROUND(2/100,9) -> 0.02 | J33: 0 | K33: =ROUND(2/100,9) -> 0.02 | O33: =ROUND(CP33,2) -> 511.55 | P33: =ROUND(CQ33*I33,2) -> 0 | Q33: =ROUND(CR33*I33,2) -> 0.65 | R33: =ROUND(CS33*I33,2) -> 0.01 | S33: =ROUND(CT33*I33,2) -> 510.9 | T33: =ROUND(CU33*I33,2) -> 0 | U33: =CV33*I33 -> 0.7844 | V33: =CW33*I33 -> 0 | W33: =ROUND(CX33*I33,2) -> 0 | X33: =ROUND(CY33,2) -> 357.63 | Y33: =ROUND(CZ33,2) -> 51.09 | AA33: 35364244 | AB33: =ROUND((AC33+AD33+AF33),6) -> 25577.73 | AC33: =ROUND((ES33),6) -> 0 | AD33: =ROUND((((ET33)-(EU33))+AE33),6) -> 32.57 | AE33: =ROUND((EU33),6) -> 0.69 | AF33: =ROUND((EV33),6) -> 25545.16 | AG33: =ROUND((AP33),6) -> 0 | AH33: =(EW33) -> 39.22 | AI33: =(EX33) -> 0 | AJ33: =(AS33) -> 0 | AK33: 25577.73 | AL33: 0 | AM33: 32.57 | AN33: 0.69 | AO33: 25545.16 | AP33: 0 | AQ33: 39.22 | AR33: 0 | AS33: 0 | AT33: 70 | AU33: 10 | AV33: 1 | AW33: 1 | AZ33: 1 | BA33: 1 | BB33: 1 | BC33: 1 | BH33: 0 | BI33: 4 | BJ33: СН-2012.1 Выпуск № 6 (в текущих ценах по состоянию на 01.01.2026 г.). 1.20-3103-1-1/1 | BM33: 0 | BN33: 0 | BP33: 0 | BQ33: 1 | BR33: 0 | BS33: 1 | BT33: 1 | BU33: 1 | BV33: 1 | BW33: 1 | BX33: 1 | BZ33: 70 | CA33: 10 | CE33: 0 | CF33: 0 | CG33: 0 | CM33: 0 | CO33: 0 | CP33: =(P33+Q33+S33) -> 511.55 | CQ33: =(AC33*BC33*AW33) -> 0 | CR33: =((((ET33)*BB33-(EU33)*BS33)+AE33*BS33)*AV33) -> 32.57 | CS33: =(AE33*BS33*AV33) -> 0.69 | CT33: =(AF33*BA33*AV33) -> 25545.16 | CU33: =AG33 -> 0 | CV33: =(AH33*AV33) -> 39.22 | CW33: =AI33 -> 0 | CX33: =AJ33 -> 0 | CY33: =((S33*BZ33)/100) -> 357.63 | CZ33: =((S33*CA33)/100) -> 51.09 | DN33: 0 | DO33: 0 | DP33: 1 | DQ33: 1 | DU33: 1010 | DV33: 100 шт. | DW33: 100 шт. | DX33: 100 | EE33: 35096056 | EF33: 1 | EG33: СН-2012 | EH33: 0 | EJ33: 4 | EK33: 0 | EL33: Подрядные работы, гл. 1-5,7 | EM33: работа | EQ33: 262144 | ER33: 25577.73 | ES33: 0 | ET33: 32.57 | EU33: 0.69 | EV33: 25545.16 | EW33: 39.22 | EX33: 0 | EY33: 0 | FQ33: 0 | FR33: 0 | FS33: 0 | FX33: 70 | FY33: 10 | GD33: 0 | GF33: 1212913616 | GG33: 2 | GH33: 1 | GI33: -2 | GJ33: 0 | GK33: =ROUND(R33*(R12)/100,2) -> 0.01 | GL33: =ROUND(IF(AND(BH33=3,BI33=3,FS33<>0),P33,0),2) -> 0 | GM33: =ROUND(O33+X33+Y33+GK33,2)+GX33 -> 920.28 | GN33: =IF(OR(BI33=0,BI33=1),GM33-GX33,0) -> 0 | GO33: =IF(BI33=2,GM33-GX33,0) -> 0 | GP33: =IF(BI33=4,GM33-GX33,0) -> 920.28 | GR33: 0 | GS33: 3 | GT33: 0 | GV33: =ROUND((GT33),6) -> 0 | GW33: 1 | GX33: =ROUND(HC33*I33,2) -> 0 | HA33: 0 | HB33: 0 | HC33: =GV33*GW33 -> 0 | HS33: 0 | IK33: 0
A34: 17 | B34: 1 | C34: =ROW(SmtRes!A29) -> 29 | D34: =ROW(EtalonRes!A29) -> 29 | E34: 7 | F34: 1.20-3103-1-4/1 | G34: Установка выключателя двухклавишного неутопленного типа при открытой проводке | H34: 100 шт. | I34: =ROUND(2/100,9) -> 0.02 | J34: 0 | K34: =ROUND(2/100,9) -> 0.02 | O34: =ROUND(CP34,2) -> 571.48 | P34: =ROUND(CQ34*I34,2) -> 0 | Q34: =ROUND(CR34*I34,2) -> 0.65 | R34: =ROUND(CS34*I34,2) -> 0.01 | S34: =ROUND(CT34*I34,2) -> 570.83 | T34: =ROUND(CU34*I34,2) -> 0 | U34: =CV34*I34 -> 0.8764 | V34: =CW34*I34 -> 0 | W34: =ROUND(CX34*I34,2) -> 0 | X34: =ROUND(CY34,2) -> 399.58 | Y34: =ROUND(CZ34,2) -> 57.08 | AA34: 35364244 | AB34: =ROUND((AC34+AD34+AF34),6) -> 28573.85 | AC34: =ROUND((ES34),6) -> 0 | AD34: =ROUND((((ET34)-(EU34))+AE34),6) -> 32.57 | AE34: =ROUND((EU34),6) -> 0.69 | AF34: =ROUND((EV34),6) -> 28541.28 | AG34: =ROUND((AP34),6) -> 0 | AH34: =(EW34) -> 43.82 | AI34: =(EX34) -> 0 | AJ34: =(AS34) -> 0 | AK34: 28573.85 | AL34: 0 | AM34: 32.57 | AN34: 0.69 | AO34: 28541.28 | AP34: 0 | AQ34: 43.82 | AR34: 0 | AS34: 0 | AT34: 70 | AU34: 10 | AV34: 1 | AW34: 1 | AZ34: 1 | BA34: 1 | BB34: 1 | BC34: 1 | BH34: 0 | BI34: 4 | BJ34: СН-2012.1 Выпуск № 6 (в текущих ценах по состоянию на 01.01.2026 г.). 1.20-3103-1-4/1 | BM34: 0 | BN34: 0 | BP34: 0 | BQ34: 1 | BR34: 0 | BS34: 1 | BT34: 1 | BU34: 1 | BV34: 1 | BW34: 1 | BX34: 1 | BZ34: 70 | CA34: 10 | CE34: 0 | CF34: 0 | CG34: 0 | CM34: 0 | CO34: 0 | CP34: =(P34+Q34+S34) -> 571.48 | CQ34: =(AC34*BC34*AW34) -> 0 | CR34: =((((ET34)*BB34-(EU34)*BS34)+AE34*BS34)*AV34) -> 32.57 | CS34: =(AE34*BS34*AV34) -> 0.69 | CT34: =(AF34*BA34*AV34) -> 28541.28 | CU34: =AG34 -> 0 | CV34: =(AH34*AV34) -> 43.82 | CW34: =AI34 -> 0 | CX34: =AJ34 -> 0 | CY34: =((S34*BZ34)/100) -> 399.581 | CZ34: =((S34*CA34)/100) -> 57.083 | DN34: 0 | DO34: 0 | DP34: 1 | DQ34: 1 | DU34: 1010 | DV34: 100 шт. | DW34: 100 шт. | DX34: 100 | EE34: 35096056 | EF34: 1 | EG34: СН-2012 | EH34: 0 | EJ34: 4 | EK34: 0 | EL34: Подрядные работы, гл. 1-5,7 | EM34: работа | EQ34: 262144 | ER34: 28573.85 | ES34: 0 | ET34: 32.57 | EU34: 0.69 | EV34: 28541.28 | EW34: 43.82 | EX34: 0 | EY34: 0 | FQ34: 0 | FR34: 0 | FS34: 0 | FX34: 70 | FY34: 10 | GD34: 0 | GF34: -1730436719 | GG34: 2 | GH34: 1 | GI34: -2 | GJ34: 0 | GK34: =ROUND(R34*(R12)/100,2) -> 0.01 | GL34: =ROUND(IF(AND(BH34=3,BI34=3,FS34<>0),P34,0),2) -> 0 | GM34: =ROUND(O34+X34+Y34+GK34,2)+GX34 -> 1028.15 | GN34: =IF(OR(BI34=0,BI34=1),GM34-GX34,0) -> 0 | GO34: =IF(BI34=2,GM34-GX34,0) -> 0 | GP34: =IF(BI34=4,GM34-GX34,0) -> 1028.15 | GR34: 0 | GS34: 3 | GT34: 0 | GV34: =ROUND((GT34),6) -> 0 | GW34: 1 | GX34: =ROUND(HC34*I34,2) -> 0 | HA34: 0 | HB34: 0 | HC34: =GV34*GW34 -> 0 | HS34: 0 | IK34: 0
A35: 17 | B35: 1 | C35: =ROW(SmtRes!A32) -> 32 | D35: =ROW(EtalonRes!A32) -> 32 | E35: 8 | F35: 1.20-3103-23-1/1 | G35: Установка светильника светодиодного (панели) 595х595 мм в подвесном потолке, устанавливаемого на профиле, со встроенным драйвером / светильник (панель) 595х595х19 мм, 27 Вт, 3000 Лм, 4000 К, IP40 / (демонтаж) | H35: шт. | I35: 22 | J35: 0 | K35: 22 | O35: =ROUND(CP35,2) -> 1418.74 | P35: =ROUND(CQ35*I35,2) -> 0 | Q35: =ROUND(CR35*I35,2) -> 0 | R35: =ROUND(CS35*I35,2) -> 0 | S35: =ROUND(CT35*I35,2) -> 1418.74 | T35: =ROUND(CU35*I35,2) -> 0 | U35: =CV35*I35 -> 2.464 | V35: =CW35*I35 -> 0 | W35: =ROUND(CX35*I35,2) -> 0 | X35: =ROUND(CY35,2) -> 993.12 | Y35: =ROUND(CZ35,2) -> 141.87 | AA35: 35364244 | AB35: =ROUND((AC35+AD35+AF35),6) -> 64.488 | AC35: =ROUND(((ES35*0)),6) -> 0 | AD35: =ROUND(((((ET35*0.2))-((EU35*0.2)))+AE35),6) -> 0 | AE35: =ROUND(((EU35*0.2)),6) -> 0 | AF35: =ROUND(((EV35*0.2)),6) -> 64.488 | AG35: =ROUND((AP35),6) -> 0 | AH35: =((EW35*0.2)) -> 0.112 | AI35: =((EX35*0.2)) -> 0 | AJ35: =(AS35) -> 0 | AK35: 2841.38 | AL35: 2518.94 | AM35: 0 | AN35: 0 | AO35: 322.44 | AP35: 0 | AQ35: 0.56 | AR35: 0 | AS35: 0 | AT35: 70 | AU35: 10 | AV35: 1 | AW35: 1 | AZ35: 1 | BA35: 1 | BB35: 1 | BC35: 1 | BH35: 0 | BI35: 4 | BJ35: СН-2012.1 Выпуск № 6 (в текущих ценах по состоянию на 01.01.2026 г.). 1.20-3103-23-1/1 | BM35: 0 | BN35: 0 | BP35: 0 | BQ35: 1 | BR35: 0 | BS35: 1 | BT35: 1 | BU35: 1 | BV35: 1 | BW35: 1 | BX35: 1 | BZ35: 70 | CA35: 10 | CE35: 0 | CF35: 0 | CG35: 0 | CM35: 0 | CN35: Поправка: СН-2012 О.П. п.22 Наименование: Демонтаж, разборка отдельных бетонных, железобетонных, металлических, деревянных, пластмассовых конструктивных элементов зданий и сооружений, внутренних и наружных инженерных систем и коммуникаций при отсутствии необходимых стоимостных нормативов в сборниках СН-2012 | CO35: 0 | CP35: =(P35+Q35+S35) -> 1418.74 | CQ35: =(AC35*BC35*AW35) -> 0 | CR35: =(((((ET35*0.2))*BB35-((EU35*0.2))*BS35)+AE35*BS35)*AV35) -> 0 | CS35: =(AE35*BS35*AV35) -> 0 | CT35: =(AF35*BA35*AV35) -> 64.488 | CU35: =AG35 -> 0 | CV35: =(AH35*AV35) -> 0.112 | CW35: =AI35 -> 0 | CX35: =AJ35 -> 0 | CY35: =((S35*BZ35)/100) -> 993.118 | CZ35: =((S35*CA35)/100) -> 141.874 | DB35: 1 | DD35: *0 | DE35: *0,2 | DF35: *0,2 | DG35: *0,2 | DI35: *0,2 | DJ35: *0,2 | DN35: 0 | DO35: 0 | DP35: 1 | DQ35: 1 | DU35: 1010 | DV35: шт. | DW35: шт. | DX35: 1 | EE35: 35096056 | EF35: 1 | EG35: СН-2012 | EH35: 0 | EJ35: 4 | EK35: 0 | EL35: Подрядные работы, гл. 1-5,7 | EM35: работа | EO35: Поправка: СН-2012 О.П. п.22 | EQ35: 0 | ER35: 2841.38 | ES35: 2518.94 | ET35: 0 | EU35: 0 | EV35: 322.44 | EW35: 0.56 | EX35: 0 | EY35: 0 | FQ35: 0 | FR35: 0 | FS35: 0 | FX35: 70 | FY35: 10 | GD35: 0 | GF35: 32409756 | GG35: 2 | GH35: 1 | GI35: -2 | GJ35: 0 | GK35: =ROUND(R35*(R12)/100,2) -> 0 | GL35: =ROUND(IF(AND(BH35=3,BI35=3,FS35<>0),P35,0),2) -> 0 | GM35: =ROUND(O35+X35+Y35+GK35,2)+GX35 -> 2553.73 | GN35: =IF(OR(BI35=0,BI35=1),GM35-GX35,0) -> 0 | GO35: =IF(BI35=2,GM35-GX35,0) -> 0 | GP35: =IF(BI35=4,GM35-GX35,0) -> 2553.73 | GR35: 0 | GS35: 3 | GT35: 0 | GV35: =ROUND((GT35),6) -> 0 | GW35: 1 | GX35: =ROUND(HC35*I35,2) -> 0 | HA35: 0 | HB35: 0 | HC35: =GV35*GW35 -> 0 | HS35: 0 | IK35: 0
A36: 17 | B36: 1 | C36: =ROW(SmtRes!A44) -> 44 | D36: =ROW(EtalonRes!A44) -> 44 | E36: 9 | F36: 1.20-3103-4-10/1 | G36: Установка светильников с люминесцентными лампами в подвесных потолках, устанавливаемых на подвесках, с количеством ламп в светильнике до 2 | H36: 100 шт. | I36: =ROUND(30/100,9) -> 0.3 | J36: 0 | K36: =ROUND(30/100,9) -> 0.3 | O36: =ROUND(CP36,2) -> 63834.12 | P36: =ROUND(CQ36*I36,2) -> 10857.01 | Q36: =ROUND(CR36*I36,2) -> 23.98 | R36: =ROUND(CS36*I36,2) -> 0.17 | S36: =ROUND(CT36*I36,2) -> 52953.13 | T36: =ROUND(CU36*I36,2) -> 0 | U36: =CV36*I36 -> 81.3 | V36: =CW36*I36 -> 0 | W36: =ROUND(CX36*I36,2) -> 0 | X36: =ROUND(CY36,2) -> 37067.19 | Y36: =ROUND(CZ36,2) -> 5295.31 | AA36: 35364244 | AB36: =ROUND((AC36+AD36+AF36),6) -> 212780.39 | AC36: =ROUND((ES36),6) -> 36190.04 | AD36: =ROUND((((ET36)-(EU36))+AE36),6) -> 79.92 | AE36: =ROUND((EU36),6) -> 0.55 | AF36: =ROUND((EV36),6) -> 176510.43 | AG36: =ROUND((AP36),6) -> 0 | AH36: =(EW36) -> 271 | AI36: =(EX36) -> 0 | AJ36: =(AS36) -> 0 | AK36: 212780.39 | AL36: 36190.04 | AM36: 79.92 | AN36: 0.55 | AO36: 176510.43 | AP36: 0 | AQ36: 271 | AR36: 0 | AS36: 0 | AT36: 70 | AU36: 10 | AV36: 1 | AW36: 1 | AZ36: 1 | BA36: 1 | BB36: 1 | BC36: 1 | BH36: 0 | BI36: 4 | BJ36: СН-2012.1 Выпуск № 6 (в текущих ценах по состоянию на 01.01.2026 г.). 1.20-3103-4-10/1 | BM36: 0 | BN36: 0 | BP36: 0 | BQ36: 1 | BR36: 0 | BS36: 1 | BT36: 1 | BU36: 1 | BV36: 1 | BW36: 1 | BX36: 1 | BZ36: 70 | CA36: 10 | CE36: 0 | CF36: 0 | CG36: 0 | CM36: 0 | CO36: 0 | CP36: =(P36+Q36+S36) -> 63834.12 | CQ36: =(AC36*BC36*AW36) -> 36190.04 | CR36: =((((ET36)*BB36-(EU36)*BS36)+AE36*BS36)*AV36) -> 79.92 | CS36: =(AE36*BS36*AV36) -> 0.55 | CT36: =(AF36*BA36*AV36) -> 176510.43 | CU36: =AG36 -> 0 | CV36: =(AH36*AV36) -> 271 | CW36: =AI36 -> 0 | CX36: =AJ36 -> 0 | CY36: =((S36*BZ36)/100) -> 37067.191 | CZ36: =((S36*CA36)/100) -> 5295.313 | DN36: 0 | DO36: 0 | DP36: 1 | DQ36: 1 | DU36: 1010 | DV36: 100 шт. | DW36: 100 шт. | DX36: 100 | EE36: 35096056 | EF36: 1 | EG36: СН-2012 | EH36: 0 | EJ36: 4 | EK36: 0 | EL36: Подрядные работы, гл. 1-5,7 | EM36: работа | EQ36: 0 | ER36: 212780.39 | ES36: 36190.04 | ET36: 79.92 | EU36: 0.55 | EV36: 176510.43 | EW36: 271 | EX36: 0 | EY36: 0 | FQ36: 0 | FR36: 0 | FS36: 0 | FX36: 70 | FY36: 10 | GD36: 0 | GF36: -46929286 | GG36: 2 | GH36: 1 | GI36: -2 | GJ36: 0 | GK36: =ROUND(R36*(R12)/100,2) -> 0.18 | GL36: =ROUND(IF(AND(BH36=3,BI36=3,FS36<>0),P36,0),2) -> 0 | GM36: =ROUND(O36+X36+Y36+GK36,2)+GX36 -> 106196.8 | GN36: =IF(OR(BI36=0,BI36=1),GM36-GX36,0) -> 0 | GO36: =IF(BI36=2,GM36-GX36,0) -> 0 | GP36: =IF(BI36=4,GM36-GX36,0) -> 106196.8 | GR36: 0 | GS36: 3 | GT36: 0 | GV36: =ROUND((GT36),6) -> 0 | GW36: 1 | GX36: =ROUND(HC36*I36,2) -> 0 | HA36: 0 | HB36: 0 | HC36: =GV36*GW36 -> 0 | HS36: 0 | IK36: 0
A37: 17 | B37: 1 | C37: =ROW(SmtRes!A45) -> 45 | D37: =ROW(EtalonRes!A45) -> 45 | E37: 10 | F37: 1.21-3703-4-1/1 | G37: Разводка по устройствам и подключение жил кабелей или проводов внешней сети к блокам зажимов и к зажимам аппаратов и приборов, установленных на устройствах, кабели и провода сечение до 10 мм2 (без стоимости материалов) | H37: 100 жил | I37: =ROUND(90/100,9) -> 0.9 | J37: 0 | K37: =ROUND(90/100,9) -> 0.9 | O37: =ROUND(CP37,2) -> 10416.72 | P37: =ROUND(CQ37*I37,2) -> 0 | Q37: =ROUND(CR37*I37,2) -> 0 | R37: =ROUND(CS37*I37,2) -> 0 | S37: =ROUND(CT37*I37,2) -> 10416.72 | T37: =ROUND(CU37*I37,2) -> 0 | U37: =CV37*I37 -> 15.993 | V37: =CW37*I37 -> 0 | W37: =ROUND(CX37*I37,2) -> 0 | X37: =ROUND(CY37,2) -> 7291.7 | Y37: =ROUND(CZ37,2) -> 1041.67 | AA37: 35364244 | AB37: =ROUND((AC37+AD37+AF37),6) -> 11574.13 | AC37: =ROUND((ES37),6) -> 0 | AD37: =ROUND((((ET37)-(EU37))+AE37),6) -> 0 | AE37: =ROUND((EU37),6) -> 0 | AF37: =ROUND((EV37),6) -> 11574.13 | AG37: =ROUND((AP37),6) -> 0 | AH37: =(EW37) -> 17.77 | AI37: =(EX37) -> 0 | AJ37: =(AS37) -> 0 | AK37: 11574.13 | AL37: 0 | AM37: 0 | AN37: 0 | AO37: 11574.13 | AP37: 0 | AQ37: 17.77 | AR37: 0 | AS37: 0 | AT37: 70 | AU37: 10 | AV37: 1 | AW37: 1 | AZ37: 1 | BA37: 1 | BB37: 1 | BC37: 1 | BH37: 0 | BI37: 4 | BJ37: СН-2012.1 Выпуск № 6 (в текущих ценах по состоянию на 01.01.2026 г.). 1.21-3703-4-1/1 | BM37: 0 | BN37: 0 | BP37: 0 | BQ37: 1 | BR37: 0 | BS37: 1 | BT37: 1 | BU37: 1 | BV37: 1 | BW37: 1 | BX37: 1 | BZ37: 70 | CA37: 10 | CE37: 0 | CF37: 0 | CG37: 0 | CM37: 0 | CO37: 0 | CP37: =(P37+Q37+S37) -> 10416.72 | CQ37: =(AC37*BC37*AW37) -> 0 | CR37: =((((ET37)*BB37-(EU37)*BS37)+AE37*BS37)*AV37) -> 0 | CS37: =(AE37*BS37*AV37) -> 0 | CT37: =(AF37*BA37*AV37) -> 11574.13 | CU37: =AG37 -> 0 | CV37: =(AH37*AV37) -> 17.77 | CW37: =AI37 -> 0 | CX37: =AJ37 -> 0 | CY37: =((S37*BZ37)/100) -> 7291.704 | CZ37: =((S37*CA37)/100) -> 1041.672 | DN37: 0 | DO37: 0 | DP37: 1 | DQ37: 1 | DU37: 1013 | DV37: 100 жил | DW37: 100 жил | DX37: 1 | EE37: 35096056 | EF37: 1 | EG37: СН-2012 | EH37: 0 | EJ37: 4 | EK37: 0 | EL37: Подрядные работы, гл. 1-5,7 | EM37: работа | EQ37: 0 | ER37: 11574.13 | ES37: 0 | ET37: 0 | EU37: 0 | EV37: 11574.13 | EW37: 17.77 | EX37: 0 | EY37: 0 | FQ37: 0 | FR37: 0 | FS37: 0 | FX37: 70 | FY37: 10 | GD37: 0 | GF37: 407535083 | GG37: 2 | GH37: 1 | GI37: -2 | GJ37: 0 | GK37: =ROUND(R37*(R12)/100,2) -> 0 | GL37: =ROUND(IF(AND(BH37=3,BI37=3,FS37<>0),P37,0),2) -> 0 | GM37: =ROUND(O37+X37+Y37+GK37,2)+GX37 -> 18750.09 | GN37: =IF(OR(BI37=0,BI37=1),GM37-GX37,0) -> 0 | GO37: =IF(BI37=2,GM37-GX37,0) -> 0 | GP37: =IF(BI37=4,GM37-GX37,0) -> 18750.09 | GR37: 0 | GS37: 3 | GT37: 0 | GV37: =ROUND((GT37),6) -> 0 | GW37: 1 | GX37: =ROUND(HC37*I37,2) -> 0 | HA37: 0 | HB37: 0 | HC37: =GV37*GW37 -> 0 | HS37: 0 | IK37: 0
A39: 51 | B39: =B24 -> 1 | C39: =A24 -> 4 | D39: =ROW(A24) -> 24 | F39: =IF(F24<>"",F24,"") -> Новый раздел | G39: =IF(G24<>"",G24,"") -> Помещение 312 Актовый зал | H39: 0 | O39: =ROUND(AB39,2) -> 336394.13 | P39: =ROUND(AC39,2) -> 177844.64 | Q39: =ROUND(AD39,2) -> 3050.01 | R39: =ROUND(AE39,2) -> 1434.4 | S39: =ROUND(AF39,2) -> 155499.48 | T39: =ROUND(AG39,2) -> 0 | U39: =AH39 -> 258.213 | V39: =AI39 -> 0 | W39: =ROUND(AJ39,2) -> 0 | X39: =ROUND(AK39,2) -> 108849.65 | Y39: =ROUND(AL39,2) -> 15549.95 | AB39: =ROUND(SUMIF(AA28:AA37,"=35364244",O28:O37),2) -> 336394.13 | AC39: =ROUND(SUMIF(AA28:AA37,"=35364244",P28:P37),2) -> 177844.64 | AD39: =ROUND(SUMIF(AA28:AA37,"=35364244",Q28:Q37),2) -> 3050.01 | AE39: =ROUND(SUMIF(AA28:AA37,"=35364244",R28:R37),2) -> 1434.4 | AF39: =ROUND(SUMIF(AA28:AA37,"=35364244",S28:S37),2) -> 155499.48 | AG39: =ROUND(SUMIF(AA28:AA37,"=35364244",T28:T37),2) -> 0 | AH39: =SUMIF(AA28:AA37,"=35364244",U28:U37) -> 258.213 | AI39: =SUMIF(AA28:AA37,"=35364244",V28:V37) -> 0 | AJ39: =ROUND(SUMIF(AA28:AA37,"=35364244",W28:W37),2) -> 0 | AK39: =ROUND(SUMIF(AA28:AA37,"=35364244",X28:X37),2) -> 108849.65 | AL39: =ROUND(SUMIF(AA28:AA37,"=35364244",Y28:Y37),2) -> 15549.95 | AO39: =ROUND(BX39,2) -> 0 | AP39: =ROUND(BY39,2) -> 0 | AQ39: =ROUND(BZ39,2) -> 0 | AR39: =ROUND(CA39,2) -> 462342.88 | AS39: =ROUND(CB39,2) -> 0 | AT39: =ROUND(CC39,2) -> 0 | AU39: =ROUND(CD39,2) -> 462342.88 | AV39: =ROUND(CE39,2) -> 177844.64 | ... BD39: =ROUND(CM39,2) -> 0 | BX39: =ROUND(SUMIF(AA28:AA37,"=35364244",FQ28:FQ37),2) -> 0 | BY39: =ROUND(SUMIF(AA28:AA37,"=35364244",FR28:FR37),2) -> 0 | BZ39: =ROUND(SUMIF(AA28:AA37,"=35364244",GL28:GL37),2) -> 0 | CA39: =ROUND(SUMIF(AA28:AA37,"=35364244",GM28:GM37),2) -> 462342.88 | CB39: =ROUND(SUMIF(AA28:AA37,"=35364244",GN28:GN37),2) -> 0 | CC39: =ROUND(SUMIF(AA28:AA37,"=35364244",GO28:GO37),2) -> 0 | CD39: =ROUND(SUMIF(AA28:AA37,"=35364244",GP28:GP37),2) -> 462342.88 | CE39: =AC39-BX39 -> 177844.64 | CF39: =AC39-BY39 -> 177844.64 | CG39: =BX39-BZ39 -> 0 | CH39: =AC39-BX39-BY39+BZ39 -> 177844.64 | CI39: =BY39-BZ39 -> 0 | CJ39: =ROUND(SUMIF(AA28:AA37,"=35364244",GX28:GX37),2) -> 0 | CK39: =ROUND(SUMIF(AA28:AA37,"=35364244",GY28:GY37),2) -> 0 | CL39: =ROUND(SUMIF(AA28:AA37,"=35364244",GZ28:GZ37),2) -> 0 | CM39: =ROUND(SUMIF(AA28:AA37,"=35364244",HD28:HD37),2) -> 0 | GX39: 0
A41: 50 | B41: 0 | C41: 0 | D41: 1 | E41: 201 | F41: =ROUND(Source!O39,O41) -> 336394.13 | G41: ПЗ | H41: Прямые затраты | K41: 201 | L41: 1 | M41: 3 | O41: 2 | W41: 336394.13 | X41: 1 | Y41: 336394.13
A42: 50 | B42: 0 | C42: 0 | D42: 1 | E42: 202 | F42: =ROUND(Source!P39,O42) -> 177844.64 | G42: СтМатОб | H42: Стоимость материальных ресурсов (всего) | K42: 202 | L42: 2 | M42: 3 | O42: 2 | W42: 177844.64 | X42: 1 | Y42: 177844.64
A43: 50 | B43: 0 | C43: 0 | D43: 1 | E43: 222 | F43: =ROUND(Source!AO39,O43) -> 0 | G43: СтМатОбЗак | H43: Стоимость материалов и оборудования заказчика | K43: 222 | L43: 3 | M43: 3 | O43: 2 | W43: 0 | X43: 1 | Y43: 0
A44: 50 | B44: 0 | C44: 0 | D44: 1 | E44: 225 | F44: =ROUND(Source!AV39,O44) -> 177844.64 | G44: СтМатОбПод | H44: Стоимость материалов и оборудования подрядчика | K44: 225 | L44: 4 | M44: 3 | O44: 2 | W44: 177844.64 | X44: 1 | Y44: 177844.64
A45: 50 | B45: 0 | C45: 0 | D45: 1 | E45: 226 | F45: =ROUND(Source!AW39,O45) -> 177844.64 | G45: СтМат | H45: Стоимость материалов (всего) | K45: 226 | L45: 5 | M45: 3 | O45: 2 | W45: 177844.64 | X45: 1 | Y45: 177844.64
A46: 50 | B46: 0 | C46: 0 | D46: 1 | E46: 227 | F46: =ROUND(Source!AX39,O46) -> 0 | G46: СтМатЗак | H46: Стоимость материалов заказчика | K46: 227 | L46: 6 | M46: 3 | O46: 2 | W46: 0 | X46: 1 | Y46: 0
A47: 50 | B47: 0 | C47: 0 | D47: 1 | E47: 228 | F47: =ROUND(Source!AY39,O47) -> 177844.64 | G47: СтМатПод | H47: Стоимость материалов подрядчика | K47: 228 | L47: 7 | M47: 3 | O47: 2 | W47: 177844.64 | X47: 1 | Y47: 177844.64
A48: 50 | B48: 0 | C48: 0 | D48: 1 | E48: 216 | F48: =ROUND(Source!AP39,O48) -> 0 | G48: Оборуд | H48: Стоимость оборудования (всего) | K48: 216 | L48: 8 | M48: 3 | O48: 2 | W48: 0 | X48: 1 | Y48: 0
A49: 50 | B49: 0 | C49: 0 | D49: 1 | E49: 223 | F49: =ROUND(Source!AQ39,O49) -> 0 | G49: ОборудЗак | H49: Стоимость оборудования заказчика | K49: 223 | L49: 9 | M49: 3 | O49: 2 | W49: 0 | X49: 1 | Y49: 0
A50: 50 | B50: 0 | C50: 0 | D50: 1 | E50: 229 | F50: =ROUND(Source!AZ39,O50) -> 0 | G50: ОборудПод | H50: Стоимость оборудования подрядчика | K50: 229 | L50: 10 | M50: 3 | O50: 2 | W50: 0 | X50: 1 | Y50: 0
A51: 50 | B51: 0 | C51: 0 | D51: 1 | E51: 203 | F51: =ROUND(Source!Q39,O51) -> 3050.01 | G51: ЭММ | H51: Эксплуатация машин | K51: 203 | L51: 11 | M51: 3 | O51: 2 | W51: 3050.01 | X51: 1 | Y51: 3050.01
A52: 50 | B52: 0 | C52: 0 | D52: 1 | E52: 231 | F52: =ROUND(Source!BB39,O52) -> 0 | G52: ЭММсНРиСП | H52: Эксплуатация машин по ТСН-2001.16 | K52: 231 | L52: 12 | M52: 3 | O52: 2 | W52: 0 | X52: 1 | Y52: 0
A53: 50 | B53: 0 | C53: 0 | D53: 1 | E53: 204 | F53: =ROUND(Source!R39,O53) -> 1434.4 | G53: ЗПМ | H53: ЗП машинистов | K53: 204 | L53: 13 | M53: 3 | O53: 2 | W53: 1434.4 | X53: 1 | Y53: 1434.4
A54: 50 | B54: 0 | C54: 0 | D54: 1 | E54: 205 | F54: =ROUND(Source!S39,O54) -> 155499.48 | G54: ОЗП | H54: Основная ЗП рабочих | K54: 205 | L54: 14 | M54: 3 | O54: 2 | W54: 155499.48 | X54: 1 | Y54: 155499.48
A55: 50 | B55: 0 | C55: 0 | D55: 1 | E55: 232 | F55: =ROUND(Source!BC39,O55) -> 0 | G55: ОЗПсНРиСП | H55: Основная ЗП рабочих по ТСН-2001.16 | K55: 232 | L55: 15 | M55: 3 | O55: 2 | W55: 0 | X55: 1 | Y55: 0
A56: 50 | B56: 0 | C56: 0 | D56: 1 | E56: 214 | F56: =ROUND(Source!AS39,O56) -> 0 | G56: Строит | H56: Строительные работы с НР и СП | K56: 214 | L56: 16 | M56: 3 | O56: 2 | W56: 0 | X56: 1 | Y56: 0
A57: 50 | B57: 0 | C57: 0 | D57: 1 | E57: 215 | F57: =ROUND(Source!AT39,O57) -> 0 | G57: Монтаж | H57: Монтажные работы с НР и СП | K57: 215 | L57: 17 | M57: 3 | O57: 2 | W57: 0 | X57: 1 | Y57: 0
A58: 50 | B58: 0 | C58: 0 | D58: 1 | E58: 217 | F58: =ROUND(Source!AU39,O58) -> 462342.88 | G58: Прочие | H58: Прочие работы с НР и СП | K58: 217 | L58: 18 | M58: 3 | O58: 2 | W58: 462342.88 | X58: 1 | Y58: 462342.88
A59: 50 | B59: 0 | C59: 0 | D59: 1 | E59: 230 | F59: =ROUND(Source!BA39,O59) -> 0 | G59: ПрочиеЗатр | H59: Прочие затраты по ТСН-2001.16 | K59: 230 | L59: 19 | M59: 3 | O59: 2 | W59: 0 | X59: 1 | Y59: 0
A60: 50 | B60: 0 | C60: 0 | D60: 1 | E60: 206 | F60: =ROUND(Source!T39,O60) -> 0 | G60: ВозврМат | H60: Возврат материалов | K60: 206 | L60: 20 | M60: 3 | O60: 2 | W60: 0 | X60: 1 | Y60: 0
A61: 50 | B61: 0 | C61: 0 | D61: 1 | E61: 207 | F61: =Source!U39 -> 258.213 | G61: ТрудСтр | H61: Трудозатраты строителей | K61: 207 | L61: 21 | M61: 3 | O61: -1 | W61: 258.213 | X61: 1 | Y61: 258.213
A62: 50 | B62: 0 | C62: 0 | D62: 1 | E62: 208 | F62: =Source!V39 -> 0 | G62: ТрудМаш | H62: Трудозатраты машинистов | K62: 208 | L62: 22 | M62: 3 | O62: -1 | W62: 0 | X62: 1 | Y62: 0
A63: 50 | B63: 0 | C63: 0 | D63: 1 | E63: 209 | F63: =ROUND(Source!W39,O63) -> 0 | G63: ТранспМат | H63: Транспорт материалов | K63: 209 | L63: 23 | M63: 3 | O63: 2 | W63: 0 | X63: 1 | Y63: 0
A64: 50 | B64: 0 | C64: 0 | D64: 1 | E64: 233 | F64: =ROUND(Source!BD39,O64) -> 0 | G64: Перевозка | H64: Перевозка грузов | K64: 233 | L64: 24 | M64: 3 | O64: 2 | W64: 0 | X64: 1 | Y64: 0
A65: 50 | B65: 0 | C65: 0 | D65: 1 | E65: 210 | F65: =ROUND(Source!X39,O65) -> 108849.65 | G65: НР | H65: Накладные расходы | K65: 210 | L65: 25 | M65: 3 | O65: 2 | W65: 108849.65 | X65: 1 | Y65: 108849.65
A66: 50 | B66: 0 | C66: 0 | D66: 1 | E66: 211 | F66: =ROUND(Source!Y39,O66) -> 15549.95 | G66: СмПриб | H66: Сметная прибыль | K66: 211 | L66: 26 | M66: 3 | O66: 2 | W66: 15549.95 | X66: 1 | Y66: 15549.95
A67: 50 | B67: 0 | C67: 0 | D67: 1 | E67: 224 | F67: =ROUND(Source!AR39,O67) -> 462342.88 | G67: Всего | H67: Всего с НР и СП | K67: 224 | L67: 27 | M67: 3 | O67: 2 | W67: 462342.88 | X67: 1 | Y67: 462342.88
A69: 4 | B69: 1 | D69: =ROW(A77) -> 77 | F69: Новый раздел | G69: Электрощит ЩАО (актовый зал) | I69: 0 | K69: 0 | S69: 0 | V69: 0 | BX69: 0 | CJ69: 0
A71: 52 | B71: =B77 -> 1 | C71: =C77 -> 4 | D71: =D77 -> 69 | E71: =E77 -> 0 | F71: =F77 -> Новый раздел | G71: =G77 -> Электрощит ЩАО (актовый зал) | O71: =O77 -> 23319.35 | P71: =P77 -> 0 | Q71: =Q77 -> 1033.5 | R71: =R77 -> 4.84 | S71: =S77 -> 22285.85 | T71: =T77 -> 0 | U71: =U77 -> 35.88 | V71: =V77 -> 0 | ... GX71: =GX77 -> 0
A73: 17 | B73: 1 | C73: =ROW(SmtRes!A50) -> 50 | D73: =ROW(EtalonRes!A50) -> 50 | E73: 11 | F73: 1.21-3603-6-2/1 | G73: Установка выключателя установочного автоматического (автомата) или неавтоматического одно-, двух-, трехполюсного на конструкции на стене или колонне на ток до 100 А (демонтаж) | H73: шт. | I73: 13 | J73: 0 | K73: 13 | O73: =ROUND(CP73,2) -> 3886.56 | P73: =ROUND(CQ73*I73,2) -> 0 | Q73: =ROUND(CR73*I73,2) -> 172.25 | R73: =ROUND(CS73*I73,2) -> 0.81 | S73: =ROUND(CT73*I73,2) -> 3714.31 | T73: =ROUND(CU73*I73,2) -> 0 | U73: =CV73*I73 -> 5.98 | V73: =CW73*I73 -> 0 | W73: =ROUND(CX73*I73,2) -> 0 | X73: =ROUND(CY73,2) -> 2600.02 | Y73: =ROUND(CZ73,2) -> 371.43 | AA73: 35364244 | AB73: =ROUND((AC73+AD73+AF73),6) -> 298.966 | AC73: =ROUND(((ES73*0)),6) -> 0 | AD73: =ROUND(((((ET73*0.2))-((EU73*0.2)))+AE73),6) -> 13.25 | AE73: =ROUND(((EU73*0.2)),6) -> 0.062 | AF73: =ROUND(((EV73*0.2)),6) -> 285.716 | AG73: =ROUND((AP73),6) -> 0 | AH73: =((EW73*0.2)) -> 0.46 | AI73: =((EX73*0.2)) -> 0 | AJ73: =(AS73) -> 0 | AK73: 3700.99 | AL73: 2206.16 | AM73: 66.25 | AN73: 0.31 | AO73: 1428.58 | AP73: 0 | AQ73: 2.3 | AR73: 0 | AS73: 0 | AT73: 70 | AU73: 10 | AV73: 1 | AW73: 1 | AZ73: 1 | BA73: 1 | BB73: 1 | BC73: 1 | BH73: 0 | BI73: 4 | BJ73: СН-2012.1 Выпуск № 6 (в текущих ценах по состоянию на 01.01.2026 г.). 1.21-3603-6-2/1 | BM73: 0 | BN73: 0 | BP73: 0 | BQ73: 1 | BR73: 0 | BS73: 1 | BT73: 1 | BU73: 1 | BV73: 1 | BW73: 1 | BX73: 1 | BZ73: 70 | CA73: 10 | CE73: 0 | CF73: 0 | CG73: 0 | CM73: 0 | CN73: Поправка: СН-2012 О.П. п.22 Наименование: Демонтаж, разборка отдельных бетонных, железобетонных, металлических, деревянных, пластмассовых конструктивных элементов зданий и сооружений, внутренних и наружных инженерных систем и коммуникаций при отсутствии необходимых стоимостных нормативов в сборниках СН-2012 | CO73: 0 | CP73: =(P73+Q73+S73) -> 3886.56 | CQ73: =(AC73*BC73*AW73) -> 0 | CR73: =(((((ET73*0.2))*BB73-((EU73*0.2))*BS73)+AE73*BS73)*AV73) -> 13.25 | CS73: =(AE73*BS73*AV73) -> 0.062 | CT73: =(AF73*BA73*AV73) -> 285.716 | CU73: =AG73 -> 0 | CV73: =(AH73*AV73) -> 0.46 | CW73: =AI73 -> 0 | CX73: =AJ73 -> 0 | CY73: =((S73*BZ73)/100) -> 2600.017 | CZ73: =((S73*CA73)/100) -> 371.431 | DB73: 2 | DD73: *0 | DE73: *0,2 | DF73: *0,2 | DG73: *0,2 | DI73: *0,2 | DJ73: *0,2 | DN73: 0 | DO73: 0 | DP73: 1 | DQ73: 1 | DU73: 1010 | DV73: шт. | DW73: шт. | DX73: 1 | EE73: 35096056 | EF73: 1 | EG73: СН-2012 | EH73: 0 | EJ73: 4 | EK73: 0 | EL73: Подрядные работы, гл. 1-5,7 | EM73: работа | EO73: Поправка: СН-2012 О.П. п.22 | EQ73: 0 | ER73: 3700.99 | ES73: 2206.16 | ET73: 66.25 | EU73: 0.31 | EV73: 1428.58 | EW73: 2.3 | EX73: 0 | EY73: 0 | FQ73: 0 | FR73: 0 | FS73: 0 | FX73: 70 | FY73: 10 | GD73: 0 | GF73: 845110403 | GG73: 2 | GH73: 1 | GI73: -2 | GJ73: 0 | GK73: =ROUND(R73*(R12)/100,2) -> 0.87 | GL73: =ROUND(IF(AND(BH73=3,BI73=3,FS73<>0),P73,0),2) -> 0 | GM73: =ROUND(O73+X73+Y73+GK73,2)+GX73 -> 6858.88 | GN73: =IF(OR(BI73=0,BI73=1),GM73-GX73,0) -> 0 | GO73: =IF(BI73=2,GM73-GX73,0) -> 0 | GP73: =IF(BI73=4,GM73-GX73,0) -> 6858.88 | GR73: 0 | GS73: 3 | GT73: 0 | GV73: =ROUND((GT73),6) -> 0 | GW73: 1 | GX73: =ROUND(HC73*I73,2) -> 0 | HA73: 0 | HB73: 0 | HC73: =GV73*GW73 -> 0 | HS73: 0 | IK73: 0
A74: 17 | B74: 1 | C74: =ROW(SmtRes!A55) -> 55 | D74: =ROW(EtalonRes!A55) -> 55 | E74: 12 | F74: 1.21-3603-6-2/1 | G74: Установка выключателя установочного автоматического (автомата) или неавтоматического одно-, двух-, трехполюсного на конструкции на стене или колонне на ток до 100 А | H74: шт. | I74: 13 | J74: 0 | K74: 13 | O74: =ROUND(CP74,2) -> 48112.87 | P74: =ROUND(CQ74*I74,2) -> 28680.08 | Q74: =ROUND(CR74*I74,2) -> 861.25 | R74: =ROUND(CS74*I74,2) -> 4.03 | S74: =ROUND(CT74*I74,2) -> 18571.54 | T74: =ROUND(CU74*I74,2) -> 0 | U74: =CV74*I74 -> 29.9 | V74: =CW74*I74 -> 0 | W74: =ROUND(CX74*I74,2) -> 0 | X74: =ROUND(CY74,2) -> 13000.08 | Y74: =ROUND(CZ74,2) -> 1857.15 | AA74: 35364244 | AB74: =ROUND((AC74+AD74+AF74),6) -> 3700.99 | AC74: =ROUND((ES74),6) -> 2206.16 | AD74: =ROUND((((ET74)-(EU74))+AE74),6) -> 66.25 | AE74: =ROUND((EU74),6) -> 0.31 | AF74: =ROUND((EV74),6) -> 1428.58 | AG74: =ROUND((AP74),6) -> 0 | AH74: =(EW74) -> 2.3 | AI74: =(EX74) -> 0 | AJ74: =(AS74) -> 0 | AK74: 3700.99 | AL74: 2206.16 | AM74: 66.25 | AN74: 0.31 | AO74: 1428.58 | AP74: 0 | AQ74: 2.3 | AR74: 0 | AS74: 0 | AT74: 70 | AU74: 10 | AV74: 1 | AW74: 1 | AZ74: 1 | BA74: 1 | BB74: 1 | BC74: 1 | BH74: 0 | BI74: 4 | BJ74: СН-2012.1 Выпуск № 6 (в текущих ценах по состоянию на 01.01.2026 г.). 1.21-3603-6-2/1 | BM74: 0 | BN74: 0 | BP74: 0 | BQ74: 1 | BR74: 0 | BS74: 1 | BT74: 1 | BU74: 1 | BV74: 1 | BW74: 1 | BX74: 1 | BZ74: 70 | CA74: 10 | CE74: 0 | CF74: 0 | CG74: 0 | CM74: 0 | CO74: 0 | CP74: =(P74+Q74+S74) -> 48112.87 | CQ74: =(AC74*BC74*AW74) -> 2206.16 | CR74: =((((ET74)*BB74-(EU74)*BS74)+AE74*BS74)*AV74) -> 66.25 | CS74: =(AE74*BS74*AV74) -> 0.31 | CT74: =(AF74*BA74*AV74) -> 1428.58 | CU74: =AG74 -> 0 | CV74: =(AH74*AV74) -> 2.3 | CW74: =AI74 -> 0 | CX74: =AJ74 -> 0 | CY74: =((S74*BZ74)/100) -> 13000.078 | CZ74: =((S74*CA74)/100) -> 1857.154 | DN74: 0 | DO74: 0 | DP74: 1 | DQ74: 1 | DU74: 1010 | DV74: шт. | DW74: шт. | DX74: 1 | EE74: 35096056 | EF74: 1 | EG74: СН-2012 | EH74: 0 | EJ74: 4 | EK74: 0 | EL74: Подрядные работы, гл. 1-5,7 | EM74: работа | EQ74: 0 | ER74: 3700.99 | ES74: 2206.16 | ET74: 66.25 | EU74: 0.31 | EV74: 1428.58 | EW74: 2.3 | EX74: 0 | EY74: 0 | FQ74: 0 | FR74: 0 | FS74: 0 | FX74: 70 | FY74: 10 | GD74: 0 | GF74: -1068314092 | GG74: 2 | GH74: 1 | GI74: -2 | GJ74: 0 | GK74: =ROUND(R74*(R12)/100,2) -> 4.35 | GL74: =ROUND(IF(AND(BH74=3,BI74=3,FS74<>0),P74,0),2) -> 0 | GM74: =ROUND(O74+X74+Y74+GK74,2)+GX74 -> 62974.45 | GN74: =IF(OR(BI74=0,BI74=1),GM74-GX74,0) -> 0 | GO74: =IF(BI74=2,GM74-GX74,0) -> 0 | GP74: =IF(BI74=4,GM74-GX74,0) -> 62974.45 | GR74: 0 | GS74: 3 | GT74: 0 | GV74: =ROUND((GT74),6) -> 0 | GW74: 1 | GX74: =ROUND(HC74*I74,2) -> 0 | HA74: 0 | HB74: 0 | HC74: =GV74*GW74 -> 0 | HS74: 0 | IK74: 0
A75: 18 | B75: 1 | C75: 55 | E75: 12,1 | F75: 21.21-5-19 | G75: Выключатели автоматические, серия "Домовой", трехполюсные, тип ВА 63(С), на ток: 50 А, 63 А | H75: шт. | I75: =I74*J75 -> -13 | J75: -1 | K75: -1 | O75: =ROUND(CP75,2) -> -28680.08 | P75: =ROUND(CQ75*I75,2) -> -28680.08 | Q75: =ROUND(CR75*I75,2) -> 0 | R75: =ROUND(CS75*I75,2) -> 0 | S75: =ROUND(CT75*I75,2) -> 0 | T75: =ROUND(CU75*I75,2) -> 0 | U75: =CV75*I75 -> 0 | V75: =CW75*I75 -> 0 | W75: =ROUND(CX75*I75,2) -> 0 | X75: =ROUND(CY75,2) -> 0 | Y75: =ROUND(CZ75,2) -> 0 | AA75: 35364244 | AB75: =ROUND((AC75+AD75+AF75),6) -> 2206.16 | AC75: =ROUND((ES75),6) -> 2206.16 | AD75: =ROUND((((ET75)-(EU75))+AE75),6) -> 0 | AE75: =ROUND((EU75),6) -> 0 | AF75: =ROUND((EV75),6) -> 0 | AG75: =ROUND((AP75),6) -> 0 | AH75: =(EW75) -> 0 | AI75: =(EX75) -> 0 | AJ75: =(AS75) -> 0 | AK75: 2206.16 | AL75: 2206.16 | AM75: 0 | AN75: 0 | AO75: 0 | AP75: 0 | AQ75: 0 | AR75: 0 | AS75: 0 | AT75: 70 | AU75: 10 | AV75: 1 | AW75: 1 | AZ75: 1 | BA75: 1 | BB75: 1 | BC75: 1 | BH75: 3 | BI75: 4 | BJ75: СН-2012.21 Выпуск № 6 (в текущих ценах по состоянию на 01.01.2026 г.). 21.21-5-19 | BM75: 0 | BN75: 0 | BP75: 0 | BQ75: 1 | BR75: 1 | BS75: 1 | BT75: 1 | BU75: 1 | BV75: 1 | BW75: 1 | BX75: 1 | BZ75: 70 | CA75: 10 | CE75: 0 | CF75: 0 | CG75: 0 | CM75: 0 | CO75: 0 | CP75: =(P75+Q75+S75) -> -28680.08 | CQ75: =(AC75*BC75*AW75) -> 2206.16 | CR75: =((((ET75)*BB75-(EU75)*BS75)+AE75*BS75)*AV75) -> 0 | CS75: =(AE75*BS75*AV75) -> 0 | CT75: =(AF75*BA75*AV75) -> 0 | CU75: =AG75 -> 0 | CV75: =(AH75*AV75) -> 0 | CW75: =AI75 -> 0 | CX75: =AJ75 -> 0 | CY75: =((S75*BZ75)/100) -> 0 | CZ75: =((S75*CA75)/100) -> 0 | DN75: 0 | DO75: 0 | DP75: 1 | DQ75: 1 | DU75: 1010 | DV75: шт. | DW75: шт. | DX75: 1 | EE75: 35096056 | EF75: 1 | EG75: СН-2012 | EH75: 0 | EJ75: 4 | EK75: 0 | EL75: Подрядные работы, гл. 1-5,7 | EM75: работа | EQ75: 0 | ER75: 2206.16 | ES75: 2206.16 | ET75: 0 | EU75: 0 | EV75: 0 | EW75: 0 | EX75: 0 | FQ75: 0 | FR75: 0 | FS75: 0 | FX75: 70 | FY75: 10 | GD75: 0 | GF75: -2080535723 | GG75: 2 | GH75: 1 | GI75: -2 | GJ75: 0 | GK75: =ROUND(R75*(R12)/100,2) -> 0 | GL75: =ROUND(IF(AND(BH75=3,BI75=3,FS75<>0),P75,0),2) -> 0 | GM75: =ROUND(O75+X75+Y75+GK75,2)+GX75 -> -28680.08 | GN75: =IF(OR(BI75=0,BI75=1),GM75-GX75,0) -> 0 | GO75: =IF(BI75=2,GM75-GX75,0) -> 0 | GP75: =IF(BI75=4,GM75-GX75,0) -> -28680.08 | GR75: 0 | GS75: 3 | GT75: 0 | GV75: =ROUND((GT75),6) -> 0 | GW75: 1 | GX75: =ROUND(HC75*I75,2) -> 0 | HA75: 0 | HB75: 0 | HC75: =GV75*GW75 -> 0 | HS75: 0 | IK75: 0
A77: 51 | B77: =B69 -> 1 | C77: =A69 -> 4 | D77: =ROW(A69) -> 69 | F77: =IF(F69<>"",F69,"") -> Новый раздел | G77: =IF(G69<>"",G69,"") -> Электрощит ЩАО (актовый зал) | H77: 0 | O77: =ROUND(AB77,2) -> 23319.35 | P77: =ROUND(AC77,2) -> 0 | Q77: =ROUND(AD77,2) -> 1033.5 | R77: =ROUND(AE77,2) -> 4.84 | S77: =ROUND(AF77,2) -> 22285.85 | T77: =ROUND(AG77,2) -> 0 | U77: =AH77 -> 35.88 | V77: =AI77 -> 0 | W77: =ROUND(AJ77,2) -> 0 | X77: =ROUND(AK77,2) -> 15600.1 | Y77: =ROUND(AL77,2) -> 2228.58 | AB77: =ROUND(SUMIF(AA73:AA75,"=35364244",O73:O75),2) -> 23319.35 | AC77: =ROUND(SUMIF(AA73:AA75,"=35364244",P73:P75),2) -> 0 | AD77: =ROUND(SUMIF(AA73:AA75,"=35364244",Q73:Q75),2) -> 1033.5 | AE77: =ROUND(SUMIF(AA73:AA75,"=35364244",R73:R75),2) -> 4.84 | AF77: =ROUND(SUMIF(AA73:AA75,"=35364244",S73:S75),2) -> 22285.85 | AG77: =ROUND(SUMIF(AA73:AA75,"=35364244",T73:T75),2) -> 0 | AH77: =SUMIF(AA73:AA75,"=35364244",U73:U75) -> 35.88 | AI77: =SUMIF(AA73:AA75,"=35364244",V73:V75) -> 0 | AJ77: =ROUND(SUMIF(AA73:AA75,"=35364244",W73:W75),2) -> 0 | AK77: =ROUND(SUMIF(AA73:AA75,"=35364244",X73:X75),2) -> 15600.1 | AL77: =ROUND(SUMIF(AA73:AA75,"=35364244",Y73:Y75),2) -> 2228.58 | AO77: =ROUND(BX77,2) -> 0 | AP77: =ROUND(BY77,2) -> 0 | AQ77: =ROUND(BZ77,2) -> 0 | AR77: =ROUND(CA77,2) -> 41153.25 | AS77: =ROUND(CB77,2) -> 0 | AT77: =ROUND(CC77,2) -> 0 | AU77: =ROUND(CD77,2) -> 41153.25 | AV77: =ROUND(CE77,2) -> 0 | ... BD77: =ROUND(CM77,2) -> 0 | BX77: =ROUND(SUMIF(AA73:AA75,"=35364244",FQ73:FQ75),2) -> 0 | BY77: =ROUND(SUMIF(AA73:AA75,"=35364244",FR73:FR75),2) -> 0 | BZ77: =ROUND(SUMIF(AA73:AA75,"=35364244",GL73:GL75),2) -> 0 | CA77: =ROUND(SUMIF(AA73:AA75,"=35364244",GM73:GM75),2) -> 41153.25 | CB77: =ROUND(SUMIF(AA73:AA75,"=35364244",GN73:GN75),2) -> 0 | CC77: =ROUND(SUMIF(AA73:AA75,"=35364244",GO73:GO75),2) -> 0 | CD77: =ROUND(SUMIF(AA73:AA75,"=35364244",GP73:GP75),2) -> 41153.25 | CE77: =AC77-BX77 -> 0 | CF77: =AC77-BY77 -> 0 | CG77: =BX77-BZ77 -> 0 | CH77: =AC77-BX77-BY77+BZ77 -> 0 | CI77: =BY77-BZ77 -> 0 | CJ77: =ROUND(SUMIF(AA73:AA75,"=35364244",GX73:GX75),2) -> 0 | CK77: =ROUND(SUMIF(AA73:AA75,"=35364244",GY73:GY75),2) -> 0 | CL77: =ROUND(SUMIF(AA73:AA75,"=35364244",GZ73:GZ75),2) -> 0 | CM77: =ROUND(SUMIF(AA73:AA75,"=35364244",HD73:HD75),2) -> 0 | GX77: 0
A79: 50 | B79: 0 | C79: 0 | D79: 1 | E79: 201 | F79: =ROUND(Source!O77,O79) -> 23319.35 | G79: ПЗ | H79: Прямые затраты | K79: 201 | L79: 1 | M79: 3 | O79: 2 | W79: 23319.35 | X79: 1 | Y79: 23319.35
A80: 50 | B80: 0 | C80: 0 | D80: 1 | E80: 202 | F80: =ROUND(Source!P77,O80) -> 0 | G80: СтМатОб | H80: Стоимость материальных ресурсов (всего) | K80: 202 | L80: 2 | M80: 3 | O80: 2 | W80: 0 | X80: 1 | Y80: 0
A81: 50 | B81: 0 | C81: 0 | D81: 1 | E81: 222 | F81: =ROUND(Source!AO77,O81) -> 0 | G81: СтМатОбЗак | H81: Стоимость материалов и оборудования заказчика | K81: 222 | L81: 3 | M81: 3 | O81: 2 | W81: 0 | X81: 1 | Y81: 0
A82: 50 | B82: 0 | C82: 0 | D82: 1 | E82: 225 | F82: =ROUND(Source!AV77,O82) -> 0 | G82: СтМатОбПод | H82: Стоимость материалов и оборудования подрядчика | K82: 225 | L82: 4 | M82: 3 | O82: 2 | W82: 0 | X82: 1 | Y82: 0
A83: 50 | B83: 0 | C83: 0 | D83: 1 | E83: 226 | F83: =ROUND(Source!AW77,O83) -> 0 | G83: СтМат | H83: Стоимость материалов (всего) | K83: 226 | L83: 5 | M83: 3 | O83: 2 | W83: 0 | X83: 1 | Y83: 0
A84: 50 | B84: 0 | C84: 0 | D84: 1 | E84: 227 | F84: =ROUND(Source!AX77,O84) -> 0 | G84: СтМатЗак | H84: Стоимость материалов заказчика | K84: 227 | L84: 6 | M84: 3 | O84: 2 | W84: 0 | X84: 1 | Y84: 0
A85: 50 | B85: 0 | C85: 0 | D85: 1 | E85: 228 | F85: =ROUND(Source!AY77,O85) -> 0 | G85: СтМатПод | H85: Стоимость материалов подрядчика | K85: 228 | L85: 7 | M85: 3 | O85: 2 | W85: 0 | X85: 1 | Y85: 0
A86: 50 | B86: 0 | C86: 0 | D86: 1 | E86: 216 | F86: =ROUND(Source!AP77,O86) -> 0 | G86: Оборуд | H86: Стоимость оборудования (всего) | K86: 216 | L86: 8 | M86: 3 | O86: 2 | W86: 0 | X86: 1 | Y86: 0
A87: 50 | B87: 0 | C87: 0 | D87: 1 | E87: 223 | F87: =ROUND(Source!AQ77,O87) -> 0 | G87: ОборудЗак | H87: Стоимость оборудования заказчика | K87: 223 | L87: 9 | M87: 3 | O87: 2 | W87: 0 | X87: 1 | Y87: 0
A88: 50 | B88: 0 | C88: 0 | D88: 1 | E88: 229 | F88: =ROUND(Source!AZ77,O88) -> 0 | G88: ОборудПод | H88: Стоимость оборудования подрядчика | K88: 229 | L88: 10 | M88: 3 | O88: 2 | W88: 0 | X88: 1 | Y88: 0
A89: 50 | B89: 0 | C89: 0 | D89: 1 | E89: 203 | F89: =ROUND(Source!Q77,O89) -> 1033.5 | G89: ЭММ | H89: Эксплуатация машин | K89: 203 | L89: 11 | M89: 3 | O89: 2 | W89: 1033.5 | X89: 1 | Y89: 1033.5
A90: 50 | B90: 0 | C90: 0 | D90: 1 | E90: 231 | F90: =ROUND(Source!BB77,O90) -> 0 | G90: ЭММсНРиСП | H90: Эксплуатация машин по ТСН-2001.16 | K90: 231 | L90: 12 | M90: 3 | O90: 2 | W90: 0 | X90: 1 | Y90: 0
A91: 50 | B91: 0 | C91: 0 | D91: 1 | E91: 204 | F91: =ROUND(Source!R77,O91) -> 4.84 | G91: ЗПМ | H91: ЗП машинистов | K91: 204 | L91: 13 | M91: 3 | O91: 2 | W91: 4.84 | X91: 1 | Y91: 4.84
A92: 50 | B92: 0 | C92: 0 | D92: 1 | E92: 205 | F92: =ROUND(Source!S77,O92) -> 22285.85 | G92: ОЗП | H92: Основная ЗП рабочих | K92: 205 | L92: 14 | M92: 3 | O92: 2 | W92: 22285.85 | X92: 1 | Y92: 22285.85
A93: 50 | B93: 0 | C93: 0 | D93: 1 | E93: 232 | F93: =ROUND(Source!BC77,O93) -> 0 | G93: ОЗПсНРиСП | H93: Основная ЗП рабочих по ТСН-2001.16 | K93: 232 | L93: 15 | M93: 3 | O93: 2 | W93: 0 | X93: 1 | Y93: 0
A94: 50 | B94: 0 | C94: 0 | D94: 1 | E94: 214 | F94: =ROUND(Source!AS77,O94) -> 0 | G94: Строит | H94: Строительные работы с НР и СП | K94: 214 | L94: 16 | M94: 3 | O94: 2 | W94: 0 | X94: 1 | Y94: 0
A95: 50 | B95: 0 | C95: 0 | D95: 1 | E95: 215 | F95: =ROUND(Source!AT77,O95) -> 0 | G95: Монтаж | H95: Монтажные работы с НР и СП | K95: 215 | L95: 17 | M95: 3 | O95: 2 | W95: 0 | X95: 1 | Y95: 0
A96: 50 | B96: 0 | C96: 0 | D96: 1 | E96: 217 | F96: =ROUND(Source!AU77,O96) -> 41153.25 | G96: Прочие | H96: Прочие работы с НР и СП | K96: 217 | L96: 18 | M96: 3 | O96: 2 | W96: 41153.25 | X96: 1 | Y96: 41153.25
A97: 50 | B97: 0 | C97: 0 | D97: 1 | E97: 230 | F97: =ROUND(Source!BA77,O97) -> 0 | G97: ПрочиеЗатр | H97: Прочие затраты по ТСН-2001.16 | K97: 230 | L97: 19 | M97: 3 | O97: 2 | W97: 0 | X97: 1 | Y97: 0
A98: 50 | B98: 0 | C98: 0 | D98: 1 | E98: 206 | F98: =ROUND(Source!T77,O98) -> 0 | G98: ВозврМат | H98: Возврат материалов | K98: 206 | L98: 20 | M98: 3 | O98: 2 | W98: 0 | X98: 1 | Y98: 0
A99: 50 | B99: 0 | C99: 0 | D99: 1 | E99: 207 | F99: =Source!U77 -> 35.88 | G99: ТрудСтр | H99: Трудозатраты строителей | K99: 207 | L99: 21 | M99: 3 | O99: -1 | W99: 35.88 | X99: 1 | Y99: 35.88
A100: 50 | B100: 0 | C100: 0 | D100: 1 | E100: 208 | F100: =Source!V77 -> 0 | G100: ТрудМаш | H100: Трудозатраты машинистов | K100: 208 | L100: 22 | M100: 3 | O100: -1 | W100: 0 | X100: 1 | Y100: 0
A101: 50 | B101: 0 | C101: 0 | D101: 1 | E101: 209 | F101: =ROUND(Source!W77,O101) -> 0 | G101: ТранспМат | H101: Транспорт материалов | K101: 209 | L101: 23 | M101: 3 | O101: 2 | W101: 0 | X101: 1 | Y101: 0
A102: 50 | B102: 0 | C102: 0 | D102: 1 | E102: 233 | F102: =ROUND(Source!BD77,O102) -> 0 | G102: Перевозка | H102: Перевозка грузов | K102: 233 | L102: 24 | M102: 3 | O102: 2 | W102: 0 | X102: 1 | Y102: 0
A103: 50 | B103: 0 | C103: 0 | D103: 1 | E103: 210 | F103: =ROUND(Source!X77,O103) -> 15600.1 | G103: НР | H103: Накладные расходы | K103: 210 | L103: 25 | M103: 3 | O103: 2 | W103: 15600.1 | X103: 1 | Y103: 15600.1
A104: 50 | B104: 0 | C104: 0 | D104: 1 | E104: 211 | F104: =ROUND(Source!Y77,O104) -> 2228.58 | G104: СмПриб | H104: Сметная прибыль | K104: 211 | L104: 26 | M104: 3 | O104: 2 | W104: 2228.58 | X104: 1 | Y104: 2228.58
A105: 50 | B105: 0 | C105: 0 | D105: 1 | E105: 224 | F105: =ROUND(Source!AR77,O105) -> 41153.25 | G105: Всего | H105: Всего с НР и СП | K105: 224 | L105: 27 | M105: 3 | O105: 2 | W105: 41153.25 | X105: 1 | Y105: 41153.25
A107: 4 | B107: 1 | D107: =ROW(A115) -> 115 | F107: Новый раздел | G107: Электрощит ЩО (актовый зал) | I107: 0 | K107: 0 | S107: 0 | V107: 0 | BX107: 0 | CJ107: 0
A109: 52 | B109: =B115 -> 1 | C109: =C115 -> 4 | D109: =D115 -> 107 | E109: =E115 -> 0 | F109: =F115 -> Новый раздел | G109: =G115 -> Электрощит ЩО (актовый зал) | O109: =O115 -> 19731.76 | P109: =P115 -> 0 | Q109: =Q115 -> 874.5 | R109: =R115 -> 4.09 | S109: =S115 -> 18857.26 | T109: =T115 -> 0 | U109: =U115 -> 30.36 | V109: =V115 -> 0 | ... GX109: =GX115 -> 0
A111: 17 | B111: 1 | C111: =ROW(SmtRes!A60) -> 60 | D111: =ROW(EtalonRes!A60) -> 60 | E111: 13 | F111: 1.21-3603-6-2/1 | G111: Установка выключателя установочного автоматического (автомата) или неавтоматического одно-, двух-, трехполюсного на конструкции на стене или колонне на ток до 100 А (демонтаж) | H111: шт. | I111: 11 | J111: 0 | K111: 11 | O111: =ROUND(CP111,2) -> 3288.63 | P111: =ROUND(CQ111*I111,2) -> 0 | Q111: =ROUND(CR111*I111,2) -> 145.75 | R111: =ROUND(CS111*I111,2) -> 0.68 | S111: =ROUND(CT111*I111,2) -> 3142.88 | T111: =ROUND(CU111*I111,2) -> 0 | U111: =CV111*I111 -> 5.06 | V111: =CW111*I111 -> 0 | W111: =ROUND(CX111*I111,2) -> 0 | X111: =ROUND(CY111,2) -> 2200.02 | Y111: =ROUND(CZ111,2) -> 314.29 | AA111: 35364244 | AB111: =ROUND((AC111+AD111+AF111),6) -> 298.966 | AC111: =ROUND(((ES111*0)),6) -> 0 | AD111: =ROUND(((((ET111*0.2))-((EU111*0.2)))+AE111),6) -> 13.25 | AE111: =ROUND(((EU111*0.2)),6) -> 0.062 | AF111: =ROUND(((EV111*0.2)),6) -> 285.716 | AG111: =ROUND((AP111),6) -> 0 | AH111: =((EW111*0.2)) -> 0.46 | AI111: =((EX111*0.2)) -> 0 | AJ111: =(AS111) -> 0 | AK111: 3700.99 | AL111: 2206.16 | AM111: 66.25 | AN111: 0.31 | AO111: 1428.58 | AP111: 0 | AQ111: 2.3 | AR111: 0 | AS111: 0 | AT111: 70 | AU111: 10 | AV111: 1 | AW111: 1 | AZ111: 1 | BA111: 1 | BB111: 1 | BC111: 1 | BH111: 0 | BI111: 4 | BJ111: СН-2012.1 Выпуск № 6 (в текущих ценах по состоянию на 01.01.2026 г.). 1.21-3603-6-2/1 | BM111: 0 | BN111: 0 | BP111: 0 | BQ111: 1 | BR111: 0 | BS111: 1 | BT111: 1 | BU111: 1 | BV111: 1 | BW111: 1 | BX111: 1 | BZ111: 70 | CA111: 10 | CE111: 0 | CF111: 0 | CG111: 0 | CM111: 0 | CN111: Поправка: СН-2012 О.П. п.22 Наименование: Демонтаж, разборка отдельных бетонных, железобетонных, металлических, деревянных, пластмассовых конструктивных элементов зданий и сооружений, внутренних и наружных инженерных систем и коммуникаций при отсутствии необходимых стоимостных нормативов в сборниках СН-2012 | CO111: 0 | CP111: =(P111+Q111+S111) -> 3288.63 | CQ111: =(AC111*BC111*AW111) -> 0 | CR111: =(((((ET111*0.2))*BB111-((EU111*0.2))*BS111)+AE111*BS111)*AV111) -> 13.25 | CS111: =(AE111*BS111*AV111) -> 0.062 | CT111: =(AF111*BA111*AV111) -> 285.716 | CU111: =AG111 -> 0 | CV111: =(AH111*AV111) -> 0.46 | CW111: =AI111 -> 0 | CX111: =AJ111 -> 0 | CY111: =((S111*BZ111)/100) -> 2200.016 | CZ111: =((S111*CA111)/100) -> 314.288 | DB111: 3 | DD111: *0 | DE111: *0,2 | DF111: *0,2 | DG111: *0,2 | DI111: *0,2 | DJ111: *0,2 | DN111: 0 | DO111: 0 | DP111: 1 | DQ111: 1 | DU111: 1010 | DV111: шт. | DW111: шт. | DX111: 1 | EE111: 35096056 | EF111: 1 | EG111: СН-2012 | EH111: 0 | EJ111: 4 | EK111: 0 | EL111: Подрядные работы, гл. 1-5,7 | EM111: работа | EO111: Поправка: СН-2012 О.П. п.22 | EQ111: 0 | ER111: 3700.99 | ES111: 2206.16 | ET111: 66.25 | EU111: 0.31 | EV111: 1428.58 | EW111: 2.3 | EX111: 0 | EY111: 0 | FQ111: 0 | FR111: 0 | FS111: 0 | FX111: 70 | FY111: 10 | GD111: 0 | GF111: 845110403 | GG111: 2 | GH111: 1 | GI111: -2 | GJ111: 0 | GK111: =ROUND(R111*(R12)/100,2) -> 0.73 | GL111: =ROUND(IF(AND(BH111=3,BI111=3,FS111<>0),P111,0),2) -> 0 | GM111: =ROUND(O111+X111+Y111+GK111,2)+GX111 -> 5803.67 | GN111: =IF(OR(BI111=0,BI111=1),GM111-GX111,0) -> 0 | GO111: =IF(BI111=2,GM111-GX111,0) -> 0 | GP111: =IF(BI111=4,GM111-GX111,0) -> 5803.67 | GR111: 0 | GS111: 3 | GT111: 0 | GV111: =ROUND((GT111),6) -> 0 | GW111: 1 | GX111: =ROUND(HC111*I111,2) -> 0 | HA111: 0 | HB111: 0 | HC111: =GV111*GW111 -> 0 | HS111: 0 | IK111: 0
A112: 17 | B112: 1 | C112: =ROW(SmtRes!A65) -> 65 | D112: =ROW(EtalonRes!A65) -> 65 | E112: 14 | F112: 1.21-3603-6-2/1 | G112: Установка выключателя установочного автоматического (автомата) или неавтоматического одно-, двух-, трехполюсного на конструкции на стене или колонне на ток до 100 А | H112: шт. | I112: 11 | J112: 0 | K112: 11 | O112: =ROUND(CP112,2) -> 40710.89 | P112: =ROUND(CQ112*I112,2) -> 24267.76 | Q112: =ROUND(CR112*I112,2) -> 728.75 | R112: =ROUND(CS112*I112,2) -> 3.41 | S112: =ROUND(CT112*I112,2) -> 15714.38 | T112: =ROUND(CU112*I112,2) -> 0 | U112: =CV112*I112 -> 25.3 | V112: =CW112*I112 -> 0 | W112: =ROUND(CX112*I112,2) -> 0 | X112: =ROUND(CY112,2) -> 11000.07 | Y112: =ROUND(CZ112,2) -> 1571.44 | AA112: 35364244 | AB112: =ROUND((AC112+AD112+AF112),6) -> 3700.99 | AC112: =ROUND((ES112),6) -> 2206.16 | AD112: =ROUND((((ET112)-(EU112))+AE112),6) -> 66.25 | AE112: =ROUND((EU112),6) -> 0.31 | AF112: =ROUND((EV112),6) -> 1428.58 | AG112: =ROUND((AP112),6) -> 0 | AH112: =(EW112) -> 2.3 | AI112: =(EX112) -> 0 | AJ112: =(AS112) -> 0 | AK112: 3700.99 | AL112: 2206.16 | AM112: 66.25 | AN112: 0.31 | AO112: 1428.58 | AP112: 0 | AQ112: 2.3 | AR112: 0 | AS112: 0 | AT112: 70 | AU112: 10 | AV112: 1 | AW112: 1 | AZ112: 1 | BA112: 1 | BB112: 1 | BC112: 1 | BH112: 0 | BI112: 4 | BJ112: СН-2012.1 Выпуск № 6 (в текущих ценах по состоянию на 01.01.2026 г.). 1.21-3603-6-2/1 | BM112: 0 | BN112: 0 | BP112: 0 | BQ112: 1 | BR112: 0 | BS112: 1 | BT112: 1 | BU112: 1 | BV112: 1 | BW112: 1 | BX112: 1 | BZ112: 70 | CA112: 10 | CE112: 0 | CF112: 0 | CG112: 0 | CM112: 0 | CO112: 0 | CP112: =(P112+Q112+S112) -> 40710.89 | CQ112: =(AC112*BC112*AW112) -> 2206.16 | CR112: =((((ET112)*BB112-(EU112)*BS112)+AE112*BS112)*AV112) -> 66.25 | CS112: =(AE112*BS112*AV112) -> 0.31 | CT112: =(AF112*BA112*AV112) -> 1428.58 | CU112: =AG112 -> 0 | CV112: =(AH112*AV112) -> 2.3 | CW112: =AI112 -> 0 | CX112: =AJ112 -> 0 | CY112: =((S112*BZ112)/100) -> 11000.066 | CZ112: =((S112*CA112)/100) -> 1571.438 | DN112: 0 | DO112: 0 | DP112: 1 | DQ112: 1 | DU112: 1010 | DV112: шт. | DW112: шт. | DX112: 1 | EE112: 35096056 | EF112: 1 | EG112: СН-2012 | EH112: 0 | EJ112: 4 | EK112: 0 | EL112: Подрядные работы, гл. 1-5,7 | EM112: работа | EQ112: 0 | ER112: 3700.99 | ES112: 2206.16 | ET112: 66.25 | EU112: 0.31 | EV112: 1428.58 | EW112: 2.3 | EX112: 0 | EY112: 0 | FQ112: 0 | FR112: 0 | FS112: 0 | FX112: 70 | FY112: 10 | GD112: 0 | GF112: -1068314092 | GG112: 2 | GH112: 1 | GI112: -2 | GJ112: 0 | GK112: =ROUND(R112*(R12)/100,2) -> 3.68 | GL112: =ROUND(IF(AND(BH112=3,BI112=3,FS112<>0),P112,0),2) -> 0 | GM112: =ROUND(O112+X112+Y112+GK112,2)+GX112 -> 53286.08 | GN112: =IF(OR(BI112=0,BI112=1),GM112-GX112,0) -> 0 | GO112: =IF(BI112=2,GM112-GX112,0) -> 0 | GP112: =IF(BI112=4,GM112-GX112,0) -> 53286.08 | GR112: 0 | GS112: 3 | GT112: 0 | GV112: =ROUND((GT112),6) -> 0 | GW112: 1 | GX112: =ROUND(HC112*I112,2) -> 0 | HA112: 0 | HB112: 0 | HC112: =GV112*GW112 -> 0 | HS112: 0 | IK112: 0
A113: 18 | B113: 1 | C113: 65 | E113: 14,1 | F113: 21.21-5-19 | G113: Выключатели автоматические, серия "Домовой", трехполюсные, тип ВА 63(С), на ток: 50 А, 63 А | H113: шт. | I113: =I112*J113 -> -11 | J113: -1 | K113: -1 | O113: =ROUND(CP113,2) -> -24267.76 | P113: =ROUND(CQ113*I113,2) -> -24267.76 | Q113: =ROUND(CR113*I113,2) -> 0 | R113: =ROUND(CS113*I113,2) -> 0 | S113: =ROUND(CT113*I113,2) -> 0 | T113: =ROUND(CU113*I113,2) -> 0 | U113: =CV113*I113 -> 0 | V113: =CW113*I113 -> 0 | W113: =ROUND(CX113*I113,2) -> 0 | X113: =ROUND(CY113,2) -> 0 | Y113: =ROUND(CZ113,2) -> 0 | AA113: 35364244 | AB113: =ROUND((AC113+AD113+AF113),6) -> 2206.16 | AC113: =ROUND((ES113),6) -> 2206.16 | AD113: =ROUND((((ET113)-(EU113))+AE113),6) -> 0 | AE113: =ROUND((EU113),6) -> 0 | AF113: =ROUND((EV113),6) -> 0 | AG113: =ROUND((AP113),6) -> 0 | AH113: =(EW113) -> 0 | AI113: =(EX113) -> 0 | AJ113: =(AS113) -> 0 | AK113: 2206.16 | AL113: 2206.16 | AM113: 0 | AN113: 0 | AO113: 0 | AP113: 0 | AQ113: 0 | AR113: 0 | AS113: 0 | AT113: 70 | AU113: 10 | AV113: 1 | AW113: 1 | AZ113: 1 | BA113: 1 | BB113: 1 | BC113: 1 | BH113: 3 | BI113: 4 | BJ113: СН-2012.21 Выпуск № 6 (в текущих ценах по состоянию на 01.01.2026 г.). 21.21-5-19 | BM113: 0 | BN113: 0 | BP113: 0 | BQ113: 1 | BR113: 1 | BS113: 1 | BT113: 1 | BU113: 1 | BV113: 1 | BW113: 1 | BX113: 1 | BZ113: 70 | CA113: 10 | CE113: 0 | CF113: 0 | CG113: 0 | CM113: 0 | CO113: 0 | CP113: =(P113+Q113+S113) -> -24267.76 | CQ113: =(AC113*BC113*AW113) -> 2206.16 | CR113: =((((ET113)*BB113-(EU113)*BS113)+AE113*BS113)*AV113) -> 0 | CS113: =(AE113*BS113*AV113) -> 0 | CT113: =(AF113*BA113*AV113) -> 0 | CU113: =AG113 -> 0 | CV113: =(AH113*AV113) -> 0 | CW113: =AI113 -> 0 | CX113: =AJ113 -> 0 | CY113: =((S113*BZ113)/100) -> 0 | CZ113: =((S113*CA113)/100) -> 0 | DN113: 0 | DO113: 0 | DP113: 1 | DQ113: 1 | DU113: 1010 | DV113: шт. | DW113: шт. | DX113: 1 | EE113: 35096056 | EF113: 1 | EG113: СН-2012 | EH113: 0 | EJ113: 4 | EK113: 0 | EL113: Подрядные работы, гл. 1-5,7 | EM113: работа | EQ113: 0 | ER113: 2206.16 | ES113: 2206.16 | ET113: 0 | EU113: 0 | EV113: 0 | EW113: 0 | EX113: 0 | FQ113: 0 | FR113: 0 | FS113: 0 | FX113: 70 | FY113: 10 | GD113: 0 | GF113: -2080535723 | GG113: 2 | GH113: 1 | GI113: -2 | GJ113: 0 | GK113: =ROUND(R113*(R12)/100,2) -> 0 | GL113: =ROUND(IF(AND(BH113=3,BI113=3,FS113<>0),P113,0),2) -> 0 | GM113: =ROUND(O113+X113+Y113+GK113,2)+GX113 -> -24267.76 | GN113: =IF(OR(BI113=0,BI113=1),GM113-GX113,0) -> 0 | GO113: =IF(BI113=2,GM113-GX113,0) -> 0 | GP113: =IF(BI113=4,GM113-GX113,0) -> -24267.76 | GR113: 0 | GS113: 3 | GT113: 0 | GV113: =ROUND((GT113),6) -> 0 | GW113: 1 | GX113: =ROUND(HC113*I113,2) -> 0 | HA113: 0 | HB113: 0 | HC113: =GV113*GW113 -> 0 | HS113: 0 | IK113: 0
A115: 51 | B115: =B107 -> 1 | C115: =A107 -> 4 | D115: =ROW(A107) -> 107 | F115: =IF(F107<>"",F107,"") -> Новый раздел | G115: =IF(G107<>"",G107,"") -> Электрощит ЩО (актовый зал) | H115: 0 | O115: =ROUND(AB115,2) -> 19731.76 | P115: =ROUND(AC115,2) -> 0 | Q115: =ROUND(AD115,2) -> 874.5 | R115: =ROUND(AE115,2) -> 4.09 | S115: =ROUND(AF115,2) -> 18857.26 | T115: =ROUND(AG115,2) -> 0 | U115: =AH115 -> 30.36 | V115: =AI115 -> 0 | W115: =ROUND(AJ115,2) -> 0 | X115: =ROUND(AK115,2) -> 13200.09 | Y115: =ROUND(AL115,2) -> 1885.73 | AB115: =ROUND(SUMIF(AA111:AA113,"=35364244",O111:O113),2) -> 19731.76 | AC115: =ROUND(SUMIF(AA111:AA113,"=35364244",P111:P113),2) -> 0 | AD115: =ROUND(SUMIF(AA111:AA113,"=35364244",Q111:Q113),2) -> 874.5 | AE115: =ROUND(SUMIF(AA111:AA113,"=35364244",R111:R113),2) -> 4.09 | AF115: =ROUND(SUMIF(AA111:AA113,"=35364244",S111:S113),2) -> 18857.26 | AG115: =ROUND(SUMIF(AA111:AA113,"=35364244",T111:T113),2) -> 0 | AH115: =SUMIF(AA111:AA113,"=35364244",U111:U113) -> 30.36 | AI115: =SUMIF(AA111:AA113,"=35364244",V111:V113) -> 0 | AJ115: =ROUND(SUMIF(AA111:AA113,"=35364244",W111:W113),2) -> 0 | AK115: =ROUND(SUMIF(AA111:AA113,"=35364244",X111:X113),2) -> 13200.09 | AL115: =ROUND(SUMIF(AA111:AA113,"=35364244",Y111:Y113),2) -> 1885.73 | AO115: =ROUND(BX115,2) -> 0 | AP115: =ROUND(BY115,2) -> 0 | AQ115: =ROUND(BZ115,2) -> 0 | AR115: =ROUND(CA115,2) -> 34821.99 | AS115: =ROUND(CB115,2) -> 0 | AT115: =ROUND(CC115,2) -> 0 | AU115: =ROUND(CD115,2) -> 34821.99 | AV115: =ROUND(CE115,2) -> 0 | ... BD115: =ROUND(CM115,2) -> 0 | BX115: =ROUND(SUMIF(AA111:AA113,"=35364244",FQ111:FQ113),2) -> 0 | BY115: =ROUND(SUMIF(AA111:AA113,"=35364244",FR111:FR113),2) -> 0 | BZ115: =ROUND(SUMIF(AA111:AA113,"=35364244",GL111:GL113),2) -> 0 | CA115: =ROUND(SUMIF(AA111:AA113,"=35364244",GM111:GM113),2) -> 34821.99 | CB115: =ROUND(SUMIF(AA111:AA113,"=35364244",GN111:GN113),2) -> 0 | CC115: =ROUND(SUMIF(AA111:AA113,"=35364244",GO111:GO113),2) -> 0 | CD115: =ROUND(SUMIF(AA111:AA113,"=35364244",GP111:GP113),2) -> 34821.99 | CE115: =AC115-BX115 -> 0 | CF115: =AC115-BY115 -> 0 | CG115: =BX115-BZ115 -> 0 | CH115: =AC115-BX115-BY115+BZ115 -> 0 | CI115: =BY115-BZ115 -> 0 | CJ115: =ROUND(SUMIF(AA111:AA113,"=35364244",GX111:GX113),2) -> 0 | CK115: =ROUND(SUMIF(AA111:AA113,"=35364244",GY111:GY113),2) -> 0 | CL115: =ROUND(SUMIF(AA111:AA113,"=35364244",GZ111:GZ113),2) -> 0 | CM115: =ROUND(SUMIF(AA111:AA113,"=35364244",HD111:HD113),2) -> 0 | GX115: 0
A117: 50 | B117: 0 | C117: 0 | D117: 1 | E117: 201 | F117: =ROUND(Source!O115,O117) -> 19731.76 | G117: ПЗ | H117: Прямые затраты | K117: 201 | L117: 1 | M117: 3 | O117: 2 | W117: 19731.76 | X117: 1 | Y117: 19731.76
A118: 50 | B118: 0 | C118: 0 | D118: 1 | E118: 202 | F118: =ROUND(Source!P115,O118) -> 0 | G118: СтМатОб | H118: Стоимость материальных ресурсов (всего) | K118: 202 | L118: 2 | M118: 3 | O118: 2 | W118: 0 | X118: 1 | Y118: 0
A119: 50 | B119: 0 | C119: 0 | D119: 1 | E119: 222 | F119: =ROUND(Source!AO115,O119) -> 0 | G119: СтМатОбЗак | H119: Стоимость материалов и оборудования заказчика | K119: 222 | L119: 3 | M119: 3 | O119: 2 | W119: 0 | X119: 1 | Y119: 0
A120: 50 | B120: 0 | C120: 0 | D120: 1 | E120: 225 | F120: =ROUND(Source!AV115,O120) -> 0 | G120: СтМатОбПод | H120: Стоимость материалов и оборудования подрядчика | K120: 225 | L120: 4 | M120: 3 | O120: 2 | W120: 0 | X120: 1 | Y120: 0
A121: 50 | B121: 0 | C121: 0 | D121: 1 | E121: 226 | F121: =ROUND(Source!AW115,O121) -> 0 | G121: СтМат | H121: Стоимость материалов (всего) | K121: 226 | L121: 5 | M121: 3 | O121: 2 | W121: 0 | X121: 1 | Y121: 0
A122: 50 | B122: 0 | C122: 0 | D122: 1 | E122: 227 | F122: =ROUND(Source!AX115,O122) -> 0 | G122: СтМатЗак | H122: Стоимость материалов заказчика | K122: 227 | L122: 6 | M122: 3 | O122: 2 | W122: 0 | X122: 1 | Y122: 0
A123: 50 | B123: 0 | C123: 0 | D123: 1 | E123: 228 | F123: =ROUND(Source!AY115,O123) -> 0 | G123: СтМатПод | H123: Стоимость материалов подрядчика | K123: 228 | L123: 7 | M123: 3 | O123: 2 | W123: 0 | X123: 1 | Y123: 0
A124: 50 | B124: 0 | C124: 0 | D124: 1 | E124: 216 | F124: =ROUND(Source!AP115,O124) -> 0 | G124: Оборуд | H124: Стоимость оборудования (всего) | K124: 216 | L124: 8 | M124: 3 | O124: 2 | W124: 0 | X124: 1 | Y124: 0
A125: 50 | B125: 0 | C125: 0 | D125: 1 | E125: 223 | F125: =ROUND(Source!AQ115,O125) -> 0 | G125: ОборудЗак | H125: Стоимость оборудования заказчика | K125: 223 | L125: 9 | M125: 3 | O125: 2 | W125: 0 | X125: 1 | Y125: 0
A126: 50 | B126: 0 | C126: 0 | D126: 1 | E126: 229 | F126: =ROUND(Source!AZ115,O126) -> 0 | G126: ОборудПод | H126: Стоимость оборудования подрядчика | K126: 229 | L126: 10 | M126: 3 | O126: 2 | W126: 0 | X126: 1 | Y126: 0
A127: 50 | B127: 0 | C127: 0 | D127: 1 | E127: 203 | F127: =ROUND(Source!Q115,O127) -> 874.5 | G127: ЭММ | H127: Эксплуатация машин | K127: 203 | L127: 11 | M127: 3 | O127: 2 | W127: 874.5 | X127: 1 | Y127: 874.5
A128: 50 | B128: 0 | C128: 0 | D128: 1 | E128: 231 | F128: =ROUND(Source!BB115,O128) -> 0 | G128: ЭММсНРиСП | H128: Эксплуатация машин по ТСН-2001.16 | K128: 231 | L128: 12 | M128: 3 | O128: 2 | W128: 0 | X128: 1 | Y128: 0
A129: 50 | B129: 0 | C129: 0 | D129: 1 | E129: 204 | F129: =ROUND(Source!R115,O129) -> 4.09 | G129: ЗПМ | H129: ЗП машинистов | K129: 204 | L129: 13 | M129: 3 | O129: 2 | W129: 4.09 | X129: 1 | Y129: 4.09
A130: 50 | B130: 0 | C130: 0 | D130: 1 | E130: 205 | F130: =ROUND(Source!S115,O130) -> 18857.26 | G130: ОЗП | H130: Основная ЗП рабочих | K130: 205 | L130: 14 | M130: 3 | O130: 2 | W130: 18857.26 | X130: 1 | Y130: 18857.26
A131: 50 | B131: 0 | C131: 0 | D131: 1 | E131: 232 | F131: =ROUND(Source!BC115,O131) -> 0 | G131: ОЗПсНРиСП | H131: Основная ЗП рабочих по ТСН-2001.16 | K131: 232 | L131: 15 | M131: 3 | O131: 2 | W131: 0 | X131: 1 | Y131: 0
...

Sheet SourceObSm
A1: 0 | B1: Smeta.RU (495) 974-1589 | D1: _OBSM_ | F1: 0 | G1: 0 | H1: 0 | I1: Smeta.RU | K1: 1 | L1: 54800 | M1: 10 | N1: 11 | O1: 15 | P1: 0 | Q1: 2
A12: 1 | B12: 54 | C12: 0 | E12: 0 | F12: Новый объект | G12: Электрика новая | I12: 0 | K12: 0 | L12: 0 | M12: 2 | O12: 0 | P12: 0 | Q12: 0 | R12: 108 | T12: 1 | V12: 0 | BB12: 0 | BH12: Сметные нормы списания | BI12: Коды ОКП для СН-2012 Выпуск № 6 (в ценах на 01.01.2026 г) | BJ12: 1 | BK12: 1 | BL12: 0 | BM12: 0 | BN12: 1 | BO12: 0 | BP12: 6 | BQ12: 2 | BR12: 1 | BS12: 1 | BT12: 0 | BU12: 0 | BV12: 1 | BW12: 0 | BX12: 0 | BY12: СН-2012 Выпуск № 6. (в ценах на 01.01.2026) глава_1-5, 7 | BZ12: Типовой расчет для СН-2012 Выпуск №6 (в ценах на 01.01.2026 г) | CA12: СН-2012 Выпуск № 6. База данных "Сборник стоимостных нормативов" в текущих ценах по состоянию на 01.01.2026 года | CB12: СН-2012 Выпуск № 6. База данных "Сборник стоимостных нормативов" в текущих ценах по состоянию на 01.01.2026 года | CC12: СН-2012 Выпуск № 6. База данных "Сборник стоимостных нормативов" в текущих ценах по состоянию на 01.01.2026 года | CD12: СН-2012 Выпуск № 6. База данных "Сборник стоимостных нормативов" в текущих ценах по состоянию на 01.01.2026 года | CE12: Поправки для СН-2012 Выпуск № 6 в ценах на 01.01.2026 г от 12.01.2026 | CF12: 0 | CG12: 0 | CH12: 2097160 | CK12: 0 | CY12: 0 | EC12: 0
A14: 22 | B14: 1 | C14: 0 | D14: 35364244 | E14: 0 | F14: 2 | G14: 1
A16: 3 | B16: 1 | C16: Новая локальная смета | D16: Новая локальная смета | E16: =ROUND((Source!F3904)/1000,2) -> 2489.84 | F16: =ROUND((Source!F3905)/1000,2) -> 0 | G16: =ROUND((Source!F3896)/1000,2) -> 0 | H16: =ROUND((Source!F3906)/1000+(Source!F3907)/1000,2) -> 7868.48 | I16: =E16+F16+G16+H16 -> 10358.32 | J16: =ROUND((Source!F3902+Source!F3901)/1000,2) -> 3759.69 | K16: 10903.66 | L16: 0 | M16: 0 | N16: =I16+L16+M16 -> 10358.32 | AI16: 0 | AJ16: 0 | AN16: 0 | AT16: 7348913 | AU16: 3554749.7 | AV16: 0 | AW16: 0 | AX16: 0 | AY16: 40402.55 | AZ16: 5925.72 | BA16: 3753760.7 | BB16: 2489841.4 | BC16: 0 | BD16: 7868480.2 | BE16: 0 | BF16: 5228.5613 | BG16: 0 | BH16: 0 | BI16: 2627632.9 | BJ16: 375376.51 | BK16: 10358322
A18: 51 | E18: 2489.84 | F18: 0 | G18: 0 | H18: 7868.48 | I18: 10358.32 | J18: 3759.69 | K18: 10903.66 | L18: 0 | M18: 0 | N18: 10358.32
A20: 50 | B20: 0 | C20: 0 | D20: 1 | E20: 201 | F20: 7348913 | G20: ПЗ | H20: Прямые затраты | K20: 201 | L20: 1 | M20: 3 | O20: 2
A21: 50 | B21: 0 | C21: 0 | D21: 1 | E21: 202 | F21: 3554749.7 | G21: СтМатОб | H21: Стоимость материальных ресурсов (всего) | K21: 202 | L21: 2 | M21: 3 | O21: 2
A22: 50 | B22: 0 | C22: 0 | D22: 1 | E22: 222 | F22: 0 | G22: СтМатОбЗак | H22: Стоимость материалов и оборудования заказчика | K22: 222 | L22: 3 | M22: 3 | O22: 2
A23: 50 | B23: 0 | C23: 0 | D23: 1 | E23: 225 | F23: 3554749.7 | G23: СтМатОбПод | H23: Стоимость материалов и оборудования подрядчика | K23: 225 | L23: 4 | M23: 3 | O23: 2
A24: 50 | B24: 0 | C24: 0 | D24: 1 | E24: 226 | F24: 3554749.7 | G24: СтМат | H24: Стоимость материалов (всего) | K24: 226 | L24: 5 | M24: 3 | O24: 2
A25: 50 | B25: 0 | C25: 0 | D25: 1 | E25: 227 | F25: 0 | G25: СтМатЗак | H25: Стоимость материалов заказчика | K25: 227 | L25: 6 | M25: 3 | O25: 2
A26: 50 | B26: 0 | C26: 0 | D26: 1 | E26: 228 | F26: 3554749.7 | G26: СтМатПод | H26: Стоимость материалов подрядчика | K26: 228 | L26: 7 | M26: 3 | O26: 2
A27: 50 | B27: 0 | C27: 0 | D27: 1 | E27: 216 | F27: 0 | G27: Оборуд | H27: Стоимость оборудования (всего) | K27: 216 | L27: 8 | M27: 3 | O27: 2
A28: 50 | B28: 0 | C28: 0 | D28: 1 | E28: 223 | F28: 0 | G28: ОборудЗак | H28: Стоимость оборудования заказчика | K28: 223 | L28: 9 | M28: 3 | O28: 2
A29: 50 | B29: 0 | C29: 0 | D29: 1 | E29: 229 | F29: 0 | G29: ОборудПод | H29: Стоимость оборудования подрядчика | K29: 229 | L29: 10 | M29: 3 | O29: 2
A30: 50 | B30: 0 | C30: 0 | D30: 1 | E30: 203 | F30: 40402.55 | G30: ЭММ | H30: Эксплуатация машин | K30: 203 | L30: 11 | M30: 3 | O30: 2
A31: 50 | B31: 0 | C31: 0 | D31: 1 | E31: 231 | F31: 0 | G31: ЭММсНРиСП | H31: Эксплуатация машин по ТСН-2001.16 | K31: 231 | L31: 12 | M31: 3 | O31: 2
... A49: 50 | B49: 1 | C49: 0 | D49: 2 | E49: 213 | F49: 12637152 | G49: и3 | H49: Всего | K49: 212 | L49: 30 | M49: 0 | O49: 2
A51: -1
A54: 75 | B54: Уровень цен | C54: 2026 | D54: 0 | E54: 1 | F54: 0 | G54: 0 | H54: 1 | I54: 0 | J54: 1 | K54: 78 | L54: 30 | M54: 0 | N54: 35364244 | O54: 1

Sheet SmtRes
A1: =ROW(Source!A28) -> 28 | B1: 35364244 | C1: 35364428 | D1: 35111398 | E1: 15872964 | F1: 1 | G1: 15872964 | H1: 1 | I1: 9999990008 | K1: Трудозатраты рабочих | L1: 1191 | N1: 1013 | O1: чел.-ч. | P1: чел.-ч. | Q1: 1 | W1: 0 | X1: 476480486 | Y1: =AT1 -> 5.84 | AA1: 0 | AB1: 0 | AC1: 0 | AD1: 0 | AE1: 0 | AF1: 0 | AG1: 0 | AH1: 0 | AI1: 1 | AJ1: 1 | AK1: 1 | AL1: 1 | AM1: -2 | AN1: 0 | AO1: 1 | AP1: 1 | AQ1: 0 | AR1: 0 | AT1: 5.84 | AV1: 1 | AW1: 2 | AX1: 35364430 | AY1: 1 | AZ1: 0 | BA1: 1 | BB1: 0 | BC1: 0 | BD1: 0 | BE1: 0 | BF1: 0 | BG1: 0 | BH1: 0 | BI1: 0 | BJ1: 0 | BK1: 0 | BL1: 0 | BM1: 0 | BN1: 0 | BO1: 0 | BP1: 0 | BQ1: 0 | BR1: 0 | BS1: 0 | BT1: 0 | BU1: 0 | BV1: 0 | BW1: 0 | CU1: =ROUND(AT1*Source!I28*AH1*AL1,2) -> 0 | CV1: =ROUND(Y1*Source!I28,9) -> 0.584 | CW1: 0 | CX1: =ROUND(Y1*Source!I28,9) -> 0.584 | CY1: =AD1 -> 0 | CZ1: =AH1 -> 0 | DA1: =AL1 -> 1 | DB1: =ROUND(ROUND(AT1*CZ1,2),6) -> 0 | DC1: =ROUND(ROUND(AT1*AG1,2),6) -> 0 | DF1: =ROUND(ROUND(AE1,2)*CX1,2) -> 0 | DG1: =ROUND(ROUND(AF1,2)*CX1,2) -> 0 | DH1: =ROUND(ROUND(AG1,2)*CX1,2) -> 0 | DI1: =ROUND(ROUND(AH1,2)*CX1,2) -> 0 | DJ1: =DI1 -> 0 | DK1: 0 | DM1: 0 | DO1: 0
A2: =ROW(Source!A29) -> 29 | B2: 35364244 | C2: 35364431 | D2: 35111398 | E2: 15872964 | F2: 1 | G2: 15872964 | H2: 1 | I2: 9999990008 | K2: Трудозатраты рабочих | L2: 1191 | N2: 1013 | O2: чел.-ч. | P2: чел.-ч. | Q2: 1 | W2: 0 | X2: 476480486 | Y2: =AT2 -> 46.78 | AA2: 0 | AB2: 0 | AC2: 0 | AD2: 0 | AE2: 0 | AF2: 0 | AG2: 0 | AH2: 0 | AI2: 1 | AJ2: 1 | AK2: 1 | AL2: 1 | AM2: -2 | AN2: 0 | AO2: 1 | AP2: 1 | AQ2: 0 | AR2: 0 | AT2: 46.78 | AV2: 1 | AW2: 2 | AX2: 35364433 | AY2: 1 | AZ2: 0 | BA2: 2 | BB2: 0 | BC2: 0 | BD2: 0 | BE2: 0 | BF2: 0 | BG2: 0 | BH2: 0 | BI2: 0 | BJ2: 0 | BK2: 0 | BL2: 0 | BM2: 0 | BN2: 0 | BO2: 0 | BP2: 0 | BQ2: 0 | BR2: 0 | BS2: 0 | BT2: 0 | BU2: 0 | BV2: 0 | BW2: 0 | CU2: =ROUND(AT2*Source!I29*AH2*AL2,2) -> 0 | CV2: =ROUND(Y2*Source!I29,9) -> 147.357 | CW2: 0 | CX2: =ROUND(Y2*Source!I29,9) -> 147.357 | CY2: =AD2 -> 0 | CZ2: =AH2 -> 0 | DA2: =AL2 -> 1 | DB2: =ROUND(ROUND(AT2*CZ2,2),6) -> 0 | DC2: =ROUND(ROUND(AT2*AG2,2),6) -> 0 | DF2: =ROUND(ROUND(AE2,2)*CX2,2) -> 0 | DG2: =ROUND(ROUND(AF2,2)*CX2,2) -> 0 | DH2: =ROUND(ROUND(AG2,2)*CX2,2) -> 0 | DI2: =ROUND(ROUND(AH2,2)*CX2,2) -> 0 | DJ2: =DI2 -> 0 | DK2: 0 | DM2: 0 | DO2: 0
A3: =ROW(Source!A29) -> 29 | B3: 35364244 | C3: 35364431 | D3: 35113133 | E3: 1 | F3: 1 | G3: 15872964 | H3: 2 | I3: 22.1-30-10 | J3: СН-2012.22 Выпуск № 6 (в текущих ценах по состоянию на 01.01.2026 г.). 22.1-30-10 | K3: Перфораторы электрические, мощность до 500 Вт | L3: 1368 | N3: 1011 | O3: маш.-ч | P3: маш.-ч | Q3: 1 | W3: 0 | X3: 71529876 | Y3: =AT3 -> 13 | AA3: 0 | AB3: 5.13 | AC3: 0.07 | AD3: 0 | AE3: 0 | AF3: 5.13 | AG3: 0.07 | AH3: 0 | AI3: 1 | AJ3: 1 | AK3: 1 | AL3: 1 | AM3: -2 | AN3: 0 | AO3: 1 | AP3: 1 | AQ3: 0 | AR3: 0 | AT3: 13 | AV3: 0 | AW3: 2 | AX3: 35364434 | AY3: 1 | AZ3: 0 | BA3: 3 | BB3: 0 | BC3: 0 | BD3: 0 | BE3: 0 | BF3: 0 | BG3: 0 | BH3: 0 | BI3: 0 | BJ3: 0 | BK3: 0 | BL3: 0 | BM3: 0 | BN3: 0 | BO3: 0 | BP3: 0 | BQ3: 0 | BR3: 0 | BS3: 0 | BT3: 0 | BU3: 0 | BV3: 0 | BW3: 0 | CV3: 0 | CW3: =ROUND(Y3*Source!I29*DO3,9) -> 0 | CX3: =ROUND(Y3*Source!I29,9) -> 40.95 | CY3: =AB3 -> 5.13 | CZ3: =AF3 -> 5.13 | DA3: =AJ3 -> 1 | DB3: =ROUND(ROUND(AT3*CZ3,2),6) -> 66.69 | DC3: =ROUND(ROUND(AT3*AG3,2),6) -> 0.91 | DF3: =ROUND(ROUND(AE3,2)*CX3,2) -> 0 | DG3: =ROUND(ROUND(AF3,2)*CX3,2) -> 210.07 | DH3: =ROUND(ROUND(AG3,2)*CX3,2) -> 2.87 | DI3: =ROUND(ROUND(AH3,2)*CX3,2) -> 0 | DJ3: =DG3 -> 210.07 | DK3: 0 | DM3: 0 | DO3: 0
A4: =ROW(Source!A29) -> 29 | B4: 35364244 | C4: 35364431 | D4: 35113206 | E4: 1 | F4: 1 | G4: 15872964 | H4: 2 | I4: 22.1-30-102 | J4: СН-2012.22 Выпуск № 6 (в текущих ценах по состоянию на 01.01.2026 г.). 22.1-30-102 | K4: Дрели электрические, двухскоростные, мощностью 600 Вт | L4: 1368 | N4: 1011 | O4: маш.-ч | P4: маш.-ч | Q4: 1 | W4: 0 | X4: -1817365194 | Y4: =AT4 -> 0.15 | AA4: 0 | AB4: 4.72 | AC4: 0.1 | AD4: 0 | AE4: 0 | AF4: 4.72 | AG4: 0.1 | AH4: 0 | AI4: 1 | AJ4: 1 | AK4: 1 | AL4: 1 | AM4: -2 | AN4: 0 | AO4: 1 | AP4: 1 | AQ4: 0 | AR4: 0 | AT4: 0.15 | AV4: 0 | AW4: 2 | AX4: 35364435 | AY4: 1 | AZ4: 0 | BA4: 4 | BB4: 0 | BC4: 0 | BD4: 0 | BE4: 0 | BF4: 0 | BG4: 0 | BH4: 0 | BI4: 0 | BJ4: 0 | BK4: 0 | BL4: 0 | BM4: 0 | BN4: 0 | BO4: 0 | BP4: 0 | BQ4: 0 | BR4: 0 | BS4: 0 | BT4: 0 | BU4: 0 | BV4: 0 | BW4: 0 | CV4: 0 | CW4: =ROUND(Y4*Source!I29*DO4,9) -> 0 | CX4: =ROUND(Y4*Source!I29,9) -> 0.4725 | CY4: =AB4 -> 4.72 | CZ4: =AF4 -> 4.72 | DA4: =AJ4 -> 1 | DB4: =ROUND(ROUND(AT4*CZ4,2),6) -> 0.71 | DC4: =ROUND(ROUND(AT4*AG4,2),6) -> 0.02 | DF4: =ROUND(ROUND(AE4,2)*CX4,2) -> 0 | DG4: =ROUND(ROUND(AF4,2)*CX4,2) -> 2.23 | DH4: =ROUND(ROUND(AG4,2)*CX4,2) -> 0.05 | DI4: =ROUND(ROUND(AH4,2)*CX4,2) -> 0 | DJ4: =DG4 -> 2.23 | DK4: 0 | DM4: 0 | DO4: 0
A5: =ROW(Source!A29) -> 29 | B5: 35364244 | C5: 35364431 | D5: 35114359 | E5: 1 | F5: 1 | G5: 15872964 | H5: 3 | I5: 21.1-11-108 | J5: СН-2012.21 Выпуск № 6 (в текущих ценах по состоянию на 01.01.2026 г.). 21.1-11-108 | K5: Шурупы-саморезы, размер 3,5х45 мм | L5: 1348 | N5: 1009 | O5: т | P5: т | Q5: 1000 | W5: 0 | X5: -181271767 | Y5: =AT5 -> 0.00074 | AA5: 190540.34 | AB5: 0 | AC5: 0 | AD5: 0 | AE5: 190540.34 | AF5: 0 | AG5: 0 | AH5: 0 | AI5: 1 | AJ5: 1 | AK5: 1 | AL5: 1 | AM5: -2 | AN5: 0 | AO5: 1 | AP5: 1 | AQ5: 0 | AR5: 0 | AT5: 0.00074 | AV5: 0 | AW5: 2 | AX5: 35364436 | AY5: 1 | AZ5: 0 | BA5: 5 | BB5: 0 | BC5: 0 | BD5: 0 | BE5: 0 | BF5: 0 | BG5: 0 | BH5: 0 | BI5: 0 | BJ5: 0 | BK5: 0 | BL5: 0 | BM5: 0 | BN5: 0 | BO5: 0 | BP5: 0 | BQ5: 0 | BR5: 0 | BS5: 0 | BT5: 0 | BU5: 0 | BV5: 0 | BW5: 0 | CV5: 0 | CW5: 0 | CX5: =ROUND(Y5*Source!I29,9) -> 0.002331 | CY5: =AA5 -> 190540.34 | CZ5: =AE5 -> 190540.34 | DA5: =AI5 -> 1 | DB5: =ROUND(ROUND(AT5*CZ5,2),6) -> 141 | DC5: =ROUND(ROUND(AT5*AG5,2),6) -> 0 | DF5: =ROUND(ROUND(AE5,2)*CX5,2) -> 444.15 | DG5: =ROUND(ROUND(AF5,2)*CX5,2) -> 0 | DH5: =ROUND(ROUND(AG5,2)*CX5,2) -> 0 | DI5: =ROUND(ROUND(AH5,2)*CX5,2) -> 0 | DJ5: =DF5 -> 444.15 | DK5: 0 | DM5: 0 | DO5: 0
A6: =ROW(Source!A29) -> 29 | B6: 35364244 | C6: 35364431 | D6: 35114332 | E6: 1 | F6: 1 | G6: 15872964 | H6: 3 | I6: 21.1-11-81 | J6: СН-2012.21 Выпуск № 6 (в текущих ценах по состоянию на 01.01.2026 г.). 21.1-11-81 | K6: Патроны, калибр 6,8/11 М для дюбеля | L6: 1355 | N6: 1010 | O6: 100 шт. | P6: 100 шт. | Q6: 100 | W6: 0 | X6: 1583670906 | Y6: =AT6 -> 4 | AA6: 997.35 | AB6: 0 | AC6: 0 | AD6: 0 | AE6: 997.35 | AF6: 0 | AG6: 0 | AH6: 0 | AI6: 1 | AJ6: 1 | AK6: 1 | AL6: 1 | AM6: -2 | AN6: 0 | AO6: 1 | AP6: 1 | AQ6: 0 | AR6: 0 | AT6: 4 | AV6: 0 | AW6: 2 | AX6: 35364437 | AY6: 1 | AZ6: 0 | BA6: 6 | BB6: 0 | BC6: 0 | BD6: 0 | BE6: 0 | BF6: 0 | BG6: 0 | BH6: 0 | BI6: 0 | BJ6: 0 | BK6: 0 | BL6: 0 | BM6: 0 | BN6: 0 | BO6: 0 | BP6: 0 | BQ6: 0 | BR6: 0 | BS6: 0 | BT6: 0 | BU6: 0 | BV6: 0 | BW6: 0 | CV6: 0 | CW6: 0 | CX6: =ROUND(Y6*Source!I29,9) -> 12.6 | CY6: =AA6 -> 997.35 | CZ6: =AE6 -> 997.35 | DA6: =AI6 -> 1 | DB6: =ROUND(ROUND(AT6*CZ6,2),6) -> 3989.4 | DC6: =ROUND(ROUND(AT6*AG6,2),6) -> 0 | DF6: =ROUND(ROUND(AE6,2)*CX6,2) -> 12566.61 | DG6: =ROUND(ROUND(AF6,2)*CX6,2) -> 0 | DH6: =ROUND(ROUND(AG6,2)*CX6,2) -> 0 | DI6: =ROUND(ROUND(AH6,2)*CX6,2) -> 0 | DJ6: =DF6 -> 12566.61 | DK6: 0 | DM6: 0 | DO6: 0
A7: =ROW(Source!A29) -> 29 | B7: 35364244 | C7: 35364431 | D7: 35115994 | E7: 1 | F7: 1 | G7: 15872964 | H7: 3 | I7: 21.1-25-1027 | J7: СН-2012.21 Выпуск № 6 (в текущих ценах по состоянию на 01.01.2026 г.). 21.1-25-1027 | K7: Кабель-каналы, размер 60х40 мм: кабель-каналы | L7: 1301 | N7: 1003 | O7: м | P7: м | Q7: 1 | W7: 0 | X7: 1471616812 | Y7: =AT7 -> 100 | AA7: 138.94 | AB7: 0 | AC7: 0 | AD7: 0 | AE7: 138.94 | AF7: 0 | AG7: 0 | AH7: 0 | AI7: 1 | AJ7: 1 | AK7: 1 | AL7: 1 | AM7: -2 | AN7: 0 | AO7: 1 | AP7: 1 | AQ7: 0 | AR7: 0 | AT7: 100 | AV7: 0 | AW7: 2 | AX7: 35364438 | AY7: 1 | AZ7: 0 | BA7: 7 | BB7: 0 | BC7: 0 | BD7: 0 | BE7: 0 | BF7: 0 | BG7: 0 | BH7: 0 | BI7: 0 | BJ7: 0 | BK7: 0 | BL7: 0 | BM7: 0 | BN7: 0 | BO7: 0 | BP7: 0 | BQ7: 0 | BR7: 0 | BS7: 0 | BT7: 0 | BU7: 0 | BV7: 0 | BW7: 0 | CV7: 0 | CW7: 0 | CX7: =ROUND(Y7*Source!I29,9) -> 315 | CY7: =AA7 -> 138.94 | CZ7: =AE7 -> 138.94 | DA7: =AI7 -> 1 | DB7: =ROUND(ROUND(AT7*CZ7,2),6) -> 13894 | DC7: =ROUND(ROUND(AT7*AG7,2),6) -> 0 | DF7: =ROUND(ROUND(AE7,2)*CX7,2) -> 43766.1 | DG7: =ROUND(ROUND(AF7,2)*CX7,2) -> 0 | DH7: =ROUND(ROUND(AG7,2)*CX7,2) -> 0 | DI7: =ROUND(ROUND(AH7,2)*CX7,2) -> 0 | DJ7: =DF7 -> 43766.1 | DK7: 0 | DM7: 0 | DO7: 0
A8: =ROW(Source!A29) -> 29 | B8: 35364244 | C8: 35364431 | D8: 35115995 | E8: 1 | F8: 1 | G8: 15872964 | H8: 3 | I8: 21.1-25-1028 | J8: СН-2012.21 Выпуск № 6 (в текущих ценах по состоянию на 01.01.2026 г.). 21.1-25-1028 | K8: Кабель-каналы, размер 60х40 мм: заглушки | L8: 1354 | N8: 1010 | O8: шт. | P8: шт. | Q8: 1 | W8: 0 | X8: -1986506557 | Y8: =AT8 -> 15 | AA8: 145.46 | AB8: 0 | AC8: 0 | AD8: 0 | AE8: 145.46 | AF8: 0 | AG8: 0 | AH8: 0 | AI8: 1 | AJ8: 1 | AK8: 1 | AL8: 1 | AM8: -2 | AN8: 0 | AO8: 1 | AP8: 1 | AQ8: 0 | AR8: 0 | AT8: 15 | AV8: 0 | AW8: 2 | AX8: 35364439 | AY8: 1 | AZ8: 0 | BA8: 8 | BB8: 0 | BC8: 0 | BD8: 0 | BE8: 0 | BF8: 0 | BG8: 0 | BH8: 0 | BI8: 0 | BJ8: 0 | BK8: 0 | BL8: 0 | BM8: 0 | BN8: 0 | BO8: 0 | BP8: 0 | BQ8: 0 | BR8: 0 | BS8: 0 | BT8: 0 | BU8: 0 | BV8: 0 | BW8: 0 | CV8: 0 | CW8: 0 | CX8: =ROUND(Y8*Source!I29,9) -> 47.25 | CY8: =AA8 -> 145.46 | CZ8: =AE8 -> 145.46 | DA8: =AI8 -> 1 | DB8: =ROUND(ROUND(AT8*CZ8,2),6) -> 2181.9 | DC8: =ROUND(ROUND(AT8*AG8,2),6) -> 0 | DF8: =ROUND(ROUND(AE8,2)*CX8,2) -> 6872.99 | DG8: =ROUND(ROUND(AF8,2)*CX8,2) -> 0 | DH8: =ROUND(ROUND(AG8,2)*CX8,2) -> 0 | DI8: =ROUND(ROUND(AH8,2)*CX8,2) -> 0 | DJ8: =DF8 -> 6872.99 | DK8: 0 | DM8: 0 | DO8: 0
A9: =ROW(Source!A29) -> 29 | B9: 35364244 | C9: 35364431 | D9: 35115996 | E9: 1 | F9: 1 | G9: 15872964 | H9: 3 | I9: 21.1-25-1029 | J9: СН-2012.21 Выпуск № 6 (в текущих ценах по состоянию на 01.01.2026 г.). 21.1-25-1029 | K9: Кабель-каналы, размер 60х40 мм: накладки стыковые | L9: 1354 | N9: 1010 | O9: шт. | P9: шт. | Q9: 1 | W9: 0 | X9: -1376764488 | Y9: =AT9 -> 4 | AA9: 126.89 | AB9: 0 | AC9: 0 | AD9: 0 | AE9: 126.89 | AF9: 0 | AG9: 0 | AH9: 0 | AI9: 1 | AJ9: 1 | AK9: 1 | AL9: 1 | AM9: -2 | AN9: 0 | AO9: 1 | AP9: 1 | AQ9: 0 | AR9: 0 | AT9: 4 | AV9: 0 | AW9: 2 | AX9: 35364440 | AY9: 1 | AZ9: 0 | BA9: 9 | BB9: 0 | BC9: 0 | BD9: 0 | BE9: 0 | BF9: 0 | BG9: 0 | BH9: 0 | BI9: 0 | BJ9: 0 | BK9: 0 | BL9: 0 | BM9: 0 | BN9: 0 | BO9: 0 | BP9: 0 | BQ9: 0 | BR9: 0 | BS9: 0 | BT9: 0 | BU9: 0 | BV9: 0 | BW9: 0 | CV9: 0 | CW9: 0 | CX9: =ROUND(Y9*Source!I29,9) -> 12.6 | CY9: =AA9 -> 126.89 | CZ9: =AE9 -> 126.89 | DA9: =AI9 -> 1 | DB9: =ROUND(ROUND(AT9*CZ9,2),6) -> 507.56 | DC9: =ROUND(ROUND(AT9*AG9,2),6) -> 0 | DF9: =ROUND(ROUND(AE9,2)*CX9,2) -> 1598.81 | DG9: =ROUND(ROUND(AF9,2)*CX9,2) -> 0 | DH9: =ROUND(ROUND(AG9,2)*CX9,2) -> 0 | DI9: =ROUND(ROUND(AH9,2)*CX9,2) -> 0 | DJ9: =DF9 -> 1598.81 | DK9: 0 | DM9: 0 | DO9: 0
