Workbook

Sheet Смета СН-2012 по гл. 1-5
A1: =CONCATENATE(Source!B1, " СН-2012 (© ОАО МЦЦС 'Мосстройцены', ", "2024", ")") -> Smeta.RU Flash (495) 974-1589 СН-2012 (© ОАО МЦЦС 'Мосстройцены', 2024)
J2: Форма № 1а (глава 1-5)
B3: "СОГЛАСОВАНО" | G3: "УТВЕРЖДАЮ"
B6: =CONCATENATE("______________________ ", IF(Source!AL12<>"", Source!AL12, "")) -> ______________________ | G6: =CONCATENATE("______________________ ", IF(Source!AH12<>"", Source!AH12, "")) -> ______________________
B7: "_____"________________ 2024 г. | G7: "_____"________________ 2024 г.
A10: =CONCATENATE( "ЛОКАЛЬНАЯ СМЕТА № ",IF(Source!F12<>"Новый объект", Source!F12, "")) -> ЛОКАЛЬНАЯ СМЕТА №
A11: (локальный сметный расчет)
A15: =IF(Source!G12<>"Новый объект", Source!G12, "") -> +Текущий ремонт спортзала №1 + раздевалки по адресу: г. Москва, ул. Митинская улица, д. 48, корп. 2 | AE15: =IF(Source!G12<>"Новый объект", Source!G12, "") -> +Текущий ремонт спортзала №1 + раздевалки по адресу: г. Москва, ул. Митинская улица, д. 48, корп. 2
A16: (наименование работ и затрат, наименование объекта)
A18: =CONCATENATE( "Основание: чертежи № ", Source!J12) -> Основание: чертежи №
F20: Сметная стоимость | I20: =I21+I22+I23+I24 -> 2116.77 | K20: тыс.руб
F21: Строительные работы | I21: =ROUND((Source!F539)/1000, 2) -> 0 | K21: тыс.руб
F22: Монтажные работы | I22: =ROUND((Source!F540)/1000, 2) -> 0 | K22: тыс.руб
F23: Оборудование | I23: =ROUND((Source!F531)/1000, 2) -> 0 | K23: тыс.руб
F24: Прочие работы | I24: =ROUND((Source!F541+Source!F542)/1000, 2) -> 2116.77 | K24: тыс.руб
F25: Средства на оплату труда | I25: =(Source!F537+ Source!F536)/1000 -> 609.91757 | K25: тыс.руб
A26: Составлен(а) в уровне текущих (прогнозных) цен на январь 2024 года
A27: №№ п/п | B27: Шифр расценки и коды ресурсов | C27: Наименование работ и затрат | D27: Единица измерения | E27: Кол-во единиц | F27: Цена на ед. изм. руб. | G27: Попра-вочные коэфф. | H27: Коэфф. зимних удоро-жаний | I27: Коэфф. пересчета | J27: ВСЕГО затрат, руб. | K27: Справочно
K28: ЗТР, всего чел.-час
K29: Ст-ть ед. с начислен.
A30: 1 | B30: 2 | C30: 3 | D30: 4 | E30: 5 | F30: 6 | G30: 7 | H30: 8 | I30: 9 | J30: 10 | K30: 11
A32: =CONCATENATE("Локальная смета: ",IF(Source!G20<>"Новая локальная смета", Source!G20, "")) -> Локальная смета:
A34: =CONCATENATE("Раздел: ",IF(Source!G24<>"Новый раздел", Source!G24, "")) -> Раздел: 1. Спортзал №1
A36: =CONCATENATE("Подраздел: ",IF(Source!G28<>"Новый подраздел", Source!G28, "")) -> Подраздел: 1.1 Демонтажные работы
A37: 1 | B37: =Source!F32 -> 1.1-3404-4-2/1 | C37: =Source!G32 -> Разборка плинтусов поливинилхлоридных с креплением шурупами | D37: =Source!H32 -> 100 м | E37: =Source!I32 -> 0.6504 | Q37: =ROUND((Source!BZ32/100)*ROUND((Source!AF32*Source!AV32)*Source!I32, 2), 2) -> 318.48 | R37: =Source!X32 -> 318.48 | S37: =ROUND((Source!CA32/100)*ROUND((Source!AF32*Source!AV32)*Source!I32, 2), 2) -> 45.5 | T37: =Source!Y32 -> 45.5 | U37: =ROUND((175/100)*ROUND((Source!AE32*Source!AV32)*Source!I32, 2), 2) -> 0 | V37: =ROUND((108/100)*ROUND(Source!CS32*Source!I32, 2), 2) -> 0
C38: ЗП | F38: =Source!AO32 -> 699.53 | G38: =Source!DG32 | H38: =Source!AV32 -> 1 | I38: =IF(Source!BA32<> 0, Source!BA32, 1) -> 1 | J38: =Source!S32 -> 454.97
C39: ЭМ | F39: =Source!AM32 -> 1.79 | G39: =Source!DE32 | H39: =Source!AV32 -> 1 | I39: =IF(Source!BB32<> 0, Source!BB32, 1) -> 1 | J39: =Source!Q32 -> 1.16
C40: НР от ЗП | D40: % | E40: =Source!AT32 -> 70 | J40: =SUM(R37:R39) -> 318.48
C41: СП от ЗП | D41: % | E41: =Source!AU32 -> 10 | J41: =SUM(T37:T40) -> 45.5
C42: ЗТР | D42: чел-ч | E42: =Source!AQ32 -> 2.78 | G42: =Source!DI32 | H42: =Source!AV32 -> 1 | K42: =Source!U32 -> 1.808112
I43: =J38+J39+J40+J41 -> 820.11 | K43: =IF(Source!I32<>0, ROUND(I43/Source!I32, 2), 0) -> 1260.93 | P43: =I43 -> 820.11
A44: 2 | B44: =Source!F33 -> 1.3-3204-1-1/1 | C44: =Source!G33 -> Расчистка поверхностей от старых покрасок (шпателем, щетками и т.д.) | D44: =Source!H33 -> м2 | E44: =Source!I33 -> 401.97 | Q44: =ROUND((Source!BZ33/100)*ROUND((Source!AF33*Source!AV33)*Source!I33, 2), 2) -> 41857.94 | R44: =Source!X33 -> 41857.94 | S44: =ROUND((Source!CA33/100)*ROUND((Source!AF33*Source!AV33)*Source!I33, 2), 2) -> 5979.71 | T44: =Source!Y33 -> 5979.71 | U44: =ROUND((175/100)*ROUND((Source!AE33*Source!AV33)*Source!I33, 2), 2) -> 0 | V44: =ROUND((108/100)*ROUND(Source!CS33*Source!I33, 2), 2) -> 0
C45: ="Объем: "&Source!I33&"=283,2+"&"118,77" -> Объем: 401,97=283,2+118,77
C46: ЗП | F46: =Source!AO33 -> 148.76 | G46: =Source!DG33 | H46: =Source!AV33 -> 1 | I46: =IF(Source!BA33<> 0, Source!BA33, 1) -> 1 | J46: =Source!S33 -> 59797.06
C47: НР от ЗП | D47: % | E47: =Source!AT33 -> 70 | J47: =SUM(R44:R46) -> 41857.94
C48: СП от ЗП | D48: % | E48: =Source!AU33 -> 10 | J48: =SUM(T44:T47) -> 5979.71
C49: ЗТР | D49: чел-ч | E49: =Source!AQ33 -> 0.6 | G49: =Source!DI33 | H49: =Source!AV33 -> 1 | K49: =Source!U33 -> 241.182
I50: =J46+J47+J48 -> 107634.71 | K50: =IF(Source!I33<>0, ROUND(I50/Source!I33, 2), 0) -> 267.77 | P50: =I50 -> 107634.71
A51: 3 | B51: =Source!F34 -> 1.1-3304-1-1/1 | C51: =Source!G34 -> Демонтаж радиатора массой до 80 кг | D51: =Source!H34 -> 100 шт. | E51: =Source!I34 -> 0.26 | Q51: =ROUND((Source!BZ34/100)*ROUND((Source!AF34*Source!AV34)*Source!I34, 2), 2) -> 5764.04 | R51: =Source!X34 -> 5764.04 | S51: =ROUND((Source!CA34/100)*ROUND((Source!AF34*Source!AV34)*Source!I34, 2), 2) -> 823.43 | T51: =Source!Y34 -> 823.43 | U51: =ROUND((175/100)*ROUND((Source!AE34*Source!AV34)*Source!I34, 2), 2) -> 0 | V51: =ROUND((108/100)*ROUND(Source!CS34*Source!I34, 2), 2) -> 0
C52: ЗП | F52: =Source!AO34 -> 31670.55 | G52: =Source!DG34 | H52: =Source!AV34 -> 1 | I52: =IF(Source!BA34<> 0, Source!BA34, 1) -> 1 | J52: =Source!S34 -> 8234.34
A53: 4 | B53: =Source!F35 -> 9999990001 | C53: =Source!G35 -> Масса мусора | D53: =Source!H35 -> т | E53: =Source!I35 -> -2.08 | F53: =Source!AK35 -> 0 | H53: =Source!AW35 -> 1 | I53: =IF(Source!BC35<> 0, Source!BC35, 1) -> 1 | J53: =Source!O35 -> 0 | Q53: =ROUND((Source!BZ35/100)*ROUND((Source!AF35*Source!AV35)*Source!I35, 2), 2) -> 0 | R53: =Source!X35 -> 0 | S53: =ROUND((Source!CA35/100)*ROUND((Source!AF35*Source!AV35)*Source!I35, 2), 2) -> 0 | T53: =Source!Y35 -> 0 | U53: =ROUND((175/100)*ROUND((Source!AE35*Source!AV35)*Source!I35, 2), 2) -> 0 | V53: =ROUND((108/100)*ROUND(Source!CS35*Source!I35, 2), 2) -> 0
C54: НР от ЗП | D54: % | E54: =Source!AT34 -> 70 | J54: =SUM(R51:R53) -> 5764.04
C55: СП от ЗП | D55: % | E55: =Source!AU34 -> 10 | J55: =SUM(T51:T54) -> 823.43
C56: ЗТР | D56: чел-ч | E56: =Source!AQ34 -> 120.59 | G56: =Source!DI34 | H56: =Source!AV34 -> 1 | K56: =Source!U34 -> 31.3534
I57: =J52+J54+J55+SUM(J53:J53) -> 14821.81 | K57: =IF(Source!I34<>0, ROUND(I57/Source!I34, 2), 0) -> 57006.96 | P57: =I57 -> 14821.81
A58: 5 | B58: =Source!F36 -> 1.50-3203-34-1/1 | C58: =Source!G36 -> Устройство и разборка защитного ограждения лесов из сетки | D58: =Source!H36 -> 100 м2 | E58: =Source!I36 -> 0.776 | Q58: =ROUND((Source!BZ36/100)*ROUND((Source!AF36*Source!AV36)*Source!I36, 2), 2) -> 2135.13 | R58: =Source!X36 -> 2135.13 | S58: =ROUND((Source!CA36/100)*ROUND((Source!AF36*Source!AV36)*Source!I36, 2), 2) -> 305.02 | T58: =Source!Y36 -> 305.02 | U58: =ROUND((175/100)*ROUND((Source!AE36*Source!AV36)*Source!I36, 2), 2) -> 0 | V58: =ROUND((108/100)*ROUND(Source!CS36*Source!I36, 2), 2) -> 0
C59: ЗП | F59: =Source!AO36 -> 3930.65 | G59: =Source!DG36 | H59: =Source!AV36 -> 1 | I59: =IF(Source!BA36<> 0, Source!BA36, 1) -> 1 | J59: =Source!S36 -> 3050.18
C60: МР | F60: =Source!AL36 -> 1389.73 | G60: =Source!DD36 | H60: =Source!AW36 -> 1 | I60: =IF(Source!BC36<> 0, Source!BC36, 1) -> 1 | J60: =Source!P36 -> 1078.43
C61: НР от ЗП | D61: % | E61: =Source!AT36 -> 70 | J61: =SUM(R58:R60) -> 2135.13
C62: СП от ЗП | D62: % | E62: =Source!AU36 -> 10 | J62: =SUM(T58:T61) -> 305.02
C63: ЗТР | D63: чел-ч | E63: =Source!AQ36 -> 12.77 | G63: =Source!DI36 | H63: =Source!AV36 -> 1 | K63: =Source!U36 -> 9.90952
I64: =J59+J60+J61+J62 -> 6568.76 | K64: =IF(Source!I36<>0, ROUND(I64/Source!I36, 2), 0) -> 8464.9 | P64: =I64 -> 6568.76
A65: 6 | B65: =Source!F37 -> 1.7-3204-1-4/1 | C65: =Source!G37 -> Разборка трубопроводов центрального отопления на сварке диаметром труб до 50 мм | D65: =Source!H37 -> 100 м | E65: =Source!I37 -> 0.4 | Q65: =ROUND((Source!BZ37/100)*ROUND((Source!AF37*Source!AV37)*Source!I37, 2), 2) -> 3750 | R65: =Source!X37 -> 3750 | S65: =ROUND((Source!CA37/100)*ROUND((Source!AF37*Source!AV37)*Source!I37, 2), 2) -> 535.71 | T65: =Source!Y37 -> 535.71 | U65: =ROUND((175/100)*ROUND((Source!AE37*Source!AV37)*Source!I37, 2), 2) -> 0.6 | V65: =ROUND((108/100)*ROUND(Source!CS37*Source!I37, 2), 2) -> 0.37
C66: ЗП | F66: =Source!AO37 -> 13392.85 | G66: =Source!DG37 | H66: =Source!AV37 -> 1 | I66: =IF(Source!BA37<> 0, Source!BA37, 1) -> 1 | J66: =Source!S37 -> 5357.14
C67: ЭМ | F67: =Source!AM37 -> 29.75 | G67: =Source!DE37 | H67: =Source!AV37 -> 1 | I67: =IF(Source!BB37<> 0, Source!BB37, 1) -> 1 | J67: =Source!Q37 -> 11.9
C68: в т.ч. ЗПМ | F68: =Source!AN37 -> 0.85 | G68: =Source!DF37 | H68: =Source!AV37 -> 1 | I68: =IF(Source!BS37<> 0, Source!BS37, 1) -> 1 | J68: =Source!R37 -> 0.34
C69: МР | F69: =Source!AL37 -> 539.47 | G69: =Source!DD37 | H69: =Source!AW37 -> 1 | I69: =IF(Source!BC37<> 0, Source!BC37, 1) -> 1 | J69: =Source!P37 -> 215.79
A70: 7 | B70: =Source!F38 -> 9999990001 | C70: =Source!G38 -> Масса мусора | D70: =Source!H38 -> т | E70: =Source!I38 -> -0.1816 | F70: =Source!AK38 -> 0 | H70: =Source!AW38 -> 1 | I70: =IF(Source!BC38<> 0, Source!BC38, 1) -> 1 | J70: =Source!O38 -> 0 | Q70: =ROUND((Source!BZ38/100)*ROUND((Source!AF38*Source!AV38)*Source!I38, 2), 2) -> 0 | R70: =Source!X38 -> 0 | S70: =ROUND((Source!CA38/100)*ROUND((Source!AF38*Source!AV38)*Source!I38, 2), 2) -> 0 | T70: =Source!Y38 -> 0 | U70: =ROUND((175/100)*ROUND((Source!AE38*Source!AV38)*Source!I38, 2), 2) -> 0 | V70: =ROUND((108/100)*ROUND(Source!CS38*Source!I38, 2), 2) -> 0
C71: НР от ЗП | D71: % | E71: =Source!AT37 -> 70 | J71: =SUM(R65:R70) -> 3750
C72: СП от ЗП | D72: % | E72: =Source!AU37 -> 10 | J72: =SUM(T65:T71) -> 535.71
C73: НР и СП от ЗПМ | D73: % | E73: =108 -> 108 | J73: =SUM(V65:V72) -> 0.37
C74: ЗТР | D74: чел-ч | E74: =Source!AQ37 -> 49.34 | G74: =Source!DI37 | H74: =Source!AV37 -> 1 | K74: =Source!U37 -> 19.736
I75: =J66+J67+J69+J71+J72+J73+SUM(J70:J70) -> 9870.91 | K75: =IF(Source!I37<>0, ROUND(I75/Source!I37, 2), 0) -> 24677.28 | P75: =I75 -> 9870.91
A76: 8 | B76: =Source!F39 -> 1.2-3105-1-1/1 | C76: =Source!G39 -> Вынос и занос мебели, в том числе спортивных снарядов массой до 50 кг | D76: =Source!H39 -> шт. | E76: =Source!I39 -> 15 | Q76: =ROUND((Source!BZ39/100)*ROUND((Source!AF39*Source!AV39)*Source!I39, 2), 2) -> 494.66 | R76: =Source!X39 -> 494.66 | S76: =ROUND((Source!CA39/100)*ROUND((Source!AF39*Source!AV39)*Source!I39, 2), 2) -> 70.67 | T76: =Source!Y39 -> 70.67 | U76: =ROUND((175/100)*ROUND((Source!AE39*Source!AV39)*Source!I39, 2), 2) -> 0 | V76: =ROUND((108/100)*ROUND(Source!CS39*Source!I39, 2), 2) -> 0
C77: ЗП | F77: =Source!AO39 -> 47.11 | G77: =Source!DG39 | H77: =Source!AV39 -> 1 | I77: =IF(Source!BA39<> 0, Source!BA39, 1) -> 1 | J77: =Source!S39 -> 706.65
C78: НР от ЗП | D78: % | E78: =Source!AT39 -> 70 | J78: =SUM(R76:R77) -> 494.66
C79: СП от ЗП | D79: % | E79: =Source!AU39 -> 10 | J79: =SUM(T76:T78) -> 70.67
C80: ЗТР | D80: чел-ч | E80: =Source!AQ39 -> 0.19 | G80: =Source!DI39 | H80: =Source!AV39 -> 1 | K80: =Source!U39 -> 2.85
I81: =J77+J78+J79 -> 1271.98 | K81: =IF(Source!I39<>0, ROUND(I81/Source!I39, 2), 0) -> 84.8 | P81: =I81 -> 1271.98
A82: 9 | B82: 1.50-3203-37-1/1 Поправка: СН-2012 О.П. п.22 | C82: Монтаж мелких конструкций из стали различного профиля массой до 20 кг Поправка: СН-2012 О.П. п.22 Наименование: Демонтаж, разборка отдельных бетонных, железобетонных, металлических, деревянных, пластмассовых конструктивных элементов зданий и сооружений, внутренних и наружных инженерных систем и коммуникаций при отсутствии необходимых стоимостных нормативов в сборниках СН-2012 | D82: =Source!H40 -> т | E82: =Source!I40 -> 0.13744 | Q82: =ROUND((Source!BZ40/100)*ROUND((Source!AF40*Source!AV40)*Source!I40, 2), 2) -> 906.07 | R82: =Source!X40 -> 906.07 | S82: =ROUND((Source!CA40/100)*ROUND((Source!AF40*Source!AV40)*Source!I40, 2), 2) -> 129.44 | T82: =Source!Y40 -> 129.44 | U82: =ROUND((175/100)*ROUND((Source!AE40*Source!AV40)*Source!I40, 2), 2) -> 2.35 | V82: =ROUND((108/100)*ROUND(Source!CS40*Source!I40, 2), 2) -> 1.45
C83: ЗП | F83: =Source!AO40 -> 47088.86 | G83: =Source!DG40 -> )*0,2 | H83: =Source!AV40 -> 1 | I83: =IF(Source!BA40<> 0, Source!BA40, 1) -> 1 | J83: =Source!S40 -> 1294.38
C84: ЭМ | F84: =Source!AM40 -> 952.94 | G84: =Source!DE40 -> )*0,2 | H84: =Source!AV40 -> 1 | I84: =IF(Source!BB40<> 0, Source!BB40, 1) -> 1 | J84: =Source!Q40 -> 26.19
C85: в т.ч. ЗПМ | F85: =Source!AN40 -> 48.72 | G85: =Source!DF40 -> )*0,2 | H85: =Source!AV40 -> 1 | I85: =IF(Source!BS40<> 0, Source!BS40, 1) -> 1 | J85: =Source!R40 -> 1.34
C86: НР от ЗП | D86: % | E86: =Source!AT40 -> 70 | J86: =SUM(R82:R85) -> 906.07
C87: СП от ЗП | D87: % | E87: =Source!AU40 -> 10 | J87: =SUM(T82:T86) -> 129.44
C88: НР и СП от ЗПМ | D88: % | E88: =108 -> 108 | J88: =SUM(V82:V87) -> 1.45
C89: ЗТР | D89: чел-ч | E89: =Source!AQ40 -> 133.4 | G89: =Source!DI40 -> )*0,2 | H89: =Source!AV40 -> 1 | K89: =Source!U40 -> 3.6668992
I90: =J83+J84+J86+J87+J88 -> 2357.53 | K90: =IF(Source!I40<>0, ROUND(I90/Source!I40, 2), 0) -> 17153.16 | P90: =I90 -> 2357.53
A91: 10 | B91: =Source!F41 -> 1.50-3204-4-1/1 | C91: =Source!G41 -> Пробивка отбойным молотком сквозных отверстий в бетонных стенах и фундаментах толщиной 0,4 м для трубопроводов диаметром 100 мм | D91: =Source!H41 -> 100 шт. | E91: =Source!I41 -> 0.05 | Q91: =ROUND((Source!BZ41/100)*ROUND((Source!AF41*Source!AV41)*Source!I41, 2), 2) -> 1723.18 | R91: =Source!X41 -> 1723.18 | S91: =ROUND((Source!CA41/100)*ROUND((Source!AF41*Source!AV41)*Source!I41, 2), 2) -> 246.17 | T91: =Source!Y41 -> 246.17 | U91: =ROUND((175/100)*ROUND((Source!AE41*Source!AV41)*Source!I41, 2), 2) -> 2942.82 | V91: =ROUND((108/100)*ROUND(Source!CS41*Source!I41, 2), 2) -> 1816.14
C92: ЗП | F92: =Source!AO41 -> 49233.8 | G92: =Source!DG41 | H92: =Source!AV41 -> 1 | I92: =IF(Source!BA41<> 0, Source!BA41, 1) -> 1 | J92: =Source!S41 -> 2461.69
C93: ЭМ | F93: =Source!AM41 -> 44753.25 | G93: =Source!DE41 | H93: =Source!AV41 -> 1 | I93: =IF(Source!BB41<> 0, Source!BB41, 1) -> 1 | J93: =Source!Q41 -> 2237.66
C94: в т.ч. ЗПМ | F94: =Source!AN41 -> 33632.25 | G94: =Source!DF41 | H94: =Source!AV41 -> 1 | I94: =IF(Source!BS41<> 0, Source!BS41, 1) -> 1 | J94: =Source!R41 -> 1681.61
C95: НР от ЗП | D95: % | E95: =Source!AT41 -> 70 | J95: =SUM(R91:R94) -> 1723.18
C96: СП от ЗП | D96: % | E96: =Source!AU41 -> 10 | J96: =SUM(T91:T95) -> 246.17
C97: НР и СП от ЗПМ | D97: % | E97: =108 -> 108 | J97: =SUM(V91:V96) -> 1816.14
C98: ЗТР | D98: чел-ч | E98: =Source!AQ41 -> 154 | G98: =Source!DI41 | H98: =Source!AV41 -> 1 | K98: =Source!U41 -> 7.7
I99: =J92+J93+J95+J96+J97 -> 8484.84 | K99: =IF(Source!I41<>0, ROUND(I99/Source!I41, 2), 0) -> 169696.8 | P99: =I99 -> 8484.84
A101: =CONCATENATE("Итого по подразделу: ",IF(Source!G43<>"Новый подраздел", Source!G43, "")) -> Итого по подразделу: 1.1 Демонтажные работы | I101: =SUM(P36:P100) -> 151830.65
A104: =CONCATENATE("Подраздел: ",IF(Source!G73<>"Новый подраздел", Source!G73, "")) -> Подраздел: 1.2 Ремонтно-строительные работы
A105: 11 | B105: =Source!F77 -> 1.13-3103-1-1/1 | C105: =Source!G77 -> Простая штукатурка поверхностей стен по камню и бетону известковым раствором | D105: =Source!H77 -> 100 м2 | E105: =Source!I77 -> 3.9591 | Q105: =ROUND((Source!BZ77/100)*ROUND((Source!AF77*Source!AV77)*Source!I77, 2), 2) -> 52359.47 | R105: =Source!X77 -> 52359.47 | S105: =ROUND((Source!CA77/100)*ROUND((Source!AF77*Source!AV77)*Source!I77, 2), 2) -> 7479.92 | T105: =Source!Y77 -> 7479.92 | U105: =ROUND((175/100)*ROUND((Source!AE77*Source!AV77)*Source!I77, 2), 2) -> 14524.27 | V105: =ROUND((108/100)*ROUND(Source!CS77*Source!I77, 2), 2) -> 8963.55
C106: ЗП | F106: =Source!AO77 -> 18892.99 | G106: =Source!DG77 | H106: =Source!AV77 -> 1 | I106: =IF(Source!BA77<> 0, Source!BA77, 1) -> 1 | J106: =Source!S77 -> 74799.24
C107: ЭМ | F107: =Source!AM77 -> 2362.37 | G107: =Source!DE77 | H107: =Source!AV77 -> 1 | I107: =IF(Source!BB77<> 0, Source!BB77, 1) -> 1 | J107: =Source!Q77 -> 9352.86
C108: в т.ч. ЗПМ | F108: =Source!AN77 -> 2096.33 | G108: =Source!DF77 | H108: =Source!AV77 -> 1 | I108: =IF(Source!BS77<> 0, Source!BS77, 1) -> 1 | J108: =Source!R77 -> 8299.58
C109: МР | F109: =Source!AL77 -> 12290.28 | G109: =Source!DD77 | H109: =Source!AW77 -> 1 | I109: =IF(Source!BC77<> 0, Source!BC77, 1) -> 1 | J109: =Source!P77 -> 48658.45
C110: НР от ЗП | D110: % | E110: =Source!AT77 -> 70 | J110: =SUM(R105:R109) -> 52359.47
C111: СП от ЗП | D111: % | E111: =Source!AU77 -> 10 | J111: =SUM(T105:T110) -> 7479.92
C112: НР и СП от ЗПМ | D112: % | E112: =108 -> 108 | J112: =SUM(V105:V111) -> 8963.55
C113: ЗТР | D113: чел-ч | E113: =Source!AQ77 -> 63.94 | G113: =Source!DI77 | H113: =Source!AV77 -> 1 | K113: =Source!U77 -> 253.14485
I114: =J106+J107+J109+J110+J111+J112 -> 201613.49 | K114: =IF(Source!I77<>0, ROUND(I114/Source!I77, 2), 0) -> 50924.07 | P114: =I114 -> 201613.49
A115: 12 | B115: =Source!F78 -> 1.13-3703-1-1/1 | C115: =Source!G78 -> Обработка поверхностей стен грунтовкой глубокого проникновения внутри помещения | D115: =Source!H78 -> 100 м2 | E115: =Source!I78 -> 3.9591 | Q115: =ROUND((Source!BZ78/100)*ROUND((Source!AF78*Source!AV78)*Source!I78, 2), 2) -> 4110.97 | R115: =Source!X78 -> 4110.97 | S115: =ROUND((Source!CA78/100)*ROUND((Source!AF78*Source!AV78)*Source!I78, 2), 2) -> 587.28 | T115: =Source!Y78 -> 587.28 | U115: =ROUND((175/100)*ROUND((Source!AE78*Source!AV78)*Source!I78, 2), 2) -> 0.07 | V115: =ROUND((108/100)*ROUND(Source!CS78*Source!I78, 2), 2) -> 0.04
...

Sheet Дефектная ведомость
A1: =Source!B1 -> Smeta.RU Flash (495) 974-1589
D3: "УТВЕРЖДАЮ"
C5: ___________________________
C7: ___________________________
C9: " ___ " ___________ 20 ___ г.
A11: =CONCATENATE("Дефектный акт ", IF(Source!AN15<>"", Source!AN15," ")) -> Дефектный акт
A12: На Текущий ремонт спортзала №1 + раздевалки по адресу: г. Москва, ул. Митинская улица, д. 48, корп. 2 | AD12: =CONCATENATE("На капитальный ремонт ", Source!G12) -> На капитальный ремонт +Текущий ремонт спортзала №1 + раздевалки по адресу: г. Москва, ул. Митинская улица, д. 48, корп. 2
B14: Мы, нижеподписавшиеся, произвели осмотр объекта
B15: и постановили произвести ремонт объекта в
B16: следующем объеме:
A17: № п/п | B17: Наименование работ и затрат | C17: Единица измерения | D17: Количество | E17: Примечание
A18: 1 | B18: 2 | C18: 3 | D18: 4 | E18: 5
A19: =CONCATENATE("Локальная смета: ", Source!G20) -> Локальная смета: Новая локальная смета
A20: =CONCATENATE("Раздел: ", Source!G24) -> Раздел: 1. Спортзал №1
A21: =CONCATENATE("Подраздел: ", Source!G28) -> Подраздел: 1.1 Демонтажные работы
A22: 1 | B22: =Source!G32 -> Разборка плинтусов поливинилхлоридных с креплением шурупами | C22: =Source!H32 -> 100 м | D22: =Source!I32 -> 0.6504
A23: 2 | B23: =Source!G33 -> Расчистка поверхностей от старых покрасок (шпателем, щетками и т.д.) | C23: =Source!H33 -> м2 | D23: =Source!I33 -> 401.97
A24: 3 | B24: =Source!G34 -> Демонтаж радиатора массой до 80 кг | C24: =Source!H34 -> 100 шт. | D24: =Source!I34 -> 0.26
A25: 3.1 | B25: =Source!G35 -> Масса мусора | C25: =Source!H35 -> т | D25: =Source!I35 -> -2.08
A26: 4 | B26: =Source!G36 -> Устройство и разборка защитного ограждения лесов из сетки | C26: =Source!H36 -> 100 м2 | D26: =Source!I36 -> 0.776
A27: 5 | B27: =Source!G37 -> Разборка трубопроводов центрального отопления на сварке диаметром труб до 50 мм | C27: =Source!H37 -> 100 м | D27: =Source!I37 -> 0.4
A28: 5.1 | B28: =Source!G38 -> Масса мусора | C28: =Source!H38 -> т | D28: =Source!I38 -> -0.1816
A29: 6 | B29: =Source!G39 -> Вынос и занос мебели, в том числе спортивных снарядов массой до 50 кг | C29: =Source!H39 -> шт. | D29: =Source!I39 -> 15
A30: 7 | B30: =Source!G40 -> Монтаж мелких конструкций из стали различного профиля массой до 20 кг | C30: =Source!H40 -> т | D30: =Source!I40 -> 0.13744
A31: 8 | B31: =Source!G41 -> Пробивка отбойным молотком сквозных отверстий в бетонных стенах и фундаментах толщиной 0,4 м для трубопроводов диаметром 100 мм | C31: =Source!H41 -> 100 шт. | D31: =Source!I41 -> 0.05
A32: =CONCATENATE("Подраздел: ", Source!G73) -> Подраздел: 1.2 Ремонтно-строительные работы
A33: 9 | B33: =Source!G77 -> Простая штукатурка поверхностей стен по камню и бетону известковым раствором | C33: =Source!H77 -> 100 м2 | D33: =Source!I77 -> 3.9591
A34: 10 | B34: =Source!G78 -> Обработка поверхностей стен грунтовкой глубокого проникновения внутри помещения | C34: =Source!H78 -> 100 м2 | D34: =Source!I78 -> 3.9591
A35: 11 | B35: =Source!G79 -> Улучшенная окраска стен внутри помещений водно-дисперсионными акриловыми красками - краска моющаяся типа ВД-АК-210 | C35: =Source!H79 -> 100 м2 | D35: =Source!I79 -> 3.9591
A36: 12 | B36: =Source!G80 -> Установка и разборка инвентарных лесов внутренних трубчатых при высоте помещений до 6 м (без затрат по эксплуатации лесов) | C36: =Source!H80 -> 100 м2 | D36: =Source!I80 -> 2.837
A37: 13 | B37: =Source!G81 -> Простая штукатурка поверхностей потолков по камню и бетону известковым раствором | C37: =Source!H81 -> 100 м2 | D37: =Source!I81 -> 2.837
A38: 14 | B38: =Source!G82 -> Обработка поверхностей потолков грунтовкой глубокого проникновения внутри помещения | C38: =Source!H82 -> 100 м2 | D38: =Source!I82 -> 2.837
A39: 15 | B39: =Source!G83 -> Улучшенная окраска потолков внутри помещений водно-дисперсионными акриловыми красками - краска моющаяся типа ВД-АК-210 | C39: =Source!H83 -> 100 м2 | D39: =Source!I83 -> 2.837
A40: 16 | B40: =Source!G84 -> Устройство плинтусов - поливинилхлоридных на винтах самонарезающих с креплением через защёлку / с мягким краем, размеры 50-62х21 мм | C40: =Source!H84 -> 100 м | D40: =Source!I84 -> 0.6504
A41: 17 | B41: =Source!G85 -> Установка штучных изделий столов, шкафов под мойки, холодильных шкафов и др. (без стоимости изделий) | C41: =Source!H85 -> 100 шт. | D41: =Source!I85 -> 0.04
A42: 17.1 | B42: =Source!G86 -> Шведская стенка деревянная с турником 1x3 м или эквивалент | C42: =Source!H86 -> шт. | D42: =Source!I86 -> 4
A43: =CONCATENATE("Подраздел: ", Source!G118) -> Подраздел: 1.3 Сантехнические работы
A44: 18 | B44: =Source!G122 -> Установка радиаторов биметаллических "Рифар" / 10 секций, размеры 261х100х800 мм, теплоотдача 1010 Вт | C44: =Source!H122 -> 100 квт | D44: =Source!I122 -> 0.5096
A45: 18.1 | B45: =Source!G123 -> Радиаторы биметаллические секционные "Рифар", межосевое расстояние 200 мм, 10 секций, размеры 261х100х800 мм, теплоотдача 1010 Вт | C45: =Source!H123 -> шт. | D45: =Source!I123 -> -50.455496
A46: 18.2 | B46: =Source!G124 -> Радиатор Rifar Monolit 500/100 биметалл 10 секций или эквивалент | C46: =Source!H124 -> шт. | D46: =Source!I124 -> 26
A47: 18.3 | B47: =Source!G125 -> Кронштейны для крепления отопительных приборов, марка КР1-РС | C47: =Source!H125 -> компл. | D47: =Source!I125 -> -22.52432
A48: 18.4 | B48: =Source!G126 -> Кронштейны для крепления отопительных приборов, марка КРД, длина 131 мм | C48: =Source!H126 -> шт. | D48: =Source!I126 -> 52
A49: 19 | B49: =Source!G127 -> Установка терморегулирующих клапанов на отопительных приборах | C49: =Source!H127 -> 100 шт. | D49: =Source!I127 -> 0.02
A50: 20 | B50: =Source!G128 -> Окраска суриком металлических решеток, переплетов, радиаторов, труб диаметром менее 50 мм и т.п. за два раза | C50: =Source!H128 -> 100 м2 | D50: =Source!I128 -> 0.02188
A51: 21 | B51: =Source!G129 -> Прокладка трубопроводов отопления из стальных водогазопроводных неоцинкованных труб диаметром 20 мм (без стоимости арматуры и креплений) | C51: =Source!H129 -> 100 м | D51: =Source!I129 -> 0.54
A52: 21.1 | B52: =Source!G130 -> Арматурные заготовки (стержни, хомуты и т.п.), не собранные в каркасы или сетки, арматурная сталь периодического профиля, класс А-III, диаметр 20-22 мм | C52: =Source!H130 -> т | D52: =Source!I130 -> 0.0729
A53: 22 | B53: =Source!G131 -> Прокладка трубопроводов отопления из стальных водогазопроводных неоцинкованных труб диаметром 25 мм (без стоимости арматуры и креплений) | C53: =Source!H131 -> 100 м | D53: =Source!I131 -> 0.3
A54: 22.1 | B54: =Source!G132 -> Арматурные заготовки (стержни, хомуты и т.п.), не собранные в каркасы или сетки, арматурная сталь периодического профиля, класс А-III, диаметр 20-22 мм | C54: =Source!H132 -> т | D54: =Source!I132 -> 0.0405
A55: 23 | B55: =Source!G133 -> Гидравлическое испытание трубопроводов систем отопления диаметром до 50 мм | C55: =Source!H133 -> 100 м | D55: =Source!I133 -> 0.84
... A60: 26 | B60: =Source!G138 -> Заделка отверстий в бетонных перекрытиях в местах прохода трубопроводов | C60: =Source!H138 -> 100 шт. | D60: =Source!I138 -> 0.05
A61: =CONCATENATE("Подраздел: ", Source!G170) -> Подраздел: 1.4 Электромонтажные работы
A62: 27 | B62: =Source!G174 -> Демонтаж осветительных приборов - светильник для люминесцентных ламп | C62: =Source!H174 -> 100 шт. | D62: =Source!I174 -> 0.98
A63: 28 | B63: =Source!G175 -> Демонтаж кабеля | C63: =Source!H175 -> 100 м | D63: =Source!I175 -> 0.3549
A64: 29 | B64: =Source!G176 -> Прокладка пластикового кабель-канала по бетонному основанию / сечение 20х12,5 мм | C64: =Source!H176 -> 100 м | D64: =Source!I176 -> 0.1
A65: 30 | B65: =Source!G177 -> Прокладка труб гофрированных поливинилхлоридных наружным диаметром 20 мм открыто по стенам и потолкам с установкой соединительных коробок | C65: =Source!H177 -> 100 м | D65: =Source!I177 -> 0.3549
A66: 31 | B66: =Source!G178 -> Затягивание проводов и кабелей в проложенные трубы и металлические рукава, провод первый одножильный или многожильный в общей оплетке, суммарное сечение до 6 мм2 (без стоимости материалов) | C66: =Source!H178 -> 100 м | D66: =Source!I178 -> 0.3549
A67: 31.1 | B67: =Source!G179 -> Кабели силовые, с медными жилами, с изоляц. и оболоч.из ПВХ пластиката пониж.пожар.опасности, не распростр.горение, с пониж.дымо- и газовыделением и с низк.токсич-тью продуктов горения, напряж.1000 В, марка ВВГнг(А)-LSLTx, число жил и сечение, мм2: 3х1,5 | C67: =Source!H179 -> км | D67: =Source!I179 -> 0.0362
A68: 32 | B68: =Source!G180 -> Замена электроустановочных изделий, открытая проводка, выключатель, розетка (без стоимости материалов) | C68: =Source!H180 -> 100 шт. | D68: =Source!I180 -> 0.02
A69: 32.1 | B69: =Source!G181 -> Выключатели, серия "Прима", напряжение 250 В, сила тока 6 А, тип: А16-051, одноклавишный, открытой установки | C69: =Source!H181 -> шт. | D69: =Source!I181 -> 1
A70: 32.2 | B70: =Source!G182 -> Выключатели серии "Прима", напряжение 250 В, сила тока 6 А, открытой установки двухклавишные, тип А56-029 | C70: =Source!H182 -> шт. | D70: =Source!I182 -> 1
A71: 33 | B71: =Source!G183 -> Установка светильников с люминесцентными лампами, отдельно устанавливаемых на штырях с количеством ламп в светильнике до 4 (без стоимости материалов) | C71: =Source!H183 -> 100 шт. | D71: =Source!I183 -> 0.64
A72: 33.1 | B72: =Source!G184 -> Светильник светодиодный Geniled ЛПО 1200х180х40мм 40Вт 4000К Опал или эквивалент | C72: =Source!H184 -> шт. | D72: =Source!I184 -> 56
A73: 33.2 | B73: =Source!G185 -> Светильник светодиодный Geniled ЛПО 1200х180х40мм 40Вт 4000К Опал БАП или эквивалент | C73: =Source!H185 -> шт. | D73: =Source!I185 -> 8
A74: =CONCATENATE("Раздел: ", Source!G247) -> Раздел: 2. Тренерская
A75: =CONCATENATE("Подраздел: ", Source!G251) -> Подраздел: 2.1 Тренерская
A76: 34 | B76: =Source!G255 -> Разборка плинтусов поливинилхлоридных с креплением шурупами | C76: =Source!H255 -> 100 м | D76: =Source!I255 -> 0.261
A77: 35 | B77: =Source!G256 -> Расчистка поверхностей от старых покрасок (шпателем, щетками и т.д.) | C77: =Source!H256 -> м2 | D77: =Source!I256 -> 16.5
A78: 36 | B78: =Source!G257 -> Демонтаж радиатора массой до 80 кг | C78: =Source!H257 -> 100 шт. | D78: =Source!I257 -> 0.03
A79: 36.1 | B79: =Source!G258 -> Масса мусора | C79: =Source!H258 -> т | D79: =Source!I258 -> -0.24
A80: 37 | B80: =Source!G259 -> Разборка трубопроводов центрального отопления на сварке диаметром труб до 50 мм | C80: =Source!H259 -> 100 м | D80: =Source!I259 -> 0.0574
A81: 37.1 | B81: =Source!G260 -> Масса мусора | C81: =Source!H260 -> т | D81: =Source!I260 -> -0.02606
A82: 38 | B82: =Source!G261 -> Разборка покрытий из линолеума и релина | C82: =Source!H261 -> 100 м2 | D82: =Source!I261 -> 0.338
A83: 38.1 | B83: =Source!G262 -> Масса мусора | C83: =Source!H262 -> т | D83: =Source!I262 -> -0.15886
A84: =CONCATENATE("Подраздел: ", Source!G294) -> Подраздел: 2.2 Ремонтно-строительные работы
A85: 39 | B85: =Source!G298 -> Монтаж потолка кассетного типа на металлическом каркасе - размер алюминиевых кассет 595 х 595 мм, при площади помещения до 100 м2, с установкой направляющих и креплением подвесок дюбель-гвоздями | C85: =Source!H298 -> 100 м2 | D85: =Source!I298 -> 0.338
A86: 40 | B86: =Source!G299 -> Устройство самовыравнивающихся стяжек из специализированных сухих смесей толщиной 5 мм | C86: =Source!H299 -> 100 м2 | D86: =Source!I299 -> 0.338
A87: 41 | B87: =Source!G300 -> Добавляется или исключается на каждый 1 мм изменения толщины стяжки к поз.10-3103-2-11 | C87: =Source!H300 -> 100 м2 | D87: =Source!I300 -> 0.338
A88: 42 | B88: =Source!G301 -> Устройство полов из крупноразмерных керамогранитных плиток на клее из сухих смесей толщиной клеевого слоя 4 мм с затиркой швов / смеси для плиточных работ водостойкие, суперэластичные | C88: =Source!H301 -> 100 м2 | D88: =Source!I301 -> 0.338
A89: 43 | B89: =Source!G302 -> Устройство плинтусов из крупноразмерной плитки типа "керамогранит" | C89: =Source!H302 -> 100 м | D89: =Source!I302 -> 0.261
A90: 44 | B90: =Source!G303 -> Настенное покрытие стеклообоями с окраской поливинилацетатными красками за один раз с подготовкой / обои стеклотканевые под покраску для стен и потолков, однослойные | C90: =Source!H303 -> 100 м2 | D90: =Source!I303 -> 1.0026
A91: 45 | B91: =Source!G304 -> Добавляется на окраску поливинилацетатными красками стеклообоев на каждый последующий слой к поз. 13-3303-5-1, 13-3303-5-2 | C91: =Source!H304 -> 100 м2 | D91: =Source!I304 -> 1.0026
A92: =CONCATENATE("Подраздел: ", Source!G336) -> Подраздел: 2.3 Сантехнические работы
A93: 46 | B93: =Source!G340 -> Установка радиаторов биметаллических "Рифар" / 10 секций, размеры 261х100х800 мм, теплоотдача 1010 Вт | C93: =Source!H340 -> 100 квт | D93: =Source!I340 -> 0.0392
A94: 46.1 | B94: =Source!G341 -> Радиаторы биметаллические секционные "Рифар", межосевое расстояние 200 мм, 10 секций, размеры 261х100х800 мм, теплоотдача 1010 Вт | C94: =Source!H341 -> шт. | D94: =Source!I341 -> -3.881192
A95: 46.2 | B95: =Source!G342 -> Радиатор Rifar Monolit 500/100 биметалл 10 секций или эквивалент | C95: =Source!H342 -> шт. | D95: =Source!I342 -> 3
A96: 46.3 | B96: =Source!G343 -> Кронштейны для крепления отопительных приборов, марка КР1-РС | C96: =Source!H343 -> компл. | D96: =Source!I343 -> -1.73264
A97: 46.4 | B97: =Source!G344 -> Кронштейны для крепления отопительных приборов, марка КРД, длина 131 мм | C97: =Source!H344 -> шт. | D97: =Source!I344 -> 6
A98: 47 | B98: =Source!G345 -> Прокладка трубопроводов отопления из стальных водогазопроводных неоцинкованных труб диаметром 20 мм (без стоимости арматуры и креплений) | C98: =Source!H345 -> 100 м | D98: =Source!I345 -> 0.15
A99: 47.1 | B99: =Source!G346 -> Арматурные заготовки (стержни, хомуты и т.п.), не собранные в каркасы или сетки, арматурная сталь периодического профиля, класс А-III, диаметр 20-22 мм | C99: =Source!H346 -> т | D99: =Source!I346 -> 0.02025
A100: 48 | B100: =Source!G347 -> Гидравлическое испытание трубопроводов систем отопления диаметром до 50 мм | C100: =Source!H347 -> 100 м | D100: =Source!I347 -> 0.15
A101: 49 | B101: =Source!G348 -> Установка муфтовой арматуры диаметром 20 мм (без стоимости арматуры) | C101: =Source!H348 -> 10 шт. | D101: =Source!I348 -> 0.7
A102: 49.1 | B102: =Source!G349 -> Кран шаровой Ду 20 Бугатти или эквивалент | C102: =Source!H349 -> шт. | D102: =Source!I349 -> 7
A103: =CONCATENATE("Подраздел: ", Source!G381) -> Подраздел: 2.4 Электромонтажные работы
A104: 50 | B104: =Source!G385 -> Демонтаж осветительных приборов - светильник для люминесцентных ламп | C104: =Source!H385 -> 100 шт. | D104: =Source!I385 -> 0.06
A105: 51 | B105: =Source!G386 -> Замена электроустановочных изделий, открытая проводка, выключатель, розетка (без стоимости материалов) | C105: =Source!H386 -> 100 шт. | D105: =Source!I386 -> 0.02
A106: 51.1 | B106: =Source!G387 -> Выключатели серии "Прима", напряжение 250 В, сила тока 6 А, открытой установки двухклавишные, тип А56-029 | C106: =Source!H387 -> шт. | D106: =Source!I387 -> 2
A107: 52 | B107: =Source!G388 -> Прокладка труб гофрированных поливинилхлоридных наружным диаметром 20 мм открыто по стенам и потолкам с установкой соединительных коробок | C107: =Source!H388 -> 100 м | D107: =Source!I388 -> 0.1
A108: 53 | B108: =Source!G389 -> Затягивание проводов и кабелей в проложенные трубы и металлические рукава, провод первый одножильный или многожильный в общей оплетке, суммарное сечение до 6 мм2 (без стоимости материалов) | C108: =Source!H389 -> 100 м | D108: =Source!I389 -> 0.1
A109: 53.1 | B109: =Source!G390 -> Кабели силовые, с медными жилами, с изоляц. и оболоч.из ПВХ пластиката пониж.пожар.опасности, не распростр.горение, с пониж.дымо- и газовыделением и с низк.токсич-тью продуктов горения, напряж.1000 В, марка ВВГнг(А)-LSLTx, число жил и сечение, мм2: 3х1,5 | C109: =Source!H390 -> км | D109: =Source!I390 -> 0.0102
A110: 54 | B110: =Source!G391 -> Установка светильников с люминесцентными лампами, отдельно устанавливаемых на штырях с количеством ламп в светильнике до 4 (без стоимости материалов) | C110: =Source!H391 -> 100 шт. | D110: =Source!I391 -> 0.06
...

Sheet RV_DATA
A1: BuildingFinished | B1: Trud | C1: Mash | D1: Mat | E1: MatZak | F1: Oborud | G1: OborudZak | H1: ZeroStoim | I1: NegativeKoll | J1: ReUnionKollResurcy | K1: UnionOneUchRes | L1: IdLevel | M1: ViewCodes | N1: UnionCodes | O1: PEREVOZKA
A2: 1 | B2: 0 | C2: 0 | D2: 1 | E2: 1 | F2: 1 | G2: 1 | H2: 0 | I2: 0 | J2: 0 | K2: 1 | L2: 72192302 | M2: 0 | N2: 0 | O2: 0
A4: TYPE | B4: SOURCE_LINK | C4: RABMAT_EX | D4: TIP_RAB | E4: TYPE_TRUD | F4: TAB | G4: NAME | H4: EDIZM | I4: KOLL | J4: UCH | K4: PRICE_B | L4: PRICE_ED | M4: STOIM_B | N4: PRICE_C | O4: STOIM_C | P4: ZPM_B | Q4: ZPM_ED | R4: STOIM_ZPM_B | S4: ZPM_C | T4: STOIM_ZPM_C | U4: RABMAT | V4: WBS | W4: CBSI | X4: CBSII | Y4: TechSpecCVORPP | Z4: CRC_GR_RES | AA4: CRC_B | AB4: CRC_C
A6: =Source!A20 -> 3 | B6: 20 | G6: =Source!G20 -> Новая локальная смета
A7: =Source!A24 -> 4 | B7: 24 | G7: =Source!G24 -> 1. Спортзал №1
A8: =Source!A28 -> 5 | B8: 28 | G8: =Source!G28 -> 1.1 Демонтажные работы
A9: =Source!A73 -> 5 | B9: 73 | G9: =Source!G73 -> 1.2 Ремонтно-строительные работы
A10: =Source!A86 -> 18 | B10: 86 | C10: 3 | D10: =Source!BI86 -> 4 | E10: =Source!FS86 -> 0 | F10: =Source!F86 -> Цена поставщика | G10: =Source!G86 -> Шведская стенка деревянная с турником 1x3 м или эквивалент | H10: =Source!H86 -> шт. | I10: =Source!I86 -> 4 | J10: 1 | K10: =Source!AC86 -> 8545.05 | M10: =ROUND(K10*I10, 2) -> 34180.2 | N10: =Source!AC86*IF(Source!BC86<> 0, Source!BC86, 1) -> 8545.05 | O10: =ROUND(N10*I10, 2) -> 34180.2 | P10: =Source!AE86 -> 0 | R10: =ROUND(P10*I10, 2) -> 0 | S10: =Source!AE86*IF(Source!BS86<> 0, Source!BS86, 1) -> 0 | T10: =ROUND(S10*I10, 2) -> 0 | U10: 3 | Z10: =Source!GF86 -> 1111623754 | AA10: 290821961 | AB10: 290821961
A11: =Source!A118 -> 5 | B11: 118 | G11: =Source!G118 -> 1.3 Сантехнические работы
A12: =Source!A124 -> 18 | B12: 124 | C12: 3 | D12: =Source!BI124 -> 4 | E12: =Source!FS124 -> 0 | F12: =Source!F124 -> Цена поставщика | G12: =Source!G124 -> Радиатор Rifar Monolit 500/100 биметалл 10 секций или эквивалент | H12: =Source!H124 -> шт. | I12: =Source!I124 -> 26 | J12: 1 | K12: =Source!AC124 -> 12673.5 | M12: =ROUND(K12*I12, 2) -> 329511 | N12: =Source!AC124*IF(Source!BC124<> 0, Source!BC124, 1) -> 12673.5 | O12: =ROUND(N12*I12, 2) -> 329511 | P12: =Source!AE124 -> 0 | R12: =ROUND(P12*I12, 2) -> 0 | S12: =Source!AE124*IF(Source!BS124<> 0, Source!BS124, 1) -> 0 | T12: =ROUND(S12*I12, 2) -> 0 | U12: 3 | Z12: =Source!GF124 -> 195406401 | AA12: 549507648 | AB12: 549507648
A13: =Source!A126 -> 18 | B13: 126 | C13: 3 | D13: =Source!BI126 -> 4 | E13: =Source!FS126 -> 0 | F13: =Source!F126 -> 21.12-10-45 | G13: =Source!G126 -> Кронштейны для крепления отопительных приборов, марка КРД, длина 131 мм | H13: =Source!H126 -> шт. | I13: =Source!I126 -> 52 | J13: 1 | K13: =Source!AC126 -> 51.23 | M13: =ROUND(K13*I13, 2) -> 2663.96 | N13: =Source!AC126*IF(Source!BC126<> 0, Source!BC126, 1) -> 51.23 | O13: =ROUND(N13*I13, 2) -> 2663.96 | P13: =Source!AE126 -> 0 | R13: =ROUND(P13*I13, 2) -> 0 | S13: =Source!AE126*IF(Source!BS126<> 0, Source!BS126, 1) -> 0 | T13: =ROUND(S13*I13, 2) -> 0 | U13: 3 | Z13: =Source!GF126 -> 140294319 | AA13: 196322037 | AB13: 196322037
A14: =Source!A130 -> 18 | B14: 130 | C14: 3 | D14: =Source!BI130 -> 4 | E14: =Source!FS130 -> 0 | F14: =Source!F130 -> 21.3-4-19 | G14: =Source!G130 -> Арматурные заготовки (стержни, хомуты и т.п.), не собранные в каркасы или сетки, арматурная сталь периодического профиля, класс А-III, диаметр 20-22 мм | H14: =Source!H130 -> т | I14: =Source!I130 -> 0.0729 | J14: 1 | K14: =Source!AC130 -> 71207.52 | M14: =ROUND(K14*I14, 2) -> 5191.03 | N14: =Source!AC130*IF(Source!BC130<> 0, Source!BC130, 1) -> 71207.52 | O14: =ROUND(N14*I14, 2) -> 5191.03 | P14: =Source!AE130 -> 0 | R14: =ROUND(P14*I14, 2) -> 0 | S14: =Source!AE130*IF(Source!BS130<> 0, Source!BS130, 1) -> 0 | T14: =ROUND(S14*I14, 2) -> 0 | U14: 3 | Z14: =Source!GF130 -> 1622126655 | AA14: -1439171684 | AB14: -1439171684
A15: =Source!A132 -> 18 | B15: 132 | C15: 3 | D15: =Source!BI132 -> 4 | E15: =Source!FS132 -> 0 | F15: =Source!F132 -> 21.3-4-19 | G15: =Source!G132 -> Арматурные заготовки (стержни, хомуты и т.п.), не собранные в каркасы или сетки, арматурная сталь периодического профиля, класс А-III, диаметр 20-22 мм | H15: =Source!H132 -> т | I15: =Source!I132 -> 0.0405 | J15: 1 | K15: =Source!AC132 -> 71207.52 | M15: =ROUND(K15*I15, 2) -> 2883.9 | N15: =Source!AC132*IF(Source!BC132<> 0, Source!BC132, 1) -> 71207.52 | O15: =ROUND(N15*I15, 2) -> 2883.9 | P15: =Source!AE132 -> 0 | R15: =ROUND(P15*I15, 2) -> 0 | S15: =Source!AE132*IF(Source!BS132<> 0, Source!BS132, 1) -> 0 | T15: =ROUND(S15*I15, 2) -> 0 | U15: 3 | Z15: =Source!GF132 -> 1622126655 | AA15: -1439171684 | AB15: -1439171684
A16: =Source!A135 -> 18 | B16: 135 | C16: 3 | D16: =Source!BI135 -> 4 | E16: =Source!FS135 -> 0 | F16: =Source!F135 -> Цена поставщика | G16: =Source!G135 -> Кран шаровой Ду 20 Бугатти или эквивалент | H16: =Source!H135 -> шт. | I16: =Source!I135 -> 10 | J16: 1 | K16: =Source!AC135 -> 544 | M16: =ROUND(K16*I16, 2) -> 5440 | N16: =Source!AC135*IF(Source!BC135<> 0, Source!BC135, 1) -> 544 | O16: =ROUND(N16*I16, 2) -> 5440 | P16: =Source!AE135 -> 0 | R16: =ROUND(P16*I16, 2) -> 0 | S16: =Source!AE135*IF(Source!BS135<> 0, Source!BS135, 1) -> 0 | T16: =ROUND(S16*I16, 2) -> 0 | U16: 3 | Z16: =Source!GF135 -> 502732464 | AA16: 1765282897 | AB16: 1765282897
A17: =Source!A137 -> 18 | B17: 137 | C17: 3 | D17: =Source!BI137 -> 4 | E17: =Source!FS137 -> 0 | F17: =Source!F137 -> Цена поставщика | G17: =Source!G137 -> Кран шаровой Ду 25 Бугатти или эквивалент | H17: =Source!H137 -> шт. | I17: =Source!I137 -> 4 | J17: 1 | K17: =Source!AC137 -> 1471.35 | M17: =ROUND(K17*I17, 2) -> 5885.4 | N17: =Source!AC137*IF(Source!BC137<> 0, Source!BC137, 1) -> 1471.35 | O17: =ROUND(N17*I17, 2) -> 5885.4 | P17: =Source!AE137 -> 0 | R17: =ROUND(P17*I17, 2) -> 0 | S17: =Source!AE137*IF(Source!BS137<> 0, Source!BS137, 1) -> 0 | T17: =ROUND(S17*I17, 2) -> 0 | U17: 3 | Z17: =Source!GF137 -> 1738626795 | AA17: -1886084189 | AB17: -1886084189
A18: =Source!A170 -> 5 | B18: 170 | G18: =Source!G170 -> 1.4 Электромонтажные работы
A19: =Source!A179 -> 18 | B19: 179 | C19: 3 | D19: =Source!BI179 -> 4 | E19: =Source!FS179 -> 0 | F19: =Source!F179 -> 21.23-8-269 | G19: =Source!G179 -> Кабели силовые, с медными жилами, с изоляц. и оболоч.из ПВХ пластиката пониж.пожар.опасности, не распростр.горение, с пониж.дымо- и газовыделением и с низк.токсич-тью продуктов горения, напряж.1000 В, марка ВВГнг(А)-LSLTx, число жил и сечение, мм2: 3х1,5 | H19: =Source!H179 -> км | I19: =Source!I179 -> 0.0362 | J19: 1 | K19: =Source!AC179 -> 100115.51 | M19: =ROUND(K19*I19, 2) -> 3624.18 | N19: =Source!AC179*IF(Source!BC179<> 0, Source!BC179, 1) -> 100115.51 | O19: =ROUND(N19*I19, 2) -> 3624.18 | P19: =Source!AE179 -> 0 | R19: =ROUND(P19*I19, 2) -> 0 | S19: =Source!AE179*IF(Source!BS179<> 0, Source!BS179, 1) -> 0 | T19: =ROUND(S19*I19, 2) -> 0 | U19: 3 | Z19: =Source!GF179 -> 918109215 | AA19: 688701120 | AB19: 688701120
A20: =Source!A181 -> 18 | B20: 181 | C20: 3 | D20: =Source!BI181 -> 4 | E20: =Source!FS181 -> 0 | F20: =Source!F181 -> 21.21-5-24 | G20: =Source!G181 -> Выключатели, серия "Прима", напряжение 250 В, сила тока 6 А, тип: А16-051, одноклавишный, открытой установки | H20: =Source!H181 -> шт. | I20: =Source!I181 -> 1 | J20: 1 | K20: =Source!AC181 -> 39.99 | M20: =ROUND(K20*I20, 2) -> 39.99 | N20: =Source!AC181*IF(Source!BC181<> 0, Source!BC181, 1) -> 39.99 | O20: =ROUND(N20*I20, 2) -> 39.99 | P20: =Source!AE181 -> 0 | R20: =ROUND(P20*I20, 2) -> 0 | S20: =Source!AE181*IF(Source!BS181<> 0, Source!BS181, 1) -> 0 | T20: =ROUND(S20*I20, 2) -> 0 | U20: 3 | Z20: =Source!GF181 -> -1721790415 | AA20: -275146849 | AB20: -275146849
A21: =Source!A182 -> 18 | B21: 182 | C21: 3 | D21: =Source!BI182 -> 4 | E21: =Source!FS182 -> 0 | F21: =Source!F182 -> 21.21-5-25 | G21: =Source!G182 -> Выключатели серии "Прима", напряжение 250 В, сила тока 6 А, открытой установки двухклавишные, тип А56-029 | H21: =Source!H182 -> шт. | I21: =Source!I182 -> 1 | J21: 1 | K21: =Source!AC182 -> 102.63 | M21: =ROUND(K21*I21, 2) -> 102.63 | N21: =Source!AC182*IF(Source!BC182<> 0, Source!BC182, 1) -> 102.63 | O21: =ROUND(N21*I21, 2) -> 102.63 | P21: =Source!AE182 -> 0 | R21: =ROUND(P21*I21, 2) -> 0 | S21: =Source!AE182*IF(Source!BS182<> 0, Source!BS182, 1) -> 0 | T21: =ROUND(S21*I21, 2) -> 0 | U21: 3 | Z21: =Source!GF182 -> 154001895 | AA21: 598563480 | AB21: 598563480
A22: =Source!A184 -> 18 | B22: 184 | C22: 3 | D22: =Source!BI184 -> 4 | E22: =Source!FS184 -> 0 | F22: =Source!F184 -> Цена поставщика | G22: =Source!G184 -> Светильник светодиодный Geniled ЛПО 1200х180х40мм 40Вт 4000К Опал или эквивалент | H22: =Source!H184 -> шт. | I22: =Source!I184 -> 56 | J22: 1 | K22: =Source!AC184 -> 3323.5 | M22: =ROUND(K22*I22, 2) -> 186116 | N22: =Source!AC184*IF(Source!BC184<> 0, Source!BC184, 1) -> 3323.5 | O22: =ROUND(N22*I22, 2) -> 186116 | P22: =Source!AE184 -> 0 | R22: =ROUND(P22*I22, 2) -> 0 | S22: =Source!AE184*IF(Source!BS184<> 0, Source!BS184, 1) -> 0 | T22: =ROUND(S22*I22, 2) -> 0 | U22: 3 | Z22: =Source!GF184 -> -1650221762 | AA22: -915922714 | AB22: -915922714
A23: =Source!A185 -> 18 | B23: 185 | C23: 3 | D23: =Source!BI185 -> 4 | E23: =Source!FS185 -> 0 | F23: =Source!F185 -> Цена поставщика | G23: =Source!G185 -> Светильник светодиодный Geniled ЛПО 1200х180х40мм 40Вт 4000К Опал БАП или эквивалент | H23: =Source!H185 -> шт. | I23: =Source!I185 -> 8 | J23: 1 | K23: =Source!AC185 -> 5321 | M23: =ROUND(K23*I23, 2) -> 42568 | N23: =Source!AC185*IF(Source!BC185<> 0, Source!BC185, 1) -> 5321 | O23: =ROUND(N23*I23, 2) -> 42568 | P23: =Source!AE185 -> 0 | R23: =ROUND(P23*I23, 2) -> 0 | S23: =Source!AE185*IF(Source!BS185<> 0, Source!BS185, 1) -> 0 | T23: =ROUND(S23*I23, 2) -> 0 | U23: 3 | Z23: =Source!GF185 -> -1747291611 | AA23: -209616135 | AB23: -209616135
A24: =Source!A247 -> 4 | B24: 247 | G24: =Source!G247 -> 2. Тренерская
A25: =Source!A251 -> 5 | B25: 251 | G25: =Source!G251 -> 2.1 Тренерская
A26: =Source!A294 -> 5 | B26: 294 | G26: =Source!G294 -> 2.2 Ремонтно-строительные работы
A27: =Source!A336 -> 5 | B27: 336 | G27: =Source!G336 -> 2.3 Сантехнические работы
A28: =Source!A342 -> 18 | B28: 342 | C28: 3 | D28: =Source!BI342 -> 4 | E28: =Source!FS342 -> 0 | F28: =Source!F342 -> Цена поставщика | G28: =Source!G342 -> Радиатор Rifar Monolit 500/100 биметалл 10 секций или эквивалент | H28: =Source!H342 -> шт. | I28: =Source!I342 -> 3 | J28: 1 | K28: =Source!AC342 -> 12673.5 | M28: =ROUND(K28*I28, 2) -> 38020.5 | N28: =Source!AC342*IF(Source!BC342<> 0, Source!BC342, 1) -> 12673.5 | O28: =ROUND(N28*I28, 2) -> 38020.5 | P28: =Source!AE342 -> 0 | R28: =ROUND(P28*I28, 2) -> 0 | S28: =Source!AE342*IF(Source!BS342<> 0, Source!BS342, 1) -> 0 | T28: =ROUND(S28*I28, 2) -> 0 | U28: 3 | Z28: =Source!GF342 -> 195406401 | AA28: 549507648 | AB28: 549507648
A29: =Source!A344 -> 18 | B29: 344 | C29: 3 | D29: =Source!BI344 -> 4 | E29: =Source!FS344 -> 0 | F29: =Source!F344 -> 21.12-10-45 | G29: =Source!G344 -> Кронштейны для крепления отопительных приборов, марка КРД, длина 131 мм | H29: =Source!H344 -> шт. | I29: =Source!I344 -> 6 | J29: 1 | K29: =Source!AC344 -> 51.23 | M29: =ROUND(K29*I29, 2) -> 307.38 | N29: =Source!AC344*IF(Source!BC344<> 0, Source!BC344, 1) -> 51.23 | O29: =ROUND(N29*I29, 2) -> 307.38 | P29: =Source!AE344 -> 0 | R29: =ROUND(P29*I29, 2) -> 0 | S29: =Source!AE344*IF(Source!BS344<> 0, Source!BS344, 1) -> 0 | T29: =ROUND(S29*I29, 2) -> 0 | U29: 3 | Z29: =Source!GF344 -> 140294319 | AA29: 196322037 | AB29: 196322037
A30: =Source!A346 -> 18 | B30: 346 | C30: 3 | D30: =Source!BI346 -> 4 | E30: =Source!FS346 -> 0 | F30: =Source!F346 -> 21.3-4-19 | G30: =Source!G346 -> Арматурные заготовки (стержни, хомуты и т.п.), не собранные в каркасы или сетки, арматурная сталь периодического профиля, класс А-III, диаметр 20-22 мм | H30: =Source!H346 -> т | I30: =Source!I346 -> 0.02025 | J30: 1 | K30: =Source!AC346 -> 71207.52 | M30: =ROUND(K30*I30, 2) -> 1441.95 | N30: =Source!AC346*IF(Source!BC346<> 0, Source!BC346, 1) -> 71207.52 | O30: =ROUND(N30*I30, 2) -> 1441.95 | P30: =Source!AE346 -> 0 | R30: =ROUND(P30*I30, 2) -> 0 | S30: =Source!AE346*IF(Source!BS346<> 0, Source!BS346, 1) -> 0 | T30: =ROUND(S30*I30, 2) -> 0 | U30: 3 | Z30: =Source!GF346 -> 1622126655 | AA30: -1439171684 | AB30: -1439171684
A31: =Source!A349 -> 18 | B31: 349 | C31: 3 | D31: =Source!BI349 -> 4 | E31: =Source!FS349 -> 0 | F31: =Source!F349 -> Цена поставщика | G31: =Source!G349 -> Кран шаровой Ду 20 Бугатти или эквивалент | H31: =Source!H349 -> шт. | I31: =Source!I349 -> 7 | J31: 1 | K31: =Source!AC349 -> 544 | M31: =ROUND(K31*I31, 2) -> 3808 | N31: =Source!AC349*IF(Source!BC349<> 0, Source!BC349, 1) -> 544 | O31: =ROUND(N31*I31, 2) -> 3808 | P31: =Source!AE349 -> 0 | R31: =ROUND(P31*I31, 2) -> 0 | S31: =Source!AE349*IF(Source!BS349<> 0, Source!BS349, 1) -> 0 | T31: =ROUND(S31*I31, 2) -> 0 | U31: 3 | Z31: =Source!GF349 -> 502732464 | AA31: 1765282897 | AB31: 1765282897
A32: =Source!A381 -> 5 | B32: 381 | G32: =Source!G381 -> 2.4 Электромонтажные работы
A33: =Source!A387 -> 18 | B33: 387 | C33: 3 | D33: =Source!BI387 -> 4 | E33: =Source!FS387 -> 0 | F33: =Source!F387 -> 21.21-5-25 | G33: =Source!G387 -> Выключатели серии "Прима", напряжение 250 В, сила тока 6 А, открытой установки двухклавишные, тип А56-029 | H33: =Source!H387 -> шт. | I33: =Source!I387 -> 2 | J33: 1 | K33: =Source!AC387 -> 102.63 | M33: =ROUND(K33*I33, 2) -> 205.26 | N33: =Source!AC387*IF(Source!BC387<> 0, Source!BC387, 1) -> 102.63 | O33: =ROUND(N33*I33, 2) -> 205.26 | P33: =Source!AE387 -> 0 | R33: =ROUND(P33*I33, 2) -> 0 | S33: =Source!AE387*IF(Source!BS387<> 0, Source!BS387, 1) -> 0 | T33: =ROUND(S33*I33, 2) -> 0 | U33: 3 | Z33: =Source!GF387 -> 154001895 | AA33: 598563480 | AB33: 598563480
A34: =Source!A390 -> 18 | B34: 390 | C34: 3 | D34: =Source!BI390 -> 4 | E34: =Source!FS390 -> 0 | F34: =Source!F390 -> 21.23-8-269 | G34: =Source!G390 -> Кабели силовые, с медными жилами, с изоляц. и оболоч.из ПВХ пластиката пониж.пожар.опасности, не распростр.горение, с пониж.дымо- и газовыделением и с низк.токсич-тью продуктов горения, напряж.1000 В, марка ВВГнг(А)-LSLTx, число жил и сечение, мм2: 3х1,5 | H34: =Source!H390 -> км | I34: =Source!I390 -> 0.0102 | J34: 1 | K34: =Source!AC390 -> 100115.51 | M34: =ROUND(K34*I34, 2) -> 1021.18 | N34: =Source!AC390*IF(Source!BC390<> 0, Source!BC390, 1) -> 100115.51 | O34: =ROUND(N34*I34, 2) -> 1021.18 | P34: =Source!AE390 -> 0 | R34: =ROUND(P34*I34, 2) -> 0 | S34: =Source!AE390*IF(Source!BS390<> 0, Source!BS390, 1) -> 0 | T34: =ROUND(S34*I34, 2) -> 0 | U34: 3 | Z34: =Source!GF390 -> 918109215 | AA34: 688701120 | AB34: 688701120
A35: =Source!A392 -> 18 | B35: 392 | C35: 3 | D35: =Source!BI392 -> 4 | E35: =Source!FS392 -> 0 | F35: =Source!F392 -> Цена поставщика | G35: =Source!G392 -> Светильник GENILED офис, потребляемая мощность 40 Вт, световой поток 4000 Лм, цветовая температура 5000 К, степень защиты IP20, габаритные размеры 595х595х20 мм или эквивалент | H35: =Source!H392 -> шт. | I35: =Source!I392 -> 6 | J35: 1 | K35: =Source!AC392 -> 3570 | M35: =ROUND(K35*I35, 2) -> 21420 | N35: =Source!AC392*IF(Source!BC392<> 0, Source!BC392, 1) -> 3570 | O35: =ROUND(N35*I35, 2) -> 21420 | P35: =Source!AE392 -> 0 | R35: =ROUND(P35*I35, 2) -> 0 | S35: =Source!AE392*IF(Source!BS392<> 0, Source!BS392, 1) -> 0 | T35: =ROUND(S35*I35, 2) -> 0 | U35: 3 | Z35: =Source!GF392 -> 515220028 | AA35: -1554945508 | AB35: -1554945508
A36: =Source!A454 -> 4 | B36: 454 | G36: =Source!G454 -> 3. Вывоз мусора
A37: 999

Sheet Расчет стоимости ресурсов
A2: Ресурсная ведомость на
A3: =CONCATENATE("Объект: ",IF(Source!G522<>"Новый объект", Source!G522, "")) -> Объект: +Текущий ремонт спортзала №1 + раздевалки по адресу: г. Москва, ул. Митинская улица, д. 48, корп. 2 | O3: Объект: +Текущий ремонт спортзала №1 + раздевалки по адресу: г. Москва, ул. Митинская улица, д. 48, корп. 2
A4: Обоснование | B4: Наименование | C4: Единица измерения | D4: Объем | E4: Текущая
E6: цена | F6: стоимость
A7: 1 | B7: 2 | C7: 3 | D7: 4 | E7: 5 | F7: 6
A8: =CONCATENATE("Локальная смета: ",IF(Source!G22<>"Новая локальная смета", Source!G22, "")) -> Локальная смета:
A9: =CONCATENATE("Раздел: ",IF(Source!G26<>"Новый раздел", Source!G26, "")) -> Раздел: 1. Спортзал №1
A10: =CONCATENATE("Подраздел: ",IF(Source!G30<>"Новый подраздел", Source!G30, "")) -> Подраздел: 1.1 Демонтажные работы
A11: =CONCATENATE("Подраздел: ",IF(Source!G75<>"Новый подраздел", Source!G75, "")) -> Подраздел: 1.2 Ремонтно-строительные работы
A12: Материальные ресурсы
A13: Цена поставщика | B13: Шведская стенка деревянная с турником 1x3 м | C13: шт. | D13: =ROUND(SUMIF(RV_DATA!AB10:AB10, 290821961, RV_DATA!I10:I10), 6) -> 4 | E13: =ROUND(RV_DATA!N10, 6) -> 8545.05 | F13: =ROUND(SUMIF(RV_DATA!AB10:AB10, 290821961, RV_DATA!O10:O10), 6) -> 34180.2 | Q13: 3
A14: Итого материальные ресурсы | E14: =SUMIF(Q13:Q13, 3, F13:F13) -> 34180.2
A15: =CONCATENATE("Подраздел: ",IF(Source!G120<>"Новый подраздел", Source!G120, "")) -> Подраздел: 1.3 Сантехнические работы
A16: Материальные ресурсы
A17: 21.12-10-45 | B17: Кронштейны для крепления отопительных приборов, марка КРД, длина 131 мм | C17: шт. | D17: =ROUND(SUMIF(RV_DATA!AB12:AB17, 196322037, RV_DATA!I12:I17), 6) -> 52 | E17: =ROUND(RV_DATA!N13, 6) -> 51.23 | F17: =ROUND(SUMIF(RV_DATA!AB12:AB17, 196322037, RV_DATA!O12:O17), 6) -> 2663.96 | Q17: 3
A18: 21.3-4-19 | B18: Арматурные заготовки (стержни, хомуты и т.п.), не собранные в каркасы или сетки, арматурная сталь периодического профиля, класс А-III, диаметр 20-22 мм | C18: т | D18: =ROUND(SUMIF(RV_DATA!AB12:AB17, -1439171684, RV_DATA!I12:I17), 6) -> 0.1134 | E18: =ROUND(RV_DATA!N14, 6) -> 71207.52 | F18: =ROUND(SUMIF(RV_DATA!AB12:AB17, -1439171684, RV_DATA!O12:O17), 6) -> 8074.93 | Q18: 3
A19: Цена поставщика | B19: Радиатор Rifar Monolit 500/100 биметалл 10 секций | C19: шт. | D19: =ROUND(SUMIF(RV_DATA!AB12:AB17, 549507648, RV_DATA!I12:I17), 6) -> 26 | E19: =ROUND(RV_DATA!N12, 6) -> 12673.5 | F19: =ROUND(SUMIF(RV_DATA!AB12:AB17, 549507648, RV_DATA!O12:O17), 6) -> 329511 | Q19: 3
A20: Цена поставщика | B20: Кран шаровой Ду 20 Бугатти | C20: шт. | D20: =ROUND(SUMIF(RV_DATA!AB12:AB17, 1765282897, RV_DATA!I12:I17), 6) -> 10 | E20: =ROUND(RV_DATA!N16, 6) -> 544 | F20: =ROUND(SUMIF(RV_DATA!AB12:AB17, 1765282897, RV_DATA!O12:O17), 6) -> 5440 | Q20: 3
A21: Цена поставщика | B21: Кран шаровой Ду 25 Бугатти | C21: шт. | D21: =ROUND(SUMIF(RV_DATA!AB12:AB17, -1886084189, RV_DATA!I12:I17), 6) -> 4 | E21: =ROUND(RV_DATA!N17, 6) -> 1471.35 | F21: =ROUND(SUMIF(RV_DATA!AB12:AB17, -1886084189, RV_DATA!O12:O17), 6) -> 5885.4 | Q21: 3
A22: Итого материальные ресурсы | E22: =SUMIF(Q17:Q21, 3, F17:F21) -> 351575.29
A23: =CONCATENATE("Подраздел: ",IF(Source!G172<>"Новый подраздел", Source!G172, "")) -> Подраздел: 1.4 Электромонтажные работы
A24: Материальные ресурсы
A25: 21.21-5-24 | B25: Выключатели, серия "Прима", напряжение 250 В, сила тока 6 А, тип: А16-051, одноклавишный, открытой установки | C25: шт. | D25: =ROUND(SUMIF(RV_DATA!AB19:AB23, -275146849, RV_DATA!I19:I23), 6) -> 1 | E25: =ROUND(RV_DATA!N20, 6) -> 39.99 | F25: =ROUND(SUMIF(RV_DATA!AB19:AB23, -275146849, RV_DATA!O19:O23), 6) -> 39.99 | Q25: 3
A26: 21.21-5-25 | B26: Выключатели серии "Прима", напряжение 250 В, сила тока 6 А, открытой установки двухклавишные, тип А56-029 | C26: шт. | D26: =ROUND(SUMIF(RV_DATA!AB19:AB23, 598563480, RV_DATA!I19:I23), 6) -> 1 | E26: =ROUND(RV_DATA!N21, 6) -> 102.63 | F26: =ROUND(SUMIF(RV_DATA!AB19:AB23, 598563480, RV_DATA!O19:O23), 6) -> 102.63 | Q26: 3
A27: 21.23-8-269 | B27: Кабели силовые, с медными жилами, с изоляц. и оболоч.из ПВХ пластиката пониж.пожар.опасности, не распростр.горение, с пониж.дымо- и газовыделением и с низк.токсич-тью продуктов горения, напряж.1000 В, марка ВВГнг(А)-LSLTx, число жил и сечение, мм2: 3х1,5 | C27: км | D27: =ROUND(SUMIF(RV_DATA!AB19:AB23, 688701120, RV_DATA!I19:I23), 6) -> 0.0362 | E27: =ROUND(RV_DATA!N19, 6) -> 100115.51 | F27: =ROUND(SUMIF(RV_DATA!AB19:AB23, 688701120, RV_DATA!O19:O23), 6) -> 3624.18 | Q27: 3
A28: Цена поставщика | B28: Светильник светодиодный Geniled ЛПО 1200х180х40мм 40Вт 4000К Опал | C28: шт. | D28: =ROUND(SUMIF(RV_DATA!AB19:AB23, -915922714, RV_DATA!I19:I23), 6) -> 56 | E28: =ROUND(RV_DATA!N22, 6) -> 3323.5 | F28: =ROUND(SUMIF(RV_DATA!AB19:AB23, -915922714, RV_DATA!O19:O23), 6) -> 186116 | Q28: 3
A29: Цена поставщика | B29: Светильник светодиодный Geniled ЛПО 1200х180х40мм 40Вт 4000К Опал БАП | C29: шт. | D29: =ROUND(SUMIF(RV_DATA!AB19:AB23, -209616135, RV_DATA!I19:I23), 6) -> 8 | E29: =ROUND(RV_DATA!N23, 6) -> 5321 | F29: =ROUND(SUMIF(RV_DATA!AB19:AB23, -209616135, RV_DATA!O19:O23), 6) -> 42568 | Q29: 3
A30: Итого материальные ресурсы | E30: =SUMIF(Q25:Q29, 3, F25:F29) -> 232450.8
A31: =CONCATENATE("Раздел: ",IF(Source!G249<>"Новый раздел", Source!G249, "")) -> Раздел: 2. Тренерская
A32: =CONCATENATE("Подраздел: ",IF(Source!G253<>"Новый подраздел", Source!G253, "")) -> Подраздел: 2.1 Тренерская
A33: =CONCATENATE("Подраздел: ",IF(Source!G296<>"Новый подраздел", Source!G296, "")) -> Подраздел: 2.2 Ремонтно-строительные работы
A34: =CONCATENATE("Подраздел: ",IF(Source!G338<>"Новый подраздел", Source!G338, "")) -> Подраздел: 2.3 Сантехнические работы
A35: Материальные ресурсы
A36: 21.12-10-45 | B36: Кронштейны для крепления отопительных приборов, марка КРД, длина 131 мм | C36: шт. | D36: =ROUND(SUMIF(RV_DATA!AB28:AB31, 196322037, RV_DATA!I28:I31), 6) -> 6 | E36: =ROUND(RV_DATA!N29, 6) -> 51.23 | F36: =ROUND(SUMIF(RV_DATA!AB28:AB31, 196322037, RV_DATA!O28:O31), 6) -> 307.38 | Q36: 3
A37: 21.3-4-19 | B37: Арматурные заготовки (стержни, хомуты и т.п.), не собранные в каркасы или сетки, арматурная сталь периодического профиля, класс А-III, диаметр 20-22 мм | C37: т | D37: =ROUND(SUMIF(RV_DATA!AB28:AB31, -1439171684, RV_DATA!I28:I31), 6) -> 0.02025 | E37: =ROUND(RV_DATA!N30, 6) -> 71207.52 | F37: =ROUND(SUMIF(RV_DATA!AB28:AB31, -1439171684, RV_DATA!O28:O31), 6) -> 1441.95 | Q37: 3
A38: Цена поставщика | B38: Радиатор Rifar Monolit 500/100 биметалл 10 секций | C38: шт. | D38: =ROUND(SUMIF(RV_DATA!AB28:AB31, 549507648, RV_DATA!I28:I31), 6) -> 3 | E38: =ROUND(RV_DATA!N28, 6) -> 12673.5 | F38: =ROUND(SUMIF(RV_DATA!AB28:AB31, 549507648, RV_DATA!O28:O31), 6) -> 38020.5 | Q38: 3
A39: Цена поставщика | B39: Кран шаровой Ду 20 Бугатти | C39: шт. | D39: =ROUND(SUMIF(RV_DATA!AB28:AB31, 1765282897, RV_DATA!I28:I31), 6) -> 7 | E39: =ROUND(RV_DATA!N31, 6) -> 544 | F39: =ROUND(SUMIF(RV_DATA!AB28:AB31, 1765282897, RV_DATA!O28:O31), 6) -> 3808 | Q39: 3
A40: Итого материальные ресурсы | E40: =SUMIF(Q36:Q39, 3, F36:F39) -> 43577.83
A41: =CONCATENATE("Подраздел: ",IF(Source!G383<>"Новый подраздел", Source!G383, "")) -> Подраздел: 2.4 Электромонтажные работы
A42: Материальные ресурсы
A43: 21.21-5-25 | B43: Выключатели серии "Прима", напряжение 250 В, сила тока 6 А, открытой установки двухклавишные, тип А56-029 | C43: шт. | D43: =ROUND(SUMIF(RV_DATA!AB33:AB35, 598563480, RV_DATA!I33:I35), 6) -> 2 | E43: =ROUND(RV_DATA!N33, 6) -> 102.63 | F43: =ROUND(SUMIF(RV_DATA!AB33:AB35, 598563480, RV_DATA!O33:O35), 6) -> 205.26 | Q43: 3
A44: 21.23-8-269 | B44: Кабели силовые, с медными жилами, с изоляц. и оболоч.из ПВХ пластиката пониж.пожар.опасности, не распростр.горение, с пониж.дымо- и газовыделением и с низк.токсич-тью продуктов горения, напряж.1000 В, марка ВВГнг(А)-LSLTx, число жил и сечение, мм2: 3х1,5 | C44: км | D44: =ROUND(SUMIF(RV_DATA!AB33:AB35, 688701120, RV_DATA!I33:I35), 6) -> 0.0102 | E44: =ROUND(RV_DATA!N34, 6) -> 100115.51 | F44: =ROUND(SUMIF(RV_DATA!AB33:AB35, 688701120, RV_DATA!O33:O35), 6) -> 1021.18 | Q44: 3
A45: Цена поставщика | B45: Светильник GENILED офис, потребляемая мощность 40 Вт, световой поток 4000 Лм, цветовая температура 5000 К, степень защиты IP20, габаритные размеры 595х595х20 мм | C45: шт. | D45: =ROUND(SUMIF(RV_DATA!AB33:AB35, -1554945508, RV_DATA!I33:I35), 6) -> 6 | E45: =ROUND(RV_DATA!N35, 6) -> 3570 | F45: =ROUND(SUMIF(RV_DATA!AB33:AB35, -1554945508, RV_DATA!O33:O35), 6) -> 21420 | Q45: 3
A46: Итого материальные ресурсы | E46: =SUMIF(Q43:Q45, 3, F43:F45) -> 22646.44
A47: =CONCATENATE("Раздел: ",IF(Source!G456<>"Новый раздел", Source!G456, "")) -> Раздел: 3. Вывоз мусора

Sheet Source
A1: 0 | B1: Smeta.RU Flash (495) 974-1589 | D1: _PS_ | F1: 0 | G1: 0 | H1: 0 | I1: Smeta.RU Flash | K1: 1 | L1: 62169 | M1: 10 | N1: 11 | O1: 8 | P1: 0 | Q1: 0
A12: 1 | B12: 581 | C12: 0 | D12: =ROW(A522) -> 522 | E12: 0 | F12: Новый объект | G12: +Текущий ремонт спортзала №1 + раздевалки по адресу: г. Москва, ул. Митинская улица, д. 48, корп. 2 | I12: 0 | K12: 0 | L12: 0 | M12: 2 | O12: 0 | P12: 0 | Q12: 0 | R12: 108 | T12: 1 | V12: 0 | BB12: 0 | BH12: Сметные нормы списания | BI12: Коды ОКП для СН-2012 - 2024 г. (в ценах на 01.01.2024 г) | BJ12: 1 | BK12: 1 | BL12: 0 | BM12: 0 | BN12: 1 | BO12: 0 | BP12: 6 | BQ12: 2 | BR12: 1 | BS12: 1 | BT12: 1 | BU12: 0 | BV12: 1 | BW12: 0 | BX12: 0 | BY12: СН-2012 - 2024 г. (в ценах на 01.01.2024 г)_глава_1-5 | BZ12: Типовой расчет для СН-2012 - 2024 г. (в ценах на 01.01.2024 г) И0 | CA12: СН-2012-2024 г. База данных "Сборник стоимостных нормативов" (в ценах на 01.01.2024 г) | CB12: СН-2012-2024 г. База данных "Сборник стоимостных нормативов" (в ценах на 01.01.2024 г) | CC12: СН-2012-2024 г. База данных "Сборник стоимостных нормативов" (в ценах на 01.01.2024 г) | CD12: СН-2012-2024 г. База данных "Сборник стоимостных нормативов" (в ценах на 01.01.2024 г) | CE12: Поправки для СН-2012-2024 в ценах на 01.01.2024 г И0 (05.03.2024) | CF12: 0 | CG12: 0 | CH12: 8 | CK12: 0 | CY12: 0 | EC12: 0
A15: 15 | B15: 1
A18: 52 | B18: =B522 -> 581 | C18: =C522 -> 1 | D18: =D522 -> 12 | E18: =E522 -> 0 | F18: =F522 -> Новый объект | G18: =G522 -> +Текущий ремонт спортзала №1 + раздевалки по адресу: г. Москва, ул. Митинская улица, д. 48, корп. 2 | O18: =O522 -> 1626320.4 | P18: =P522 -> 1011274.7 | Q18: =Q522 -> 23758.01 | R18: =R522 -> 18629.83 | S18: =S522 -> 591287.74 | T18: =T522 -> 0 | U18: =U522 -> 1979.8973 | V18: =V522 -> 0 | ... GX18: =GX522 -> 0
A20: 3 | B20: 1 | D20: =ROW(A492) -> 492 | F20: Новая локальная смета | G20: Новая локальная смета | I20: 0 | K20: 0 | S20: 0 | V20: 0 | BX20: 0 | CF20: 0 | CG20: 0
A22: 52 | B22: =B492 -> 1 | C22: =C492 -> 3 | D22: =D492 -> 20 | E22: =E492 -> 0 | F22: =F492 -> Новая локальная смета | G22: =G492 -> Новая локальная смета | O22: =O492 -> 1626320.4 | P22: =P492 -> 1011274.7 | Q22: =Q492 -> 23758.01 | R22: =R492 -> 18629.83 | S22: =S492 -> 591287.74 | T22: =T492 -> 0 | U22: =U492 -> 1979.8973 | V22: =V492 -> 0 | ... GX22: =GX492 -> 0
A24: 4 | B24: 1 | D24: =ROW(A217) -> 217 | F24: Новый раздел | G24: 1. Спортзал №1 | I24: 0 | K24: -1 | S24: 0 | V24: 0 | BX24: 0 | CJ24: 0
A26: 52 | B26: =B217 -> 1 | C26: =C217 -> 4 | D26: =D217 -> 24 | E26: =E217 -> 0 | F26: =F217 -> Новый раздел | G26: =G217 -> 1. Спортзал №1 | O26: =O217 -> 1324696.3 | P26: =P217 -> 823257.85 | Q26: =Q217 -> 18608.83 | R26: =R217 -> 15938.48 | S26: =S217 -> 482829.6 | T26: =T217 -> 0 | U26: =U217 -> 1632.4503 | V26: =V217 -> 0 | ... GX26: =GX217 -> 0
A28: 5 | B28: 1 | D28: =ROW(A43) -> 43 | F28: Новый подраздел | G28: 1.1 Демонтажные работы | I28: 0 | K28: -1 | S28: 0 | V28: 0 | BX28: 0 | CJ28: 0
A30: 52 | B30: =B43 -> 1 | C30: =C43 -> 5 | D30: =D43 -> 28 | E30: =E43 -> 0 | F30: =F43 -> Новый подраздел | G30: =G43 -> 1.1 Демонтажные работы | O30: =O43 -> 84927.54 | P30: =P43 -> 1294.22 | Q30: =Q43 -> 2276.91 | R30: =R43 -> 1683.29 | S30: =S43 -> 81356.41 | T30: =T43 -> 0 | U30: =U43 -> 318.20593 | V30: =V43 -> 0 | ... GX30: =GX43 -> 0
A32: 17 | B32: 1 | D32: =ROW(EtalonRes!A2) -> 2 | E32: 1 | F32: 1.1-3404-4-2/1 | G32: Разборка плинтусов поливинилхлоридных с креплением шурупами | H32: 100 м | I32: 0.6504 | J32: 0 | K32: 0.6504 | O32: =ROUND(CP32,2) -> 456.13 | P32: =ROUND(CQ32*I32,2) -> 0 | Q32: =ROUND(CR32*I32,2) -> 1.16 | R32: =ROUND(CS32*I32,2) -> 0 | S32: =ROUND(CT32*I32,2) -> 454.97 | T32: =ROUND(CU32*I32,2) -> 0 | U32: =CV32*I32 -> 1.808112 | V32: =CW32*I32 -> 0 | W32: =ROUND(CX32*I32,2) -> 0 | X32: =ROUND(CY32,2) -> 318.48 | Y32: =ROUND(CZ32,2) -> 45.5 | AA32: 72192302 | AB32: =ROUND((AC32+AD32+AF32),6) -> 701.32 | AC32: =ROUND((ES32),6) -> 0 | AD32: =ROUND((((ET32)-(EU32))+AE32),6) -> 1.79 | AE32: =ROUND((EU32),6) -> 0 | AF32: =ROUND((EV32),6) -> 699.53 | AG32: =ROUND((AP32),6) -> 0 | AH32: =(EW32) -> 2.78 | AI32: =(EX32) -> 0 | AJ32: =(AS32) -> 0 | AK32: 701.32 | AL32: 0 | AM32: 1.79 | AN32: 0 | AO32: 699.53 | AP32: 0 | AQ32: 2.78 | AR32: 0 | AS32: 0 | AT32: 70 | AU32: 10 | AV32: 1 | AW32: 1 | AZ32: 1 | BA32: 1 | BB32: 1 | BC32: 1 | BH32: 0 | BI32: 4 | BJ32: СН-2012-2024.1. База. Сб.10-3404-4-2/1 | BM32: 0 | BN32: 0 | BP32: 0 | BQ32: 1 | BR32: 0 | BS32: 1 | BT32: 1 | BU32: 1 | BV32: 1 | BW32: 1 | BX32: 1 | BZ32: 70 | CA32: 10 | CE32: 0 | CF32: 0 | CG32: 0 | CM32: 0 | CO32: 0 | CP32: =(P32+Q32+S32) -> 456.13 | CQ32: =(AC32*BC32*AW32) -> 0 | CR32: =((((ET32)*BB32-(EU32)*BS32)+AE32*BS32)*AV32) -> 1.79 | CS32: =(AE32*BS32*AV32) -> 0 | CT32: =(AF32*BA32*AV32) -> 699.53 | CU32: =AG32 -> 0 | CV32: =(AH32*AV32) -> 2.78 | CW32: =AI32 -> 0 | CX32: =AJ32 -> 0 | CY32: =((S32*BZ32)/100) -> 318.479 | CZ32: =((S32*CA32)/100) -> 45.497 | DN32: 0 | DO32: 0 | DP32: 1 | DQ32: 1 | DU32: 1003 | DV32: 100 м | DW32: 100 м | DX32: 100 | EE32: 71753531 | EF32: 1 | EG32: СН-2012 | EH32: 0 | EJ32: 4 | EK32: 0 | EL32: Подрядные работы, гл. 1-5,7 | EM32: работа | EQ32: 0 | ER32: 701.32 | ES32: 0 | ET32: 1.79 | EU32: 0 | EV32: 699.53 | EW32: 2.78 | EX32: 0 | EY32: 0 | FQ32: 0 | FR32: =ROUND(IF(BI32=3,GM32,0),2) -> 0 | FS32: 0 | FX32: 70 | FY32: 10 | GD32: 0 | GF32: -1249124778 | GG32: 2 | GH32: 1 | GI32: -2 | GJ32: 0 | GK32: =ROUND(R32*(R12)/100,2) -> 0 | GL32: =ROUND(IF(AND(BH32=3,BI32=3,FS32<>0),P32,0),2) -> 0 | GM32: =ROUND(O32+X32+Y32+GK32,2)+GX32 -> 820.11 | GN32: =IF(OR(BI32=0,BI32=1),GM32,0) -> 0 | GO32: =IF(BI32=2,GM32,0) -> 0 | GP32: =IF(BI32=4,GM32+GX32,0) -> 820.11 | GR32: 0 | GS32: 3 | GT32: 0 | GV32: =ROUND((GT32),6) -> 0 | GW32: 1 | GX32: =ROUND(HC32*I32,2) -> 0 | HA32: 0 | HB32: 0 | HC32: =GV32*GW32 -> 0 | IK32: 0
A33: 17 | B33: 1 | D33: =ROW(EtalonRes!A3) -> 3 | E33: 2 | F33: 1.3-3204-1-1/1 | G33: Расчистка поверхностей от старых покрасок (шпателем, щетками и т.д.) | H33: м2 | I33: =ROUND(283.2+118.77,9) -> 401.97 | J33: 0 | K33: =ROUND(283.2+118.77,9) -> 401.97 | O33: =ROUND(CP33,2) -> 59797.06 | P33: =ROUND(CQ33*I33,2) -> 0 | Q33: =ROUND(CR33*I33,2) -> 0 | R33: =ROUND(CS33*I33,2) -> 0 | S33: =ROUND(CT33*I33,2) -> 59797.06 | T33: =ROUND(CU33*I33,2) -> 0 | U33: =CV33*I33 -> 241.182 | V33: =CW33*I33 -> 0 | W33: =ROUND(CX33*I33,2) -> 0 | X33: =ROUND(CY33,2) -> 41857.94 | Y33: =ROUND(CZ33,2) -> 5979.71 | AA33: 72192302 | AB33: =ROUND((AC33+AD33+AF33),6) -> 148.76 | AC33: =ROUND((ES33),6) -> 0 | AD33: =ROUND((((ET33)-(EU33))+AE33),6) -> 0 | AE33: =ROUND((EU33),6) -> 0 | AF33: =ROUND((EV33),6) -> 148.76 | AG33: =ROUND((AP33),6) -> 0 | AH33: =(EW33) -> 0.6 | AI33: =(EX33) -> 0 | AJ33: =(AS33) -> 0 | AK33: 148.76 | AL33: 0 | AM33: 0 | AN33: 0 | AO33: 148.76 | AP33: 0 | AQ33: 0.6 | AR33: 0 | AS33: 0 | AT33: 70 | AU33: 10 | AV33: 1 | AW33: 1 | AZ33: 1 | BA33: 1 | BB33: 1 | BC33: 1 | BH33: 0 | BI33: 4 | BJ33: СН-2012-2024.1. База. Сб.13-3204-1-1/1 | BM33: 0 | BN33: 0 | BP33: 0 | BQ33: 1 | BR33: 0 | BS33: 1 | BT33: 1 | BU33: 1 | BV33: 1 | BW33: 1 | BX33: 1 | BZ33: 70 | CA33: 10 | CE33: 0 | CF33: 0 | CG33: 0 | CM33: 0 | CO33: 0 | CP33: =(P33+Q33+S33) -> 59797.06 | CQ33: =(AC33*BC33*AW33) -> 0 | CR33: =((((ET33)*BB33-(EU33)*BS33)+AE33*BS33)*AV33) -> 0 | CS33: =(AE33*BS33*AV33) -> 0 | CT33: =(AF33*BA33*AV33) -> 148.76 | CU33: =AG33 -> 0 | CV33: =(AH33*AV33) -> 0.6 | CW33: =AI33 -> 0 | CX33: =AJ33 -> 0 | CY33: =((S33*BZ33)/100) -> 41857.942 | CZ33: =((S33*CA33)/100) -> 5979.706 | DN33: 0 | DO33: 0 | DP33: 1 | DQ33: 1 | DU33: 1005 | DV33: м2 | DW33: м2 | DX33: 1 | EE33: 71753531 | EF33: 1 | EG33: СН-2012 | EH33: 0 | EJ33: 4 | EK33: 0 | EL33: Подрядные работы, гл. 1-5,7 | EM33: работа | EQ33: 0 | ER33: 148.76 | ES33: 0 | ET33: 0 | EU33: 0 | EV33: 148.76 | EW33: 0.6 | EX33: 0 | EY33: 0 | FQ33: 0 | FR33: =ROUND(IF(BI33=3,GM33,0),2) -> 0 | FS33: 0 | FX33: 70 | FY33: 10 | GD33: 0 | GF33: -1536673318 | GG33: 2 | GH33: 1 | GI33: -2 | GJ33: 0 | GK33: =ROUND(R33*(R12)/100,2) -> 0 | GL33: =ROUND(IF(AND(BH33=3,BI33=3,FS33<>0),P33,0),2) -> 0 | GM33: =ROUND(O33+X33+Y33+GK33,2)+GX33 -> 107634.71 | GN33: =IF(OR(BI33=0,BI33=1),GM33,0) -> 0 | GO33: =IF(BI33=2,GM33,0) -> 0 | GP33: =IF(BI33=4,GM33+GX33,0) -> 107634.71 | GR33: 0 | GS33: 3 | GT33: 0 | GV33: =ROUND((GT33),6) -> 0 | GW33: 1 | GX33: =ROUND(HC33*I33,2) -> 0 | HA33: 0 | HB33: 0 | HC33: =GV33*GW33 -> 0 | IK33: 0
A34: 17 | B34: 1 | D34: =ROW(EtalonRes!A5) -> 5 | E34: 3 | F34: 1.1-3304-1-1/1 | G34: Демонтаж радиатора массой до 80 кг | H34: 100 шт. | I34: 0.26 | J34: 0 | K34: 0.26 | O34: =ROUND(CP34,2) -> 8234.34 | P34: =ROUND(CQ34*I34,2) -> 0 | Q34: =ROUND(CR34*I34,2) -> 0 | R34: =ROUND(CS34*I34,2) -> 0 | S34: =ROUND(CT34*I34,2) -> 8234.34 | T34: =ROUND(CU34*I34,2) -> 0 | U34: =CV34*I34 -> 31.3534 | V34: =CW34*I34 -> 0 | W34: =ROUND(CX34*I34,2) -> 0 | X34: =ROUND(CY34,2) -> 5764.04 | Y34: =ROUND(CZ34,2) -> 823.43 | AA34: 72192302 | AB34: =ROUND((AC34+AD34+AF34),6) -> 31670.55 | AC34: =ROUND((ES34),6) -> 0 | AD34: =ROUND((((ET34)-(EU34))+AE34),6) -> 0 | AE34: =ROUND((EU34),6) -> 0 | AF34: =ROUND((EV34),6) -> 31670.55 | AG34: =ROUND((AP34),6) -> 0 | AH34: =(EW34) -> 120.59 | AI34: =(EX34) -> 0 | AJ34: =(AS34) -> 0 | AK34: 31670.55 | AL34: 0 | AM34: 0 | AN34: 0 | AO34: 31670.55 | AP34: 0 | AQ34: 120.59 | AR34: 0 | AS34: 0 | AT34: 70 | AU34: 10 | AV34: 1 | AW34: 1 | AZ34: 1 | BA34: 1 | BB34: 1 | BC34: 1 | BH34: 0 | BI34: 4 | BJ34: СН-2012-2024.1. База. Сб.17-3304-1-1/1 | BM34: 0 | BN34: 0 | BP34: 0 | BQ34: 1 | BR34: 0 | BS34: 1 | BT34: 1 | BU34: 1 | BV34: 1 | BW34: 1 | BX34: 1 | BZ34: 70 | CA34: 10 | CE34: 0 | CF34: 0 | CG34: 0 | CM34: 0 | CO34: 0 | CP34: =(P34+Q34+S34) -> 8234.34 | CQ34: =(AC34*BC34*AW34) -> 0 | CR34: =((((ET34)*BB34-(EU34)*BS34)+AE34*BS34)*AV34) -> 0 | CS34: =(AE34*BS34*AV34) -> 0 | CT34: =(AF34*BA34*AV34) -> 31670.55 | CU34: =AG34 -> 0 | CV34: =(AH34*AV34) -> 120.59 | CW34: =AI34 -> 0 | CX34: =AJ34 -> 0 | CY34: =((S34*BZ34)/100) -> 5764.038 | CZ34: =((S34*CA34)/100) -> 823.434 | DN34: 0 | DO34: 0 | DP34: 1 | DQ34: 1 | DU34: 1010 | DV34: 100 шт. | DW34: 100 шт. | DX34: 100 | EE34: 71753531 | EF34: 1 | EG34: СН-2012 | EH34: 0 | EJ34: 4 | EK34: 0 | EL34: Подрядные работы, гл. 1-5,7 | EM34: работа | EQ34: 0 | ER34: 31670.55 | ES34: 0 | ET34: 0 | EU34: 0 | EV34: 31670.55 | EW34: 120.59 | EX34: 0 | EY34: 0 | FQ34: 0 | FR34: =ROUND(IF(BI34=3,GM34,0),2) -> 0 | FS34: 0 | FX34: 70 | FY34: 10 | GD34: 0 | GF34: 1879916655 | GG34: 2 | GH34: 1 | GI34: -2 | GJ34: 0 | GK34: =ROUND(R34*(R12)/100,2) -> 0 | GL34: =ROUND(IF(AND(BH34=3,BI34=3,FS34<>0),P34,0),2) -> 0 | GM34: =ROUND(O34+X34+Y34+GK34,2)+GX34 -> 14821.81 | GN34: =IF(OR(BI34=0,BI34=1),GM34,0) -> 0 | GO34: =IF(BI34=2,GM34,0) -> 0 | GP34: =IF(BI34=4,GM34+GX34,0) -> 14821.81 | GR34: 0 | GS34: 3 | GT34: 0 | GV34: =ROUND((GT34),6) -> 0 | GW34: 1 | GX34: =ROUND(HC34*I34,2) -> 0 | HA34: 0 | HB34: 0 | HC34: =GV34*GW34 -> 0 | IK34: 0
A35: 18 | B35: 1 | E35: 4 | F35: 9999990001 | G35: Масса мусора | H35: т | I35: =I34*J35 -> -2.08 | J35: -8 | K35: -8 | O35: =ROUND(CP35,2) -> 0 | P35: =ROUND(CQ35*I35,2) -> 0 | Q35: =ROUND(CR35*I35,2) -> 0 | R35: =ROUND(CS35*I35,2) -> 0 | S35: =ROUND(CT35*I35,2) -> 0 | T35: =ROUND(CU35*I35,2) -> 0 | U35: =CV35*I35 -> 0 | V35: =CW35*I35 -> 0 | W35: =ROUND(CX35*I35,2) -> 0 | X35: =ROUND(CY35,2) -> 0 | Y35: =ROUND(CZ35,2) -> 0 | AA35: 72192302 | AB35: =ROUND((AC35+AD35+AF35),6) -> 0 | AC35: =ROUND((ES35),6) -> 0 | AD35: =ROUND((((ET35)-(EU35))+AE35),6) -> 0 | AE35: =ROUND((EU35),6) -> 0 | AF35: =ROUND((EV35),6) -> 0 | AG35: =ROUND((AP35),6) -> 0 | AH35: =(EW35) -> 0 | AI35: =(EX35) -> 0 | AJ35: =(AS35) -> 0 | AK35: 0 | AL35: 0 | AM35: 0 | AN35: 0 | AO35: 0 | AP35: 0 | AQ35: 0 | AR35: 0 | AS35: 0 | AT35: 70 | AU35: 10 | AV35: 1 | AW35: 1 | AZ35: 1 | BA35: 1 | BB35: 1 | BC35: 1 | BH35: 3 | BI35: 4 | BM35: 0 | BN35: 0 | BP35: 0 | BQ35: 1 | BR35: 1 | BS35: 1 | BT35: 1 | BU35: 1 | BV35: 1 | BW35: 1 | BX35: 1 | BZ35: 70 | CA35: 10 | CE35: 0 | CF35: 0 | CG35: 0 | CM35: 0 | CO35: 0 | CP35: =(P35+Q35+S35) -> 0 | CQ35: =(AC35*BC35*AW35) -> 0 | CR35: =((((ET35)*BB35-(EU35)*BS35)+AE35*BS35)*AV35) -> 0 | CS35: =(AE35*BS35*AV35) -> 0 | CT35: =(AF35*BA35*AV35) -> 0 | CU35: =AG35 -> 0 | CV35: =(AH35*AV35) -> 0 | CW35: =AI35 -> 0 | CX35: =AJ35 -> 0 | CY35: =((S35*BZ35)/100) -> 0 | CZ35: =((S35*CA35)/100) -> 0 | DN35: 0 | DO35: 0 | DP35: 1 | DQ35: 1 | DU35: 1009 | DV35: т | DW35: т | DX35: 1000 | EE35: 71753531 | EF35: 1 | EG35: СН-2012 | EH35: 0 | EJ35: 4 | EK35: 0 | EL35: Подрядные работы, гл. 1-5,7 | EM35: работа | EQ35: 0 | ER35: 0 | ES35: 0 | ET35: 0 | EU35: 0 | EV35: 0 | EW35: 0 | EX35: 0 | FQ35: 0 | FR35: =ROUND(IF(BI35=3,GM35,0),2) -> 0 | FS35: 0 | FX35: 70 | FY35: 10 | GD35: 0 | GF35: 1489638031 | GG35: 2 | GH35: 1 | GI35: -2 | GJ35: 0 | GK35: =ROUND(R35*(R12)/100,2) -> 0 | GL35: =ROUND(IF(AND(BH35=3,BI35=3,FS35<>0),P35,0),2) -> 0 | GM35: =ROUND(O35+X35+Y35+GK35,2)+GX35 -> 0 | GN35: =IF(OR(BI35=0,BI35=1),GM35,0) -> 0 | GO35: =IF(BI35=2,GM35,0) -> 0 | GP35: =IF(BI35=4,GM35+GX35,0) -> 0 | GR35: 0 | GS35: 3 | GT35: 0 | GV35: =ROUND((GT35),6) -> 0 | GW35: 1 | GX35: =ROUND(HC35*I35,2) -> 0 | HA35: 0 | HB35: 0 | HC35: =GV35*GW35 -> 0 | IK35: 0
A36: 17 | B36: 1 | D36: =ROW(EtalonRes!A8) -> 8 | E36: 5 | F36: 1.50-3203-34-1/1 | G36: Устройство и разборка защитного ограждения лесов из сетки | H36: 100 м2 | I36: 0.776 | J36: 0 | K36: 0.776 | O36: =ROUND(CP36,2) -> 4128.61 | P36: =ROUND(CQ36*I36,2) -> 1078.43 | Q36: =ROUND(CR36*I36,2) -> 0 | R36: =ROUND(CS36*I36,2) -> 0 | S36: =ROUND(CT36*I36,2) -> 3050.18 | T36: =ROUND(CU36*I36,2) -> 0 | U36: =CV36*I36 -> 9.90952 | V36: =CW36*I36 -> 0 | W36: =ROUND(CX36*I36,2) -> 0 | X36: =ROUND(CY36,2) -> 2135.13 | Y36: =ROUND(CZ36,2) -> 305.02 | AA36: 72192302 | AB36: =ROUND((AC36+AD36+AF36),6) -> 5320.38 | AC36: =ROUND((ES36),6) -> 1389.73 | AD36: =ROUND((((ET36)-(EU36))+AE36),6) -> 0 | AE36: =ROUND((EU36),6) -> 0 | AF36: =ROUND((EV36),6) -> 3930.65 | AG36: =ROUND((AP36),6) -> 0 | AH36: =(EW36) -> 12.77 | AI36: =(EX36) -> 0 | AJ36: =(AS36) -> 0 | AK36: 5320.38 | AL36: 1389.73 | AM36: 0 | AN36: 0 | AO36: 3930.65 | AP36: 0 | AQ36: 12.77 | AR36: 0 | AS36: 0 | AT36: 70 | AU36: 10 | AV36: 1 | AW36: 1 | AZ36: 1 | BA36: 1 | BB36: 1 | BC36: 1 | BH36: 0 | BI36: 4 | BJ36: СН-2012-2024.1. База. Сб.50-3203-34-1/1 | BM36: 0 | BN36: 0 | BP36: 0 | BQ36: 1 | BR36: 0 | BS36: 1 | BT36: 1 | BU36: 1 | BV36: 1 | BW36: 1 | BX36: 1 | BZ36: 70 | CA36: 10 | CE36: 0 | CF36: 0 | CG36: 0 | CM36: 0 | CO36: 0 | CP36: =(P36+Q36+S36) -> 4128.61 | CQ36: =(AC36*BC36*AW36) -> 1389.73 | CR36: =((((ET36)*BB36-(EU36)*BS36)+AE36*BS36)*AV36) -> 0 | CS36: =(AE36*BS36*AV36) -> 0 | CT36: =(AF36*BA36*AV36) -> 3930.65 | CU36: =AG36 -> 0 | CV36: =(AH36*AV36) -> 12.77 | CW36: =AI36 -> 0 | CX36: =AJ36 -> 0 | CY36: =((S36*BZ36)/100) -> 2135.126 | CZ36: =((S36*CA36)/100) -> 305.018 | DN36: 0 | DO36: 0 | DP36: 1 | DQ36: 1 | DU36: 1005 | DV36: 100 м2 | DW36: 100 м2 | DX36: 100 | EE36: 71753531 | EF36: 1 | EG36: СН-2012 | EH36: 0 | EJ36: 4 | EK36: 0 | EL36: Подрядные работы, гл. 1-5,7 | EM36: работа | EQ36: 0 | ER36: 5320.38 | ES36: 1389.73 | ET36: 0 | EU36: 0 | EV36: 3930.65 | EW36: 12.77 | EX36: 0 | EY36: 0 | FQ36: 0 | FR36: =ROUND(IF(BI36=3,GM36,0),2) -> 0 | FS36: 0 | FX36: 70 | FY36: 10 | GD36: 0 | GF36: 550753279 | GG36: 2 | GH36: 1 | GI36: -2 | GJ36: 0 | GK36: =ROUND(R36*(R12)/100,2) -> 0 | GL36: =ROUND(IF(AND(BH36=3,BI36=3,FS36<>0),P36,0),2) -> 0 | GM36: =ROUND(O36+X36+Y36+GK36,2)+GX36 -> 6568.76 | GN36: =IF(OR(BI36=0,BI36=1),GM36,0) -> 0 | GO36: =IF(BI36=2,GM36,0) -> 0 | GP36: =IF(BI36=4,GM36+GX36,0) -> 6568.76 | GR36: 0 | GS36: 3 | GT36: 0 | GV36: =ROUND((GT36),6) -> 0 | GW36: 1 | GX36: =ROUND(HC36*I36,2) -> 0 | HA36: 0 | HB36: 0 | HC36: =GV36*GW36 -> 0 | IK36: 0
A37: 17 | B37: 1 | D37: =ROW(EtalonRes!A13) -> 13 | E37: 6 | F37: 1.7-3204-1-4/1 | G37: Разборка трубопроводов центрального отопления на сварке диаметром труб до 50 мм | H37: 100 м | I37: 0.4 | J37: 0 | K37: 0.4 | O37: =ROUND(CP37,2) -> 5584.83 | P37: =ROUND(CQ37*I37,2) -> 215.79 | Q37: =ROUND(CR37*I37,2) -> 11.9 | R37: =ROUND(CS37*I37,2) -> 0.34 | S37: =ROUND(CT37*I37,2) -> 5357.14 | T37: =ROUND(CU37*I37,2) -> 0 | U37: =CV37*I37 -> 19.736 | V37: =CW37*I37 -> 0 | W37: =ROUND(CX37*I37,2) -> 0 | X37: =ROUND(CY37,2) -> 3750 | Y37: =ROUND(CZ37,2) -> 535.71 | AA37: 72192302 | AB37: =ROUND((AC37+AD37+AF37),6) -> 13962.07 | AC37: =ROUND((ES37),6) -> 539.47 | AD37: =ROUND((((ET37)-(EU37))+AE37),6) -> 29.75 | AE37: =ROUND((EU37),6) -> 0.85 | AF37: =ROUND((EV37),6) -> 13392.85 | AG37: =ROUND((AP37),6) -> 0 | AH37: =(EW37) -> 49.34 | AI37: =(EX37) -> 0 | AJ37: =(AS37) -> 0 | AK37: 13962.07 | AL37: 539.47 | AM37: 29.75 | AN37: 0.85 | AO37: 13392.85 | AP37: 0 | AQ37: 49.34 | AR37: 0 | AS37: 0 | AT37: 70 | AU37: 10 | AV37: 1 | AW37: 1 | AZ37: 1 | BA37: 1 | BB37: 1 | BC37: 1 | BH37: 0 | BI37: 4 | BJ37: СН-2012-2024.1. База. Сб.17-3204-1-4/1 | BM37: 0 | BN37: 0 | BP37: 0 | BQ37: 1 | BR37: 0 | BS37: 1 | BT37: 1 | BU37: 1 | BV37: 1 | BW37: 1 | BX37: 1 | BZ37: 70 | CA37: 10 | CE37: 0 | CF37: 0 | CG37: 0 | CM37: 0 | CO37: 0 | CP37: =(P37+Q37+S37) -> 5584.83 | CQ37: =(AC37*BC37*AW37) -> 539.47 | CR37: =((((ET37)*BB37-(EU37)*BS37)+AE37*BS37)*AV37) -> 29.75 | CS37: =(AE37*BS37*AV37) -> 0.85 | CT37: =(AF37*BA37*AV37) -> 13392.85 | CU37: =AG37 -> 0 | CV37: =(AH37*AV37) -> 49.34 | CW37: =AI37 -> 0 | CX37: =AJ37 -> 0 | CY37: =((S37*BZ37)/100) -> 3749.998 | CZ37: =((S37*CA37)/100) -> 535.714 | DN37: 0 | DO37: 0 | DP37: 1 | DQ37: 1 | DU37: 1003 | DV37: 100 м | DW37: 100 м | DX37: 100 | EE37: 71753531 | EF37: 1 | EG37: СН-2012 | EH37: 0 | EJ37: 4 | EK37: 0 | EL37: Подрядные работы, гл. 1-5,7 | EM37: работа | EQ37: 0 | ER37: 13962.07 | ES37: 539.47 | ET37: 29.75 | EU37: 0.85 | EV37: 13392.85 | EW37: 49.34 | EX37: 0 | EY37: 0 | FQ37: 0 | FR37: =ROUND(IF(BI37=3,GM37,0),2) -> 0 | FS37: 0 | FX37: 70 | FY37: 10 | GD37: 0 | GF37: 393771794 | GG37: 2 | GH37: 1 | GI37: -2 | GJ37: 0 | GK37: =ROUND(R37*(R12)/100,2) -> 0.37 | GL37: =ROUND(IF(AND(BH37=3,BI37=3,FS37<>0),P37,0),2) -> 0 | GM37: =ROUND(O37+X37+Y37+GK37,2)+GX37 -> 9870.91 | GN37: =IF(OR(BI37=0,BI37=1),GM37,0) -> 0 | GO37: =IF(BI37=2,GM37,0) -> 0 | GP37: =IF(BI37=4,GM37+GX37,0) -> 9870.91 | GR37: 0 | GS37: 3 | GT37: 0 | GV37: =ROUND((GT37),6) -> 0 | GW37: 1 | GX37: =ROUND(HC37*I37,2) -> 0 | HA37: 0 | HB37: 0 | HC37: =GV37*GW37 -> 0 | IK37: 0
A38: 18 | B38: 1 | E38: 7 | F38: 9999990001 | G38: Масса мусора | H38: т | I38: =I37*J38 -> -0.1816 | J38: -0.454 | K38: -0.454 | O38: =ROUND(CP38,2) -> 0 | P38: =ROUND(CQ38*I38,2) -> 0 | Q38: =ROUND(CR38*I38,2) -> 0 | R38: =ROUND(CS38*I38,2) -> 0 | S38: =ROUND(CT38*I38,2) -> 0 | T38: =ROUND(CU38*I38,2) -> 0 | U38: =CV38*I38 -> 0 | V38: =CW38*I38 -> 0 | W38: =ROUND(CX38*I38,2) -> 0 | X38: =ROUND(CY38,2) -> 0 | Y38: =ROUND(CZ38,2) -> 0 | AA38: 72192302 | AB38: =ROUND((AC38+AD38+AF38),6) -> 0 | AC38: =ROUND((ES38),6) -> 0 | AD38: =ROUND((((ET38)-(EU38))+AE38),6) -> 0 | AE38: =ROUND((EU38),6) -> 0 | AF38: =ROUND((EV38),6) -> 0 | AG38: =ROUND((AP38),6) -> 0 | AH38: =(EW38) -> 0 | AI38: =(EX38) -> 0 | AJ38: =(AS38) -> 0 | AK38: 0 | AL38: 0 | AM38: 0 | AN38: 0 | AO38: 0 | AP38: 0 | AQ38: 0 | AR38: 0 | AS38: 0 | AT38: 70 | AU38: 10 | AV38: 1 | AW38: 1 | AZ38: 1 | BA38: 1 | BB38: 1 | BC38: 1 | BH38: 3 | BI38: 4 | BM38: 0 | BN38: 0 | BP38: 0 | BQ38: 1 | BR38: 1 | BS38: 1 | BT38: 1 | BU38: 1 | BV38: 1 | BW38: 1 | BX38: 1 | BZ38: 70 | CA38: 10 | CE38: 0 | CF38: 0 | CG38: 0 | CM38: 0 | CO38: 0 | CP38: =(P38+Q38+S38) -> 0 | CQ38: =(AC38*BC38*AW38) -> 0 | CR38: =((((ET38)*BB38-(EU38)*BS38)+AE38*BS38)*AV38) -> 0 | CS38: =(AE38*BS38*AV38) -> 0 | CT38: =(AF38*BA38*AV38) -> 0 | CU38: =AG38 -> 0 | CV38: =(AH38*AV38) -> 0 | CW38: =AI38 -> 0 | CX38: =AJ38 -> 0 | CY38: =((S38*BZ38)/100) -> 0 | CZ38: =((S38*CA38)/100) -> 0 | DN38: 0 | DO38: 0 | DP38: 1 | DQ38: 1 | DU38: 1009 | DV38: т | DW38: т | DX38: 1000 | EE38: 71753531 | EF38: 1 | EG38: СН-2012 | EH38: 0 | EJ38: 4 | EK38: 0 | EL38: Подрядные работы, гл. 1-5,7 | EM38: работа | EQ38: 0 | ER38: 0 | ES38: 0 | ET38: 0 | EU38: 0 | EV38: 0 | EW38: 0 | EX38: 0 | FQ38: 0 | FR38: =ROUND(IF(BI38=3,GM38,0),2) -> 0 | FS38: 0 | FX38: 70 | FY38: 10 | GD38: 0 | GF38: 1489638031 | GG38: 2 | GH38: 1 | GI38: -2 | GJ38: 0 | GK38: =ROUND(R38*(R12)/100,2) -> 0 | GL38: =ROUND(IF(AND(BH38=3,BI38=3,FS38<>0),P38,0),2) -> 0 | GM38: =ROUND(O38+X38+Y38+GK38,2)+GX38 -> 0 | GN38: =IF(OR(BI38=0,BI38=1),GM38,0) -> 0 | GO38: =IF(BI38=2,GM38,0) -> 0 | GP38: =IF(BI38=4,GM38+GX38,0) -> 0 | GR38: 0 | GS38: 3 | GT38: 0 | GV38: =ROUND((GT38),6) -> 0 | GW38: 1 | GX38: =ROUND(HC38*I38,2) -> 0 | HA38: 0 | HB38: 0 | HC38: =GV38*GW38 -> 0 | IK38: 0
A39: 17 | B39: 1 | D39: =ROW(EtalonRes!A14) -> 14 | E39: 8 | F39: 1.2-3105-1-1/1 | G39: Вынос и занос мебели, в том числе спортивных снарядов массой до 50 кг | H39: шт. | I39: 15 | J39: 0 | K39: 15 | O39: =ROUND(CP39,2) -> 706.65 | P39: =ROUND(CQ39*I39,2) -> 0 | Q39: =ROUND(CR39*I39,2) -> 0 | R39: =ROUND(CS39*I39,2) -> 0 | S39: =ROUND(CT39*I39,2) -> 706.65 | T39: =ROUND(CU39*I39,2) -> 0 | U39: =CV39*I39 -> 2.85 | V39: =CW39*I39 -> 0 | W39: =ROUND(CX39*I39,2) -> 0 | X39: =ROUND(CY39,2) -> 494.66 | Y39: =ROUND(CZ39,2) -> 70.67 | AA39: 72192302 | AB39: =ROUND((AC39+AD39+AF39),6) -> 47.11 | AC39: =ROUND((ES39),6) -> 0 | AD39: =ROUND((((ET39)-(EU39))+AE39),6) -> 0 | AE39: =ROUND((EU39),6) -> 0 | AF39: =ROUND((EV39),6) -> 47.11 | AG39: =ROUND((AP39),6) -> 0 | AH39: =(EW39) -> 0.19 | AI39: =(EX39) -> 0 | AJ39: =(AS39) -> 0 | AK39: 47.11 | AL39: 0 | AM39: 0 | AN39: 0 | AO39: 47.11 | AP39: 0 | AQ39: 0.19 | AR39: 0 | AS39: 0 | AT39: 70 | AU39: 10 | AV39: 1 | AW39: 1 | AZ39: 1 | BA39: 1 | BB39: 1 | BC39: 1 | BH39: 0 | BI39: 4 | BJ39: СН-2012-2024.1. База. Сб.26-3105-1-1/1 | BM39: 0 | BN39: 0 | BP39: 0 | BQ39: 1 | BR39: 0 | BS39: 1 | BT39: 1 | BU39: 1 | BV39: 1 | BW39: 1 | BX39: 1 | BZ39: 70 | CA39: 10 | CE39: 0 | CF39: 0 | CG39: 0 | CM39: 0 | CO39: 0 | CP39: =(P39+Q39+S39) -> 706.65 | CQ39: =(AC39*BC39*AW39) -> 0 | CR39: =((((ET39)*BB39-(EU39)*BS39)+AE39*BS39)*AV39) -> 0 | CS39: =(AE39*BS39*AV39) -> 0 | CT39: =(AF39*BA39*AV39) -> 47.11 | CU39: =AG39 -> 0 | CV39: =(AH39*AV39) -> 0.19 | CW39: =AI39 -> 0 | CX39: =AJ39 -> 0 | CY39: =((S39*BZ39)/100) -> 494.655 | CZ39: =((S39*CA39)/100) -> 70.665 | DN39: 0 | DO39: 0 | DP39: 1 | DQ39: 1 | DU39: 1010 | DV39: шт. | DW39: шт. | DX39: 1 | EE39: 71753531 | EF39: 1 | EG39: СН-2012 | EH39: 0 | EJ39: 4 | EK39: 0 | EL39: Подрядные работы, гл. 1-5,7 | EM39: работа | EQ39: 0 | ER39: 47.11 | ES39: 0 | ET39: 0 | EU39: 0 | EV39: 47.11 | EW39: 0.19 | EX39: 0 | EY39: 0 | FQ39: 0 | FR39: =ROUND(IF(BI39=3,GM39,0),2) -> 0 | FS39: 0 | FX39: 70 | FY39: 10 | GD39: 0 | GF39: -873001244 | GG39: 2 | GH39: 1 | GI39: -2 | GJ39: 0 | GK39: =ROUND(R39*(R12)/100,2) -> 0 | GL39: =ROUND(IF(AND(BH39=3,BI39=3,FS39<>0),P39,0),2) -> 0 | GM39: =ROUND(O39+X39+Y39+GK39,2)+GX39 -> 1271.98 | GN39: =IF(OR(BI39=0,BI39=1),GM39,0) -> 0 | GO39: =IF(BI39=2,GM39,0) -> 0 | GP39: =IF(BI39=4,GM39+GX39,0) -> 1271.98 | GR39: 0 | GS39: 3 | GT39: 0 | GV39: =ROUND((GT39),6) -> 0 | GW39: 1 | GX39: =ROUND(HC39*I39,2) -> 0 | HA39: 0 | HB39: 0 | HC39: =GV39*GW39 -> 0 | IK39: 0
A40: 17 | B40: 1 | D40: =ROW(EtalonRes!A19) -> 19 | E40: 9 | F40: 1.50-3203-37-1/1 | G40: Монтаж мелких конструкций из стали различного профиля массой до 20 кг | H40: т | I40: 0.13744 | J40: 0 | K40: 0.13744 | O40: =ROUND(CP40,2) -> 1320.57 | P40: =ROUND(CQ40*I40,2) -> 0 | Q40: =ROUND(CR40*I40,2) -> 26.19 | R40: =ROUND(CS40*I40,2) -> 1.34 | S40: =ROUND(CT40*I40,2) -> 1294.38 | T40: =ROUND(CU40*I40,2) -> 0 | U40: =CV40*I40 -> 3.6668992 | V40: =CW40*I40 -> 0 | W40: =ROUND(CX40*I40,2) -> 0 | X40: =ROUND(CY40,2) -> 906.07 | Y40: =ROUND(CZ40,2) -> 129.44 | AA40: 72192302 | AB40: =ROUND((AC40+AD40+AF40),6) -> 9608.36 | AC40: =ROUND(((ES40*0)),6) -> 0 | AD40: =ROUND(((((ET40*0.2))-((EU40*0.2)))+AE40),6) -> 190.588 | AE40: =ROUND(((EU40*0.2)),6) -> 9.744 | AF40: =ROUND(((EV40*0.2)),6) -> 9417.772 | AG40: =ROUND((AP40),6) -> 0 | AH40: =((EW40*0.2)) -> 26.68 | AI40: =((EX40*0.2)) -> 0 | AJ40: =(AS40) -> 0 | AK40: 188846.85 | AL40: 140805.05 | AM40: 952.94 | AN40: 48.72 | AO40: 47088.86 | AP40: 0 | AQ40: 133.4 | AR40: 0 | AS40: 0 | AT40: 70 | AU40: 10 | AV40: 1 | AW40: 1 | AZ40: 1 | BA40: 1 | BB40: 1 | BC40: 1 | BH40: 0 | BI40: 4 | BJ40: СН-2012-2024.1. База. Сб.50-3203-37-1/1 | BM40: 0 | BN40: 0 | BP40: 0 | BQ40: 1 | BR40: 0 | BS40: 1 | BT40: 1 | BU40: 1 | BV40: 1 | BW40: 1 | BX40: 1 | BZ40: 70 | CA40: 10 | CE40: 0 | CF40: 0 | CG40: 0 | CM40: 0 | CN40: Поправка: СН-2012 О.П. п.22 Наименование: Демонтаж, разборка отдельных бетонных, железобетонных, металлических, деревянных, пластмассовых конструктивных элементов зданий и сооружений, внутренних и наружных инженерных систем и коммуникаций при отсутствии необходимых стоимостных нормативов в сборниках СН-2012 | CO40: 0 | CP40: =(P40+Q40+S40) -> 1320.57 | CQ40: =(AC40*BC40*AW40) -> 0 | CR40: =(((((ET40*0.2))*BB40-((EU40*0.2))*BS40)+AE40*BS40)*AV40) -> 190.588 | CS40: =(AE40*BS40*AV40) -> 9.744 | CT40: =(AF40*BA40*AV40) -> 9417.772 | CU40: =AG40 -> 0 | CV40: =(AH40*AV40) -> 26.68 | CW40: =AI40 -> 0 | CX40: =AJ40 -> 0 | CY40: =((S40*BZ40)/100) -> 906.066 | CZ40: =((S40*CA40)/100) -> 129.438 | DD40: )*0 | DE40: )*0,2 | DF40: )*0,2 | DG40: )*0,2 | DI40: )*0,2 | DJ40: )*0,2 | DN40: 0 | DO40: 0 | DP40: 1 | DQ40: 1 | DU40: 1009 | DV40: т | DW40: т | DX40: 1000 | EE40: 71753531 | EF40: 1 | EG40: СН-2012 | EH40: 0 | EJ40: 4 | EK40: 0 | EL40: Подрядные работы, гл. 1-5,7 | EM40: работа | EO40: Поправка: СН-2012 О.П. п.22 | EQ40: 0 | ER40: 188846.85 | ES40: 140805.05 | ET40: 952.94 | EU40: 48.72 | EV40: 47088.86 | EW40: 133.4 | EX40: 0 | EY40: 0 | FQ40: 0 | FR40: =ROUND(IF(BI40=3,GM40,0),2) -> 0 | FS40: 0 | FX40: 70 | FY40: 10 | GD40: 0 | GF40: 606636601 | GG40: 2 | GH40: 1 | GI40: -2 | GJ40: 0 | GK40: =ROUND(R40*(R12)/100,2) -> 1.45 | GL40: =ROUND(IF(AND(BH40=3,BI40=3,FS40<>0),P40,0),2) -> 0 | GM40: =ROUND(O40+X40+Y40+GK40,2)+GX40 -> 2357.53 | GN40: =IF(OR(BI40=0,BI40=1),GM40,0) -> 0 | GO40: =IF(BI40=2,GM40,0) -> 0 | GP40: =IF(BI40=4,GM40+GX40,0) -> 2357.53 | GR40: 0 | GS40: 3 | GT40: 0 | GV40: =ROUND((GT40),6) -> 0 | GW40: 1 | GX40: =ROUND(HC40*I40,2) -> 0 | HA40: 0 | HB40: 0 | HC40: =GV40*GW40 -> 0 | IK40: 0
A41: 17 | B41: 1 | D41: =ROW(EtalonRes!A22) -> 22 | E41: 10 | F41: 1.50-3204-4-1/1 | G41: Пробивка отбойным молотком сквозных отверстий в бетонных стенах и фундаментах толщиной 0,4 м для трубопроводов диаметром 100 мм | H41: 100 шт. | I41: 0.05 | J41: 0 | K41: 0.05 | O41: =ROUND(CP41,2) -> 4699.35 | P41: =ROUND(CQ41*I41,2) -> 0 | Q41: =ROUND(CR41*I41,2) -> 2237.66 | R41: =ROUND(CS41*I41,2) -> 1681.61 | S41: =ROUND(CT41*I41,2) -> 2461.69 | T41: =ROUND(CU41*I41,2) -> 0 | U41: =CV41*I41 -> 7.7 | V41: =CW41*I41 -> 0 | W41: =ROUND(CX41*I41,2) -> 0 | X41: =ROUND(CY41,2) -> 1723.18 | Y41: =ROUND(CZ41,2) -> 246.17 | AA41: 72192302 | AB41: =ROUND((AC41+AD41+AF41),6) -> 93987.05 | AC41: =ROUND((ES41),6) -> 0 | AD41: =ROUND((((ET41)-(EU41))+AE41),6) -> 44753.25 | AE41: =ROUND((EU41),6) -> 33632.25 | AF41: =ROUND((EV41),6) -> 49233.8 | AG41: =ROUND((AP41),6) -> 0 | AH41: =(EW41) -> 154 | AI41: =(EX41) -> 0 | AJ41: =(AS41) -> 0 | AK41: 93987.05 | AL41: 0 | AM41: 44753.25 | AN41: 33632.25 | AO41: 49233.8 | AP41: 0 | AQ41: 154 | AR41: 0 | AS41: 0 | AT41: 70 | AU41: 10 | AV41: 1 | AW41: 1 | AZ41: 1 | BA41: 1 | BB41: 1 | BC41: 1 | BH41: 0 | BI41: 4 | BJ41: СН-2012-2024.1. База. Сб.50-3204-4-1/1 | BM41: 0 | BN41: 0 | BP41: 0 | BQ41: 1 | BR41: 0 | BS41: 1 | BT41: 1 | BU41: 1 | BV41: 1 | BW41: 1 | BX41: 1 | BZ41: 70 | CA41: 10 | CE41: 0 | CF41: 0 | CG41: 0 | CM41: 0 | CO41: 0 | CP41: =(P41+Q41+S41) -> 4699.35 | CQ41: =(AC41*BC41*AW41) -> 0 | CR41: =((((ET41)*BB41-(EU41)*BS41)+AE41*BS41)*AV41) -> 44753.25 | CS41: =(AE41*BS41*AV41) -> 33632.25 | CT41: =(AF41*BA41*AV41) -> 49233.8 | CU41: =AG41 -> 0 | CV41: =(AH41*AV41) -> 154 | CW41: =AI41 -> 0 | CX41: =AJ41 -> 0 | CY41: =((S41*BZ41)/100) -> 1723.183 | CZ41: =((S41*CA41)/100) -> 246.169 | DN41: 0 | DO41: 0 | DP41: 1 | DQ41: 1 | DU41: 1010 | DV41: 100 шт. | DW41: 100 шт. | DX41: 100 | EE41: 71753531 | EF41: 1 | EG41: СН-2012 | EH41: 0 | EJ41: 4 | EK41: 0 | EL41: Подрядные работы, гл. 1-5,7 | EM41: работа | EQ41: 0 | ER41: 93987.05 | ES41: 0 | ET41: 44753.25 | EU41: 33632.25 | EV41: 49233.8 | EW41: 154 | EX41: 0 | EY41: 0 | FQ41: 0 | FR41: =ROUND(IF(BI41=3,GM41,0),2) -> 0 | FS41: 0 | FX41: 70 | FY41: 10 | GD41: 0 | GF41: 1919355405 | GG41: 2 | GH41: 1 | GI41: -2 | GJ41: 0 | GK41: =ROUND(R41*(R12)/100,2) -> 1816.14 | GL41: =ROUND(IF(AND(BH41=3,BI41=3,FS41<>0),P41,0),2) -> 0 | GM41: =ROUND(O41+X41+Y41+GK41,2)+GX41 -> 8484.84 | GN41: =IF(OR(BI41=0,BI41=1),GM41,0) -> 0 | GO41: =IF(BI41=2,GM41,0) -> 0 | GP41: =IF(BI41=4,GM41+GX41,0) -> 8484.84 | GR41: 0 | GS41: 3 | GT41: 0 | GV41: =ROUND((GT41),6) -> 0 | GW41: 1 | GX41: =ROUND(HC41*I41,2) -> 0 | HA41: 0 | HB41: 0 | HC41: =GV41*GW41 -> 0 | IK41: 0
A43: 51 | B43: =B28 -> 1 | C43: =A28 -> 5 | D43: =ROW(A28) -> 28 | F43: =IF(F28<>"",F28,"") -> Новый подраздел | G43: =IF(G28<>"",G28,"") -> 1.1 Демонтажные работы | H43: 0 | O43: =ROUND(AB43,2) -> 84927.54 | P43: =ROUND(AC43,2) -> 1294.22 | Q43: =ROUND(AD43,2) -> 2276.91 | R43: =ROUND(AE43,2) -> 1683.29 | S43: =ROUND(AF43,2) -> 81356.41 | T43: =ROUND(AG43,2) -> 0 | U43: =AH43 -> 318.20593 | V43: =AI43 -> 0 | W43: =ROUND(AJ43,2) -> 0 | X43: =ROUND(AK43,2) -> 56949.5 | Y43: =ROUND(AL43,2) -> 8135.65 | AB43: =ROUND(SUMIF(AA32:AA41,"=72192302",O32:O41),2) -> 84927.54 | AC43: =ROUND(SUMIF(AA32:AA41,"=72192302",P32:P41),2) -> 1294.22 | AD43: =ROUND(SUMIF(AA32:AA41,"=72192302",Q32:Q41),2) -> 2276.91 | AE43: =ROUND(SUMIF(AA32:AA41,"=72192302",R32:R41),2) -> 1683.29 | AF43: =ROUND(SUMIF(AA32:AA41,"=72192302",S32:S41),2) -> 81356.41 | AG43: =ROUND(SUMIF(AA32:AA41,"=72192302",T32:T41),2) -> 0 | AH43: =SUMIF(AA32:AA41,"=72192302",U32:U41) -> 318.20593 | AI43: =SUMIF(AA32:AA41,"=72192302",V32:V41) -> 0 | AJ43: =ROUND(SUMIF(AA32:AA41,"=72192302",W32:W41),2) -> 0 | AK43: =ROUND(SUMIF(AA32:AA41,"=72192302",X32:X41),2) -> 56949.5 | AL43: =ROUND(SUMIF(AA32:AA41,"=72192302",Y32:Y41),2) -> 8135.65 | AO43: =ROUND(BX43,2) -> 0 | AP43: =ROUND(BY43,2) -> 0 | AQ43: =ROUND(BZ43,2) -> 0 | AR43: =ROUND(CA43,2) -> 151830.65 | AS43: =ROUND(CB43,2) -> 0 | AT43: =ROUND(CC43,2) -> 0 | AU43: =ROUND(CD43,2) -> 151830.65 | AV43: =ROUND(CE43,2) -> 1294.22 | ... BD43: =ROUND(CM43,2) -> 0 | BX43: =ROUND(SUMIF(AA32:AA41,"=72192302",FQ32:FQ41),2) -> 0 | BY43: =ROUND(SUMIF(AA32:AA41,"=72192302",FR32:FR41),2) -> 0 | BZ43: =ROUND(SUMIF(AA32:AA41,"=72192302",GL32:GL41),2) -> 0 | CA43: =ROUND(SUMIF(AA32:AA41,"=72192302",GM32:GM41),2) -> 151830.65 | CB43: =ROUND(SUMIF(AA32:AA41,"=72192302",GN32:GN41),2) -> 0 | CC43: =ROUND(SUMIF(AA32:AA41,"=72192302",GO32:GO41),2) -> 0 | CD43: =ROUND(SUMIF(AA32:AA41,"=72192302",GP32:GP41),2) -> 151830.65 | CE43: =AC43-BX43 -> 1294.22 | CF43: =AC43-BY43 -> 1294.22 | CG43: =BX43-BZ43 -> 0 | CH43: =AC43-BX43-BY43+BZ43 -> 1294.22 | CI43: =BY43-BZ43 -> 0 | CJ43: =ROUND(SUMIF(AA32:AA41,"=72192302",GX32:GX41),2) -> 0 | CK43: =ROUND(SUMIF(AA32:AA41,"=72192302",GY32:GY41),2) -> 0 | CL43: =ROUND(SUMIF(AA32:AA41,"=72192302",GZ32:GZ41),2) -> 0 | CM43: =ROUND(SUMIF(AA32:AA41,"=72192302",HD32:HD41),2) -> 0 | GX43: 0
A45: 50 | B45: 0 | C45: 0 | D45: 1 | E45: 201 | F45: =ROUND(Source!O43,O45) -> 84927.54 | G45: ПЗ | H45: Прямые затраты | K45: 201 | L45: 1 | M45: 3 | O45: 2 | W45: 84927.54 | X45: 1 | Y45: 84927.54
A46: 50 | B46: 0 | C46: 0 | D46: 1 | E46: 202 | F46: =ROUND(Source!P43,O46) -> 1294.22 | G46: СтМатОб | H46: Стоимость материальных ресурсов (всего) | K46: 202 | L46: 2 | M46: 3 | O46: 2 | W46: 1294.22 | X46: 1 | Y46: 1294.22
A47: 50 | B47: 0 | C47: 0 | D47: 1 | E47: 222 | F47: =ROUND(Source!AO43,O47) -> 0 | G47: СтМатОбЗак | H47: Стоимость материалов и оборудования заказчика | K47: 222 | L47: 3 | M47: 3 | O47: 2 | W47: 0 | X47: 1 | Y47: 0
A48: 50 | B48: 0 | C48: 0 | D48: 1 | E48: 225 | F48: =ROUND(Source!AV43,O48) -> 1294.22 | G48: СтМатОбПод | H48: Стоимость материалов и оборудования подрядчика | K48: 225 | L48: 4 | M48: 3 | O48: 2 | W48: 1294.22 | X48: 1 | Y48: 1294.22
A49: 50 | B49: 0 | C49: 0 | D49: 1 | E49: 226 | F49: =ROUND(Source!AW43,O49) -> 1294.22 | G49: СтМат | H49: Стоимость материалов (всего) | K49: 226 | L49: 5 | M49: 3 | O49: 2 | W49: 1294.22 | X49: 1 | Y49: 1294.22
A50: 50 | B50: 0 | C50: 0 | D50: 1 | E50: 227 | F50: =ROUND(Source!AX43,O50) -> 0 | G50: СтМатЗак | H50: Стоимость материалов заказчика | K50: 227 | L50: 6 | M50: 3 | O50: 2 | W50: 0 | X50: 1 | Y50: 0
A51: 50 | B51: 0 | C51: 0 | D51: 1 | E51: 228 | F51: =ROUND(Source!AY43,O51) -> 1294.22 | G51: СтМатПод | H51: Стоимость материалов подрядчика | K51: 228 | L51: 7 | M51: 3 | O51: 2 | W51: 1294.22 | X51: 1 | Y51: 1294.22
A52: 50 | B52: 0 | C52: 0 | D52: 1 | E52: 216 | F52: =ROUND(Source!AP43,O52) -> 0 | G52: Оборуд | H52: Стоимость оборудования (всего) | K52: 216 | L52: 8 | M52: 3 | O52: 2 | W52: 0 | X52: 1 | Y52: 0
A53: 50 | B53: 0 | C53: 0 | D53: 1 | E53: 223 | F53: =ROUND(Source!AQ43,O53) -> 0 | G53: ОборудЗак | H53: Стоимость оборудования заказчика | K53: 223 | L53: 9 | M53: 3 | O53: 2 | W53: 0 | X53: 1 | Y53: 0
A54: 50 | B54: 0 | C54: 0 | D54: 1 | E54: 229 | F54: =ROUND(Source!AZ43,O54) -> 0 | G54: ОборудПод | H54: Стоимость оборудования подрядчика | K54: 229 | L54: 10 | M54: 3 | O54: 2 | W54: 0 | X54: 1 | Y54: 0
A55: 50 | B55: 0 | C55: 0 | D55: 1 | E55: 203 | F55: =ROUND(Source!Q43,O55) -> 2276.91 | G55: ЭММ | H55: Эксплуатация машин | K55: 203 | L55: 11 | M55: 3 | O55: 2 | W55: 2276.91 | X55: 1 | Y55: 2276.91
A56: 50 | B56: 0 | C56: 0 | D56: 1 | E56: 231 | F56: =ROUND(Source!BB43,O56) -> 0 | G56: ЭММсНРиСП | H56: Эксплуатация машин по ТСН-2001.16 | K56: 231 | L56: 12 | M56: 3 | O56: 2 | W56: 0 | X56: 1 | Y56: 0
A57: 50 | B57: 0 | C57: 0 | D57: 1 | E57: 204 | F57: =ROUND(Source!R43,O57) -> 1683.29 | G57: ЗПМ | H57: ЗП машинистов | K57: 204 | L57: 13 | M57: 3 | O57: 2 | W57: 1683.29 | X57: 1 | Y57: 1683.29
A58: 50 | B58: 0 | C58: 0 | D58: 1 | E58: 205 | F58: =ROUND(Source!S43,O58) -> 81356.41 | G58: ОЗП | H58: Основная ЗП рабочих | K58: 205 | L58: 14 | M58: 3 | O58: 2 | W58: 81356.41 | X58: 1 | Y58: 81356.41
A59: 50 | B59: 0 | C59: 0 | D59: 1 | E59: 232 | F59: =ROUND(Source!BC43,O59) -> 0 | G59: ОЗПсНРиСП | H59: Основная ЗП рабочих по ТСН-2001.16 | K59: 232 | L59: 15 | M59: 3 | O59: 2 | W59: 0 | X59: 1 | Y59: 0
A60: 50 | B60: 0 | C60: 0 | D60: 1 | E60: 214 | F60: =ROUND(Source!AS43,O60) -> 0 | G60: Строит | H60: Строительные работы с НР и СП | K60: 214 | L60: 16 | M60: 3 | O60: 2 | W60: 0 | X60: 1 | Y60: 0
A61: 50 | B61: 0 | C61: 0 | D61: 1 | E61: 215 | F61: =ROUND(Source!AT43,O61) -> 0 | G61: Монтаж | H61: Монтажные работы с НР и СП | K61: 215 | L61: 17 | M61: 3 | O61: 2 | W61: 0 | X61: 1 | Y61: 0
A62: 50 | B62: 0 | C62: 0 | D62: 1 | E62: 217 | F62: =ROUND(Source!AU43,O62) -> 151830.65 | G62: Прочие | H62: Прочие работы с НР и СП | K62: 217 | L62: 18 | M62: 3 | O62: 2 | W62: 151830.65 | X62: 1 | Y62: 151830.65
A63: 50 | B63: 0 | C63: 0 | D63: 1 | E63: 230 | F63: =ROUND(Source!BA43,O63) -> 0 | G63: ПрочиеЗатр | H63: Прочие затраты по ТСН-2001.16 | K63: 230 | L63: 19 | M63: 3 | O63: 2 | W63: 0 | X63: 1 | Y63: 0
A64: 50 | B64: 0 | C64: 0 | D64: 1 | E64: 206 | F64: =ROUND(Source!T43,O64) -> 0 | G64: ВозврМат | H64: Возврат материалов | K64: 206 | L64: 20 | M64: 3 | O64: 2 | W64: 0 | X64: 1 | Y64: 0
A65: 50 | B65: 0 | C65: 0 | D65: 1 | E65: 207 | F65: =Source!U43 -> 318.20593 | G65: ТрудСтр | H65: Трудозатраты строителей | K65: 207 | L65: 21 | M65: 3 | O65: -1 | W65: 318.20593 | X65: 1 | Y65: 318.20593
A66: 50 | B66: 0 | C66: 0 | D66: 1 | E66: 208 | F66: =Source!V43 -> 0 | G66: ТрудМаш | H66: Трудозатраты машинистов | K66: 208 | L66: 22 | M66: 3 | O66: -1 | W66: 0 | X66: 1 | Y66: 0
A67: 50 | B67: 0 | C67: 0 | D67: 1 | E67: 209 | F67: =ROUND(Source!W43,O67) -> 0 | G67: ТранспМат | H67: Транспорт материалов | K67: 209 | L67: 23 | M67: 3 | O67: 2 | W67: 0 | X67: 1 | Y67: 0
A68: 50 | B68: 0 | C68: 0 | D68: 1 | E68: 233 | F68: =ROUND(Source!BD43,O68) -> 0 | G68: Перевозка | H68: Перевозка грузов | K68: 233 | L68: 24 | M68: 3 | O68: 2 | W68: 0 | X68: 1 | Y68: 0
A69: 50 | B69: 0 | C69: 0 | D69: 1 | E69: 210 | F69: =ROUND(Source!X43,O69) -> 56949.5 | G69: НР | H69: Накладные расходы | K69: 210 | L69: 25 | M69: 3 | O69: 2 | W69: 56949.5 | X69: 1 | Y69: 56949.5
A70: 50 | B70: 0 | C70: 0 | D70: 1 | E70: 211 | F70: =ROUND(Source!Y43,O70) -> 8135.65 | G70: СмПриб | H70: Сметная прибыль | K70: 211 | L70: 26 | M70: 3 | O70: 2 | W70: 8135.65 | X70: 1 | Y70: 8135.65
A71: 50 | B71: 0 | C71: 0 | D71: 1 | E71: 224 | F71: =ROUND(Source!AR43,O71) -> 151830.65 | G71: Всего | H71: Всего с НР и СП | K71: 224 | L71: 27 | M71: 3 | O71: 2 | W71: 151830.65 | X71: 1 | Y71: 151830.65
A73: 5 | B73: 1 | D73: =ROW(A88) -> 88 | F73: Новый подраздел | G73: 1.2 Ремонтно-строительные работы | I73: 0 | K73: 0 | S73: 0 | V73: 0 | BX73: 0 | CJ73: 0
A75: 52 | B75: =B88 -> 1 | C75: =C88 -> 5 | D75: =D88 -> 73 | E75: =E88 -> 0 | F75: =F88 -> Новый подраздел | G75: =G88 -> 1.2 Ремонтно-строительные работы | O75: =O88 -> 531337.61 | P75: =P88 -> 194371.06 | Q75: =Q88 -> 16302.94 | R75: =R88 -> 14252.71 | S75: =S88 -> 320663.61 | T75: =T88 -> 0 | U75: =U88 -> 1068.9519 | V75: =V88 -> 0 | ... GX75: =GX88 -> 0
A77: 17 | B77: 1 | D77: =ROW(EtalonRes!A30) -> 30 | E77: 11 | F77: 1.13-3103-1-1/1 | G77: Простая штукатурка поверхностей стен по камню и бетону известковым раствором | H77: 100 м2 | I77: 3.9591 | J77: 0 | K77: 3.9591 | O77: =ROUND(CP77,2) -> 132810.55 | P77: =ROUND(CQ77*I77,2) -> 48658.45 | Q77: =ROUND(CR77*I77,2) -> 9352.86 | R77: =ROUND(CS77*I77,2) -> 8299.58 | S77: =ROUND(CT77*I77,2) -> 74799.24 | T77: =ROUND(CU77*I77,2) -> 0 | U77: =CV77*I77 -> 253.14485 | V77: =CW77*I77 -> 0 | W77: =ROUND(CX77*I77,2) -> 0 | X77: =ROUND(CY77,2) -> 52359.47 | Y77: =ROUND(CZ77,2) -> 7479.92 | AA77: 72192302 | AB77: =ROUND((AC77+AD77+AF77),6) -> 33545.64 | AC77: =ROUND((ES77),6) -> 12290.28 | AD77: =ROUND((((ET77)-(EU77))+AE77),6) -> 2362.37 | AE77: =ROUND((EU77),6) -> 2096.33 | AF77: =ROUND((EV77),6) -> 18892.99 | AG77: =ROUND((AP77),6) -> 0 | AH77: =(EW77) -> 63.94 | AI77: =(EX77) -> 0 | AJ77: =(AS77) -> 0 | AK77: 33545.64 | AL77: 12290.28 | AM77: 2362.37 | AN77: 2096.33 | AO77: 18892.99 | AP77: 0 | AQ77: 63.94 | AR77: 0 | AS77: 0 | AT77: 70 | AU77: 10 | AV77: 1 | AW77: 1 | AZ77: 1 | BA77: 1 | BB77: 1 | BC77: 1 | BH77: 0 | BI77: 4 | BJ77: СН-2012-2024.1. База. Сб.13-3103-1-1/1 | BM77: 0 | BN77: 0 | BP77: 0 | BQ77: 1 | BR77: 0 | BS77: 1 | BT77: 1 | BU77: 1 | BV77: 1 | BW77: 1 | BX77: 1 | BZ77: 70 | CA77: 10 | CE77: 0 | CF77: 0 | CG77: 0 | CM77: 0 | CO77: 0 | CP77: =(P77+Q77+S77) -> 132810.55 | CQ77: =(AC77*BC77*AW77) -> 12290.28 | CR77: =((((ET77)*BB77-(EU77)*BS77)+AE77*BS77)*AV77) -> 2362.37 | CS77: =(AE77*BS77*AV77) -> 2096.33 | CT77: =(AF77*BA77*AV77) -> 18892.99 | CU77: =AG77 -> 0 | CV77: =(AH77*AV77) -> 63.94 | CW77: =AI77 -> 0 | CX77: =AJ77 -> 0 | CY77: =((S77*BZ77)/100) -> 52359.468 | CZ77: =((S77*CA77)/100) -> 7479.924 | DN77: 0 | DO77: 0 | DP77: 1 | DQ77: 1 | DU77: 1005 | DV77: 100 м2 | DW77: 100 м2 | DX77: 100 | EE77: 71753531 | EF77: 1 | EG77: СН-2012 | EH77: 0 | EJ77: 4 | EK77: 0 | EL77: Подрядные работы, гл. 1-5,7 | EM77: работа | EQ77: 0 | ER77: 33545.64 | ES77: 12290.28 | ET77: 2362.37 | EU77: 2096.33 | EV77: 18892.99 | EW77: 63.94 | EX77: 0 | EY77: 0 | FQ77: 0 | FR77: =ROUND(IF(BI77=3,GM77,0),2) -> 0 | FS77: 0 | FX77: 70 | FY77: 10 | GD77: 0 | GF77: 1035890435 | GG77: 2 | GH77: 1 | GI77: -2 | GJ77: 0 | GK77: =ROUND(R77*(R12)/100,2) -> 8963.55 | GL77: =ROUND(IF(AND(BH77=3,BI77=3,FS77<>0),P77,0),2) -> 0 | GM77: =ROUND(O77+X77+Y77+GK77,2)+GX77 -> 201613.49 | GN77: =IF(OR(BI77=0,BI77=1),GM77,0) -> 0 | GO77: =IF(BI77=2,GM77,0) -> 0 | GP77: =IF(BI77=4,GM77+GX77,0) -> 201613.49 | GR77: 0 | GS77: 3 | GT77: 0 | GV77: =ROUND((GT77),6) -> 0 | GW77: 1 | GX77: =ROUND(HC77*I77,2) -> 0 | HA77: 0 | HB77: 0 | HC77: =GV77*GW77 -> 0 | IK77: 0
A78: 17 | B78: 1 | D78: =ROW(EtalonRes!A33) -> 33 | E78: 12 | F78: 1.13-3703-1-1/1 | G78: Обработка поверхностей стен грунтовкой глубокого проникновения внутри помещения | H78: 100 м2 | I78: 3.9591 | J78: 0 | K78: 3.9591 | O78: =ROUND(CP78,2) -> 10164.39 | P78: =ROUND(CQ78*I78,2) -> 4289.92 | Q78: =ROUND(CR78*I78,2) -> 1.66 | R78: =ROUND(CS78*I78,2) -> 0.04 | S78: =ROUND(CT78*I78,2) -> 5872.81 | T78: =ROUND(CU78*I78,2) -> 0 | U78: =CV78*I78 -> 21.181185 | V78: =CW78*I78 -> 0 | W78: =ROUND(CX78*I78,2) -> 0 | X78: =ROUND(CY78,2) -> 4110.97 | Y78: =ROUND(CZ78,2) -> 587.28 | AA78: 72192302 | AB78: =ROUND((AC78+AD78+AF78),6) -> 2567.35 | AC78: =ROUND((ES78),6) -> 1083.56 | AD78: =ROUND((((ET78)-(EU78))+AE78),6) -> 0.42 | AE78: =ROUND((EU78),6) -> 0.01 | AF78: =ROUND((EV78),6) -> 1483.37 | AG78: =ROUND((AP78),6) -> 0 | AH78: =(EW78) -> 5.35 | AI78: =(EX78) -> 0 | AJ78: =(AS78) -> 0 | AK78: 2567.35 | AL78: 1083.56 | AM78: 0.42 | AN78: 0.01 | AO78: 1483.37 | AP78: 0 | AQ78: 5.35 | AR78: 0 | AS78: 0 | AT78: 70 | AU78: 10 | AV78: 1 | AW78: 1 | AZ78: 1 | BA78: 1 | BB78: 1 | BC78: 1 | BH78: 0 | BI78: 4 | BJ78: СН-2012-2024.1. База. Сб.13-3703-1-1/1 | BM78: 0 | BN78: 0 | BP78: 0 | BQ78: 1 | BR78: 0 | BS78: 1 | BT78: 1 | BU78: 1 | BV78: 1 | BW78: 1 | BX78: 1 | BZ78: 70 | CA78: 10 | CE78: 0 | CF78: 0 | CG78: 0 | CM78: 0 | CO78: 0 | CP78: =(P78+Q78+S78) -> 10164.39 | CQ78: =(AC78*BC78*AW78) -> 1083.56 | CR78: =((((ET78)*BB78-(EU78)*BS78)+AE78*BS78)*AV78) -> 0.42 | CS78: =(AE78*BS78*AV78) -> 0.01 | CT78: =(AF78*BA78*AV78) -> 1483.37 | CU78: =AG78 -> 0 | CV78: =(AH78*AV78) -> 5.35 | CW78: =AI78 -> 0 | CX78: =AJ78 -> 0 | CY78: =((S78*BZ78)/100) -> 4110.967 | CZ78: =((S78*CA78)/100) -> 587.281 | DN78: 0 | DO78: 0 | DP78: 1 | DQ78: 1 | DU78: 1005 | DV78: 100 м2 | DW78: 100 м2 | DX78: 100 | EE78: 71753531 | EF78: 1 | EG78: СН-2012 | EH78: 0 | EJ78: 4 | EK78: 0 | EL78: Подрядные работы, гл. 1-5,7 | EM78: работа | EQ78: 0 | ER78: 2567.35 | ES78: 1083.56 | ET78: 0.42 | EU78: 0.01 | EV78: 1483.37 | EW78: 5.35 | EX78: 0 | EY78: 0 | FQ78: 0 | FR78: =ROUND(IF(BI78=3,GM78,0),2) -> 0 | FS78: 0 | FX78: 70 | FY78: 10 | GD78: 0 | GF78: -1478802949 | GG78: 2 | GH78: 1 | GI78: -2 | GJ78: 0 | GK78: =ROUND(R78*(R12)/100,2) -> 0.04 | GL78: =ROUND(IF(AND(BH78=3,BI78=3,FS78<>0),P78,0),2) -> 0 | GM78: =ROUND(O78+X78+Y78+GK78,2)+GX78 -> 14862.68 | GN78: =IF(OR(BI78=0,BI78=1),GM78,0) -> 0 | GO78: =IF(BI78=2,GM78,0) -> 0 | GP78: =IF(BI78=4,GM78+GX78,0) -> 14862.68 | GR78: 0 | GS78: 3 | GT78: 0 | GV78: =ROUND((GT78),6) -> 0 | GW78: 1 | GX78: =ROUND(HC78*I78,2) -> 0 | HA78: 0 | HB78: 0 | HC78: =GV78*GW78 -> 0 | IK78: 0
A79: 17 | B79: 1 | D79: =ROW(EtalonRes!A40) -> 40 | E79: 13 | F79: 1.13-3203-26-3/3 | G79: Улучшенная окраска стен внутри помещений водно-дисперсионными акриловыми красками - краска моющаяся типа ВД-АК-210 | H79: 100 м2 | I79: 3.9591 | J79: 0 | K79: 3.9591 | O79: =ROUND(CP79,2) -> 88807.33 | P79: =ROUND(CQ79*I79,2) -> 38914.79 | Q79: =ROUND(CR79*I79,2) -> 0 | R79: =ROUND(CS79*I79,2) -> 0 | S79: =ROUND(CT79*I79,2) -> 49892.54 | T79: =ROUND(CU79*I79,2) -> 0 | U79: =CV79*I79 -> 166.95525 | V79: =CW79*I79 -> 0 | W79: =ROUND(CX79*I79,2) -> 0 | X79: =ROUND(CY79,2) -> 34924.78 | Y79: =ROUND(CZ79,2) -> 4989.25 | AA79: 72192302 | AB79: =ROUND((AC79+AD79+AF79),6) -> 22431.19 | AC79: =ROUND((ES79),6) -> 9829.2 | AD79: =ROUND((((ET79)-(EU79))+AE79),6) -> 0 | AE79: =ROUND((EU79),6) -> 0 | AF79: =ROUND((EV79),6) -> 12601.99 | AG79: =ROUND((AP79),6) -> 0 | AH79: =(EW79) -> 42.17 | AI79: =(EX79) -> 0 | AJ79: =(AS79) -> 0 | AK79: 22431.19 | AL79: 9829.2 | AM79: 0 | AN79: 0 | AO79: 12601.99 | AP79: 0 | AQ79: 42.17 | AR79: 0 | AS79: 0 | AT79: 70 | AU79: 10 | AV79: 1 | AW79: 1 | AZ79: 1 | BA79: 1 | BB79: 1 | BC79: 1 | BH79: 0 | BI79: 4 | BJ79: СН-2012-2024.1. База. Сб.13-3203-26-3/3 | BM79: 0 | BN79: 0 | BP79: 0 | BQ79: 1 | BR79: 0 | BS79: 1 | BT79: 1 | BU79: 1 | BV79: 1 | BW79: 1 | BX79: 1 | BZ79: 70 | CA79: 10 | CE79: 0 | CF79: 0 | CG79: 0 | CM79: 0 | CO79: 0 | CP79: =(P79+Q79+S79) -> 88807.33 | CQ79: =(AC79*BC79*AW79) -> 9829.2 | CR79: =((((ET79)*BB79-(EU79)*BS79)+AE79*BS79)*AV79) -> 0 | CS79: =(AE79*BS79*AV79) -> 0 | CT79: =(AF79*BA79*AV79) -> 12601.99 | CU79: =AG79 -> 0 | CV79: =(AH79*AV79) -> 42.17 | CW79: =AI79 -> 0 | CX79: =AJ79 -> 0 | CY79: =((S79*BZ79)/100) -> 34924.778 | CZ79: =((S79*CA79)/100) -> 4989.254 | DN79: 0 | DO79: 0 | DP79: 1 | DQ79: 1 | DU79: 1005 | DV79: 100 м2 | DW79: 100 м2 | DX79: 100 | EE79: 71753531 | EF79: 1 | EG79: СН-2012 | EH79: 0 | EJ79: 4 | EK79: 0 | EL79: Подрядные работы, гл. 1-5,7 | EM79: работа | EQ79: 0 | ER79: 22431.19 | ES79: 9829.2 | ET79: 0 | EU79: 0 | EV79: 12601.99 | EW79: 42.17 | EX79: 0 | EY79: 0 | FQ79: 0 | FR79: =ROUND(IF(BI79=3,GM79,0),2) -> 0 | FS79: 0 | FX79: 70 | FY79: 10 | GD79: 0 | GF79: 1793052138 | GG79: 2 | GH79: 1 | GI79: -2 | GJ79: 0 | GK79: =ROUND(R79*(R12)/100,2) -> 0 | GL79: =ROUND(IF(AND(BH79=3,BI79=3,FS79<>0),P79,0),2) -> 0 | GM79: =ROUND(O79+X79+Y79+GK79,2)+GX79 -> 128721.36 | GN79: =IF(OR(BI79=0,BI79=1),GM79,0) -> 0 | GO79: =IF(BI79=2,GM79,0) -> 0 | GP79: =IF(BI79=4,GM79+GX79,0) -> 128721.36 | GR79: 0 | GS79: 3 | GT79: 0 | GV79: =ROUND((GT79),6) -> 0 | GW79: 1 | GX79: =ROUND(HC79*I79,2) -> 0 | HA79: 0 | HB79: 0 | HC79: =GV79*GW79 -> 0 | IK79: 0
A80: 17 | B80: 1 | D80: =ROW(EtalonRes!A42) -> 42 | E80: 14 | F80: 1.50-3203-33-1/1 | G80: Установка и разборка инвентарных лесов внутренних трубчатых при высоте помещений до 6 м (без затрат по эксплуатации лесов) | H80: 100 м2 | I80: 2.837 | J80: 0 | K80: 2.837 | O80: =ROUND(CP80,2) -> 70261.57 | P80: =ROUND(CQ80*I80,2) -> 183.81 | Q80: =ROUND(CR80*I80,2) -> 0 | R80: =ROUND(CS80*I80,2) -> 0 | S80: =ROUND(CT80*I80,2) -> 70077.76 | T80: =ROUND(CU80*I80,2) -> 0 | U80: =CV80*I80 -> 247.30129 | V80: =CW80*I80 -> 0 | W80: =ROUND(CX80*I80,2) -> 0 | X80: =ROUND(CY80,2) -> 49054.43 | Y80: =ROUND(CZ80,2) -> 7007.78 | AA80: 72192302 | AB80: =ROUND((AC80+AD80+AF80),6) -> 24766.15 | AC80: =ROUND((ES80),6) -> 64.79 | AD80: =ROUND((((ET80)-(EU80))+AE80),6) -> 0 | AE80: =ROUND((EU80),6) -> 0 | AF80: =ROUND((EV80),6) -> 24701.36 | AG80: =ROUND((AP80),6) -> 0 | AH80: =(EW80) -> 87.17 | AI80: =(EX80) -> 0 | AJ80: =(AS80) -> 0 | AK80: 24766.15 | AL80: 64.79 | AM80: 0 | AN80: 0 | AO80: 24701.36 | AP80: 0 | AQ80: 87.17 | AR80: 0 | AS80: 0 | AT80: 70 | AU80: 10 | AV80: 1 | AW80: 1 | AZ80: 1 | BA80: 1 | BB80: 1 | BC80: 1 | BH80: 0 | BI80: 4 | BJ80: СН-2012-2024.1. База. Сб.50-3203-33-1/1 | BM80: 0 | BN80: 0 | BP80: 0 | BQ80: 1 | BR80: 0 | BS80: 1 | BT80: 1 | BU80: 1 | BV80: 1 | BW80: 1 | BX80: 1 | BZ80: 70 | CA80: 10 | CE80: 0 | CF80: 0 | CG80: 0 | CM80: 0 | CO80: 0 | CP80: =(P80+Q80+S80) -> 70261.57 | CQ80: =(AC80*BC80*AW80) -> 64.79 | CR80: =((((ET80)*BB80-(EU80)*BS80)+AE80*BS80)*AV80) -> 0 | CS80: =(AE80*BS80*AV80) -> 0 | CT80: =(AF80*BA80*AV80) -> 24701.36 | CU80: =AG80 -> 0 | CV80: =(AH80*AV80) -> 87.17 | CW80: =AI80 -> 0 | CX80: =AJ80 -> 0 | CY80: =((S80*BZ80)/100) -> 49054.432 | CZ80: =((S80*CA80)/100) -> 7007.776 | DN80: 0 | DO80: 0 | DP80: 1 | DQ80: 1 | DU80: 1005 | DV80: 100 м2 | DW80: 100 м2 | DX80: 100 | EE80: 71753531 | EF80: 1 | EG80: СН-2012 | EH80: 0 | EJ80: 4 | EK80: 0 | EL80: Подрядные работы, гл. 1-5,7 | EM80: работа | EQ80: 0 | ER80: 24766.15 | ES80: 64.79 | ET80: 0 | EU80: 0 | EV80: 24701.36 | EW80: 87.17 | EX80: 0 | EY80: 0 | FQ80: 0 | FR80: =ROUND(IF(BI80=3,GM80,0),2) -> 0 | FS80: 0 | FX80: 70 | FY80: 10 | GD80: 0 | GF80: -1679970347 | GG80: 2 | GH80: 1 | GI80: -2 | GJ80: 0 | GK80: =ROUND(R80*(R12)/100,2) -> 0 | GL80: =ROUND(IF(AND(BH80=3,BI80=3,FS80<>0),P80,0),2) -> 0 | GM80: =ROUND(O80+X80+Y80+GK80,2)+GX80 -> 126323.78 | GN80: =IF(OR(BI80=0,BI80=1),GM80,0) -> 0 | GO80: =IF(BI80=2,GM80,0) -> 0 | GP80: =IF(BI80=4,GM80+GX80,0) -> 126323.78 | GR80: 0 | GS80: 3 | GT80: 0 | GV80: =ROUND((GT80),6) -> 0 | GW80: 1 | GX80: =ROUND(HC80*I80,2) -> 0 | HA80: 0 | HB80: 0 | HC80: =GV80*GW80 -> 0 | IK80: 0
A81: 17 | B81: 1 | D81: =ROW(EtalonRes!A48) -> 48 | E81: 15 | F81: 1.13-3103-1-2/1 | G81: Простая штукатурка поверхностей потолков по камню и бетону известковым раствором | H81: 100 м2 | I81: 2.837 | J81: 0 | K81: 2.837 | O81: =ROUND(CP81,2) -> 102593.07 | P81: =ROUND(CQ81*I81,2) -> 30520.73 | Q81: =ROUND(CR81*I81,2) -> 6702.04 | R81: =ROUND(CS81*I81,2) -> 5947.29 | S81: =ROUND(CT81*I81,2) -> 65370.3 | T81: =ROUND(CU81*I81,2) -> 0 | U81: =CV81*I81 -> 193.4834 | V81: =CW81*I81 -> 0 | W81: =ROUND(CX81*I81,2) -> 0 | X81: =ROUND(CY81,2) -> 45759.21 | Y81: =ROUND(CZ81,2) -> 6537.03 | AA81: 72192302 | AB81: =ROUND((AC81+AD81+AF81),6) -> 36162.52 | AC81: =ROUND((ES81),6) -> 10758.1 | AD81: =ROUND((((ET81)-(EU81))+AE81),6) -> 2362.37 | AE81: =ROUND((EU81),6) -> 2096.33 | AF81: =ROUND((EV81),6) -> 23042.05 | AG81: =ROUND((AP81),6) -> 0 | AH81: =(EW81) -> 68.2 | AI81: =(EX81) -> 0 | AJ81: =(AS81) -> 0 | AK81: 36162.52 | AL81: 10758.1 | AM81: 2362.37 | AN81: 2096.33 | AO81: 23042.05 | AP81: 0 | AQ81: 68.2 | AR81: 0 | AS81: 0 | AT81: 70 | AU81: 10 | AV81: 1 | AW81: 1 | AZ81: 1 | BA81: 1 | BB81: 1 | BC81: 1 | BH81: 0 | BI81: 4 | BJ81: СН-2012-2024.1. База. Сб.13-3103-1-2/1 | BM81: 0 | BN81: 0 | BP81: 0 | BQ81: 1 | BR81: 0 | BS81: 1 | BT81: 1 | BU81: 1 | BV81: 1 | BW81: 1 | BX81: 1 | BZ81: 70 | CA81: 10 | CE81: 0 | CF81: 0 | CG81: 0 | CM81: 0 | CO81: 0 | CP81: =(P81+Q81+S81) -> 102593.07 | CQ81: =(AC81*BC81*AW81) -> 10758.1 | CR81: =((((ET81)*BB81-(EU81)*BS81)+AE81*BS81)*AV81) -> 2362.37 | CS81: =(AE81*BS81*AV81) -> 2096.33 | CT81: =(AF81*BA81*AV81) -> 23042.05 | CU81: =AG81 -> 0 | CV81: =(AH81*AV81) -> 68.2 | CW81: =AI81 -> 0 | CX81: =AJ81 -> 0 | CY81: =((S81*BZ81)/100) -> 45759.21 | CZ81: =((S81*CA81)/100) -> 6537.03 | DN81: 0 | DO81: 0 | DP81: 1 | DQ81: 1 | DU81: 1005 | DV81: 100 м2 | DW81: 100 м2 | DX81: 100 | EE81: 71753531 | EF81: 1 | EG81: СН-2012 | EH81: 0 | EJ81: 4 | EK81: 0 | EL81: Подрядные работы, гл. 1-5,7 | EM81: работа | EQ81: 0 | ER81: 36162.52 | ES81: 10758.1 | ET81: 2362.37 | EU81: 2096.33 | EV81: 23042.05 | EW81: 68.2 | EX81: 0 | EY81: 0 | FQ81: 0 | FR81: =ROUND(IF(BI81=3,GM81,0),2) -> 0 | FS81: 0 | FX81: 70 | FY81: 10 | GD81: 0 | GF81: -709330099 | GG81: 2 | GH81: 1 | GI81: -2 | GJ81: 0 | GK81: =ROUND(R81*(R12)/100,2) -> 6423.07 | GL81: =ROUND(IF(AND(BH81=3,BI81=3,FS81<>0),P81,0),2) -> 0 | GM81: =ROUND(O81+X81+Y81+GK81,2)+GX81 -> 161312.38 | GN81: =IF(OR(BI81=0,BI81=1),GM81,0) -> 0 | GO81: =IF(BI81=2,GM81,0) -> 0 | GP81: =IF(BI81=4,GM81+GX81,0) -> 161312.38 | GR81: 0 | GS81: 3 | GT81: 0 | GV81: =ROUND((GT81),6) -> 0 | GW81: 1 | GX81: =ROUND(HC81*I81,2) -> 0 | HA81: 0 | HB81: 0 | HC81: =GV81*GW81 -> 0 | IK81: 0
A82: 17 | B82: 1 | D82: =ROW(EtalonRes!A51) -> 51 | E82: 16 | F82: 1.13-3703-1-2/1 | G82: Обработка поверхностей потолков грунтовкой глубокого проникновения внутри помещения | H82: 100 м2 | I82: 2.837 | J82: 0 | K82: 2.837 | O82: =ROUND(CP82,2) -> 8211.95 | P82: =ROUND(CQ82*I82,2) -> 3074.06 | Q82: =ROUND(CR82*I82,2) -> 1.19 | R82: =ROUND(CS82*I82,2) -> 0.03 | S82: =ROUND(CT82*I82,2) -> 5136.7 | T82: =ROUND(CU82*I82,2) -> 0 | U82: =CV82*I82 -> 18.52561 | V82: =CW82*I82 -> 0 | W82: =ROUND(CX82*I82,2) -> 0 | X82: =ROUND(CY82,2) -> 3595.69 | Y82: =ROUND(CZ82,2) -> 513.67 | AA82: 72192302 | AB82: =ROUND((AC82+AD82+AF82),6) -> 2894.59 | AC82: =ROUND((ES82),6) -> 1083.56 | AD82: =ROUND((((ET82)-(EU82))+AE82),6) -> 0.42 | AE82: =ROUND((EU82),6) -> 0.01 | AF82: =ROUND((EV82),6) -> 1810.61 | AG82: =ROUND((AP82),6) -> 0 | AH82: =(EW82) -> 6.53 | AI82: =(EX82) -> 0 | AJ82: =(AS82) -> 0 | AK82: 2894.59 | AL82: 1083.56 | AM82: 0.42 | AN82: 0.01 | AO82: 1810.61 | AP82: 0 | AQ82: 6.53 | AR82: 0 | AS82: 0 | AT82: 70 | AU82: 10 | AV82: 1 | AW82: 1 | AZ82: 1 | BA82: 1 | BB82: 1 | BC82: 1 | BH82: 0 | BI82: 4 | BJ82: СН-2012-2024.1. База. Сб.13-3703-1-2/1 | BM82: 0 | BN82: 0 | BP82: 0 | BQ82: 1 | BR82: 0 | BS82: 1 | BT82: 1 | BU82: 1 | BV82: 1 | BW82: 1 | BX82: 1 | BZ82: 70 | CA82: 10 | CE82: 0 | CF82: 0 | CG82: 0 | CM82: 0 | CO82: 0 | CP82: =(P82+Q82+S82) -> 8211.95 | CQ82: =(AC82*BC82*AW82) -> 1083.56 | CR82: =((((ET82)*BB82-(EU82)*BS82)+AE82*BS82)*AV82) -> 0.42 | CS82: =(AE82*BS82*AV82) -> 0.01 | CT82: =(AF82*BA82*AV82) -> 1810.61 | CU82: =AG82 -> 0 | CV82: =(AH82*AV82) -> 6.53 | CW82: =AI82 -> 0 | CX82: =AJ82 -> 0 | CY82: =((S82*BZ82)/100) -> 3595.69 | CZ82: =((S82*CA82)/100) -> 513.67 | DN82: 0 | DO82: 0 | DP82: 1 | DQ82: 1 | DU82: 1005 | DV82: 100 м2 | DW82: 100 м2 | DX82: 100 | EE82: 71753531 | EF82: 1 | EG82: СН-2012 | EH82: 0 | EJ82: 4 | EK82: 0 | EL82: Подрядные работы, гл. 1-5,7 | EM82: работа | EQ82: 0 | ER82: 2894.59 | ES82: 1083.56 | ET82: 0.42 | EU82: 0.01 | EV82: 1810.61 | EW82: 6.53 | EX82: 0 | EY82: 0 | FQ82: 0 | FR82: =ROUND(IF(BI82=3,GM82,0),2) -> 0 | FS82: 0 | FX82: 70 | FY82: 10 | GD82: 0 | GF82: 1182519397 | GG82: 2 | GH82: 1 | GI82: -2 | GJ82: 0 | GK82: =ROUND(R82*(R12)/100,2) -> 0.03 | GL82: =ROUND(IF(AND(BH82=3,BI82=3,FS82<>0),P82,0),2) -> 0 | GM82: =ROUND(O82+X82+Y82+GK82,2)+GX82 -> 12321.34 | GN82: =IF(OR(BI82=0,BI82=1),GM82,0) -> 0 | GO82: =IF(BI82=2,GM82,0) -> 0 | GP82: =IF(BI82=4,GM82+GX82,0) -> 12321.34 | GR82: 0 | GS82: 3 | GT82: 0 | GV82: =ROUND((GT82),6) -> 0 | GW82: 1 | GX82: =ROUND(HC82*I82,2) -> 0 | HA82: 0 | HB82: 0 | HC82: =GV82*GW82 -> 0 | IK82: 0
A83: 17 | B83: 1 | D83: =ROW(EtalonRes!A58) -> 58 | E83: 17 | F83: 1.13-3203-26-4/3 | G83: Улучшенная окраска потолков внутри помещений водно-дисперсионными акриловыми красками - краска моющаяся типа ВД-АК-210 | H83: 100 м2 | I83: 2.837 | J83: 0 | K83: 2.837 | O83: =ROUND(CP83,2) -> 76001.56 | P83: =ROUND(CQ83*I83,2) -> 30261.83 | Q83: =ROUND(CR83*I83,2) -> 0 | R83: =ROUND(CS83*I83,2) -> 0 | S83: =ROUND(CT83*I83,2) -> 45739.73 | T83: =ROUND(CU83*I83,2) -> 0 | U83: =CV83*I83 -> 154.24769 | V83: =CW83*I83 -> 0 | W83: =ROUND(CX83*I83,2) -> 0 | X83: =ROUND(CY83,2) -> 32017.81 | Y83: =ROUND(CZ83,2) -> 4573.97 | AA83: 72192302 | AB83: =ROUND((AC83+AD83+AF83),6) -> 26789.41 | AC83: =ROUND((ES83),6) -> 10666.84 | AD83: =ROUND((((ET83)-(EU83))+AE83),6) -> 0 | AE83: =ROUND((EU83),6) -> 0 | AF83: =ROUND((EV83),6) -> 16122.57 | AG83: =ROUND((AP83),6) -> 0 | AH83: =(EW83) -> 54.37 | AI83: =(EX83) -> 0 | AJ83: =(AS83) -> 0 | AK83: 26789.41 | AL83: 10666.84 | AM83: 0 | AN83: 0 | AO83: 16122.57 | AP83: 0 | AQ83: 54.37 | AR83: 0 | AS83: 0 | AT83: 70 | AU83: 10 | AV83: 1 | AW83: 1 | AZ83: 1 | BA83: 1 | BB83: 1 | BC83: 1 | BH83: 0 | BI83: 4 | BJ83: СН-2012-2024.1. База. Сб.13-3203-26-4/3 | BM83: 0 | BN83: 0 | BP83: 0 | BQ83: 1 | BR83: 0 | BS83: 1 | BT83: 1 | BU83: 1 | BV83: 1 | BW83: 1 | BX83: 1 | BZ83: 70 | CA83: 10 | CE83: 0 | CF83: 0 | CG83: 0 | CM83: 0 | CO83: 0 | CP83: =(P83+Q83+S83) -> 76001.56 | CQ83: =(AC83*BC83*AW83) -> 10666.84 | CR83: =((((ET83)*BB83-(EU83)*BS83)+AE83*BS83)*AV83) -> 0 | CS83: =(AE83*BS83*AV83) -> 0 | CT83: =(AF83*BA83*AV83) -> 16122.57 | CU83: =AG83 -> 0 | CV83: =(AH83*AV83) -> 54.37 | CW83: =AI83 -> 0 | CX83: =AJ83 -> 0 | CY83: =((S83*BZ83)/100) -> 32017.811 | CZ83: =((S83*CA83)/100) -> 4573.973 | DN83: 0 | DO83: 0 | DP83: 1 | DQ83: 1 | DU83: 1005 | DV83: 100 м2 | DW83: 100 м2 | DX83: 100 | EE83: 71753531 | EF83: 1 | EG83: СН-2012 | EH83: 0 | EJ83: 4 | EK83: 0 | EL83: Подрядные работы, гл. 1-5,7 | EM83: работа | EQ83: 0 | ER83: 26789.41 | ES83: 10666.84 | ET83: 0 | EU83: 0 | EV83: 16122.57 | EW83: 54.37 | EX83: 0 | EY83: 0 | FQ83: 0 | FR83: =ROUND(IF(BI83=3,GM83,0),2) -> 0 | FS83: 0 | FX83: 70 | FY83: 10 | GD83: 0 | GF83: 772958837 | GG83: 2 | GH83: 1 | GI83: -2 | GJ83: 0 | GK83: =ROUND(R83*(R12)/100,2) -> 0 | GL83: =ROUND(IF(AND(BH83=3,BI83=3,FS83<>0),P83,0),2) -> 0 | GM83: =ROUND(O83+X83+Y83+GK83,2)+GX83 -> 112593.34 | GN83: =IF(OR(BI83=0,BI83=1),GM83,0) -> 0 | GO83: =IF(BI83=2,GM83,0) -> 0 | GP83: =IF(BI83=4,GM83+GX83,0) -> 112593.34 | GR83: 0 | GS83: 3 | GT83: 0 | GV83: =ROUND((GT83),6) -> 0 | GW83: 1 | GX83: =ROUND(HC83*I83,2) -> 0 | HA83: 0 | HB83: 0 | HC83: =GV83*GW83 -> 0 | IK83: 0
A84: 17 | B84: 1 | D84: =ROW(EtalonRes!A68) -> 68 | E84: 18 | F84: 1.10-3803-1-11/1 | G84: Устройство плинтусов - поливинилхлоридных на винтах самонарезающих с креплением через защёлку / с мягким краем, размеры 50-62х21 мм | H84: 100 м | I84: 0.6504 | J84: 0 | K84: 0.6504 | O84: =ROUND(CP84,2) -> 7019.83 | P84: =ROUND(CQ84*I84,2) -> 3799.73 | Q84: =ROUND(CR84*I84,2) -> 245.19 | R84: =ROUND(CS84*I84,2) -> 5.77 | S84: =ROUND(CT84*I84,2) -> 2974.91 | T84: =ROUND(CU84*I84,2) -> 0 | U84: =CV84*I84 -> 10.998264 | V84: =CW84*I84 -> 0 | W84: =ROUND(CX84*I84,2) -> 0 | X84: =ROUND(CY84,2) -> 2082.44 | Y84: =ROUND(CZ84,2) -> 297.49 | AA84: 72192302 | AB84: =ROUND((AC84+AD84+AF84),6) -> 10793.11 | AC84: =ROUND((ES84),6) -> 5842.15 | AD84: =ROUND((((ET84)-(EU84))+AE84),6) -> 376.99 | AE84: =ROUND((EU84),6) -> 8.87 | AF84: =ROUND((EV84),6) -> 4573.97 | AG84: =ROUND((AP84),6) -> 0 | AH84: =(EW84) -> 16.91 | AI84: =(EX84) -> 0 | AJ84: =(AS84) -> 0 | AK84: 10793.11 | AL84: 5842.15 | AM84: 376.99 | AN84: 8.87 | AO84: 4573.97 | AP84: 0 | AQ84: 16.91 | AR84: 0 | AS84: 0 | AT84: 70 | AU84: 10 | AV84: 1 | AW84: 1 | AZ84: 1 | BA84: 1 | BB84: 1 | BC84: 1 | BH84: 0 | BI84: 4 | BJ84: СН-2012-2024.1. База. Сб.10-3803-1-11/1 | BM84: 0 | BN84: 0 | BP84: 0 | BQ84: 1 | BR84: 0 | BS84: 1 | BT84: 1 | BU84: 1 | BV84: 1 | BW84: 1 | BX84: 1 | BZ84: 70 | CA84: 10 | CE84: 0 | CF84: 0 | CG84: 0 | CM84: 0 | CO84: 0 | CP84: =(P84+Q84+S84) -> 7019.83 | CQ84: =(AC84*BC84*AW84) -> 5842.15 | CR84: =((((ET84)*BB84-(EU84)*BS84)+AE84*BS84)*AV84) -> 376.99 | CS84: =(AE84*BS84*AV84) -> 8.87 | CT84: =(AF84*BA84*AV84) -> 4573.97 | CU84: =AG84 -> 0 | CV84: =(AH84*AV84) -> 16.91 | CW84: =AI84 -> 0 | CX84: =AJ84 -> 0 | CY84: =((S84*BZ84)/100) -> 2082.437 | CZ84: =((S84*CA84)/100) -> 297.491 | DN84: 0 | DO84: 0 | DP84: 1 | DQ84: 1 | DU84: 1003 | DV84: 100 м | DW84: 100 м | DX84: 100 | EE84: 71753531 | EF84: 1 | EG84: СН-2012 | EH84: 0 | EJ84: 4 | EK84: 0 | EL84: Подрядные работы, гл. 1-5,7 | EM84: работа | EQ84: 0 | ER84: 10793.11 | ES84: 5842.15 | ET84: 376.99 | EU84: 8.87 | EV84: 4573.97 | EW84: 16.91 | EX84: 0 | EY84: 0 | FQ84: 0 | FR84: =ROUND(IF(BI84=3,GM84,0),2) -> 0 | FS84: 0 | FX84: 70 | FY84: 10 | GD84: 0 | GF84: 631304529 | GG84: 2 | GH84: 1 | GI84: -2 | GJ84: 0 | GK84: =ROUND(R84*(R12)/100,2) -> 6.23 | GL84: =ROUND(IF(AND(BH84=3,BI84=3,FS84<>0),P84,0),2) -> 0 | GM84: =ROUND(O84+X84+Y84+GK84,2)+GX84 -> 9405.99 | GN84: =IF(OR(BI84=0,BI84=1),GM84,0) -> 0 | GO84: =IF(BI84=2,GM84,0) -> 0 | GP84: =IF(BI84=4,GM84+GX84,0) -> 9405.99 | GR84: 0 | GS84: 3 | GT84: 0 | GV84: =ROUND((GT84),6) -> 0 | GW84: 1 | GX84: =ROUND(HC84*I84,2) -> 0 | HA84: 0 | HB84: 0 | HC84: =GV84*GW84 -> 0 | IK84: 0
A85: 17 | B85: 1 | D85: =ROW(EtalonRes!A72) -> 72 | E85: 19 | F85: 1.26-3103-3-1/2 | G85: Установка штучных изделий столов, шкафов под мойки, холодильных шкафов и др. (без стоимости изделий) | H85: 100 шт. | I85: 0.04 | J85: 0 | K85: 0.04 | O85: =ROUND(CP85,2) -> 1287.16 | P85: =ROUND(CQ85*I85,2) -> 487.54 | Q85: =ROUND(CR85*I85,2) -> 0 | R85: =ROUND(CS85*I85,2) -> 0 | S85: =ROUND(CT85*I85,2) -> 799.62 | T85: =ROUND(CU85*I85,2) -> 0 | U85: =CV85*I85 -> 3.1144 | V85: =CW85*I85 -> 0 | W85: =ROUND(CX85*I85,2) -> 0 | X85: =ROUND(CY85,2) -> 559.73 | Y85: =ROUND(CZ85,2) -> 79.96 | AA85: 72192302 | AB85: =ROUND((AC85+AD85+AF85),6) -> 32178.99 | AC85: =ROUND((ES85),6) -> 12188.43 | AD85: =ROUND((((ET85)-(EU85))+AE85),6) -> 0 | AE85: =ROUND((EU85),6) -> 0 | AF85: =ROUND((EV85),6) -> 19990.56 | AG85: =ROUND((AP85),6) -> 0 | AH85: =(EW85) -> 77.86 | AI85: =(EX85) -> 0 | AJ85: =(AS85) -> 0 | AK85: 32178.99 | AL85: 12188.43 | AM85: 0 | AN85: 0 | AO85: 19990.56 | AP85: 0 | AQ85: 77.86 | AR85: 0 | AS85: 0 | AT85: 70 | AU85: 10 | AV85: 1 | AW85: 1 | AZ85: 1 | BA85: 1 | BB85: 1 | BC85: 1 | BH85: 0 | BI85: 4 | BJ85: СН-2012-2024.1. База. Сб.26-3103-3-1/2 | BM85: 0 | BN85: 0 | BP85: 0 | BQ85: 1 | BR85: 0 | BS85: 1 | BT85: 1 | BU85: 1 | BV85: 1 | BW85: 1 | BX85: 1 | BZ85: 70 | CA85: 10 | CE85: 0 | CF85: 0 | CG85: 0 | CM85: 0 | CO85: 0 | CP85: =(P85+Q85+S85) -> 1287.16 | CQ85: =(AC85*BC85*AW85) -> 12188.43 | CR85: =((((ET85)*BB85-(EU85)*BS85)+AE85*BS85)*AV85) -> 0 | CS85: =(AE85*BS85*AV85) -> 0 | CT85: =(AF85*BA85*AV85) -> 19990.56 | CU85: =AG85 -> 0 | CV85: =(AH85*AV85) -> 77.86 | CW85: =AI85 -> 0 | CX85: =AJ85 -> 0 | CY85: =((S85*BZ85)/100) -> 559.734 | CZ85: =((S85*CA85)/100) -> 79.962 | DN85: 0 | DO85: 0 | DP85: 1 | DQ85: 1 | DU85: 1010 | DV85: 100 шт. | DW85: 100 шт. | DX85: 100 | EE85: 71753531 | EF85: 1 | EG85: СН-2012 | EH85: 0 | EJ85: 4 | EK85: 0 | EL85: Подрядные работы, гл. 1-5,7 | EM85: работа | EQ85: 0 | ER85: 32178.99 | ES85: 12188.43 | ET85: 0 | EU85: 0 | EV85: 19990.56 | EW85: 77.86 | EX85: 0 | EY85: 0 | FQ85: 0 | FR85: =ROUND(IF(BI85=3,GM85,0),2) -> 0 | FS85: 0 | FX85: 70 | FY85: 10 | GD85: 0 | GF85: -1457482948 | GG85: 2 | GH85: 1 | GI85: -2 | GJ85: 0 | GK85: =ROUND(R85*(R12)/100,2) -> 0 | GL85: =ROUND(IF(AND(BH85=3,BI85=3,FS85<>0),P85,0),2) -> 0 | GM85: =ROUND(O85+X85+Y85+GK85,2)+GX85 -> 1926.85 | GN85: =IF(OR(BI85=0,BI85=1),GM85,0) -> 0 | GO85: =IF(BI85=2,GM85,0) -> 0 | GP85: =IF(BI85=4,GM85+GX85,0) -> 1926.85 | GR85: 0 | GS85: 3 | GT85: 0 | GV85: =ROUND((GT85),6) -> 0 | GW85: 1 | GX85: =ROUND(HC85*I85,2) -> 0 | HA85: 0 | HB85: 0 | HC85: =GV85*GW85 -> 0 | IK85: 0
A86: 18 | B86: 1 | E86: 20 | F86: Цена поставщика | G86: Шведская стенка деревянная с турником 1x3 м или эквивалент | H86: шт. | I86: =I85*J86 -> 4 | J86: 100 | K86: 100 | O86: =ROUND(CP86,2) -> 34180.2 | P86: =ROUND(CQ86*I86,2) -> 34180.2 | Q86: =ROUND(CR86*I86,2) -> 0 | R86: =ROUND(CS86*I86,2) -> 0 | S86: =ROUND(CT86*I86,2) -> 0 | T86: =ROUND(CU86*I86,2) -> 0 | U86: =CV86*I86 -> 0 | V86: =CW86*I86 -> 0 | W86: =ROUND(CX86*I86,2) -> 0 | X86: =ROUND(CY86,2) -> 0 | Y86: =ROUND(CZ86,2) -> 0 | AA86: 72192302 | AB86: =ROUND((AC86+AD86+AF86),6) -> 8545.05 | AC86: =ROUND((ES86),6) -> 8545.05 | AD86: =ROUND((((ET86)-(EU86))+AE86),6) -> 0 | AE86: =ROUND((EU86),6) -> 0 | AF86: =ROUND((EV86),6) -> 0 | AG86: =ROUND((AP86),6) -> 0 | AH86: =(EW86) -> 0 | AI86: =(EX86) -> 0 | AJ86: =(AS86) -> 0 | AK86: 8545.05 | AL86: 8545.05 | AM86: 0 | AN86: 0 | AO86: 0 | AP86: 0 | AQ86: 0 | AR86: 0 | AS86: 0 | AT86: 70 | AU86: 10 | AV86: 1 | AW86: 1 | AZ86: 1 | BA86: 1 | BB86: 1 | BC86: 1 | BH86: 3 | BI86: 4 | BM86: 0 | BN86: 0 | BP86: 0 | BQ86: 1 | BR86: 0 | BS86: 1 | BT86: 1 | BU86: 1 | BV86: 1 | BW86: 1 | BX86: 1 | BZ86: 70 | CA86: 10 | CE86: 0 | CF86: 0 | CG86: 0 | CM86: 0 | CO86: 0 | CP86: =(P86+Q86+S86) -> 34180.2 | CQ86: =(AC86*BC86*AW86) -> 8545.05 | CR86: =((((ET86)*BB86-(EU86)*BS86)+AE86*BS86)*AV86) -> 0 | CS86: =(AE86*BS86*AV86) -> 0 | CT86: =(AF86*BA86*AV86) -> 0 | CU86: =AG86 -> 0 | CV86: =(AH86*AV86) -> 0 | CW86: =AI86 -> 0 | CX86: =AJ86 -> 0 | CY86: =((S86*BZ86)/100) -> 0 | CZ86: =((S86*CA86)/100) -> 0 | DN86: 0 | DO86: 0 | DP86: 1 | DQ86: 1 | DU86: 1010 | DV86: шт. | DW86: шт. | DX86: 1 | EE86: 71753531 | EF86: 1 | EG86: СН-2012 | EH86: 0 | EJ86: 4 | EK86: 0 | EL86: Подрядные работы, гл. 1-5,7 | EM86: работа | EQ86: 0 | ER86: 8545.05 | ES86: 8545.05 | ET86: 0 | EU86: 0 | EV86: 0 | EW86: 0 | EX86: 0 | FQ86: 0 | FR86: =ROUND(IF(BI86=3,GM86,0),2) -> 0 | FS86: 0 | FX86: 70 | FY86: 10 | GD86: 0 | GF86: 1111623754 | GG86: 2 | GH86: 0 | GI86: -2 | GJ86: 0 | GK86: =ROUND(R86*(R12)/100,2) -> 0 | GL86: =ROUND(IF(AND(BH86=3,BI86=3,FS86<>0),P86,0),2) -> 0 | GM86: =ROUND(O86+X86+Y86+GK86,2)+GX86 -> 34180.2 | GN86: =IF(OR(BI86=0,BI86=1),GM86,0) -> 0 | GO86: =IF(BI86=2,GM86,0) -> 0 | GP86: =IF(BI86=4,GM86+GX86,0) -> 34180.2 | GR86: 0 | GS86: 0 | GT86: 0 | GV86: =ROUND((GT86),6) -> 0 | GW86: 1 | GX86: =ROUND(HC86*I86,2) -> 0 | HA86: 0 | HB86: 0 | HC86: =GV86*GW86 -> 0 | IK86: 0
A88: 51 | B88: =B73 -> 1 | C88: =A73 -> 5 | D88: =ROW(A73) -> 73 | F88: =IF(F73<>"",F73,"") -> Новый подраздел | G88: =IF(G73<>"",G73,"") -> 1.2 Ремонтно-строительные работы | H88: 0 | O88: =ROUND(AB88,2) -> 531337.61 | P88: =ROUND(AC88,2) -> 194371.06 | Q88: =ROUND(AD88,2) -> 16302.94 | R88: =ROUND(AE88,2) -> 14252.71 | S88: =ROUND(AF88,2) -> 320663.61 | T88: =ROUND(AG88,2) -> 0 | U88: =AH88 -> 1068.9519 | V88: =AI88 -> 0 | W88: =ROUND(AJ88,2) -> 0 | X88: =ROUND(AK88,2) -> 224464.53 | Y88: =ROUND(AL88,2) -> 32066.35 | AB88: =ROUND(SUMIF(AA77:AA86,"=72192302",O77:O86),2) -> 531337.61 | AC88: =ROUND(SUMIF(AA77:AA86,"=72192302",P77:P86),2) -> 194371.06 | AD88: =ROUND(SUMIF(AA77:AA86,"=72192302",Q77:Q86),2) -> 16302.94 | AE88: =ROUND(SUMIF(AA77:AA86,"=72192302",R77:R86),2) -> 14252.71 | AF88: =ROUND(SUMIF(AA77:AA86,"=72192302",S77:S86),2) -> 320663.61 | AG88: =ROUND(SUMIF(AA77:AA86,"=72192302",T77:T86),2) -> 0 | AH88: =SUMIF(AA77:AA86,"=72192302",U77:U86) -> 1068.9519 | AI88: =SUMIF(AA77:AA86,"=72192302",V77:V86) -> 0 | AJ88: =ROUND(SUMIF(AA77:AA86,"=72192302",W77:W86),2) -> 0 | AK88: =ROUND(SUMIF(AA77:AA86,"=72192302",X77:X86),2) -> 224464.53 | AL88: =ROUND(SUMIF(AA77:AA86,"=72192302",Y77:Y86),2) -> 32066.35 | AO88: =ROUND(BX88,2) -> 0 | AP88: =ROUND(BY88,2) -> 0 | AQ88: =ROUND(BZ88,2) -> 0 | AR88: =ROUND(CA88,2) -> 803261.41 | AS88: =ROUND(CB88,2) -> 0 | AT88: =ROUND(CC88,2) -> 0 | AU88: =ROUND(CD88,2) -> 803261.41 | AV88: =ROUND(CE88,2) -> 194371.06 | ... BD88: =ROUND(CM88,2) -> 0 | BX88: =ROUND(SUMIF(AA77:AA86,"=72192302",FQ77:FQ86),2) -> 0 | BY88: =ROUND(SUMIF(AA77:AA86,"=72192302",FR77:FR86),2) -> 0 | BZ88: =ROUND(SUMIF(AA77:AA86,"=72192302",GL77:GL86),2) -> 0 | CA88: =ROUND(SUMIF(AA77:AA86,"=72192302",GM77:GM86),2) -> 803261.41 | CB88: =ROUND(SUMIF(AA77:AA86,"=72192302",GN77:GN86),2) -> 0 | CC88: =ROUND(SUMIF(AA77:AA86,"=72192302",GO77:GO86),2) -> 0 | CD88: =ROUND(SUMIF(AA77:AA86,"=72192302",GP77:GP86),2) -> 803261.41 | CE88: =AC88-BX88 -> 194371.06 | CF88: =AC88-BY88 -> 194371.06 | CG88: =BX88-BZ88 -> 0 | CH88: =AC88-BX88-BY88+BZ88 -> 194371.06 | CI88: =BY88-BZ88 -> 0 | CJ88: =ROUND(SUMIF(AA77:AA86,"=72192302",GX77:GX86),2) -> 0 | CK88: =ROUND(SUMIF(AA77:AA86,"=72192302",GY77:GY86),2) -> 0 | CL88: =ROUND(SUMIF(AA77:AA86,"=72192302",GZ77:GZ86),2) -> 0 | CM88: =ROUND(SUMIF(AA77:AA86,"=72192302",HD77:HD86),2) -> 0 | GX88: 0
A90: 50 | B90: 0 | C90: 0 | D90: 1 | E90: 201 | F90: =ROUND(Source!O88,O90) -> 531337.61 | G90: ПЗ | H90: Прямые затраты | K90: 201 | L90: 1 | M90: 3 | O90: 2 | W90: 531337.61 | X90: 1 | Y90: 531337.61
A91: 50 | B91: 0 | C91: 0 | D91: 1 | E91: 202 | F91: =ROUND(Source!P88,O91) -> 194371.06 | G91: СтМатОб | H91: Стоимость материальных ресурсов (всего) | K91: 202 | L91: 2 | M91: 3 | O91: 2 | W91: 194371.06 | X91: 1 | Y91: 194371.06
A92: 50 | B92: 0 | C92: 0 | D92: 1 | E92: 222 | F92: =ROUND(Source!AO88,O92) -> 0 | G92: СтМатОбЗак | H92: Стоимость материалов и оборудования заказчика | K92: 222 | L92: 3 | M92: 3 | O92: 2 | W92: 0 | X92: 1 | Y92: 0
A93: 50 | B93: 0 | C93: 0 | D93: 1 | E93: 225 | F93: =ROUND(Source!AV88,O93) -> 194371.06 | G93: СтМатОбПод | H93: Стоимость материалов и оборудования подрядчика | K93: 225 | L93: 4 | M93: 3 | O93: 2 | W93: 194371.06 | X93: 1 | Y93: 194371.06
A94: 50 | B94: 0 | C94: 0 | D94: 1 | E94: 226 | F94: =ROUND(Source!AW88,O94) -> 194371.06 | G94: СтМат | H94: Стоимость материалов (всего) | K94: 226 | L94: 5 | M94: 3 | O94: 2 | W94: 194371.06 | X94: 1 | Y94: 194371.06
A95: 50 | B95: 0 | C95: 0 | D95: 1 | E95: 227 | F95: =ROUND(Source!AX88,O95) -> 0 | G95: СтМатЗак | H95: Стоимость материалов заказчика | K95: 227 | L95: 6 | M95: 3 | O95: 2 | W95: 0 | X95: 1 | Y95: 0
A96: 50 | B96: 0 | C96: 0 | D96: 1 | E96: 228 | F96: =ROUND(Source!AY88,O96) -> 194371.06 | G96: СтМатПод | H96: Стоимость материалов подрядчика | K96: 228 | L96: 7 | M96: 3 | O96: 2 | W96: 194371.06 | X96: 1 | Y96: 194371.06
A97: 50 | B97: 0 | C97: 0 | D97: 1 | E97: 216 | F97: =ROUND(Source!AP88,O97) -> 0 | G97: Оборуд | H97: Стоимость оборудования (всего) | K97: 216 | L97: 8 | M97: 3 | O97: 2 | W97: 0 | X97: 1 | Y97: 0
A98: 50 | B98: 0 | C98: 0 | D98: 1 | E98: 223 | F98: =ROUND(Source!AQ88,O98) -> 0 | G98: ОборудЗак | H98: Стоимость оборудования заказчика | K98: 223 | L98: 9 | M98: 3 | O98: 2 | W98: 0 | X98: 1 | Y98: 0
A99: 50 | B99: 0 | C99: 0 | D99: 1 | E99: 229 | F99: =ROUND(Source!AZ88,O99) -> 0 | G99: ОборудПод | H99: Стоимость оборудования подрядчика | K99: 229 | L99: 10 | M99: 3 | O99: 2 | W99: 0 | X99: 1 | Y99: 0
A100: 50 | B100: 0 | C100: 0 | D100: 1 | E100: 203 | F100: =ROUND(Source!Q88,O100) -> 16302.94 | G100: ЭММ | H100: Эксплуатация машин | K100: 203 | L100: 11 | M100: 3 | O100: 2 | W100: 16302.94 | X100: 1 | Y100: 16302.94
A101: 50 | B101: 0 | C101: 0 | D101: 1 | E101: 231 | F101: =ROUND(Source!BB88,O101) -> 0 | G101: ЭММсНРиСП | H101: Эксплуатация машин по ТСН-2001.16 | K101: 231 | L101: 12 | M101: 3 | O101: 2 | W101: 0 | X101: 1 | Y101: 0
A102: 50 | B102: 0 | C102: 0 | D102: 1 | E102: 204 | F102: =ROUND(Source!R88,O102) -> 14252.71 | G102: ЗПМ | H102: ЗП машинистов | K102: 204 | L102: 13 | M102: 3 | O102: 2 | W102: 14252.71 | X102: 1 | Y102: 14252.71
A103: 50 | B103: 0 | C103: 0 | D103: 1 | E103: 205 | F103: =ROUND(Source!S88,O103) -> 320663.61 | G103: ОЗП | H103: Основная ЗП рабочих | K103: 205 | L103: 14 | M103: 3 | O103: 2 | W103: 320663.61 | X103: 1 | Y103: 320663.61
A104: 50 | B104: 0 | C104: 0 | D104: 1 | E104: 232 | F104: =ROUND(Source!BC88,O104) -> 0 | G104: ОЗПсНРиСП | H104: Основная ЗП рабочих по ТСН-2001.16 | K104: 232 | L104: 15 | M104: 3 | O104: 2 | W104: 0 | X104: 1 | Y104: 0
A105: 50 | B105: 0 | C105: 0 | D105: 1 | E105: 214 | F105: =ROUND(Source!AS88,O105) -> 0 | G105: Строит | H105: Строительные работы с НР и СП | K105: 214 | L105: 16 | M105: 3 | O105: 2 | W105: 0 | X105: 1 | Y105: 0
A106: 50 | B106: 0 | C106: 0 | D106: 1 | E106: 215 | F106: =ROUND(Source!AT88,O106) -> 0 | G106: Монтаж | H106: Монтажные работы с НР и СП | K106: 215 | L106: 17 | M106: 3 | O106: 2 | W106: 0 | X106: 1 | Y106: 0
A107: 50 | B107: 0 | C107: 0 | D107: 1 | E107: 217 | F107: =ROUND(Source!AU88,O107) -> 803261.41 | G107: Прочие | H107: Прочие работы с НР и СП | K107: 217 | L107: 18 | M107: 3 | O107: 2 | W107: 803261.41 | X107: 1 | Y107: 803261.41
A108: 50 | B108: 0 | C108: 0 | D108: 1 | E108: 230 | F108: =ROUND(Source!BA88,O108) -> 0 | G108: ПрочиеЗатр | H108: Прочие затраты по ТСН-2001.16 | K108: 230 | L108: 19 | M108: 3 | O108: 2 | W108: 0 | X108: 1 | Y108: 0
A109: 50 | B109: 0 | C109: 0 | D109: 1 | E109: 206 | F109: =ROUND(Source!T88,O109) -> 0 | G109: ВозврМат | H109: Возврат материалов | K109: 206 | L109: 20 | M109: 3 | O109: 2 | W109: 0 | X109: 1 | Y109: 0
A110: 50 | B110: 0 | C110: 0 | D110: 1 | E110: 207 | F110: =Source!U88 -> 1068.9519 | G110: ТрудСтр | H110: Трудозатраты строителей | K110: 207 | L110: 21 | M110: 3 | O110: -1 | W110: 1068.9519 | X110: 1 | Y110: 1068.9519
A111: 50 | B111: 0 | C111: 0 | D111: 1 | E111: 208 | F111: =Source!V88 -> 0 | G111: ТрудМаш | H111: Трудозатраты машинистов | K111: 208 | L111: 22 | M111: 3 | O111: -1 | W111: 0 | X111: 1 | Y111: 0
A112: 50 | B112: 0 | C112: 0 | D112: 1 | E112: 209 | F112: =ROUND(Source!W88,O112) -> 0 | G112: ТранспМат | H112: Транспорт материалов | K112: 209 | L112: 23 | M112: 3 | O112: 2 | W112: 0 | X112: 1 | Y112: 0
A113: 50 | B113: 0 | C113: 0 | D113: 1 | E113: 233 | F113: =ROUND(Source!BD88,O113) -> 0 | G113: Перевозка | H113: Перевозка грузов | K113: 233 | L113: 24 | M113: 3 | O113: 2 | W113: 0 | X113: 1 | Y113: 0
A114: 50 | B114: 0 | C114: 0 | D114: 1 | E114: 210 | F114: =ROUND(Source!X88,O114) -> 224464.53 | G114: НР | H114: Накладные расходы | K114: 210 | L114: 25 | M114: 3 | O114: 2 | W114: 224464.53 | X114: 1 | Y114: 224464.53
A115: 50 | B115: 0 | C115: 0 | D115: 1 | E115: 211 | F115: =ROUND(Source!Y88,O115) -> 32066.35 | G115: СмПриб | H115: Сметная прибыль | K115: 211 | L115: 26 | M115: 3 | O115: 2 | W115: 32066.35 | X115: 1 | Y115: 32066.35
A116: 50 | B116: 0 | C116: 0 | D116: 1 | E116: 224 | F116: =ROUND(Source!AR88,O116) -> 803261.41 | G116: Всего | H116: Всего с НР и СП | K116: 224 | L116: 27 | M116: 3 | O116: 2 | W116: 803261.41 | X116: 1 | Y116: 803261.41
A118: 5 | B118: 1 | D118: =ROW(A140) -> 140 | F118: Новый подраздел | G118: 1.3 Сантехнические работы | I118: 0 | K118: 0 | S118: 0 | V118: 0 | BX118: 0 | CJ118: 0
A120: 52 | B120: =B140 -> 1 | C120: =C140 -> 5 | D120: =D140 -> 118 | E120: =E140 -> 0 | F120: =F140 -> Новый подраздел | G120: =G140 -> 1.3 Сантехнические работы | O120: =O140 -> 418403.53 | P120: =P140 -> 391109.9 | Q120: =Q140 -> 8.64 | R120: =R140 -> 0.35 | S120: =S140 -> 27284.99 | T120: =T140 -> 0 | U120: =U140 -> 84.708481 | V120: =V140 -> 0 | ... GX120: =GX140 -> 0
A122: 17 | B122: 1 | D122: =ROW(EtalonRes!A78) -> 78 | E122: 21 | F122: 1.17-3303-1-2/5 | G122: Установка радиаторов биметаллических "Рифар" / 10 секций, размеры 261х100х800 мм, теплоотдача 1010 Вт | H122: 100 квт | I122: =ROUND(1.96*26/100,9) -> 0.5096 | J122: 0 | K122: =ROUND(1.96*26/100,9) -> 0.5096 | O122: =ROUND(CP122,2) -> 405450.16 | P122: =ROUND(CQ122*I122,2) -> 395006.03 | Q122: =ROUND(CR122*I122,2) -> 1.07 | R122: =ROUND(CS122*I122,2) -> 0.16 | S122: =ROUND(CT122*I122,2) -> 10443.06 | T122: =ROUND(CU122*I122,2) -> 0 | U122: =CV122*I122 -> 34.632416 | V122: =CW122*I122 -> 0 | W122: =ROUND(CX122*I122,2) -> 0 | X122: =ROUND(CY122,2) -> 7310.14 | Y122: =ROUND(CZ122,2) -> 1044.31 | AA122: 72192302 | AB122: =ROUND((AC122+AD122+AF122),6) -> 795624.33 | AC122: =ROUND((ES122),6) -> 775129.57 | AD122: =ROUND((((ET122)-(EU122))+AE122),6) -> 2.1 | AE122: =ROUND((EU122),6) -> 0.32 | AF122: =ROUND((EV122),6) -> 20492.66 | AG122: =ROUND((AP122),6) -> 0 | AH122: =(EW122) -> 67.96 | AI122: =(EX122) -> 0 | AJ122: =(AS122) -> 0 | AK122: 795624.33 | AL122: 775129.57 | AM122: 2.1 | AN122: 0.32 | AO122: 20492.66 | AP122: 0 | AQ122: 67.96 | AR122: 0 | AS122: 0 | AT122: 70 | AU122: 10 | AV122: 1 | AW122: 1 | AZ122: 1 | BA122: 1 | BB122: 1 | BC122: 1 | BH122: 0 | BI122: 4 | BJ122: СН-2012-2024.1. База. Сб.17-3303-1-2/5 | BM122: 0 | BN122: 0 | BP122: 0 | BQ122: 1 | BR122: 0 | BS122: 1 | BT122: 1 | BU122: 1 | BV122: 1 | BW122: 1 | BX122: 1 | BZ122: 70 | CA122: 10 | CE122: 0 | CF122: 0 | CG122: 0 | CM122: 0 | CO122: 0 | CP122: =(P122+Q122+S122) -> 405450.16 | CQ122: =(AC122*BC122*AW122) -> 775129.57 | CR122: =((((ET122)*BB122-(EU122)*BS122)+AE122*BS122)*AV122) -> 2.1 | CS122: =(AE122*BS122*AV122) -> 0.32 | CT122: =(AF122*BA122*AV122) -> 20492.66 | CU122: =AG122 -> 0 | CV122: =(AH122*AV122) -> 67.96 | CW122: =AI122 -> 0 | CX122: =AJ122 -> 0 | CY122: =((S122*BZ122)/100) -> 7310.142 | CZ122: =((S122*CA122)/100) -> 1044.306 | DN122: 0 | DO122: 0 | DP122: 1 | DQ122: 1 | DU122: 1013 | DV122: 100 квт | DW122: 100 квт | DX122: 1 | EE122: 71753531 | EF122: 1 | EG122: СН-2012 | EH122: 0 | EJ122: 4 | EK122: 0 | EL122: Подрядные работы, гл. 1-5,7 | EM122: работа | EQ122: 0 | ER122: 795624.33 | ES122: 775129.57 | ET122: 2.1 | EU122: 0.32 | EV122: 20492.66 | EW122: 67.96 | EX122: 0 | EY122: 0 | FQ122: 0 | FR122: =ROUND(IF(BI122=3,GM122,0),2) -> 0 | FS122: 0 | FX122: 70 | FY122: 10 | GD122: 0 | GF122: 1046146772 | GG122: 2 | GH122: 1 | GI122: -2 | GJ122: 0 | GK122: =ROUND(R122*(R12)/100,2) -> 0.17 | GL122: =ROUND(IF(AND(BH122=3,BI122=3,FS122<>0),P122,0),2) -> 0 | GM122: =ROUND(O122+X122+Y122+GK122,2)+GX122 -> 413804.78 | GN122: =IF(OR(BI122=0,BI122=1),GM122,0) -> 0 | GO122: =IF(BI122=2,GM122,0) -> 0 | GP122: =IF(BI122=4,GM122+GX122,0) -> 413804.78 | GR122: 0 | GS122: 3 | GT122: 0 | GV122: =ROUND((GT122),6) -> 0 | GW122: 1 | GX122: =ROUND(HC122*I122,2) -> 0 | HA122: 0 | HB122: 0 | HC122: =GV122*GW122 -> 0 | IK122: 0
A123: 18 | B123: 1 | E123: 22 | F123: 21.18-4-174 | G123: Радиаторы биметаллические секционные "Рифар", межосевое расстояние 200 мм, 10 секций, размеры 261х100х800 мм, теплоотдача 1010 Вт | H123: шт. | I123: =I122*J123 -> -50.455496 | J123: -99.01 | K123: -99.01 | O123: =ROUND(CP123,2) -> -391446.86 | P123: =ROUND(CQ123*I123,2) -> -391446.86 | Q123: =ROUND(CR123*I123,2) -> 0 | R123: =ROUND(CS123*I123,2) -> 0 | S123: =ROUND(CT123*I123,2) -> 0 | T123: =ROUND(CU123*I123,2) -> 0 | U123: =CV123*I123 -> 0 | V123: =CW123*I123 -> 0 | W123: =ROUND(CX123*I123,2) -> 0 | X123: =ROUND(CY123,2) -> 0 | Y123: =ROUND(CZ123,2) -> 0 | AA123: 72192302 | AB123: =ROUND((AC123+AD123+AF123),6) -> 7758.26 | AC123: =ROUND((ES123),6) -> 7758.26 | AD123: =ROUND((((ET123)-(EU123))+AE123),6) -> 0 | AE123: =ROUND((EU123),6) -> 0 | AF123: =ROUND((EV123),6) -> 0 | AG123: =ROUND((AP123),6) -> 0 | AH123: =(EW123) -> 0 | AI123: =(EX123) -> 0 | AJ123: =(AS123) -> 0 | AK123: 7758.26 | AL123: 7758.26 | AM123: 0 | AN123: 0 | AO123: 0 | AP123: 0 | AQ123: 0 | AR123: 0 | AS123: 0 | AT123: 70 | AU123: 10 | AV123: 1 | AW123: 1 | AZ123: 1 | BA123: 1 | BB123: 1 | BC123: 1 | BH123: 3 | BI123: 4 | BJ123: СН-2012-2024.21. База. Р.18, о.4, поз.174 | BM123: 0 | BN123: 0 | BP123: 0 | BQ123: 1 | BR123: 1 | BS123: 1 | BT123: 1 | BU123: 1 | BV123: 1 | BW123: 1 | BX123: 1 | BZ123: 70 | CA123: 10 | CE123: 0 | CF123: 0 | CG123: 0 | CM123: 0 | CO123: 0 | CP123: =(P123+Q123+S123) -> -391446.86 | CQ123: =(AC123*BC123*AW123) -> 7758.26 | CR123: =((((ET123)*BB123-(EU123)*BS123)+AE123*BS123)*AV123) -> 0 | CS123: =(AE123*BS123*AV123) -> 0 | CT123: =(AF123*BA123*AV123) -> 0 | CU123: =AG123 -> 0 | CV123: =(AH123*AV123) -> 0 | CW123: =AI123 -> 0 | CX123: =AJ123 -> 0 | CY123: =((S123*BZ123)/100) -> 0 | CZ123: =((S123*CA123)/100) -> 0 | DN123: 0 | DO123: 0 | DP123: 1 | DQ123: 1 | DU123: 1010 | DV123: шт. | DW123: шт. | DX123: 1 | EE123: 71753531 | EF123: 1 | EG123: СН-2012 | EH123: 0 | EJ123: 4 | EK123: 0 | EL123: Подрядные работы, гл. 1-5,7 | EM123: работа | EQ123: 32768 | ER123: 7758.26 | ES123: 7758.26 | ET123: 0 | EU123: 0 | EV123: 0 | EW123: 0 | EX123: 0 | FQ123: 0 | FR123: =ROUND(IF(BI123=3,GM123,0),2) -> 0 | FS123: 0 | FX123: 70 | FY123: 10 | GD123: 0 | GF123: -572927986 | GG123: 2 | GH123: 1 | GI123: -2 | GJ123: 0 | GK123: =ROUND(R123*(R12)/100,2) -> 0 | GL123: =ROUND(IF(AND(BH123=3,BI123=3,FS123<>0),P123,0),2) -> 0 | GM123: =ROUND(O123+X123+Y123+GK123,2)+GX123 -> -391446.86 | GN123: =IF(OR(BI123=0,BI123=1),GM123,0) -> 0 | GO123: =IF(BI123=2,GM123,0) -> 0 | GP123: =IF(BI123=4,GM123+GX123,0) -> -391446.86 | GR123: 0 | GS123: 3 | GT123: 0 | GV123: =ROUND((GT123),6) -> 0 | GW123: 1 | GX123: =ROUND(HC123*I123,2) -> 0 | HA123: 0 | HB123: 0 | HC123: =GV123*GW123 -> 0 | IK123: 0
A124: 18 | B124: 1 | E124: 23 | F124: Цена поставщика | G124: Радиатор Rifar Monolit 500/100 биметалл 10 секций или эквивалент | H124: шт. | I124: =I122*J124 -> 26 | J124: 51.020408 | K124: 51.020408 | O124: =ROUND(CP124,2) -> 329511 | P124: =ROUND(CQ124*I124,2) -> 329511 | Q124: =ROUND(CR124*I124,2) -> 0 | R124: =ROUND(CS124*I124,2) -> 0 | S124: =ROUND(CT124*I124,2) -> 0 | T124: =ROUND(CU124*I124,2) -> 0 | U124: =CV124*I124 -> 0 | V124: =CW124*I124 -> 0 | W124: =ROUND(CX124*I124,2) -> 0 | X124: =ROUND(CY124,2) -> 0 | Y124: =ROUND(CZ124,2) -> 0 | AA124: 72192302 | AB124: =ROUND((AC124+AD124+AF124),6) -> 12673.5 | AC124: =ROUND((ES124),6) -> 12673.5 | AD124: =ROUND((((ET124)-(EU124))+AE124),6) -> 0 | AE124: =ROUND((EU124),6) -> 0 | AF124: =ROUND((EV124),6) -> 0 | AG124: =ROUND((AP124),6) -> 0 | AH124: =(EW124) -> 0 | AI124: =(EX124) -> 0 | AJ124: =(AS124) -> 0 | AK124: 12673.5 | AL124: 12673.5 | AM124: 0 | AN124: 0 | AO124: 0 | AP124: 0 | AQ124: 0 | AR124: 0 | AS124: 0 | AT124: 70 | AU124: 10 | AV124: 1 | AW124: 1 | AZ124: 1 | BA124: 1 | BB124: 1 | BC124: 1 | BH124: 3 | BI124: 4 | BM124: 0 | BN124: 0 | BP124: 0 | BQ124: 1 | BR124: 0 | BS124: 1 | BT124: 1 | BU124: 1 | BV124: 1 | BW124: 1 | BX124: 1 | BZ124: 70 | CA124: 10 | CE124: 0 | CF124: 0 | CG124: 0 | CM124: 0 | CO124: 0 | CP124: =(P124+Q124+S124) -> 329511 | CQ124: =(AC124*BC124*AW124) -> 12673.5 | CR124: =((((ET124)*BB124-(EU124)*BS124)+AE124*BS124)*AV124) -> 0 | CS124: =(AE124*BS124*AV124) -> 0 | CT124: =(AF124*BA124*AV124) -> 0 | CU124: =AG124 -> 0 | CV124: =(AH124*AV124) -> 0 | CW124: =AI124 -> 0 | CX124: =AJ124 -> 0 | CY124: =((S124*BZ124)/100) -> 0 | CZ124: =((S124*CA124)/100) -> 0 | DN124: 0 | DO124: 0 | DP124: 1 | DQ124: 1 | DU124: 1010 | DV124: шт. | DW124: шт. | DX124: 1 | EE124: 71753531 | EF124: 1 | EG124: СН-2012 | EH124: 0 | EJ124: 4 | EK124: 0 | EL124: Подрядные работы, гл. 1-5,7 | EM124: работа | EQ124: 0 | ER124: 12673.5 | ES124: 12673.5 | ET124: 0 | EU124: 0 | EV124: 0 | EW124: 0 | EX124: 0 | FQ124: 0 | FR124: =ROUND(IF(BI124=3,GM124,0),2) -> 0 | FS124: 0 | FX124: 70 | FY124: 10 | GD124: 0 | GF124: 195406401 | GG124: 2 | GH124: 0 | GI124: -2 | GJ124: 0 | GK124: =ROUND(R124*(R12)/100,2) -> 0 | GL124: =ROUND(IF(AND(BH124=3,BI124=3,FS124<>0),P124,0),2) -> 0 | GM124: =ROUND(O124+X124+Y124+GK124,2)+GX124 -> 329511 | GN124: =IF(OR(BI124=0,BI124=1),GM124,0) -> 0 | GO124: =IF(BI124=2,GM124,0) -> 0 | GP124: =IF(BI124=4,GM124+GX124,0) -> 329511 | GR124: 0 | GS124: 0 | GT124: 0 | GV124: =ROUND((GT124),6) -> 0 | GW124: 1 | GX124: =ROUND(HC124*I124,2) -> 0 | HA124: 0 | HB124: 0 | HC124: =GV124*GW124 -> 0 | IK124: 0
A125: 18 | B125: 1 | E125: 24 | F125: 21.12-10-20 | G125: Кронштейны для крепления отопительных приборов, марка КР1-РС | H125: компл. | I125: =I122*J125 -> -22.52432 | J125: -44.2 | K125: -44.2 | O125: =ROUND(CP125,2) -> -2968.93 | P125: =ROUND(CQ125*I125,2) -> -2968.93 | Q125: =ROUND(CR125*I125,2) -> 0 | R125: =ROUND(CS125*I125,2) -> 0 | S125: =ROUND(CT125*I125,2) -> 0 | T125: =ROUND(CU125*I125,2) -> 0 | U125: =CV125*I125 -> 0 | V125: =CW125*I125 -> 0 | W125: =ROUND(CX125*I125,2) -> 0 | X125: =ROUND(CY125,2) -> 0 | Y125: =ROUND(CZ125,2) -> 0 | AA125: 72192302 | AB125: =ROUND((AC125+AD125+AF125),6) -> 131.81 | AC125: =ROUND((ES125),6) -> 131.81 | AD125: =ROUND((((ET125)-(EU125))+AE125),6) -> 0 | AE125: =ROUND((EU125),6) -> 0 | AF125: =ROUND((EV125),6) -> 0 | AG125: =ROUND((AP125),6) -> 0 | AH125: =(EW125) -> 0 | AI125: =(EX125) -> 0 | AJ125: =(AS125) -> 0 | AK125: 131.81 | AL125: 131.81 | AM125: 0 | AN125: 0 | AO125: 0 | AP125: 0 | AQ125: 0 | AR125: 0 | AS125: 0 | AT125: 70 | AU125: 10 | AV125: 1 | AW125: 1 | AZ125: 1 | BA125: 1 | BB125: 1 | BC125: 1 | BH125: 3 | BI125: 4 | BJ125: СН-2012-2024.21. База. Р.12, о.10, поз.20 | BM125: 0 | BN125: 0 | BP125: 0 | BQ125: 1 | BR125: 1 | BS125: 1 | BT125: 1 | BU125: 1 | BV125: 1 | BW125: 1 | BX125: 1 | BZ125: 70 | CA125: 10 | CE125: 0 | CF125: 0 | CG125: 0 | CM125: 0 | CO125: 0 | CP125: =(P125+Q125+S125) -> -2968.93 | CQ125: =(AC125*BC125*AW125) -> 131.81 | CR125: =((((ET125)*BB125-(EU125)*BS125)+AE125*BS125)*AV125) -> 0 | CS125: =(AE125*BS125*AV125) -> 0 | CT125: =(AF125*BA125*AV125) -> 0 | CU125: =AG125 -> 0 | CV125: =(AH125*AV125) -> 0 | CW125: =AI125 -> 0 | CX125: =AJ125 -> 0 | CY125: =((S125*BZ125)/100) -> 0 | CZ125: =((S125*CA125)/100) -> 0 | DN125: 0 | DO125: 0 | DP125: 1 | DQ125: 1 | DU125: 1013 | DV125: компл. | DW125: компл. | DX125: 1 | EE125: 71753531 | EF125: 1 | EG125: СН-2012 | EH125: 0 | EJ125: 4 | EK125: 0 | EL125: Подрядные работы, гл. 1-5,7 | EM125: работа | EQ125: 0 | ER125: 131.81 | ES125: 131.81 | ET125: 0 | EU125: 0 | EV125: 0 | EW125: 0 | EX125: 0 | FQ125: 0 | FR125: =ROUND(IF(BI125=3,GM125,0),2) -> 0 | FS125: 0 | FX125: 70 | FY125: 10 | GD125: 0 | GF125: 1263435074 | GG125: 2 | GH125: 1 | GI125: -2 | GJ125: 0 | GK125: =ROUND(R125*(R12)/100,2) -> 0 | GL125: =ROUND(IF(AND(BH125=3,BI125=3,FS125<>0),P125,0),2) -> 0 | GM125: =ROUND(O125+X125+Y125+GK125,2)+GX125 -> -2968.93 | GN125: =IF(OR(BI125=0,BI125=1),GM125,0) -> 0 | GO125: =IF(BI125=2,GM125,0) -> 0 | GP125: =IF(BI125=4,GM125+GX125,0) -> -2968.93 | GR125: 0 | GS125: 3 | GT125: 0 | GV125: =ROUND((GT125),6) -> 0 | GW125: 1 | GX125: =ROUND(HC125*I125,2) -> 0 | HA125: 0 | HB125: 0 | HC125: =GV125*GW125 -> 0 | IK125: 0
A126: 18 | B126: 1 | E126: 25 | F126: 21.12-10-45 | G126: Кронштейны для крепления отопительных приборов, марка КРД, длина 131 мм | H126: шт. | I126: =I122*J126 -> 52 | J126: 102.04082 | K126: 102.04082 | O126: =ROUND(CP126,2) -> 2663.96 | P126: =ROUND(CQ126*I126,2) -> 2663.96 | Q126: =ROUND(CR126*I126,2) -> 0 | R126: =ROUND(CS126*I126,2) -> 0 | S126: =ROUND(CT126*I126,2) -> 0 | T126: =ROUND(CU126*I126,2) -> 0 | U126: =CV126*I126 -> 0 | V126: =CW126*I126 -> 0 | W126: =ROUND(CX126*I126,2) -> 0 | X126: =ROUND(CY126,2) -> 0 | Y126: =ROUND(CZ126,2) -> 0 | AA126: 72192302 | AB126: =ROUND((AC126+AD126+AF126),6) -> 51.23 | AC126: =ROUND((ES126),6) -> 51.23 | AD126: =ROUND((((ET126)-(EU126))+AE126),6) -> 0 | AE126: =ROUND((EU126),6) -> 0 | AF126: =ROUND((EV126),6) -> 0 | AG126: =ROUND((AP126),6) -> 0 | AH126: =(EW126) -> 0 | AI126: =(EX126) -> 0 | AJ126: =(AS126) -> 0 | AK126: 51.23 | AL126: 51.23 | AM126: 0 | AN126: 0 | AO126: 0 | AP126: 0 | AQ126: 0 | AR126: 0 | AS126: 0 | AT126: 70 | AU126: 10 | AV126: 1 | AW126: 1 | AZ126: 1 | BA126: 1 | BB126: 1 | BC126: 1 | BH126: 3 | BI126: 4 | BJ126: СН-2012-2024.21. База. Р.12, о.10, поз.45 | BM126: 0 | BN126: 0 | BP126: 0 | BQ126: 1 | BR126: 0 | BS126: 1 | BT126: 1 | BU126: 1 | BV126: 1 | BW126: 1 | BX126: 1 | BZ126: 70 | CA126: 10 | CE126: 0 | CF126: 0 | CG126: 0 | CM126: 0 | CO126: 0 | CP126: =(P126+Q126+S126) -> 2663.96 | CQ126: =(AC126*BC126*AW126) -> 51.23 | CR126: =((((ET126)*BB126-(EU126)*BS126)+AE126*BS126)*AV126) -> 0 | CS126: =(AE126*BS126*AV126) -> 0 | CT126: =(AF126*BA126*AV126) -> 0 | CU126: =AG126 -> 0 | CV126: =(AH126*AV126) -> 0 | CW126: =AI126 -> 0 | CX126: =AJ126 -> 0 | CY126: =((S126*BZ126)/100) -> 0 | CZ126: =((S126*CA126)/100) -> 0 | DN126: 0 | DO126: 0 | DP126: 1 | DQ126: 1 | DU126: 1010 | DV126: шт. | DW126: шт. | DX126: 1 | EE126: 71753531 | EF126: 1 | EG126: СН-2012 | EH126: 0 | EJ126: 4 | EK126: 0 | EL126: Подрядные работы, гл. 1-5,7 | EM126: работа | EQ126: 0 | ER126: 51.23 | ES126: 51.23 | ET126: 0 | EU126: 0 | EV126: 0 | EW126: 0 | EX126: 0 | FQ126: 0 | FR126: =ROUND(IF(BI126=3,GM126,0),2) -> 0 | FS126: 0 | FX126: 70 | FY126: 10 | GD126: 0 | GF126: 140294319 | GG126: 2 | GH126: 1 | GI126: -2 | GJ126: 0 | GK126: =ROUND(R126*(R12)/100,2) -> 0 | GL126: =ROUND(IF(AND(BH126=3,BI126=3,FS126<>0),P126,0),2) -> 0 | GM126: =ROUND(O126+X126+Y126+GK126,2)+GX126 -> 2663.96 | GN126: =IF(OR(BI126=0,BI126=1),GM126,0) -> 0 | GO126: =IF(BI126=2,GM126,0) -> 0 | GP126: =IF(BI126=4,GM126+GX126,0) -> 2663.96 | GR126: 0 | GS126: 3 | GT126: 0 | GV126: =ROUND((GT126),6) -> 0 | GW126: 1 | GX126: =ROUND(HC126*I126,2) -> 0 | HA126: 0 | HB126: 0 | HC126: =GV126*GW126 -> 0 | IK126: 0
A127: 17 | B127: 1 | D127: =ROW(EtalonRes!A83) -> 83 | E127: 26 | F127: 1.17-3303-4-1/1 | G127: Установка терморегулирующих клапанов на отопительных приборах | H127: 100 шт. | I127: 0.02 | J127: 0 | K127: 0.02 | O127: =ROUND(CP127,2) -> 8394.06 | P127: =ROUND(CQ127*I127,2) -> 7860.79 | Q127: =ROUND(CR127*I127,2) -> 0.97 | R127: =ROUND(CS127*I127,2) -> 0 | S127: =ROUND(CT127*I127,2) -> 532.3 | T127: =ROUND(CU127*I127,2) -> 0 | U127: =CV127*I127 -> 1.7306 | V127: =CW127*I127 -> 0 | W127: =ROUND(CX127*I127,2) -> 0 | X127: =ROUND(CY127,2) -> 372.61 | Y127: =ROUND(CZ127,2) -> 53.23 | AA127: 72192302 | AB127: =ROUND((AC127+AD127+AF127),6) -> 419703.21 | AC127: =ROUND((ES127),6) -> 393039.65 | AD127: =ROUND((((ET127)-(EU127))+AE127),6) -> 48.4 | AE127: =ROUND((EU127),6) -> 0.1 | AF127: =ROUND((EV127),6) -> 26615.16 | AG127: =ROUND((AP127),6) -> 0 | AH127: =(EW127) -> 86.53 | AI127: =(EX127) -> 0 | AJ127: =(AS127) -> 0 | AK127: 419703.21 | AL127: 393039.65 | AM127: 48.4 | AN127: 0.1 | AO127: 26615.16 | AP127: 0 | AQ127: 86.53 | AR127: 0 | AS127: 0 | AT127: 70 | AU127: 10 | AV127: 1 | AW127: 1 | AZ127: 1 | BA127: 1 | BB127: 1 | BC127: 1 | BH127: 0 | BI127: 4 | BJ127: СН-2012-2024.1. База. Сб.17-3303-4-1/1 | BM127: 0 | BN127: 0 | BP127: 0 | BQ127: 1 | BR127: 0 | BS127: 1 | BT127: 1 | BU127: 1 | BV127: 1 | BW127: 1 | BX127: 1 | BZ127: 70 | CA127: 10 | CE127: 0 | CF127: 0 | CG127: 0 | CM127: 0 | CO127: 0 | CP127: =(P127+Q127+S127) -> 8394.06 | CQ127: =(AC127*BC127*AW127) -> 393039.65 | CR127: =((((ET127)*BB127-(EU127)*BS127)+AE127*BS127)*AV127) -> 48.4 | CS127: =(AE127*BS127*AV127) -> 0.1 | CT127: =(AF127*BA127*AV127) -> 26615.16 | CU127: =AG127 -> 0 | CV127: =(AH127*AV127) -> 86.53 | CW127: =AI127 -> 0 | CX127: =AJ127 -> 0 | CY127: =((S127*BZ127)/100) -> 372.61 | CZ127: =((S127*CA127)/100) -> 53.23 | DN127: 0 | DO127: 0 | DP127: 1 | DQ127: 1 | DU127: 1010 | DV127: 100 шт. | DW127: 100 шт. | DX127: 100 | EE127: 71753531 | EF127: 1 | EG127: СН-2012 | EH127: 0 | EJ127: 4 | EK127: 0 | EL127: Подрядные работы, гл. 1-5,7 | EM127: работа | EQ127: 0 | ER127: 419703.21 | ES127: 393039.65 | ET127: 48.4 | EU127: 0.1 | EV127: 26615.16 | EW127: 86.53 | EX127: 0 | EY127: 0 | FQ127: 0 | FR127: =ROUND(IF(BI127=3,GM127,0),2) -> 0 | FS127: 0 | FX127: 70 | FY127: 10 | GD127: 0 | GF127: 722541396 | GG127: 2 | GH127: 1 | GI127: -2 | GJ127: 0 | GK127: =ROUND(R127*(R12)/100,2) -> 0 | GL127: =ROUND(IF(AND(BH127=3,BI127=3,FS127<>0),P127,0),2) -> 0 | GM127: =ROUND(O127+X127+Y127+GK127,2)+GX127 -> 8819.9 | GN127: =IF(OR(BI127=0,BI127=1),GM127,0) -> 0 | GO127: =IF(BI127=2,GM127,0) -> 0 | GP127: =IF(BI127=4,GM127+GX127,0) -> 8819.9 | GR127: 0 | GS127: 3 | GT127: 0 | GV127: =ROUND((GT127),6) -> 0 | GW127: 1 | GX127: =ROUND(HC127*I127,2) -> 0 | HA127: 0 | HB127: 0 | HC127: =GV127*GW127 -> 0 | IK127: 0
A128: 17 | B128: 1 | D128: =ROW(EtalonRes!A86) -> 86 | E128: 27 | F128: 1.13-3203-18-4/1 | G128: Окраска суриком металлических решеток, переплетов, радиаторов, труб диаметром менее 50 мм и т.п. за два раза | H128: 100 м2 | I128: 0.02188 | J128: 0 | K128: 0.02188 | O128: =ROUND(CP128,2) -> 556.06 | P128: =ROUND(CQ128*I128,2) -> 65.92 | Q128: =ROUND(CR128*I128,2) -> 0 | R128: =ROUND(CS128*I128,2) -> 0 | S128: =ROUND(CT128*I128,2) -> 490.14 | T128: =ROUND(CU128*I128,2) -> 0 | U128: =CV128*I128 -> 1.6254652 | V128: =CW128*I128 -> 0 | W128: =ROUND(CX128*I128,2) -> 0 | X128: =ROUND(CY128,2) -> 343.1 | Y128: =ROUND(CZ128,2) -> 49.01 | AA128: 72192302 | AB128: =ROUND((AC128+AD128+AF128),6) -> 25414.23 | AC128: =ROUND((ES128),6) -> 3012.82 | AD128: =ROUND((((ET128)-(EU128))+AE128),6) -> 0 | AE128: =ROUND((EU128),6) -> 0 | AF128: =ROUND((EV128),6) -> 22401.41 | AG128: =ROUND((AP128),6) -> 0 | AH128: =(EW128) -> 74.29 | AI128: =(EX128) -> 0 | AJ128: =(AS128) -> 0 | AK128: 25414.23 | AL128: 3012.82 | AM128: 0 | AN128: 0 | AO128: 22401.41 | AP128: 0 | AQ128: 74.29 | AR128: 0 | AS128: 0 | AT128: 70 | AU128: 10 | AV128: 1 | AW128: 1 | AZ128: 1 | BA128: 1 | BB128: 1 | BC128: 1 | BH128: 0 | BI128: 4 | BJ128: СН-2012-2024.1. База. Сб.13-3203-18-4/1 | BM128: 0 | BN128: 0 | BP128: 0 | BQ128: 1 | BR128: 0 | BS128: 1 | BT128: 1 | BU128: 1 | BV128: 1 | BW128: 1 | BX128: 1 | BZ128: 70 | CA128: 10 | CE128: 0 | CF128: 0 | CG128: 0 | CM128: 0 | CO128: 0 | CP128: =(P128+Q128+S128) -> 556.06 | CQ128: =(AC128*BC128*AW128) -> 3012.82 | CR128: =((((ET128)*BB128-(EU128)*BS128)+AE128*BS128)*AV128) -> 0 | CS128: =(AE128*BS128*AV128) -> 0 | CT128: =(AF128*BA128*AV128) -> 22401.41 | CU128: =AG128 -> 0 | CV128: =(AH128*AV128) -> 74.29 | CW128: =AI128 -> 0 | CX128: =AJ128 -> 0 | CY128: =((S128*BZ128)/100) -> 343.098 | CZ128: =((S128*CA128)/100) -> 49.014 | DN128: 0 | DO128: 0 | DP128: 1 | DQ128: 1 | DU128: 1005 | DV128: 100 м2 | DW128: 100 м2 | DX128: 100 | EE128: 71753531 | EF128: 1 | EG128: СН-2012 | EH128: 0 | EJ128: 4 | EK128: 0 | EL128: Подрядные работы, гл. 1-5,7 | EM128: работа | EQ128: 0 | ER128: 25414.23 | ES128: 3012.82 | ET128: 0 | EU128: 0 | EV128: 22401.41 | EW128: 74.29 | EX128: 0 | EY128: 0 | FQ128: 0 | FR128: =ROUND(IF(BI128=3,GM128,0),2) -> 0 | FS128: 0 | FX128: 70 | FY128: 10 | GD128: 0 | GF128: 1918166544 | GG128: 2 | GH128: 1 | GI128: -2 | GJ128: 0 | GK128: =ROUND(R128*(R12)/100,2) -> 0 | GL128: =ROUND(IF(AND(BH128=3,BI128=3,FS128<>0),P128,0),2) -> 0 | GM128: =ROUND(O128+X128+Y128+GK128,2)+GX128 -> 948.17 | GN128: =IF(OR(BI128=0,BI128=1),GM128,0) -> 0 | GO128: =IF(BI128=2,GM128,0) -> 0 | GP128: =IF(BI128=4,GM128+GX128,0) -> 948.17 | GR128: 0 | GS128: 3 | GT128: 0 | GV128: =ROUND((GT128),6) -> 0 | GW128: 1 | GX128: =ROUND(HC128*I128,2) -> 0 | HA128: 0 | HB128: 0 | HC128: =GV128*GW128 -> 0 | IK128: 0
A129: 17 | B129: 1 | D129: =ROW(EtalonRes!A99) -> 99 | E129: 28 | F129: 1.17-3203-1-2/1 | G129: Прокладка трубопроводов отопления из стальных водогазопроводных неоцинкованных труб диаметром 20 мм (без стоимости арматуры и креплений) | H129: 100 м | I129: 0.54 | J129: 0 | K129: 0.54 | O129: =ROUND(CP129,2) -> 24700.68 | P129: =ROUND(CQ129*I129,2) -> 18575.74 | Q129: =ROUND(CR129*I129,2) -> 4.24 | R129: =ROUND(CS129*I129,2) -> 0.12 | S129: =ROUND(CT129*I129,2) -> 6120.7 | T129: =ROUND(CU129*I129,2) -> 0 | U129: =CV129*I129 -> 18.4464 | V129: =CW129*I129 -> 0 | W129: =ROUND(CX129*I129,2) -> 0 | X129: =ROUND(CY129,2) -> 4284.49 | Y129: =ROUND(CZ129,2) -> 612.07 | AA129: 72192302 | AB129: =ROUND((AC129+AD129+AF129),6) -> 45741.99 | AC129: =ROUND((ES129),6) -> 34399.51 | AD129: =ROUND((((ET129)-(EU129))+AE129),6) -> 7.85 | AE129: =ROUND((EU129),6) -> 0.22 | AF129: =ROUND((EV129),6) -> 11334.63 | AG129: =ROUND((AP129),6) -> 0 | AH129: =(EW129) -> 34.16 | AI129: =(EX129) -> 0 | AJ129: =(AS129) -> 0 | AK129: 45741.99 | AL129: 34399.51 | AM129: 7.85 | AN129: 0.22 | AO129: 11334.63 | AP129: 0 | AQ129: 34.16 | AR129: 0 | AS129: 0 | AT129: 70 | AU129: 10 | AV129: 1 | AW129: 1 | AZ129: 1 | BA129: 1 | BB129: 1 | BC129: 1 | BH129: 0 | BI129: 4 | BJ129: СН-2012-2024.1. База. Сб.17-3203-1-2/1 | BM129: 0 | BN129: 0 | BP129: 0 | BQ129: 1 | BR129: 0 | BS129: 1 | BT129: 1 | BU129: 1 | BV129: 1 | BW129: 1 | BX129: 1 | BZ129: 70 | CA129: 10 | CE129: 0 | CF129: 0 | CG129: 0 | CM129: 0 | CO129: 0 | CP129: =(P129+Q129+S129) -> 24700.68 | CQ129: =(AC129*BC129*AW129) -> 34399.51 | CR129: =((((ET129)*BB129-(EU129)*BS129)+AE129*BS129)*AV129) -> 7.85 | CS129: =(AE129*BS129*AV129) -> 0.22 | CT129: =(AF129*BA129*AV129) -> 11334.63 | CU129: =AG129 -> 0 | CV129: =(AH129*AV129) -> 34.16 | CW129: =AI129 -> 0 | CX129: =AJ129 -> 0 | CY129: =((S129*BZ129)/100) -> 4284.49 | CZ129: =((S129*CA129)/100) -> 612.07 | DN129: 0 | DO129: 0 | DP129: 1 | DQ129: 1 | DU129: 1003 | DV129: 100 м | DW129: 100 м | DX129: 100 | EE129: 71753531 | EF129: 1 | EG129: СН-2012 | EH129: 0 | EJ129: 4 | EK129: 0 | EL129: Подрядные работы, гл. 1-5,7 | EM129: работа | EQ129: 0 | ER129: 45741.99 | ES129: 34399.51 | ET129: 7.85 | EU129: 0.22 | EV129: 11334.63 | EW129: 34.16 | EX129: 0 | EY129: 0 | FQ129: 0 | FR129: =ROUND(IF(BI129=3,GM129,0),2) -> 0 | FS129: 0 | FX129: 70 | FY129: 10 | GD129: 0 | GF129: -1364804565 | GG129: 2 | GH129: 1 | GI129: -2 | GJ129: 0 | GK129: =ROUND(R129*(R12)/100,2) -> 0.13 | GL129: =ROUND(IF(AND(BH129=3,BI129=3,FS129<>0),P129,0),2) -> 0 | GM129: =ROUND(O129+X129+Y129+GK129,2)+GX129 -> 29597.37 | GN129: =IF(OR(BI129=0,BI129=1),GM129,0) -> 0 | GO129: =IF(BI129=2,GM129,0) -> 0 | GP129: =IF(BI129=4,GM129+GX129,0) -> 29597.37 | GR129: 0 | GS129: 3 | GT129: 0 | GV129: =ROUND((GT129),6) -> 0 | GW129: 1 | GX129: =ROUND(HC129*I129,2) -> 0 | HA129: 0 | HB129: 0 | HC129: =GV129*GW129 -> 0 | IK129: 0
A130: 18 | B130: 1 | E130: 29 | F130: 21.3-4-19 | G130: Арматурные заготовки (стержни, хомуты и т.п.), не собранные в каркасы или сетки, арматурная сталь периодического профиля, класс А-III, диаметр 20-22 мм | H130: т | I130: =I129*J130 -> 0.0729 | J130: 0.135 | K130: 0.135 | O130: =ROUND(CP130,2) -> 5191.03 | P130: =ROUND(CQ130*I130,2) -> 5191.03 | Q130: =ROUND(CR130*I130,2) -> 0 | R130: =ROUND(CS130*I130,2) -> 0 | S130: =ROUND(CT130*I130,2) -> 0 | T130: =ROUND(CU130*I130,2) -> 0 | U130: =CV130*I130 -> 0 | V130: =CW130*I130 -> 0 | W130: =ROUND(CX130*I130,2) -> 0 | X130: =ROUND(CY130,2) -> 0 | Y130: =ROUND(CZ130,2) -> 0 | AA130: 72192302 | AB130: =ROUND((AC130+AD130+AF130),6) -> 71207.52 | AC130: =ROUND((ES130),6) -> 71207.52 | AD130: =ROUND((((ET130)-(EU130))+AE130),6) -> 0 | AE130: =ROUND((EU130),6) -> 0 | AF130: =ROUND((EV130),6) -> 0 | AG130: =ROUND((AP130),6) -> 0 | AH130: =(EW130) -> 0 | AI130: =(EX130) -> 0 | AJ130: =(AS130) -> 0 | AK130: 71207.52 | AL130: 71207.52 | AM130: 0 | AN130: 0 | AO130: 0 | AP130: 0 | AQ130: 0 | AR130: 0 | AS130: 0 | AT130: 70 | AU130: 10 | AV130: 1 | AW130: 1 | AZ130: 1 | BA130: 1 | BB130: 1 | BC130: 1 | BH130: 3 | BI130: 4 | BJ130: СН-2012-2024.21. База. Р.3, о.4, поз.19 | BM130: 0 | BN130: 0 | BP130: 0 | BQ130: 1 | BR130: 0 | BS130: 1 | BT130: 1 | BU130: 1 | BV130: 1 | BW130: 1 | BX130: 1 | BZ130: 70 | CA130: 10 | CE130: 0 | CF130: 0 | CG130: 0 | CM130: 0 | CO130: 0 | CP130: =(P130+Q130+S130) -> 5191.03 | CQ130: =(AC130*BC130*AW130) -> 71207.52 | CR130: =((((ET130)*BB130-(EU130)*BS130)+AE130*BS130)*AV130) -> 0 | CS130: =(AE130*BS130*AV130) -> 0 | CT130: =(AF130*BA130*AV130) -> 0 | CU130: =AG130 -> 0 | CV130: =(AH130*AV130) -> 0 | CW130: =AI130 -> 0 | CX130: =AJ130 -> 0 | CY130: =((S130*BZ130)/100) -> 0 | CZ130: =((S130*CA130)/100) -> 0 | DN130: 0 | DO130: 0 | DP130: 1 | DQ130: 1 | DU130: 1009 | DV130: т | DW130: т | DX130: 1000 | EE130: 71753531 | EF130: 1 | EG130: СН-2012 | EH130: 0 | EJ130: 4 | EK130: 0 | EL130: Подрядные работы, гл. 1-5,7 | EM130: работа | EQ130: 0 | ER130: 71207.52 | ES130: 71207.52 | ET130: 0 | EU130: 0 | EV130: 0 | EW130: 0 | EX130: 0 | FQ130: 0 | FR130: =ROUND(IF(BI130=3,GM130,0),2) -> 0 | FS130: 0 | FX130: 70 | FY130: 10 | GD130: 0 | GF130: 1622126655 | GG130: 2 | GH130: 1 | GI130: -2 | GJ130: 0 | GK130: =ROUND(R130*(R12)/100,2) -> 0 | GL130: =ROUND(IF(AND(BH130=3,BI130=3,FS130<>0),P130,0),2) -> 0 | GM130: =ROUND(O130+X130+Y130+GK130,2)+GX130 -> 5191.03 | GN130: =IF(OR(BI130=0,BI130=1),GM130,0) -> 0 | GO130: =IF(BI130=2,GM130,0) -> 0 | GP130: =IF(BI130=4,GM130+GX130,0) -> 5191.03 | GR130: 0 | GS130: 3 | GT130: 0 | GV130: =ROUND((GT130),6) -> 0 | GW130: 1 | GX130: =ROUND(HC130*I130,2) -> 0 | HA130: 0 | HB130: 0 | HC130: =GV130*GW130 -> 0 | IK130: 0
A131: 17 | B131: 1 | D131: =ROW(EtalonRes!A112) -> 112 | E131: 30 | F131: 1.17-3203-1-3/1 | G131: Прокладка трубопроводов отопления из стальных водогазопроводных неоцинкованных труб диаметром 25 мм (без стоимости арматуры и креплений) | H131: 100 м | I131: 0.3 | J131: 0 | K131: 0.3 | O131: =ROUND(CP131,2) -> 15425.9 | P131: =ROUND(CQ131*I131,2) -> 12023.15 | Q131: =ROUND(CR131*I131,2) -> 2.36 | R131: =ROUND(CS131*I131,2) -> 0.07 | S131: =ROUND(CT131*I131,2) -> 3400.39 | T131: =ROUND(CU131*I131,2) -> 0 | U131: =CV131*I131 -> 10.248 | V131: =CW131*I131 -> 0 | W131: =ROUND(CX131*I131,2) -> 0 | X131: =ROUND(CY131,2) -> 2380.27 | Y131: =ROUND(CZ131,2) -> 340.04 | AA131: 72192302 | AB131: =ROUND((AC131+AD131+AF131),6) -> 51419.65 | AC131: =ROUND((ES131),6) -> 40077.17 | AD131: =ROUND((((ET131)-(EU131))+AE131),6) -> 7.85 | AE131: =ROUND((EU131),6) -> 0.22 | AF131: =ROUND((EV131),6) -> 11334.63 | AG131: =ROUND((AP131),6) -> 0 | AH131: =(EW131) -> 34.16 | AI131: =(EX131) -> 0 | AJ131: =(AS131) -> 0 | AK131: 51419.65 | AL131: 40077.17 | AM131: 7.85 | AN131: 0.22 | AO131: 11334.63 | AP131: 0 | AQ131: 34.16 | AR131: 0 | AS131: 0 | AT131: 70 | AU131: 10 | AV131: 1 | AW131: 1 | AZ131: 1 | BA131: 1 | BB131: 1 | BC131: 1 | BH131: 0 | BI131: 4 | BJ131: СН-2012-2024.1. База. Сб.17-3203-1-3/1 | BM131: 0 | BN131: 0 | BP131: 0 | BQ131: 1 | BR131: 0 | BS131: 1 | BT131: 1 | BU131: 1 | BV131: 1 | BW131: 1 | BX131: 1 | BZ131: 70 | CA131: 10 | CE131: 0 | CF131: 0 | CG131: 0 | CM131: 0 | CO131: 0 | CP131: =(P131+Q131+S131) -> 15425.9 | CQ131: =(AC131*BC131*AW131) -> 40077.17 | CR131: =((((ET131)*BB131-(EU131)*BS131)+AE131*BS131)*AV131) -> 7.85 | CS131: =(AE131*BS131*AV131) -> 0.22 | CT131: =(AF131*BA131*AV131) -> 11334.63 | CU131: =AG131 -> 0 | CV131: =(AH131*AV131) -> 34.16 | CW131: =AI131 -> 0 | CX131: =AJ131 -> 0 | CY131: =((S131*BZ131)/100) -> 2380.273 | CZ131: =((S131*CA131)/100) -> 340.039 | DN131: 0 | DO131: 0 | DP131: 1 | DQ131: 1 | DU131: 1003 | DV131: 100 м | DW131: 100 м | DX131: 100 | EE131: 71753531 | EF131: 1 | EG131: СН-2012 | EH131: 0 | EJ131: 4 | EK131: 0 | EL131: Подрядные работы, гл. 1-5,7 | EM131: работа | EQ131: 0 | ER131: 51419.65 | ES131: 40077.17 | ET131: 7.85 | EU131: 0.22 | EV131: 11334.63 | EW131: 34.16 | EX131: 0 | EY131: 0 | FQ131: 0 | FR131: =ROUND(IF(BI131=3,GM131,0),2) -> 0 | FS131: 0 | FX131: 70 | FY131: 10 | GD131: 0 | GF131: 2044525755 | GG131: 2 | GH131: 1 | GI131: -2 | GJ131: 0 | GK131: =ROUND(R131*(R12)/100,2) -> 0.08 | GL131: =ROUND(IF(AND(BH131=3,BI131=3,FS131<>0),P131,0),2) -> 0 | GM131: =ROUND(O131+X131+Y131+GK131,2)+GX131 -> 18146.29 | GN131: =IF(OR(BI131=0,BI131=1),GM131,0) -> 0 | GO131: =IF(BI131=2,GM131,0) -> 0 | GP131: =IF(BI131=4,GM131+GX131,0) -> 18146.29 | GR131: 0 | GS131: 3 | GT131: 0 | GV131: =ROUND((GT131),6) -> 0 | GW131: 1 | GX131: =ROUND(HC131*I131,2) -> 0 | HA131: 0 | HB131: 0 | HC131: =GV131*GW131 -> 0 | IK131: 0
...

Sheet SourceObSm
A1: 0 | B1: Smeta.RU Flash (495) 974-1589 | D1: _OBSM_ | F1: 0 | G1: 0 | H1: 0 | I1: Smeta.RU Flash | K1: 1 | L1: 62169 | M1: 10 | N1: 11 | O1: 8 | P1: 0 | Q1: 0
A12: 1 | B12: 56 | C12: 0 | E12: 0 | F12: Новый объект | G12: +Текущий ремонт спортзала №1 + раздевалки по адресу: г. Москва, ул. Митинская улица, д. 48, корп. 2 | I12: 0 | K12: 0 | L12: 0 | M12: 2 | O12: 0 | P12: 0 | Q12: 0 | R12: 108 | T12: 1 | V12: 0 | BB12: 0 | BH12: Сметные нормы списания | BI12: Коды ОКП для СН-2012 - 2024 г. (в ценах на 01.01.2024 г) | BJ12: 1 | BK12: 1 | BL12: 0 | BM12: 0 | BN12: 1 | BO12: 0 | BP12: 6 | BQ12: 2 | BR12: 1 | BS12: 1 | BT12: 1 | BU12: 0 | BV12: 1 | BW12: 0 | BX12: 0 | BY12: СН-2012 - 2024 г. (в ценах на 01.01.2024 г)_глава_1-5 | BZ12: Типовой расчет для СН-2012 - 2024 г. (в ценах на 01.01.2024 г) И0 | CA12: СН-2012-2024 г. База данных "Сборник стоимостных нормативов" (в ценах на 01.01.2024 г) | CB12: СН-2012-2024 г. База данных "Сборник стоимостных нормативов" (в ценах на 01.01.2024 г) | CC12: СН-2012-2024 г. База данных "Сборник стоимостных нормативов" (в ценах на 01.01.2024 г) | CD12: СН-2012-2024 г. База данных "Сборник стоимостных нормативов" (в ценах на 01.01.2024 г) | CE12: Поправки для СН-2012-2024 в ценах на 01.01.2024 г И0 (05.03.2024) | CF12: 0 | CG12: 0 | CH12: 8 | CK12: 0 | CY12: 0 | EC12: 0
A14: 22 | B14: 1 | C14: 0 | D14: 72192302 | E14: 0 | F14: 2 | G14: 1
A16: 3 | B16: 0 | D16: Новая локальная смета | E16: =ROUND((Source!F509)/1000,2) -> 0 | F16: =ROUND((Source!F510)/1000,2) -> 0 | G16: =ROUND((Source!F501)/1000,2) -> 0 | H16: =ROUND((Source!F511)/1000+(Source!F512)/1000,2) -> 2116.77 | I16: =E16+F16+G16+H16 -> 2116.77 | J16: =ROUND((Source!F507+Source!F506)/1000,2) -> 609.92 | AI16: 0 | AJ16: 0 | AN16: 0 | AT16: 1626320.4 | AU16: 1011274.7 | AV16: 0 | AW16: 0 | AX16: 0 | AY16: 23758.01 | AZ16: 18629.83 | BA16: 591287.74 | BB16: 0 | BC16: 0 | BD16: 2116768.8 | BE16: 0 | BF16: 1979.8973 | BG16: 0 | BH16: 0 | BI16: 413901.44 | BJ16: 59128.79 | BK16: 2116768.8
A18: 51 | E18: =SUMIF(A16:A17,3,E16:E17) -> 0 | F18: =SUMIF(A16:A17,3,F16:F17) -> 0 | G18: =SUMIF(A16:A17,3,G16:G17) -> 0 | H18: =SUMIF(A16:A17,3,H16:H17) -> 2116.77 | I18: =SUMIF(A16:A17,3,I16:I17) -> 2116.77 | J18: =SUMIF(A16:A17,3,J16:J17) -> 609.92
A20: 50 | B20: 0 | C20: 0 | D20: 1 | E20: 201 | F20: 1626320.4 | G20: ПЗ | H20: Прямые затраты | K20: 201 | L20: 1 | M20: 3 | O20: 2
A21: 50 | B21: 0 | C21: 0 | D21: 1 | E21: 202 | F21: 1011274.7 | G21: СтМатОб | H21: Стоимость материальных ресурсов (всего) | K21: 202 | L21: 2 | M21: 3 | O21: 2
A22: 50 | B22: 0 | C22: 0 | D22: 1 | E22: 222 | F22: 0 | G22: СтМатОбЗак | H22: Стоимость материалов и оборудования заказчика | K22: 222 | L22: 3 | M22: 3 | O22: 2
A23: 50 | B23: 0 | C23: 0 | D23: 1 | E23: 225 | F23: 1011274.7 | G23: СтМатОбПод | H23: Стоимость материалов и оборудования подрядчика | K23: 225 | L23: 4 | M23: 3 | O23: 2
A24: 50 | B24: 0 | C24: 0 | D24: 1 | E24: 226 | F24: 1011274.7 | G24: СтМат | H24: Стоимость материалов (всего) | K24: 226 | L24: 5 | M24: 3 | O24: 2
A25: 50 | B25: 0 | C25: 0 | D25: 1 | E25: 227 | F25: 0 | G25: СтМатЗак | H25: Стоимость материалов заказчика | K25: 227 | L25: 6 | M25: 3 | O25: 2
A26: 50 | B26: 0 | C26: 0 | D26: 1 | E26: 228 | F26: 1011274.7 | G26: СтМатПод | H26: Стоимость материалов подрядчика | K26: 228 | L26: 7 | M26: 3 | O26: 2
A27: 50 | B27: 0 | C27: 0 | D27: 1 | E27: 216 | F27: 0 | G27: Оборуд | H27: Стоимость оборудования (всего) | K27: 216 | L27: 8 | M27: 3 | O27: 2
A28: 50 | B28: 0 | C28: 0 | D28: 1 | E28: 223 | F28: 0 | G28: ОборудЗак | H28: Стоимость оборудования заказчика | K28: 223 | L28: 9 | M28: 3 | O28: 2
A29: 50 | B29: 0 | C29: 0 | D29: 1 | E29: 229 | F29: 0 | G29: ОборудПод | H29: Стоимость оборудования подрядчика | K29: 229 | L29: 10 | M29: 3 | O29: 2
A30: 50 | B30: 0 | C30: 0 | D30: 1 | E30: 203 | F30: 23758.01 | G30: ЭММ | H30: Эксплуатация машин | K30: 203 | L30: 11 | M30: 3 | O30: 2
A31: 50 | B31: 0 | C31: 0 | D31: 1 | E31: 231 | F31: 0 | G31: ЭММсНРиСП | H31: Эксплуатация машин по ТСН-2001.16 | K31: 231 | L31: 12 | M31: 3 | O31: 2
... A51: 50 | B51: 1 | C51: 0 | D51: 2 | E51: 0 | F51: 2510590.4 | G51: 5 | H51: Всего | K51: 212 | L51: 32 | M51: 0 | O51: 2
A53: -1
A56: 75 | B56: Уровень цен на 01.01.2024 г | C56: 2024 | D56: 0 | E56: 1 | F56: 0 | G56: 0 | H56: 1 | I56: 0 | J56: 3 | K56: 78 | L56: 30 | M56: 0 | N56: 72192302 | O56: 1

Sheet SmtRes

Sheet EtalonRes
A1: =ROW(Source!A32) -> 32 | B1: 72192303 | C1: 71587957 | D1: 71757693 | E1: 35 | F1: 1 | G1: 35 | H1: 1 | I1: 9999990008 | K1: Трудозатраты рабочих | L1: 1191 | N1: 1013 | O1: чел.-ч. | P1: чел.-ч. | Q1: 1 | X1: 2.78 | Y1: 0 | Z1: 0 | AA1: 0 | AB1: 0 | AC1: 0 | AD1: 1 | AE1: 1 | AG1: 2.78 | AH1: 3 | AI1: -1 | AK1: 0 | AL1: 0 | AM1: 0 | AN1: 0 | AO1: 0 | AP1: 0 | AQ1: 0 | AR1: 0
A2: =ROW(Source!A32) -> 32 | B2: 72192304 | C2: 71587957 | D2: 71771187 | E2: 1 | F2: 1 | G2: 35 | H2: 2 | I2: 22.1-30-56 | J2: СН-2012-2024.22. База. п.1-30-56 (309101) | K2: Шуруповерты | L2: 1368 | N2: 1011 | O2: маш.-ч | P2: маш.-ч | Q2: 1 | X2: 0.34 | Y2: 0 | Z2: 5.27 | AA2: 0.01 | AB2: 0 | AC2: 0 | AD2: 1 | AE2: 0 | AG2: 0.34 | AH2: 3 | AI2: -1 | AK2: 0 | AL2: 0 | AM2: 0 | AN2: 0 | AO2: 0 | AP2: 0 | AQ2: 0 | AR2: 0
A3: =ROW(Source!A33) -> 33 | B3: 72192305 | C3: 71587960 | D3: 71757693 | E3: 35 | F3: 1 | G3: 35 | H3: 1 | I3: 9999990008 | K3: Трудозатраты рабочих | L3: 1191 | N3: 1013 | O3: чел.-ч. | P3: чел.-ч. | Q3: 1 | X3: 0.6 | Y3: 0 | Z3: 0 | AA3: 0 | AB3: 0 | AC3: 0 | AD3: 1 | AE3: 1 | AG3: 0.6 | AH3: 3 | AI3: -1 | AK3: 0 | AL3: 0 | AM3: 0 | AN3: 0 | AO3: 0 | AP3: 0 | AQ3: 0 | AR3: 0
A4: =ROW(Source!A34) -> 34 | B4: 72192306 | C4: 71587962 | D4: 71757693 | E4: 35 | F4: 1 | G4: 35 | H4: 1 | I4: 9999990008 | K4: Трудозатраты рабочих | L4: 1191 | N4: 1013 | O4: чел.-ч. | P4: чел.-ч. | Q4: 1 | X4: 120.59 | Y4: 0 | Z4: 0 | AA4: 0 | AB4: 0 | AC4: 0 | AD4: 1 | AE4: 1 | AG4: 120.59 | AH4: 3 | AI4: -1 | AK4: 0 | AL4: 0 | AM4: 0 | AN4: 0 | AO4: 0 | AP4: 0 | AQ4: 0 | AR4: 0
A5: =ROW(Source!A34) -> 34 | B5: 72192307 | C5: 71587962 | D5: 71770214 | E5: 35 | F5: 1 | G5: 35 | H5: 3 | I5: 9999990001 | K5: Масса мусора | L5: 1348 | N5: 1009 | O5: т | P5: т | Q5: 1000 | X5: 8 | Y5: 0 | Z5: 0 | AA5: 0 | AB5: 0 | AC5: 0 | AD5: 1 | AE5: 0 | AG5: 8 | AH5: 3 | AI5: -1 | AK5: 0 | AL5: 0 | AM5: 0 | AN5: 0 | AO5: 0 | AP5: 0 | AQ5: 0 | AR5: 0
A6: =ROW(Source!A36) -> 36 | B6: 72192308 | C6: 71588029 | D6: 71757693 | E6: 35 | F6: 1 | G6: 35 | H6: 1 | I6: 9999990008 | K6: Трудозатраты рабочих | L6: 1191 | N6: 1013 | O6: чел.-ч. | P6: чел.-ч. | Q6: 1 | X6: 12.77 | Y6: 0 | Z6: 0 | AA6: 0 | AB6: 0 | AC6: 0 | AD6: 1 | AE6: 1 | AG6: 12.77 | AH6: 3 | AI6: -1 | AK6: 0 | AL6: 0 | AM6: 0 | AN6: 0 | AO6: 0 | AP6: 0 | AQ6: 0 | AR6: 0
A7: =ROW(Source!A36) -> 36 | B7: 72192309 | C7: 71588029 | D7: 71772016 | E7: 1 | F7: 1 | G7: 35 | H7: 3 | I7: 21.1-10-12 | J7: СН-2012-2024.21. База. Р.1, о.10, поз.12 | K7: Проволока стальная вязальная | L7: 1348 | N7: 1009 | O7: т | P7: т | Q7: 1000 | X7: 0.009 | Y7: 96442.75 | Z7: 0 | AA7: 0 | AB7: 0 | AC7: 0 | AD7: 1 | AE7: 0 | AG7: 0.009 | AH7: 3 | AI7: -1 | AK7: 0 | AL7: 0 | AM7: 0 | AN7: 0 | AO7: 0 | AP7: 0 | AQ7: 0 | AR7: 0
A8: =ROW(Source!A36) -> 36 | B8: 72192310 | C8: 71588029 | D8: 71773722 | E8: 1 | F8: 1 | G8: 35 | H8: 3 | I8: 21.1-25-672 | J8: СН-2012-2024.21. База. Р.1, о.25, поз.672 | K8: Сетка полимерная для строительства, защитная | L8: 1327 | N8: 1005 | O8: м2 | P8: м2 | Q8: 1 | X8: 33.99 | Y8: 15.35 | Z8: 0 | AA8: 0 | AB8: 0 | AC8: 0 | AD8: 1 | AE8: 0 | AG8: 33.99 | AH8: 3 | AI8: -1 | AK8: 0 | AL8: 0 | AM8: 0 | AN8: 0 | AO8: 0 | AP8: 0 | AQ8: 0 | AR8: 0
A9: =ROW(Source!A37) -> 37 | B9: 72192311 | C9: 71588037 | D9: 71757693 | E9: 35 | F9: 1 | G9: 35 | H9: 1 | I9: 9999990008 | K9: Трудозатраты рабочих | L9: 1191 | N9: 1013 | O9: чел.-ч. | P9: чел.-ч. | Q9: 1 | X9: 49.34 | Y9: 0 | Z9: 0 | AA9: 0 | AB9: 0 | AC9: 0 | AD9: 1 | AE9: 1 | AG9: 49.34 | AH9: 3 | AI9: -1 | AK9: 0 | AL9: 0 | AM9: 0 | AN9: 0 | AO9: 0 | AP9: 0 | AQ9: 0 | AR9: 0
A10: =ROW(Source!A37) -> 37 | B10: 72192312 | C10: 71588037 | D10: 71770715 | E10: 1 | F10: 1 | G10: 35 | H10: 2 | I10: 22.1-13-16 | J10: СН-2012-2024.22. База. п.1-13-16 (136301) | K10: Аппараты для газовой сварки и резки | L10: 1368 | N10: 1011 | O10: маш.-ч | P10: маш.-ч | Q10: 1 | X10: 4.7 | Y10: 0 | Z10: 6.33 | AA10: 0.18 | AB10: 0 | AC10: 0 | AD10: 1 | AE10: 0 | AG10: 4.7 | AH10: 3 | AI10: -1 | AK10: 0 | AL10: 0 | AM10: 0 | AN10: 0 | AO10: 0 | AP10: 0 | AQ10: 0 | AR10: 0
A11: =ROW(Source!A37) -> 37 | B11: 72192313 | C11: 71588037 | D11: 71771510 | E11: 1 | F11: 1 | G11: 35 | H11: 3 | I11: 21.1-4-10 | J11: СН-2012-2024.21. База. Р.1, о.4, поз.10 | K11: Кислород технический газообразный | L11: 1339 | N11: 1007 | O11: м3 | P11: м3 | Q11: 1 | X11: 2.82 | Y11: 79.62 | Z11: 0 | AA11: 0 | AB11: 0 | AC11: 0 | AD11: 1 | AE11: 0 | AG11: 2.82 | AH11: 3 | AI11: -1 | AK11: 0 | AL11: 0 | AM11: 0 | AN11: 0 | AO11: 0 | AP11: 0 | AQ11: 0 | AR11: 0
A12: =ROW(Source!A37) -> 37 | B12: 72192314 | C12: 71588037 | D12: 71771502 | E12: 1 | F12: 1 | G12: 35 | H12: 3 | I12: 21.1-4-2 | J12: СН-2012-2024.21. База. Р.1, о.4, поз.2 | K12: Ацетилен технический | L12: 1339 | N12: 1007 | O12: м3 | P12: м3 | Q12: 1 | X12: 0.44 | Y12: 715.78 | Z12: 0 | AA12: 0 | AB12: 0 | AC12: 0 | AD12: 1 | AE12: 0 | AG12: 0.44 | AH12: 3 | AI12: -1 | AK12: 0 | AL12: 0 | AM12: 0 | AN12: 0 | AO12: 0 | AP12: 0 | AQ12: 0 | AR12: 0
A13: =ROW(Source!A37) -> 37 | B13: 72192315 | C13: 71588037 | D13: 71770214 | E13: 35 | F13: 1 | G13: 35 | H13: 3 | I13: 9999990001 | K13: Масса мусора | L13: 1348 | N13: 1009 | O13: т | P13: т | Q13: 1000 | X13: 0.454 | Y13: 0 | Z13: 0 | AA13: 0 | AB13: 0 | AC13: 0 | AD13: 1 | AE13: 0 | AG13: 0.454 | AH13: 3 | AI13: -1 | AK13: 0 | AL13: 0 | AM13: 0 | AN13: 0 | AO13: 0 | AP13: 0 | AQ13: 0 | AR13: 0
A14: =ROW(Source!A39) -> 39 | B14: 72192316 | C14: 71588045 | D14: 71757693 | E14: 35 | F14: 1 | G14: 35 | H14: 1 | I14: 9999990008 | K14: Трудозатраты рабочих | L14: 1191 | N14: 1013 | O14: чел.-ч. | P14: чел.-ч. | Q14: 1 | X14: 0.19 | Y14: 0 | Z14: 0 | AA14: 0 | AB14: 0 | AC14: 0 | AD14: 1 | AE14: 1 | AG14: 0.19 | AH14: 3 | AI14: -1 | AK14: 0 | AL14: 0 | AM14: 0 | AN14: 0 | AO14: 0 | AP14: 0 | AQ14: 0 | AR14: 0
A15: =ROW(Source!A40) -> 40 | B15: 72192317 | C15: 71588047 | D15: 71757693 | E15: 35 | F15: 1 | G15: 35 | H15: 1 | I15: 9999990008 | K15: Трудозатраты рабочих | L15: 1191 | N15: 1013 | O15: чел.-ч. | P15: чел.-ч. | Q15: 1 | X15: 133.4 | Y15: 0 | Z15: 0 | AA15: 0 | AB15: 0 | AC15: 0 | AD15: 1 | AE15: 1 | AF15: )*0,2 | AG15: 26.68 | AH15: 3 | AI15: -1 | AK15: 0 | AL15: 0 | AM15: 0 | AN15: 0 | AO15: 0 | AP15: 0 | AQ15: 0 | AR15: 0
A16: =ROW(Source!A40) -> 40 | B16: 72192318 | C16: 71588047 | D16: 71770384 | E16: 1 | F16: 1 | G16: 35 | H16: 2 | I16: 22.1-4-31 | J16: СН-2012-2024.22. База. п.1-4-31 (042903) | K16: Лебедки электрические, грузоподъемность до 1,5 т | L16: 1368 | N16: 1011 | O16: маш.-ч | P16: маш.-ч | Q16: 1 | X16: 29 | Y16: 0 | Z16: 32.86 | AA16: 1.68 | AB16: 0 | AC16: 0 | AD16: 1 | AE16: 0 | AF16: )*0,2 | AG16: 5.8 | AH16: 3 | AI16: -1 | AK16: 0 | AL16: 0 | AM16: 0 | AN16: 0 | AO16: 0 | AP16: 0 | AQ16: 0 | AR16: 0
A17: =ROW(Source!A40) -> 40 | B17: 72192319 | C17: 71588047 | D17: 71772305 | E17: 1 | F17: 1 | G17: 35 | H17: 3 | I17: 21.1-11-21 | J17: СН-2012-2024.21. База. Р.1, о.11, поз.21 | K17: Болты строительные черные с гайками и шайбами (10х100мм) | L17: 1348 | N17: 1009 | O17: т | P17: т | Q17: 1000 | X17: 0.006 | Y17: 169525.77 | Z17: 0 | AA17: 0 | AB17: 0 | AC17: 0 | AD17: 1 | AE17: 0 | AF17: )*0 | AG17: 0 | AH17: 3 | AI17: -1 | AK17: 0 | AL17: 0 | AM17: 0 | AN17: 0 | AO17: 0 | AP17: 0 | AQ17: 0 | AR17: 0
A18: =ROW(Source!A40) -> 40 | B18: 72192320 | C18: 71588047 | D18: 71773175 | E18: 1 | F18: 1 | G18: 35 | H18: 3 | I18: 21.1-23-9 | J18: СН-2012-2024.21. База. Р.1, о.23, поз.9 | K18: Электроды, тип Э-42, 46, 50, диаметр 4 - 6 мм | L18: 1348 | N18: 1009 | O18: т | P18: т | Q18: 1000 | X18: 0.003 | Y18: 116329.32 | Z18: 0 | AA18: 0 | AB18: 0 | AC18: 0 | AD18: 1 | AE18: 0 | AF18: )*0 | AG18: 0 | AH18: 3 | AI18: -1 | AK18: 0 | AL18: 0 | AM18: 0 | AN18: 0 | AO18: 0 | AP18: 0 | AQ18: 0 | AR18: 0
A19: =ROW(Source!A40) -> 40 | B19: 72192321 | C19: 71588047 | D19: 71775397 | E19: 1 | F19: 1 | G19: 35 | H19: 3 | I19: 21.6-1-49 | J19: СН-2012-2024.21. База. Р.6, о.1, поз.49 | K19: Отдельные конструктивные элементы с преобладанием горячекатаных профилей, средняя масса сборочной единицы до 0,05 т | L19: 1348 | N19: 1009 | O19: т | P19: т | Q19: 1000 | X19: 1 | Y19: 139438.91 | Z19: 0 | AA19: 0 | AB19: 0 | AC19: 0 | AD19: 1 | AE19: 0 | AF19: )*0 | AG19: 0 | AH19: 3 | AI19: -1 | AK19: 0 | AL19: 0 | AM19: 0 | AN19: 0 | AO19: 0 | AP19: 0 | AQ19: 0 | AR19: 0
A20: =ROW(Source!A41) -> 41 | B20: 72192322 | C20: 71588053 | D20: 71757693 | E20: 35 | F20: 1 | G20: 35 | H20: 1 | I20: 9999990008 | K20: Трудозатраты рабочих | L20: 1191 | N20: 1013 | O20: чел.-ч. | P20: чел.-ч. | Q20: 1 | X20: 154 | Y20: 0 | Z20: 0 | AA20: 0 | AB20: 0 | AC20: 0 | AD20: 1 | AE20: 1 | AG20: 154 | AH20: 3 | AI20: -1 | AK20: 0 | AL20: 0 | AM20: 0 | AN20: 0 | AO20: 0 | AP20: 0 | AQ20: 0 | AR20: 0
A21: =ROW(Source!A41) -> 41 | B21: 72192323 | C21: 71588053 | D21: 71770609 | E21: 1 | F21: 1 | G21: 35 | H21: 2 | I21: 22.1-10-4 | J21: СН-2012-2024.22. База. п.1-10-4 (101001) | K21: Компрессоры с дизельным двигателем прицепные до 2,5 м3/мин | L21: 1368 | N21: 1011 | O21: маш.-ч | P21: маш.-ч | Q21: 1 | X21: 75 | Y21: 0 | Z21: 584.67 | AA21: 448.39 | AB21: 0 | AC21: 0 | AD21: 1 | AE21: 0 | AG21: 75 | AH21: 3 | AI21: -1 | AK21: 0 | AL21: 0 | AM21: 0 | AN21: 0 | AO21: 0 | AP21: 0 | AQ21: 0 | AR21: 0
A22: =ROW(Source!A41) -> 41 | B22: 72192324 | C22: 71588053 | D22: 71771185 | E22: 1 | F22: 1 | G22: 35 | H22: 2 | I22: 22.1-30-54 | J22: СН-2012-2024.22. База. п.1-30-54 (308901) | K22: Молотки отбойные | L22: 1368 | N22: 1011 | O22: маш.-ч | P22: маш.-ч | Q22: 1 | X22: 150 | Y22: 0 | Z22: 6.02 | AA22: 0.02 | AB22: 0 | AC22: 0 | AD22: 1 | AE22: 0 | AG22: 150 | AH22: 3 | AI22: -1 | AK22: 0 | AL22: 0 | AM22: 0 | AN22: 0 | AO22: 0 | AP22: 0 | AQ22: 0 | AR22: 0
A23: =ROW(Source!A77) -> 77 | B23: 72192325 | C23: 71588115 | D23: 71757693 | E23: 35 | F23: 1 | G23: 35 | H23: 1 | I23: 9999990008 | K23: Трудозатраты рабочих | L23: 1191 | N23: 1013 | O23: чел.-ч. | P23: чел.-ч. | Q23: 1 | X23: 63.94 | Y23: 0 | Z23: 0 | AA23: 0 | AB23: 0 | AC23: 0 | AD23: 1 | AE23: 1 | AG23: 63.94 | AH23: 3 | AI23: -1 | AK23: 0 | AL23: 0 | AM23: 0 | AN23: 0 | AO23: 0 | AP23: 0 | AQ23: 0 | AR23: 0
A24: =ROW(Source!A77) -> 77 | B24: 72192326 | C24: 71588115 | D24: 71770528 | E24: 1 | F24: 1 | G24: 35 | H24: 2 | I24: 22.1-6-33 | J24: СН-2012-2024.22. База. п.1-6-33 (067501) | K24: Растворонасосы, производительность до 1 м3/ч | L24: 1368 | N24: 1011 | O24: маш.-ч | P24: маш.-ч | Q24: 1 | X24: 5.12 | Y24: 0 | Z24: 461.4 | AA24: 409.44 | AB24: 0 | AC24: 0 | AD24: 1 | AE24: 0 | AG24: 5.12 | AH24: 3 | AI24: -1 | AK24: 0 | AL24: 0 | AM24: 0 | AN24: 0 | AO24: 0 | AP24: 0 | AQ24: 0 | AR24: 0
A25: =ROW(Source!A77) -> 77 | B25: 72192327 | C25: 71588115 | D25: 71773291 | E25: 1 | F25: 1 | G25: 35 | H25: 3 | I25: 21.1-25-13 | J25: СН-2012-2024.21. База. Р.1, о.25, поз.13 | K25: Вода | L25: 1339 | N25: 1007 | O25: м3 | P25: м3 | Q25: 1 | X25: 0.0948 | Y25: 42.44 | Z25: 0 | AA25: 0 | AB25: 0 | AC25: 0 | AD25: 1 | AE25: 0 | AG25: 0.0948 | AH25: 3 | AI25: -1 | AK25: 0 | AL25: 0 | AM25: 0 | AN25: 0 | AO25: 0 | AP25: 0 | AQ25: 0 | AR25: 0
A26: =ROW(Source!A77) -> 77 | B26: 72192328 | C26: 71588115 | D26: 71773591 | E26: 1 | F26: 1 | G26: 35 | H26: 3 | I26: 21.1-25-335 | J26: СН-2012-2024.21. База. Р.1, о.25, поз.335 | K26: Сетка проволочная штукатурная тканая, квадрат 5х5 мм, толщина 1,6 мм | L26: 1327 | N26: 1005 | O26: м2 | P26: м2 | Q26: 1 | X26: 2.64 | Y26: 525.42 | Z26: 0 | AA26: 0 | AB26: 0 | AC26: 0 | AD26: 1 | AE26: 0 | AG26: 2.64 | AH26: 3 | AI26: -1 | AK26: 0 | AL26: 0 | AM26: 0 | AN26: 0 | AO26: 0 | AP26: 0 | AQ26: 0 | AR26: 0
A27: =ROW(Source!A77) -> 77 | B27: 72192329 | C27: 71588115 | D27: 71774360 | E27: 1 | F27: 1 | G27: 35 | H27: 3 | I27: 21.3-2-10 | J27: СН-2012-2024.21. База. Р.3, о.2, поз.10 | K27: Растворы цементно-известковые, марка 75 | L27: 1339 | N27: 1007 | O27: м3 | P27: м3 | Q27: 1 | X27: 0.224 | Y27: 3817.03 | Z27: 0 | AA27: 0 | AB27: 0 | AC27: 0 | AD27: 1 | AE27: 0 | AG27: 0.224 | AH27: 3 | AI27: -1 | AK27: 0 | AL27: 0 | AM27: 0 | AN27: 0 | AO27: 0 | AP27: 0 | AQ27: 0 | AR27: 0
A28: =ROW(Source!A77) -> 77 | B28: 72192330 | C28: 71588115 | D28: 71774354 | E28: 1 | F28: 1 | G28: 35 | H28: 3 | I28: 21.3-2-3 | J28: СН-2012-2024.21. База. Р.3, о.2, поз.3 | K28: Раствор известковый, марка 4 | L28: 1339 | N28: 1007 | O28: м3 | P28: м3 | Q28: 1 | X28: 1.12 | Y28: 3944.53 | Z28: 0 | AA28: 0 | AB28: 0 | AC28: 0 | AD28: 1 | AE28: 0 | AG28: 1.12 | AH28: 3 | AI28: -1 | AK28: 0 | AL28: 0 | AM28: 0 | AN28: 0 | AO28: 0 | AP28: 0 | AQ28: 0 | AR28: 0
A29: =ROW(Source!A77) -> 77 | B29: 72192331 | C29: 71588115 | D29: 71774437 | E29: 1 | F29: 1 | G29: 35 | H29: 3 | I29: 21.3-2-92 | J29: СН-2012-2024.21. База. Р.3, о.2, поз.92 | K29: Смеси сухие штукатурные известковые для внутренних работ, В2 (М25), крупность заполнителя не более 0,5 мм | L29: 1348 | N29: 1009 | O29: т | P29: т | Q29: 1000 | X29: 0.448 | Y29: 10609.81 | Z29: 0 | AA29: 0 | AB29: 0 | AC29: 0 | AD29: 1 | AE29: 0 | AG29: 0.448 | AH29: 3 | AI29: -1 | AK29: 0 | AL29: 0 | AM29: 0 | AN29: 0 | AO29: 0 | AP29: 0 | AQ29: 0 | AR29: 0
A30: =ROW(Source!A77) -> 77 | B30: 72192332 | C30: 71588115 | D30: 71774442 | E30: 1 | F30: 1 | G30: 35 | H30: 3 | I30: 21.3-2-97 | J30: СН-2012-2024.21. База. Р.3, о.2, поз.97 | K30: Смеси сухие штукатурные цементно-известковые для внутренних и наружных работ, для машинного и ручного нанесения, марка 75 | L30: 1348 | N30: 1009 | O30: т | P30: т | Q30: 1000 | X30: 0.0896 | Y30: 9743.97 | Z30: 0 | AA30: 0 | AB30: 0 | AC30: 0 | AD30: 1 | AE30: 0 | AG30: 0.0896 | AH30: 3 | AI30: -1 | AK30: 0 | AL30: 0 | AM30: 0 | AN30: 0 | AO30: 0 | AP30: 0 | AQ30: 0 | AR30: 0
A31: =ROW(Source!A78) -> 78 | B31: 72192333 | C31: 71588133 | D31: 71757693 | E31: 35 | F31: 1 | G31: 35 | H31: 1 | I31: 9999990008 | K31: Трудозатраты рабочих | L31: 1191 | N31: 1013 | O31: чел.-ч. | P31: чел.-ч. | Q31: 1 | X31: 5.35 | Y31: 0 | Z31: 0 | AA31: 0 | AB31: 0 | AC31: 0 | AD31: 1 | AE31: 1 | AG31: 5.35 | AH31: 3 | AI31: -1 | AK31: 0 | AL31: 0 | AM31: 0 | AN31: 0 | AO31: 0 | AP31: 0 | AQ31: 0 | AR31: 0
A32: =ROW(Source!A78) -> 78 | B32: 72192334 | C32: 71588133 | D32: 71771216 | E32: 1 | F32: 1 | G32: 35 | H32: 2 | I32: 22.1-30-90 | J32: СН-2012-2024.22. База. п.1-30-90 (302501) | K32: Дрели-миксеры импортного производства для перемешивания строительных материалов, скорость до 650 об/мин | L32: 1368 | N32: 1011 | O32: маш.-ч | P32: маш.-ч | Q32: 1 | X32: 0.04 | Y32: 0 | Z32: 10.56 | AA32: 0.16 | AB32: 0 | AC32: 0 | AD32: 1 | AE32: 0 | AG32: 0.04 | AH32: 3 | AI32: -1 | AK32: 0 | AL32: 0 | AM32: 0 | AN32: 0 | AO32: 0 | AP32: 0 | AQ32: 0 | AR32: 0
A33: =ROW(Source!A78) -> 78 | B33: 72192335 | C33: 71588133 | D33: 71771654 | E33: 1 | F33: 1 | G33: 35 | H33: 3 | I33: 21.1-6-10 | J33: СН-2012-2024.21. База. Р.1, о.6, поз.10 | K33: Грунтовка акриловая концентрированная универсальная с высокой клеевой и проникающей способностью | L33: 1296 | N33: 1002 | O33: л | P33: л | Q33: 1 | X33: 10.3 | Y33: 105.2 | Z33: 0 | AA33: 0 | AB33: 0 | AC33: 0 | AD33: 1 | AE33: 0 | AG33: 10.3 | AH33: 3 | AI33: -1 | AK33: 0 | AL33: 0 | AM33: 0 | AN33: 0 | AO33: 0 | AP33: 0 | AQ33: 0 | AR33: 0
A34: =ROW(Source!A79) -> 79 | B34: 72192336 | C34: 71588143 | D34: 71757693 | E34: 35 | F34: 1 | G34: 35 | H34: 1 | I34: 9999990008 | K34: Трудозатраты рабочих | L34: 1191 | N34: 1013 | O34: чел.-ч. | P34: чел.-ч. | Q34: 1 | X34: 42.17 | Y34: 0 | Z34: 0 | AA34: 0 | AB34: 0 | AC34: 0 | AD34: 1 | AE34: 1 | AG34: 42.17 | AH34: 3 | AI34: -1 | AK34: 0 | AL34: 0 | AM34: 0 | AN34: 0 | AO34: 0 | AP34: 0 | AQ34: 0 | AR34: 0
A35: =ROW(Source!A79) -> 79 | B35: 72192337 | C35: 71588143 | D35: 71773080 | E35: 1 | F35: 1 | G35: 35 | H35: 3 | I35: 21.1-20-7 | J35: СН-2012-2024.21. База. Р.1, о.20, поз.7 | K35: Ветошь | L35: 1346 | N35: 1009 | O35: кг | P35: кг | Q35: 1 | X35: 0.31 | Y35: 29.29 | Z35: 0 | AA35: 0 | AB35: 0 | AC35: 0 | AD35: 1 | AE35: 0 | AG35: 0.31 | AH35: 3 | AI35: -1 | AK35: 0 | AL35: 0 | AM35: 0 | AN35: 0 | AO35: 0 | AP35: 0 | AQ35: 0 | AR35: 0
A36: =ROW(Source!A79) -> 79 | B36: 72192338 | C36: 71588143 | D36: 71773291 | E36: 1 | F36: 1 | G36: 35 | H36: 3 | I36: 21.1-25-13 | J36: СН-2012-2024.21. База. Р.1, о.25, поз.13 | K36: Вода | L36: 1339 | N36: 1007 | O36: м3 | P36: м3 | Q36: 1 | X36: 0.006 | Y36: 42.44 | Z36: 0 | AA36: 0 | AB36: 0 | AC36: 0 | AD36: 1 | AE36: 0 | AG36: 0.006 | AH36: 3 | AI36: -1 | AK36: 0 | AL36: 0 | AM36: 0 | AN36: 0 | AO36: 0 | AP36: 0 | AQ36: 0 | AR36: 0
A37: =ROW(Source!A79) -> 79 | B37: 72192339 | C37: 71588143 | D37: 71773642 | E37: 1 | F37: 1 | G37: 35 | H37: 3 | I37: 21.1-25-388 | J37: СН-2012-2024.21. База. Р.1, о.25, поз.388 | K37: Шкурка шлифовальная на бумажной основе | L37: 1327 | N37: 1005 | O37: м2 | P37: м2 | Q37: 1 | X37: 0.8 | Y37: 459.29 | Z37: 0 | AA37: 0 | AB37: 0 | AC37: 0 | AD37: 1 | AE37: 0 | AG37: 0.8 | AH37: 3 | AI37: -1 | AK37: 0 | AL37: 0 | AM37: 0 | AN37: 0 | AO37: 0 | AP37: 0 | AQ37: 0 | AR37: 0
A38: =ROW(Source!A79) -> 79 | B38: 72192340 | C38: 71588143 | D38: 71773658 | E38: 1 | F38: 1 | G38: 35 | H38: 3 | I38: 21.1-25-404 | J38: СН-2012-2024.21. База. Р.1, о.25, поз.404 | K38: Шпатлевка водно-дисперсионная акриловая | L38: 1348 | N38: 1009 | O38: т | P38: т | Q38: 1000 | X38: 0.051 | Y38: 91730.92 | Z38: 0 | AA38: 0 | AB38: 0 | AC38: 0 | AD38: 1 | AE38: 0 | AG38: 0.051 | AH38: 3 | AI38: -1 | AK38: 0 | AL38: 0 | AM38: 0 | AN38: 0 | AO38: 0 | AP38: 0 | AQ38: 0 | AR38: 0
A39: =ROW(Source!A79) -> 79 | B39: 72192341 | C39: 71588143 | D39: 71771857 | E39: 1 | F39: 1 | G39: 35 | H39: 3 | I39: 21.1-6-219 | J39: СН-2012-2024.21. База. Р.1, о.6, поз.219 | K39: Краски водно-дисперсионные акриловые износостойкие, интерьерные, моющиеся, типа ВД-АК-210, белые | L39: 1346 | N39: 1009 | O39: кг | P39: кг | Q39: 1 | X39: 24.2 | Y39: 159.59 | Z39: 0 | AA39: 0 | AB39: 0 | AC39: 0 | AD39: 1 | AE39: 0 | AG39: 24.2 | AH39: 3 | AI39: -1 | AK39: 0 | AL39: 0 | AM39: 0 | AN39: 0 | AO39: 0 | AP39: 0 | AQ39: 0 | AR39: 0
A40: =ROW(Source!A79) -> 79 | B40: 72192342 | C40: 71588143 | D40: 71771859 | E40: 1 | F40: 1 | G40: 35 | H40: 3 | I40: 21.1-6-221 | J40: СН-2012-2024.21. База. Р.1, о.6, поз.221 | K40: Грунтовка водно-дисперсионная акриловая укрепляющая для минеральных поверхностей, типа ВД-АК-0110 | L40: 1346 | N40: 1009 | O40: кг | P40: кг | Q40: 1 | X40: 10.4 | Y40: 87.7 | Z40: 0 | AA40: 0 | AB40: 0 | AC40: 0 | AD40: 1 | AE40: 0 | AG40: 10.4 | AH40: 3 | AI40: -1 | AK40: 0 | AL40: 0 | AM40: 0 | AN40: 0 | AO40: 0 | AP40: 0 | AQ40: 0 | AR40: 0
A41: =ROW(Source!A80) -> 80 | B41: 72192343 | C41: 71588158 | D41: 71757693 | E41: 35 | F41: 1 | G41: 35 | H41: 1 | I41: 9999990008 | K41: Трудозатраты рабочих | L41: 1191 | N41: 1013 | O41: чел.-ч. | P41: чел.-ч. | Q41: 1 | X41: 87.17 | Y41: 0 | Z41: 0 | AA41: 0 | AB41: 0 | AC41: 0 | AD41: 1 | AE41: 1 | AG41: 87.17 | AH41: 3 | AI41: -1 | AK41: 0 | AL41: 0 | AM41: 0 | AN41: 0 | AO41: 0 | AP41: 0 | AQ41: 0 | AR41: 0
A42: =ROW(Source!A80) -> 80 | B42: 72192344 | C42: 71588158 | D42: 71771949 | E42: 1 | F42: 1 | G42: 35 | H42: 3 | I42: 21.1-9-51 | J42: СН-2012-2024.21. База. Р.1, о.9, поз.51 | K42: Доски хвойных пород, обрезные, длина 2-6,5 м, сорт II, толщина 25-32 мм | L42: 1339 | N42: 1007 | O42: м3 | P42: м3 | Q42: 1 | X42: 0.008 | Y42: 8098.45 | Z42: 0 | AA42: 0 | AB42: 0 | AC42: 0 | AD42: 1 | AE42: 0 | AG42: 0.008 | AH42: 3 | AI42: -1 | AK42: 0 | AL42: 0 | AM42: 0 | AN42: 0 | AO42: 0 | AP42: 0 | AQ42: 0 | AR42: 0
A43: =ROW(Source!A81) -> 81 | B43: 72192345 | C43: 71588120 | D43: 71757693 | E43: 35 | F43: 1 | G43: 35 | H43: 1 | I43: 9999990008 | K43: Трудозатраты рабочих | L43: 1191 | N43: 1013 | O43: чел.-ч. | P43: чел.-ч. | Q43: 1 | X43: 68.2 | Y43: 0 | Z43: 0 | AA43: 0 | AB43: 0 | AC43: 0 | AD43: 1 | AE43: 1 | AG43: 68.2 | AH43: 3 | AI43: -1 | AK43: 0 | AL43: 0 | AM43: 0 | AN43: 0 | AO43: 0 | AP43: 0 | AQ43: 0 | AR43: 0
A44: =ROW(Source!A81) -> 81 | B44: 72192346 | C44: 71588120 | D44: 71770528 | E44: 1 | F44: 1 | G44: 35 | H44: 2 | I44: 22.1-6-33 | J44: СН-2012-2024.22. База. п.1-6-33 (067501) | K44: Растворонасосы, производительность до 1 м3/ч | L44: 1368 | N44: 1011 | O44: маш.-ч | P44: маш.-ч | Q44: 1 | X44: 5.12 | Y44: 0 | Z44: 461.4 | AA44: 409.44 | AB44: 0 | AC44: 0 | AD44: 1 | AE44: 0 | AG44: 5.12 | AH44: 3 | AI44: -1 | AK44: 0 | AL44: 0 | AM44: 0 | AN44: 0 | AO44: 0 | AP44: 0 | AQ44: 0 | AR44: 0
A45: =ROW(Source!A81) -> 81 | B45: 72192347 | C45: 71588120 | D45: 71773291 | E45: 1 | F45: 1 | G45: 35 | H45: 3 | I45: 21.1-25-13 | J45: СН-2012-2024.21. База. Р.1, о.25, поз.13 | K45: Вода | L45: 1339 | N45: 1007 | O45: м3 | P45: м3 | Q45: 1 | X45: 0.08008 | Y45: 42.44 | Z45: 0 | AA45: 0 | AB45: 0 | AC45: 0 | AD45: 1 | AE45: 0 | AG45: 0.08008 | AH45: 3 | AI45: -1 | AK45: 0 | AL45: 0 | AM45: 0 | AN45: 0 | AO45: 0 | AP45: 0 | AQ45: 0 | AR45: 0
A46: =ROW(Source!A81) -> 81 | B46: 72192348 | C46: 71588120 | D46: 71773591 | E46: 1 | F46: 1 | G46: 35 | H46: 3 | I46: 21.1-25-335 | J46: СН-2012-2024.21. База. Р.1, о.25, поз.335 | K46: Сетка проволочная штукатурная тканая, квадрат 5х5 мм, толщина 1,6 мм | L46: 1327 | N46: 1005 | O46: м2 | P46: м2 | Q46: 1 | X46: 2.64 | Y46: 525.42 | Z46: 0 | AA46: 0 | AB46: 0 | AC46: 0 | AD46: 1 | AE46: 0 | AG46: 2.64 | AH46: 3 | AI46: -1 | AK46: 0 | AL46: 0 | AM46: 0 | AN46: 0 | AO46: 0 | AP46: 0 | AQ46: 0 | AR46: 0
A47: =ROW(Source!A81) -> 81 | B47: 72192349 | C47: 71588120 | D47: 71774354 | E47: 1 | F47: 1 | G47: 35 | H47: 3 | I47: 21.3-2-3 | J47: СН-2012-2024.21. База. Р.3, о.2, поз.3 | K47: Раствор известковый, марка 4 | L47: 1339 | N47: 1007 | O47: м3 | P47: м3 | Q47: 1 | X47: 1.144 | Y47: 3944.53 | Z47: 0 | AA47: 0 | AB47: 0 | AC47: 0 | AD47: 1 | AE47: 0 | AG47: 1.144 | AH47: 3 | AI47: -1 | AK47: 0 | AL47: 0 | AM47: 0 | AN47: 0 | AO47: 0 | AP47: 0 | AQ47: 0 | AR47: 0
A48: =ROW(Source!A81) -> 81 | B48: 72192350 | C48: 71588120 | D48: 71774437 | E48: 1 | F48: 1 | G48: 35 | H48: 3 | I48: 21.3-2-92 | J48: СН-2012-2024.21. База. Р.3, о.2, поз.92 | K48: Смеси сухие штукатурные известковые для внутренних работ, В2 (М25), крупность заполнителя не более 0,5 мм | L48: 1348 | N48: 1009 | O48: т | P48: т | Q48: 1000 | X48: 0.4576 | Y48: 10609.81 | Z48: 0 | AA48: 0 | AB48: 0 | AC48: 0 | AD48: 1 | AE48: 0 | AG48: 0.4576 | AH48: 3 | AI48: -1 | AK48: 0 | AL48: 0 | AM48: 0 | AN48: 0 | AO48: 0 | AP48: 0 | AQ48: 0 | AR48: 0
A49: =ROW(Source!A82) -> 82 | B49: 72192351 | C49: 71588129 | D49: 71757693 | E49: 35 | F49: 1 | G49: 35 | H49: 1 | I49: 9999990008 | K49: Трудозатраты рабочих | L49: 1191 | N49: 1013 | O49: чел.-ч. | P49: чел.-ч. | Q49: 1 | X49: 6.53 | Y49: 0 | Z49: 0 | AA49: 0 | AB49: 0 | AC49: 0 | AD49: 1 | AE49: 1 | AG49: 6.53 | AH49: 3 | AI49: -1 | AK49: 0 | AL49: 0 | AM49: 0 | AN49: 0 | AO49: 0 | AP49: 0 | AQ49: 0 | AR49: 0
A50: =ROW(Source!A82) -> 82 | B50: 72192352 | C50: 71588129 | D50: 71771216 | E50: 1 | F50: 1 | G50: 35 | H50: 2 | I50: 22.1-30-90 | J50: СН-2012-2024.22. База. п.1-30-90 (302501) | K50: Дрели-миксеры импортного производства для перемешивания строительных материалов, скорость до 650 об/мин | L50: 1368 | N50: 1011 | O50: маш.-ч | P50: маш.-ч | Q50: 1 | X50: 0.04 | Y50: 0 | Z50: 10.56 | AA50: 0.16 | AB50: 0 | AC50: 0 | AD50: 1 | AE50: 0 | AG50: 0.04 | AH50: 3 | AI50: -1 | AK50: 0 | AL50: 0 | AM50: 0 | AN50: 0 | AO50: 0 | AP50: 0 | AQ50: 0 | AR50: 0
A51: =ROW(Source!A82) -> 82 | B51: 72192353 | C51: 71588129 | D51: 71771654 | E51: 1 | F51: 1 | G51: 35 | H51: 3 | I51: 21.1-6-10 | J51: СН-2012-2024.21. База. Р.1, о.6, поз.10 | K51: Грунтовка акриловая концентрированная универсальная с высокой клеевой и проникающей способностью | L51: 1296 | N51: 1002 | O51: л | P51: л | Q51: 1 | X51: 10.3 | Y51: 105.2 | Z51: 0 | AA51: 0 | AB51: 0 | AC51: 0 | AD51: 1 | AE51: 0 | AG51: 10.3 | AH51: 3 | AI51: -1 | AK51: 0 | AL51: 0 | AM51: 0 | AN51: 0 | AO51: 0 | AP51: 0 | AQ51: 0 | AR51: 0
A52: =ROW(Source!A83) -> 83 | B52: 72192354 | C52: 71588178 | D52: 71757693 | E52: 35 | F52: 1 | G52: 35 | H52: 1 | I52: 9999990008 | K52: Трудозатраты рабочих | L52: 1191 | N52: 1013 | O52: чел.-ч. | P52: чел.-ч. | Q52: 1 | X52: 54.37 | Y52: 0 | Z52: 0 | AA52: 0 | AB52: 0 | AC52: 0 | AD52: 1 | AE52: 1 | AG52: 54.37 | AH52: 3 | AI52: -1 | AK52: 0 | AL52: 0 | AM52: 0 | AN52: 0 | AO52: 0 | AP52: 0 | AQ52: 0 | AR52: 0
A53: =ROW(Source!A83) -> 83 | B53: 72192355 | C53: 71588178 | D53: 71773080 | E53: 1 | F53: 1 | G53: 35 | H53: 3 | I53: 21.1-20-7 | J53: СН-2012-2024.21. База. Р.1, о.20, поз.7 | K53: Ветошь | L53: 1346 | N53: 1009 | O53: кг | P53: кг | Q53: 1 | X53: 0.31 | Y53: 29.29 | Z53: 0 | AA53: 0 | AB53: 0 | AC53: 0 | AD53: 1 | AE53: 0 | AG53: 0.31 | AH53: 3 | AI53: -1 | AK53: 0 | AL53: 0 | AM53: 0 | AN53: 0 | AO53: 0 | AP53: 0 | AQ53: 0 | AR53: 0
A54: =ROW(Source!A83) -> 83 | B54: 72192356 | C54: 71588178 | D54: 71773291 | E54: 1 | F54: 1 | G54: 35 | H54: 3 | I54: 21.1-25-13 | J54: СН-2012-2024.21. База. Р.1, о.25, поз.13 | K54: Вода | L54: 1339 | N54: 1007 | O54: м3 | P54: м3 | Q54: 1 | X54: 0.006 | Y54: 42.44 | Z54: 0 | AA54: 0 | AB54: 0 | AC54: 0 | AD54: 1 | AE54: 0 | AG54: 0.006 | AH54: 3 | AI54: -1 | AK54: 0 | AL54: 0 | AM54: 0 | AN54: 0 | AO54: 0 | AP54: 0 | AQ54: 0 | AR54: 0
A55: =ROW(Source!A83) -> 83 | B55: 72192357 | C55: 71588178 | D55: 71773642 | E55: 1 | F55: 1 | G55: 35 | H55: 3 | I55: 21.1-25-388 | J55: СН-2012-2024.21. База. Р.1, о.25, поз.388 | K55: Шкурка шлифовальная на бумажной основе | L55: 1327 | N55: 1005 | O55: м2 | P55: м2 | Q55: 1 | X55: 0.8 | Y55: 459.29 | Z55: 0 | AA55: 0 | AB55: 0 | AC55: 0 | AD55: 1 | AE55: 0 | AG55: 0.8 | AH55: 3 | AI55: -1 | AK55: 0 | AL55: 0 | AM55: 0 | AN55: 0 | AO55: 0 | AP55: 0 | AQ55: 0 | AR55: 0
A56: =ROW(Source!A83) -> 83 | B56: 72192358 | C56: 71588178 | D56: 71773658 | E56: 1 | F56: 1 | G56: 35 | H56: 3 | I56: 21.1-25-404 | J56: СН-2012-2024.21. База. Р.1, о.25, поз.404 | K56: Шпатлевка водно-дисперсионная акриловая | L56: 1348 | N56: 1009 | O56: т | P56: т | Q56: 1000 | X56: 0.055 | Y56: 91730.92 | Z56: 0 | AA56: 0 | AB56: 0 | AC56: 0 | AD56: 1 | AE56: 0 | AG56: 0.055 | AH56: 3 | AI56: -1 | AK56: 0 | AL56: 0 | AM56: 0 | AN56: 0 | AO56: 0 | AP56: 0 | AQ56: 0 | AR56: 0
A57: =ROW(Source!A83) -> 83 | B57: 72192359 | C57: 71588178 | D57: 71771857 | E57: 1 | F57: 1 | G57: 35 | H57: 3 | I57: 21.1-6-219 | J57: СН-2012-2024.21. База. Р.1, о.6, поз.219 | K57: Краски водно-дисперсионные акриловые износостойкие, интерьерные, моющиеся, типа ВД-АК-210, белые | L57: 1346 | N57: 1009 | O57: кг | P57: кг | Q57: 1 | X57: 26.6 | Y57: 159.59 | Z57: 0 | AA57: 0 | AB57: 0 | AC57: 0 | AD57: 1 | AE57: 0 | AG57: 26.6 | AH57: 3 | AI57: -1 | AK57: 0 | AL57: 0 | AM57: 0 | AN57: 0 | AO57: 0 | AP57: 0 | AQ57: 0 | AR57: 0
A58: =ROW(Source!A83) -> 83 | B58: 72192360 | C58: 71588178 | D58: 71771859 | E58: 1 | F58: 1 | G58: 35 | H58: 3 | I58: 21.1-6-221 | J58: СН-2012-2024.21. База. Р.1, о.6, поз.221 | K58: Грунтовка водно-дисперсионная акриловая укрепляющая для минеральных поверхностей, типа ВД-АК-0110 | L58: 1346 | N58: 1009 | O58: кг | P58: кг | Q58: 1 | X58: 11.4 | Y58: 87.7 | Z58: 0 | AA58: 0 | AB58: 0 | AC58: 0 | AD58: 1 | AE58: 0 | AG58: 11.4 | AH58: 3 | AI58: -1 | AK58: 0 | AL58: 0 | AM58: 0 | AN58: 0 | AO58: 0 | AP58: 0 | AQ58: 0 | AR58: 0
A59: =ROW(Source!A84) -> 84 | B59: 72192361 | C59: 71588193 | D59: 71757693 | E59: 35 | F59: 1 | G59: 35 | H59: 1 | I59: 9999990008 | K59: Трудозатраты рабочих | L59: 1191 | N59: 1013 | O59: чел.-ч. | P59: чел.-ч. | Q59: 1 | X59: 16.91 | Y59: 0 | Z59: 0 | AA59: 0 | AB59: 0 | AC59: 0 | AD59: 1 | AE59: 1 | AG59: 16.91 | AH59: 3 | AI59: -1 | AK59: 0 | AL59: 0 | AM59: 0 | AN59: 0 | AO59: 0 | AP59: 0 | AQ59: 0 | AR59: 0
A60: =ROW(Source!A84) -> 84 | B60: 72192362 | C60: 71588193 | D60: 71770747 | E60: 1 | F60: 1 | G60: 35 | H60: 2 | I60: 22.1-14-13 | J60: СН-2012-2024.22. База. п.1-14-13 (148501) | K60: Пылесосы, потребляемая мощность 350-1200 Вт | L60: 1368 | N60: 1011 | O60: маш.-ч | P60: маш.-ч | Q60: 1 | X60: 6.24 | Y60: 0 | Z60: 50.66 | AA60: 0.2 | AB60: 0 | AC60: 0 | AD60: 1 | AE60: 0 | AG60: 6.24 | AH60: 3 | AI60: -1 | AK60: 0 | AL60: 0 | AM60: 0 | AN60: 0 | AO60: 0 | AP60: 0 | AQ60: 0 | AR60: 0
A61: =ROW(Source!A84) -> 84 | B61: 72192363 | C61: 71588193 | D61: 71771226 | E61: 1 | F61: 1 | G61: 35 | H61: 2 | I61: 22.1-30-103 | J61: СН-2012-2024.22. База. п.1-30-103 (304104) | K61: Перфораторы электрические, мощность до 800 Вт | L61: 1368 | N61: 1011 | O61: маш.-ч | P61: маш.-ч | Q61: 1 | X61: 6.24 | Y61: 0 | Z61: 8.8 | AA61: 1.22 | AB61: 0 | AC61: 0 | AD61: 1 | AE61: 0 | AG61: 6.24 | AH61: 3 | AI61: -1 | AK61: 0 | AL61: 0 | AM61: 0 | AN61: 0 | AO61: 0 | AP61: 0 | AQ61: 0 | AR61: 0
A62: =ROW(Source!A84) -> 84 | B62: 72192364 | C62: 71588193 | D62: 71771187 | E62: 1 | F62: 1 | G62: 35 | H62: 2 | I62: 22.1-30-56 | J62: СН-2012-2024.22. База. п.1-30-56 (309101) | K62: Шуруповерты | L62: 1368 | N62: 1011 | O62: маш.-ч | P62: маш.-ч | Q62: 1 | X62: 1.13 | Y62: 0 | Z62: 5.27 | AA62: 0.01 | AB62: 0 | AC62: 0 | AD62: 1 | AE62: 0 | AG62: 1.13 | AH62: 3 | AI62: -1 | AK62: 0 | AL62: 0 | AM62: 0 | AN62: 0 | AO62: 0 | AP62: 0 | AQ62: 0 | AR62: 0
A63: =ROW(Source!A84) -> 84 | B63: 72192365 | C63: 71588193 | D63: 71772482 | E63: 1 | F63: 1 | G63: 35 | H63: 3 | I63: 21.1-11-198 | J63: СН-2012-2024.21. База. Р.1, о.11, поз.198 | K63: Дюбели пластмассовые | L63: 1354 | N63: 1010 | O63: шт. | P63: шт. | Q63: 1 | X63: 252.5 | Y63: 1.7 | Z63: 0 | AA63: 0 | AB63: 0 | AC63: 0 | AD63: 1 | AE63: 0 | AG63: 252.5 | AH63: 3 | AI63: -1 | AK63: 0 | AL63: 0 | AM63: 0 | AN63: 0 | AO63: 0 | AP63: 0 | AQ63: 0 | AR63: 0
A64: =ROW(Source!A84) -> 84 | B64: 72192366 | C64: 71588193 | D64: 71774134 | E64: 1 | F64: 1 | G64: 35 | H64: 3 | I64: 21.1-25-1099 | J64: СН-2012-2024.21. База. Р.1, о.25, поз.1099 | K64: Плинтусы поливинилхлоридные с мягким краем, с монтажной сплошной планкой и лицевым профилем с креплением через защелку, гладкие, разных цветов, размеры 50-62х21 мм | L64: 1301 | N64: 1003 | O64: м | P64: м | Q64: 1 | X64: 101 | Y64: 48.86 | Z64: 0 | AA64: 0 | AB64: 0 | AC64: 0 | AD64: 1 | AE64: 0 | AG64: 101 | AH64: 3 | AI64: -1 | AK64: 0 | AL64: 0 | AM64: 0 | AN64: 0 | AO64: 0 | AP64: 0 | AQ64: 0 | AR64: 0
A65: =ROW(Source!A84) -> 84 | B65: 72192367 | C65: 71588193 | D65: 71774135 | E65: 1 | F65: 1 | G65: 35 | H65: 3 | I65: 21.1-25-1100 | J65: СН-2012-2024.21. База. Р.1, о.25, поз.1100 | K65: Углы внутренние к плинтусам поливинилхлоридным с мягким краем, с монтажной сплошной планкой и лицевым профилем с креплением через защелку, гладкие, разных цветов, размеры 50-62х21 мм | L65: 1354 | N65: 1010 | O65: шт. | P65: шт. | Q65: 1 | X65: 8 | Y65: 28.91 | Z65: 0 | AA65: 0 | AB65: 0 | AC65: 0 | AD65: 1 | AE65: 0 | AG65: 8 | AH65: 3 | AI65: -1 | AK65: 0 | AL65: 0 | AM65: 0 | AN65: 0 | AO65: 0 | AP65: 0 | AQ65: 0 | AR65: 0
A66: =ROW(Source!A84) -> 84 | B66: 72192368 | C66: 71588193 | D66: 71774136 | E66: 1 | F66: 1 | G66: 35 | H66: 3 | I66: 21.1-25-1101 | J66: СН-2012-2024.21. База. Р.1, о.25, поз.1101 | K66: Углы наружные к плинтусам поливинилхлоридным с мягким краем, с монтажной сплошной планкой и лицевым профилем с креплением через защелку, гладкие, разных цветов, размеры 50-62х21 мм | L66: 1354 | N66: 1010 | O66: шт. | P66: шт. | Q66: 1 | X66: 2 | Y66: 21.26 | Z66: 0 | AA66: 0 | AB66: 0 | AC66: 0 | AD66: 1 | AE66: 0 | AG66: 2 | AH66: 3 | AI66: -1 | AK66: 0 | AL66: 0 | AM66: 0 | AN66: 0 | AO66: 0 | AP66: 0 | AQ66: 0 | AR66: 0
A67: =ROW(Source!A84) -> 84 | B67: 72192369 | C67: 71588193 | D67: 71774137 | E67: 1 | F67: 1 | G67: 35 | H67: 3 | I67: 21.1-25-1102 | J67: СН-2012-2024.21. База. Р.1, о.25, поз.1102 | K67: Соединители к плинтусам поливинилхлоридным с мягким краем, с монтажной сплошной планкой и лицевым профилем с креплением через защелку, гладкие, разных цветов, размеры 50-62х21 мм | L67: 1354 | N67: 1010 | O67: шт. | P67: шт. | Q67: 1 | X67: 8 | Y67: 17.02 | Z67: 0 | AA67: 0 | AB67: 0 | AC67: 0 | AD67: 1 | AE67: 0 | AG67: 8 | AH67: 3 | AI67: -1 | AK67: 0 | AL67: 0 | AM67: 0 | AN67: 0 | AO67: 0 | AP67: 0 | AQ67: 0 | AR67: 0
A68: =ROW(Source!A84) -> 84 | B68: 72192370 | C68: 71588193 | D68: 71774138 | E68: 1 | F68: 1 | G68: 35 | H68: 3 | I68: 21.1-25-1103 | J68: СН-2012-2024.21. База. Р.1, о.25, поз.1103 | K68: Заглушки торцевые к плинтусам поливинилхлоридным с мягким краем, с монтажной сплошной планкой и лицевым профилем с креплением через защелку, гладкие, разных цветов, размеры 50-62х21 мм | L68: 1354 | N68: 1010 | O68: шт. | P68: шт. | Q68: 1 | X68: 4 | Y68: 17.02 | Z68: 0 | AA68: 0 | AB68: 0 | AC68: 0 | AD68: 1 | AE68: 0 | AG68: 4 | AH68: 3 | AI68: -1 | AK68: 0 | AL68: 0 | AM68: 0 | AN68: 0 | AO68: 0 | AP68: 0 | AQ68: 0 | AR68: 0
A69: =ROW(Source!A85) -> 85 | B69: 72192371 | C69: 71588224 | D69: 71757693 | E69: 35 | F69: 1 | G69: 35 | H69: 1 | I69: 9999990008 | K69: Трудозатраты рабочих | L69: 1191 | N69: 1013 | O69: чел.-ч. | P69: чел.-ч. | Q69: 1 | X69: 77.86 | Y69: 0 | Z69: 0 | AA69: 0 | AB69: 0 | AC69: 0 | AD69: 1 | AE69: 1 | AG69: 77.86 | AH69: 3 | AI69: -1 | AK69: 0 | AL69: 0 | AM69: 0 | AN69: 0 | AO69: 0 | AP69: 0 | AQ69: 0 | AR69: 0
A70: =ROW(Source!A85) -> 85 | B70: 72192372 | C70: 71588224 | D70: 71772330 | E70: 1 | F70: 1 | G70: 35 | H70: 3 | I70: 21.1-11-46 | J70: СН-2012-2024.21. База. Р.1, о.11, поз.46 | K70: Гвозди строительные | L70: 1348 | N70: 1009 | O70: т | P70: т | Q70: 1000 | X70: 0.012 | Y70: 81885.1 | Z70: 0 | AA70: 0 | AB70: 0 | AC70: 0 | AD70: 1 | AE70: 0 | AG70: 0.012 | AH70: 3 | AI70: -1 | AK70: 0 | AL70: 0 | AM70: 0 | AN70: 0 | AO70: 0 | AP70: 0 | AQ70: 0 | AR70: 0
A71: =ROW(Source!A85) -> 85 | B71: 72192373 | C71: 71588224 | D71: 71772368 | E71: 1 | F71: 1 | G71: 35 | H71: 3 | I71: 21.1-11-84 | J71: СН-2012-2024.21. База. Р.1, о.11, поз.84 | K71: Поковки строительные (скобы, закрепы, хомуты) простые, масса 1,8 кг | L71: 1348 | N71: 1009 | O71: т | P71: т | Q71: 1000 | X71: 0.035 | Y71: 84851.61 | Z71: 0 | AA71: 0 | AB71: 0 | AC71: 0 | AD71: 1 | AE71: 0 | AG71: 0.035 | AH71: 3 | AI71: -1 | AK71: 0 | AL71: 0 | AM71: 0 | AN71: 0 | AO71: 0 | AP71: 0 | AQ71: 0 | AR71: 0
A72: =ROW(Source!A85) -> 85 | B72: 72192374 | C72: 71588224 | D72: 71776618 | E72: 1 | F72: 1 | G72: 35 | H72: 3 | I72: 21.9-12-46 | J72: СН-2012-2024.21. База. Р.9, о.12, поз.46 | K72: Раскладки хвойных пород, окрашенные, сечение 19х13(24) мм | L72: 1301 | N72: 1003 | O72: м | P72: м | Q72: 1 | X72: 400 | Y72: 20.59 | Z72: 0 | AA72: 0 | AB72: 0 | AC72: 0 | AD72: 1 | AE72: 0 | AG72: 400 | AH72: 3 | AI72: -1 | AK72: 0 | AL72: 0 | AM72: 0 | AN72: 0 | AO72: 0 | AP72: 0 | AQ72: 0 | AR72: 0
A73: =ROW(Source!A122) -> 122 | B73: 72192375 | C73: 71588290 | D73: 71757693 | E73: 35 | F73: 1 | G73: 35 | H73: 1 | I73: 9999990008 | K73: Трудозатраты рабочих | L73: 1191 | N73: 1013 | O73: чел.-ч. | P73: чел.-ч. | Q73: 1 | X73: 67.96 | Y73: 0 | Z73: 0 | AA73: 0 | AB73: 0 | AC73: 0 | AD73: 1 | AE73: 1 | AG73: 67.96 | AH73: 3 | AI73: -1 | AK73: 0 | AL73: 0 | AM73: 0 | AN73: 0 | AO73: 0 | AP73: 0 | AQ73: 0 | AR73: 0
A74: =ROW(Source!A122) -> 122 | B74: 72192376 | C74: 71588290 | D74: 71771225 | E74: 1 | F74: 1 | G74: 35 | H74: 2 | I74: 22.1-30-102 | J74: СН-2012-2024.22. База. п.1-30-102 (303704) | K74: Дрели электрические, двухскоростные, мощностью 600 Вт | L74: 1368 | N74: 1011 | O74: маш.-ч | P74: маш.-ч | Q74: 1 | X74: 0.26 | Y74: 0 | Z74: 8.07 | AA74: 1.22 | AB74: 0 | AC74: 0 | AD74: 1 | AE74: 0 | AG74: 0.26 | AH74: 3 | AI74: -1 | AK74: 0 | AL74: 0 | AM74: 0 | AN74: 0 | AO74: 0 | AP74: 0 | AQ74: 0 | AR74: 0
A75: =ROW(Source!A122) -> 122 | B75: 72192377 | C75: 71588290 | D75: 71772401 | E75: 1 | F75: 1 | G75: 35 | H75: 3 | I75: 21.1-11-117 | J75: СН-2012-2024.21. База. Р.1, о.11, поз.117 | K75: Шурупы с потайной головкой, оцинкованные, длина 35-60 мм | L75: 1348 | N75: 1009 | O75: т | P75: т | Q75: 1000 | X75: 0.0045 | Y75: 250191.91 | Z75: 0 | AA75: 0 | AB75: 0 | AC75: 0 | AD75: 1 | AE75: 0 | AG75: 0.0045 | AH75: 3 | AI75: -1 | AK75: 0 | AL75: 0 | AM75: 0 | AN75: 0 | AO75: 0 | AP75: 0 | AQ75: 0 | AR75: 0
A76: =ROW(Source!A122) -> 122 | B76: 72192378 | C76: 71588290 | D76: 71772462 | E76: 1 | F76: 1 | G76: 35 | H76: 3 | I76: 21.1-11-178 | J76: СН-2012-2024.21. База. Р.1, о.11, поз.178 | K76: Дюбели распорные пластмассовые, размеры 6х40 мм | L76: 1355 | N76: 1010 | O76: 100 шт. | P76: 100 шт. | Q76: 100 | X76: 0.89 | Y76: 36.36 | Z76: 0 | AA76: 0 | AB76: 0 | AC76: 0 | AD76: 1 | AE76: 0 | AG76: 0.89 | AH76: 3 | AI76: -1 | AK76: 0 | AL76: 0 | AM76: 0 | AN76: 0 | AO76: 0 | AP76: 0 | AQ76: 0 | AR76: 0
A77: =ROW(Source!A122) -> 122 | B77: 72192379 | C77: 71588290 | D77: 71778223 | E77: 1 | F77: 1 | G77: 35 | H77: 3 | I77: 21.12-10-20 | J77: СН-2012-2024.21. База. Р.12, о.10, поз.20 | K77: Кронштейны для крепления отопительных приборов, марка КР1-РС | L77: 1035 | N77: 1013 | O77: компл. | P77: компл. | Q77: 1 | X77: 44.2 | Y77: 131.81 | Z77: 0 | AA77: 0 | AB77: 0 | AC77: 0 | AD77: 1 | AE77: 0 | AG77: 44.2 | AH77: 3 | AI77: -1 | AK77: 0 | AL77: 0 | AM77: 0 | AN77: 0 | AO77: 0 | AP77: 0 | AQ77: 0 | AR77: 0
